Workbook

Sheet Como usar
A1: OPPA — O MAPA DA PLANILHA
A2: Catorze abas, mas você só precisa de quatro no dia a dia. A cor da aba diz o que fazer com ela.
B4: O CAMINHO MAIS CURTO
B5: 1. | C5: Abra o RESUMO e veja onde o negócio está nos três cenários.
B6: 2. | C6: Abra PREÇO para entender de onde sai o valor da assinatura e testar um preço.
B7: 3. | C7: Mude o que quiser em PREMISSAS. Tudo recalcula sozinho — não há nada para rodar.
B8: 4. | C8: Volte ao RESUMO e compare.
B10: ABA | C10: PARA QUE SERVE | D10: VOCÊ DIGITA?
B11: COMECE AQUI
B12: Como usar | C12: O mapa. Esta tela. | D12: não
B13: LEIA O RESULTADO
B14: Resumo | C14: Os três cenários lado a lado e o diagnóstico. É a aba para mostrar a um sócio ou investidor. | D14: não
B15: Preço | C15: De onde sai o valor da assinatura: nuvem, suporte, pessoas, marketing, administrativo, impostos, comissão da loja e margem. Tem um campo para testar um preço. | D15: só 3 campos
B16: DIGITE AQUI
B17: Premissas | C17: Todos os números do negócio: preços, conversão, churn, custos, tributação. É aqui que você passa a maior parte do tempo. | D17: SIM
B18: O RESULTADO EM DETALHE
B19: DRE Projetada | C19: O resultado mês a mês, de jan/2026 a dez/2030 — colunas B até BI. A soma por ano fica no rodapé, depois do detalhe mensal. | D19: não
B20: Análise Fluxo | C20: O caixa mês a mês, mais VPL, TIR e payback. Traz a linha de verificação que precisa ficar zerada. | D20: não
B21: AJUSTE E ACOMPANHAMENTO POSTERIOR
B22: Pessoas | C22: O time, linha a linha, com data de entrada e de saída de cada pessoa. | D22: SIM
B23: Aportes | C23: Todo o capital: quem aportou, quanto, quando e em que status. | D23: SIM
B24: Investimentos | C24: Cronograma de equipamentos, marca e certificações. | D24: SIM
B25: Sócios | C25: Lucro distribuível e rateio por participação. Os percentuais ainda são provisórios. | D25: SIM
B26: MOTOR E APOIO — ABAS OCULTAS
B27: Faturamento | C27: A receita aberta por linha de negócio. Mesma informação da DRE, em outro corte. | D27: não
B28: Usuários | C28: O funil de usuários e as métricas de unidade (CAC, LTV, churn). | D28: não
B29: Cenários | C29: O motor. Os três cenários rodam aqui e todas as outras abas leem daqui. Nunca edite. | D29: não
B30: Tributos | C30: As tabelas do Simples Nacional (Anexos III e V) e o Fator R. | D30: não
B32: PARA VER UMA ABA OCULTA
B33: Clique com o botão direito em qualquer aba na barra de baixo e escolha 'Reexibir' (Excel) ou 'Mostrar planilha' (LibreOffice). Elas estão ocultas porque são o motor e o apoio — nada se perde, e nada ali precisa ser editado.
B35: AS CORES DAS CÉLULAS
B36: Azul | C36: você digita — é uma premissa sua.
B37: Fundo amarelo | C37: premissa-chave: mexer nela desloca bastante o resultado.
B38: Preto | C38: fórmula calculada na própria aba. Não mexa.
B39: Verde | C39: valor que vem de outra aba. Mude na origem.
B41: SE ALGUM NÚMERO PARECER ERRADO
B42: • Na ANÁLISE FLUXO há uma linha de verificação que compara o detalhe com o motor. Ela tem de ficar zerada em todos os meses.
B43: • Na aba PREÇO há duas linhas de conferência que comparam a decomposição de custo com a DRE. Também têm de ficar zeradas.
B44: • Em PREMISSAS, a linha 'Verificação do mix' tem de somar 100% em todos os anos.
B45: • Se alguma delas sair de zero, uma fórmula foi sobrescrita por um valor digitado. Desfaça a última edição ou peça o arquivo novo.

Sheet Resumo
A1: OPPA — VIABILIDADE FINANCEIRA · PAINEL EXECUTIVO
A2: Projeção de 60 meses (jan/2026 – dez/2030). Os três cenários são calculados simultaneamente. Todos os números vêm de fórmulas — nada está digitado à mão.
B4: INDICADOR | C4: CONSERVADOR | D4: PROVÁVEL | E4: AGRESSIVO
B5: Cenário em uso nas abas de detalhe | C5: =IF(Premissas!$B$6=1,"◀ ATIVO","") | D5: =IF(Premissas!$B$6=2,"◀ ATIVO","") -> ◀ ATIVO | E5: =IF(Premissas!$B$6=3,"◀ ATIVO","")
A7: TRAÇÃO — USUÁRIOS E RECEITA
B8: Usuários na base em dez/2026 | C8: =Cenários!$M$13 -> 10860 | D8: =Cenários!$M$59 -> 18100 | E8: =Cenários!$M$105 -> 25340 | G8: Meta do brief: 50 mil usuários ao final de 2026.
B9: Usuários na base em dez/2030 | C9: =Cenários!$BI$13 -> 421839.4 | D9: =Cenários!$BI$59 -> 1115800.7 | E9: =Cenários!$BI$105 -> 2420142.7
B10: Assinantes pagantes em dez/2026 | C10: =Cenários!$M$15 -> 18 | D10: =Cenários!$M$61 -> 90 | E10: =Cenários!$M$107 -> 253 | G10: Meta do brief: 5% da base pagante.
B11: Assinantes pagantes em dez/2030 | C11: =Cenários!$BI$15 -> 4390 | D11: =Cenários!$BI$61 -> 37675 | E11: =Cenários!$BI$107 -> 183322
B12: Receita bruta de 2026 | C12: =SUMIFS(Cenários!$B$28:$BI$28,Cenários!$B$6:$BI$6,2026) -> 1438.2 | D12: =SUMIFS(Cenários!$B$74:$BI$74,Cenários!$B$6:$BI$6,2026) -> 7191 | E12: =SUMIFS(Cenários!$B$120:$BI$120,Cenários!$B$6:$BI$6,2026) -> 20214.7
B13: Receita bruta de 2030 | C13: =SUMIFS(Cenários!$B$28:$BI$28,Cenários!$B$6:$BI$6,2030) -> 4924325.7 | D13: =SUMIFS(Cenários!$B$74:$BI$74,Cenários!$B$6:$BI$6,2030) -> 35439898 | E13: =SUMIFS(Cenários!$B$120:$BI$120,Cenários!$B$6:$BI$6,2030) -> 1.6137721e+08
B14: Receita bruta acumulada em 5 anos | C14: =SUM(Cenários!$B$28:$BI$28) -> 11000912 | D14: =SUM(Cenários!$B$74:$BI$74) -> 72831521 | E14: =SUM(Cenários!$B$120:$BI$120) -> 3.0581403e+08
A16: RESULTADO OPERACIONAL
B17: EBITDA de 2026 | C17: =SUMIFS(Cenários!$B$40:$BI$40,Cenários!$B$6:$BI$6,2026) -> -36984.939 | D17: =SUMIFS(Cenários!$B$86:$BI$86,Cenários!$B$6:$BI$6,2026) -> -36635.697 | E17: =SUMIFS(Cenários!$B$132:$BI$132,Cenários!$B$6:$BI$6,2026) -> -27725.692
B18: EBITDA de 2030 | C18: =SUMIFS(Cenários!$B$40:$BI$40,Cenários!$B$6:$BI$6,2030) -> -5656476 | D18: =SUMIFS(Cenários!$B$86:$BI$86,Cenários!$B$6:$BI$6,2030) -> 4516917.9 | E18: =SUMIFS(Cenários!$B$132:$BI$132,Cenários!$B$6:$BI$6,2030) -> 47924931
B19: EBITDA acumulado em 5 anos | C19: =SUM(Cenários!$B$40:$BI$40) -> -12365859 | D19: =SUM(Cenários!$B$86:$BI$86) -> 7774451.7 | E19: =SUM(Cenários!$B$132:$BI$132) -> 86915003
B20: Margem EBITDA em 2030 (% da receita bruta) | C20: =IFERROR(C18/C13,0) -> -1.1486803 | D20: =IFERROR(D18/D13,0) -> 0.1274529 | E20: =IFERROR(E18/E13,0) -> 0.29697459
B21: Break-even do EBITDA | C21: =IF(SUM(Cenários!$B$46:$BI$46)=0,"não atinge",CHOOSE(MOD(60-SUM(Cenários!$B$46:$BI$46),12)+1,"jan","fev","mar","abr","mai","jun","jul","ago","set","out","nov","dez")&"/"&(2026+INT((60-SUM(Cenários!$B$46:$BI$46))/12))) -> não atinge | D21: =IF(SUM(Cenários!$B$92:$BI$92)=0,"não atinge",CHOOSE(MOD(60-SUM(Cenários!$B$92:$BI$92),12)+1,"jan","fev","mar","abr","mai","jun","jul","ago","set","out","nov","dez")&"/"&(2026+INT((60-SUM(Cenários!$B$92:$BI$92))/12))) -> jun/2027 | E21: =IF(SUM(Cenários!$B$138:$BI$138)=0,"não atinge",CHOOSE(MOD(60-SUM(Cenários!$B$138:$BI$138),12)+1,"jan","fev","mar","abr","mai","jun","jul","ago","set","out","nov","dez")&"/"&(2026+INT((60-SUM(Cenários!$B$138:$BI$138))/12))) -> mar/2027 | G21: Primeiro mês com EBITDA positivo — quando a operação passa a se pagar.
A23: CAPITAL E CAIXA
B24: Investimento total (CAPEX) | C24: =-SUM(Cenários!$B$41:$BI$41) -> 124127.82 | D24: =-SUM(Cenários!$B$87:$BI$87) -> 124127.82 | E24: =-SUM(Cenários!$B$133:$BI$133) -> 124127.82
B25: Capital requerido (pico de caixa negativo do FCL) | C25: =-MIN(Cenários!$B$45:$BI$45) -> 12489987 | D25: =-MIN(Cenários!$B$91:$BI$91) -> 343862.1 | E25: =-MIN(Cenários!$B$137:$BI$137) -> 145974.79 | G25: Quanto a operação precisa de capital antes de se sustentar sozinha.
B26: Capital total considerado | C26: =SUM(Aportes!$B$96:$BI$96) -> 317000 | D26: =SUM(Aportes!$B$96:$BI$96) -> 317000 | E26: =SUM(Aportes!$B$96:$BI$96) -> 317000
B27: Caixa mínimo ao longo do período | C27: =MIN(Cenários!$B$49:$BI$49) -> -12172987 | D27: =MIN(Cenários!$B$95:$BI$95) -> -46752.641 | E27: =MIN(Cenários!$B$141:$BI$141) -> -9014.1427 | G27: Se ficar negativo, o capital planejado não é suficiente — falta captar a diferença.
B28: Mês do caixa mínimo | C28: =CHOOSE(MOD(MATCH(MIN(Cenários!$B$49:$BI$49),Cenários!$B$49:$BI$49,0)-1,12)+1,"jan","fev","mar","abr","mai","jun","jul","ago","set","out","nov","dez")&"/"&(2026+INT((MATCH(MIN(Cenários!$B$49:$BI$49),Cenários!$B$49:$BI$49,0)-1)/12)) -> dez/2030 | D28: =CHOOSE(MOD(MATCH(MIN(Cenários!$B$95:$BI$95),Cenários!$B$95:$BI$95,0)-1,12)+1,"jan","fev","mar","abr","mai","jun","jul","ago","set","out","nov","dez")&"/"&(2026+INT((MATCH(MIN(Cenários!$B$95:$BI$95),Cenários!$B$95:$BI$95,0)-1)/12)) -> jan/2027 | E28: =CHOOSE(MOD(MATCH(MIN(Cenários!$B$141:$BI$141),Cenários!$B$141:$BI$141,0)-1,12)+1,"jan","fev","mar","abr","mai","jun","jul","ago","set","out","nov","dez")&"/"&(2026+INT((MATCH(MIN(Cenários!$B$141:$BI$141),Cenários!$B$141:$BI$141,0)-1)/12)) -> jan/2027 | G28: Quando o caixa chega no fundo do poço — é o mês para o qual o aporte precisa chegar antes.
B29: Caixa em dez/2030 | C29: =Cenários!$BI$49 -> -12172987 | D29: =Cenários!$BI$95 -> 7967323.9 | E29: =Cenários!$BI$141 -> 87107876
A31: INDICADORES DE VIABILIDADE (sobre o Fluxo de Caixa Livre)
B32: VPL — Valor Presente Líquido | C32: {=NPV(Premissas!$B$19,Cenários!$B$42:$BI$42)} -> -5662096.4 | D32: {=NPV(Premissas!$B$19,Cenários!$B$88:$BI$88)} -> 3051853.8 | E32: {=NPV(Premissas!$B$19,Cenários!$B$134:$BI$134)} -> 36619447 | G32: Descontado à TMA definida em Premissas. Positivo = o projeto cria valor.
B33: TIR mensal | C33: =IFERROR(IRR(Cenários!$B$42:$BI$42),"n/d") -> n/d | D33: =IFERROR(IRR(Cenários!$B$88:$BI$88),"n/d") -> 0.11586217 | E33: =IFERROR(IRR(Cenários!$B$134:$BI$134),"n/d") -> 0.39509207
B34: TIR anual | C34: =IFERROR((1+C33)^12-1,"n/d") -> n/d | D34: =IFERROR((1+D33)^12-1,"n/d") -> 2.7267192 | E34: =IFERROR((1+E33)^12-1,"n/d") -> 53.354365 | G34: Compare com a TMA. Atenção: quando o investimento inicial é pequeno diante do caixa gerado, a TIR fica muito alta e perde poder de comparação — olhe o VPL junto.
B35: Payback simples (meses) | C35: =IF(Cenários!$BI$45<0,"> 60",MAX(Cenários!$B$50:$BI$50)+1) -> > 60 | D35: =IF(Cenários!$BI$91<0,"> 60",MAX(Cenários!$B$96:$BI$96)+1) -> 28 | E35: =IF(Cenários!$BI$137<0,"> 60",MAX(Cenários!$B$142:$BI$142)+1) -> 17 | G35: Mês em que o FCL acumulado passa a positivo e não volta mais.
B36: Payback descontado (meses) | C36: =IF(Cenários!$BI$44<0,"> 60",MAX(Cenários!$B$51:$BI$51)+1) -> > 60 | D36: =IF(Cenários!$BI$90<0,"> 60",MAX(Cenários!$B$97:$BI$97)+1) -> 29 | E36: =IF(Cenários!$BI$136<0,"> 60",MAX(Cenários!$B$143:$BI$143)+1) -> 17 | G36: Critério de decisão: payback desejado definido em Premissas.
B37: FCL acumulado em 5 anos | C37: =SUM(Cenários!$B$42:$BI$42) -> -12489987 | D37: =SUM(Cenários!$B$88:$BI$88) -> 7650323.9 | E37: =SUM(Cenários!$B$134:$BI$134) -> 86790876
B38: Retorno sobre o capital requerido (múltiplo) | C38: =IFERROR(C37/C25,0) -> -1 | D38: =IFERROR(D37/D25,0) -> 22.248232 | E38: =IFERROR(E37/E25,0) -> 594.56071 | G38: Múltiplo, não percentual: 3,0x significa devolver três vezes o capital que o projeto precisou. Negativo significa que o capital não volta.
A40: TESTE DE DECISÃO — GO / NO-GO
B41: O caixa nunca fica negativo? | C41: =IF(C27>=0,"SIM","NÃO") -> NÃO | D41: =IF(D27>=0,"SIM","NÃO") -> NÃO | E41: =IF(E27>=0,"SIM","NÃO") -> NÃO
B42: O VPL é positivo? | C42: =IF(C32>0,"SIM","NÃO") -> NÃO | D42: =IF(D32>0,"SIM","NÃO") -> SIM | E42: =IF(E32>0,"SIM","NÃO") -> SIM
B43: A TIR anual supera a TMA? | C43: =IF(N(C34)>Premissas!$B$18,"SIM","NÃO") -> NÃO | D43: =IF(N(D34)>Premissas!$B$18,"SIM","NÃO") -> SIM | E43: =IF(N(E34)>Premissas!$B$18,"SIM","NÃO") -> SIM
B44: O payback descontado cabe no prazo desejado? | C44: =IF(AND(ISNUMBER(C36),N(C36)<=Premissas!$B$20),"SIM","NÃO") -> NÃO | D44: =IF(AND(ISNUMBER(D36),N(D36)<=Premissas!$B$20),"SIM","NÃO") -> SIM | E44: =IF(AND(ISNUMBER(E36),N(E36)<=Premissas!$B$20),"SIM","NÃO") -> SIM
B45: DIAGNÓSTICO | C45: =IF(COUNTIF(C41:C44,"SIM")=4,"GO — VIÁVEL",IF(COUNTIF(C41:C44,"SIM")>=2,"GO COM RESSALVAS","NO GO — INVIÁVEL")) -> NO GO — INVIÁVEL | D45: =IF(COUNTIF(D41:D44,"SIM")=4,"GO — VIÁVEL",IF(COUNTIF(D41:D44,"SIM")>=2,"GO COM RESSALVAS","NO GO — INVIÁVEL")) -> GO COM RESSALVAS | E45: =IF(COUNTIF(E41:E44,"SIM")=4,"GO — VIÁVEL",IF(COUNTIF(E41:E44,"SIM")>=2,"GO COM RESSALVAS","NO GO — INVIÁVEL")) -> GO COM RESSALVAS
A47: MÉTRICAS DE UNIDADE — CENÁRIO ATIVO (dez/2030)
B48: LTV — valor do assinante | C48: =Usuários!$BI$29 -> 502.54258
B49: CAC por assinante pagante | C49: =Usuários!$BI$25 -> 77.69847
B50: LTV ÷ CAC | C50: =Usuários!$BI$30 -> 6.4678568 | G50: Referência: ≥ 3,0x é saudável. Abaixo de 1,0x destrói valor.
B51: Payback do CAC (meses) | C51: =Usuários!$BI$31 -> 2.4753591 | G51: Ideal abaixo de 12 meses.
B52: ARPPU — receita por assinante | C52: =Usuários!$BI$26 -> 86.192
B53: Runway em dez/2026 (meses de caixa) | C53: =Usuários!$M$36 -> 3.0068507
B54: Pessoas na operação em dez/2030 | C54: =Usuários!$BI$19 -> 50 | G54: Quadro de pessoal projetado. Edite linha a linha na aba Pessoas.
A56: PONTOS DE ATENÇÃO IDENTIFICADOS NA MODELAGEM
B57: ▸ Fator R: o modelo está no Anexo V, e é isso mesmo
B58: A aba Pessoas calcula o Fator R do quadro projetado: fica entre 1% e 6%, muito abaixo dos 28% exigidos para o Anexo III. Como pagamento a PJ não conta como folha, o Anexo III simplesmente não está disponível com a estrutura atual — por isso o regime padrão do modelo é o Anexo V. Migrar parte do time para CLT ou elevar o pró-labore pode reverter isso e economizar até R$ 135 mil por ano; compare na aba Tributos antes de decidir.
B59: ▸ Dependência dos aportes não assinados
B60: Dos R$ 200 mil do caso-base, R$ 120 mil vêm de C-ioT, Felipe Martinelli e Shaiane — ainda não formalizados. Sem eles, o capital cai para R$ 80 mil e o lançamento com aquisição paga não se sustenta. Este é o maior risco de curto prazo do plano.
B61: ▸ Comissão das lojas de aplicativos
B62: Apple e Google retêm 15% da assinatura (Google desde o primeiro dia; Apple pelo Small Business Program, válido enquanto a receita anual for inferior a US$ 1 milhão). Acima disso a Apple volta a 30%. É a maior dedução isolada da receita e não estava no brief.
B63: ▸ Conversão de 5% é premissa de quartil superior
B64: Benchmarks de freemium apontam mediana de 2,2% a 2,6% e faixa típica de 2% a 5%. Os 5% do brief são defensáveis para saúde com feature paga clara (histórico de dados), mas são a premissa mais sensível do modelo — teste o cenário Conservador (3%).
B65: ▸ Teto do Simples Nacional
B66: O modelo troca automaticamente para o Lucro Presumido quando o RBT12 ultrapassa R$ 4,8 milhões. No cenário Provável isso acontece dentro do horizonte e eleva a carga tributária — planeje a transição societária e contábil com antecedência.
B67: ▸ Só a equipe do MVP está de fato contratada
B68: Hoje não há time. O único custo de pessoal comprometido são os R$ 21 mil da equipe PJ de set–out/2026 para entregar o app. Todo o quadro projetado a partir de 2027 é plano, não compromisso: está na aba Pessoas, linha a linha, e pode ser desligado inteiro pelo controle de Premissas. É a premissa de custo que mais desloca o resultado.
... B80: O acordo não está confirmado e por isso está desligado: o interruptor 'Considerar acordos em negociação' está em 0, na seção 7 de Premissas. Ligue para dimensionar o upside — e considere que a exclusividade B2B hospitalar limita outras receitas do mesmo canal. Para incluir outro investidor estratégico, some uma linha na tabela 2 da aba Aportes.

Sheet Preço
A1: PREÇO — DE ONDE SAI O VALOR DA ASSINATURA
A2: Custo de atender um assinante por mês, componente por componente, e o preço que esse custo exige. Quatro momentos, porque o custo por assinante cai com a escala: o que é caro com 90 assinantes é barato com 37 mil.
A3: =" Cenário ativo: "&Premissas!$B$6&" · todos os valores em R$ por assinante por mês, salvo onde indicado" -> Cenário ativo: 2 · todos os valores em R$ por assinante por mês, salvo onde indicado
A5: 1. OS QUATRO MOMENTOS DA TABELA
A6: Mês nº na linha do tempo (1 = jan/2026 · 60 = dez/2030) | B6: =Premissas!$B$14 -> 12 | C6: =MIN(60,Premissas!$B$14+6) -> 18 | D6: =MIN(60,Premissas!$B$14+12) -> 24 | E6: =60 -> 60 | G6: Lançamento, +6 meses, +12 meses e o último mês do modelo. Digite por cima para olhar qualquer outro mês — é a única célula desta aba que você precisa mexer.
A7: Mês | B7: =INDEX(Cenários!$B$4:$BI$4,B$6) -> 46357 | C7: =INDEX(Cenários!$B$4:$BI$4,C$6) -> 46539 | D7: =INDEX(Cenários!$B$4:$BI$4,D$6) -> 46722 | E7: =INDEX(Cenários!$B$4:$BI$4,E$6) -> 47818
A8: Base total de usuários (pagantes + gratuitos) | B8: =CHOOSE(Premissas!$B$6,INDEX(Cenários!$B$13:$BI$13,B$6),INDEX(Cenários!$B$59:$BI$59,B$6),INDEX(Cenários!$B$105:$BI$105,B$6)) -> 18100 | C8: =CHOOSE(Premissas!$B$6,INDEX(Cenários!$B$13:$BI$13,C$6),INDEX(Cenários!$B$59:$BI$59,C$6),INDEX(Cenários!$B$105:$BI$105,C$6)) -> 146500.55 | D8: =CHOOSE(Premissas!$B$6,INDEX(Cenários!$B$13:$BI$13,D$6),INDEX(Cenários!$B$59:$BI$59,D$6),INDEX(Cenários!$B$105:$BI$105,D$6)) -> 226826.12 | E8: =CHOOSE(Premissas!$B$6,INDEX(Cenários!$B$13:$BI$13,E$6),INDEX(Cenários!$B$59:$BI$59,E$6),INDEX(Cenários!$B$105:$BI$105,E$6)) -> 1115800.7
A9: Assinantes pagantes | B9: =CHOOSE(Premissas!$B$6,INDEX(Cenários!$B$15:$BI$15,B$6),INDEX(Cenários!$B$61:$BI$61,B$6),INDEX(Cenários!$B$107:$BI$107,B$6)) -> 90 | C9: =CHOOSE(Premissas!$B$6,INDEX(Cenários!$B$15:$BI$15,C$6),INDEX(Cenários!$B$61:$BI$61,C$6),INDEX(Cenários!$B$107:$BI$107,C$6)) -> 4527 | D9: =CHOOSE(Premissas!$B$6,INDEX(Cenários!$B$15:$BI$15,D$6),INDEX(Cenários!$B$61:$BI$61,D$6),INDEX(Cenários!$B$107:$BI$107,D$6)) -> 7009 | E9: =CHOOSE(Premissas!$B$6,INDEX(Cenários!$B$15:$BI$15,E$6),INDEX(Cenários!$B$61:$BI$61,E$6),INDEX(Cenários!$B$107:$BI$107,E$6)) -> 37675 | G9: É por este número que todo o custo fixo é dividido. É a variável que manda no preço.
A10: Receita de assinaturas no mês | B10: =CHOOSE(Premissas!$B$6,INDEX(Cenários!$B$23:$BI$23,B$6),INDEX(Cenários!$B$69:$BI$69,B$6),INDEX(Cenários!$B$115:$BI$115,B$6)) -> 7191 | C10: =CHOOSE(Premissas!$B$6,INDEX(Cenários!$B$23:$BI$23,C$6),INDEX(Cenários!$B$69:$BI$69,C$6),INDEX(Cenários!$B$115:$BI$115,C$6)) -> 361707.3 | D10: =CHOOSE(Premissas!$B$6,INDEX(Cenários!$B$23:$BI$23,D$6),INDEX(Cenários!$B$69:$BI$69,D$6),INDEX(Cenários!$B$115:$BI$115,D$6)) -> 560019.1 | E10: =CHOOSE(Premissas!$B$6,INDEX(Cenários!$B$23:$BI$23,E$6),INDEX(Cenários!$B$69:$BI$69,E$6),INDEX(Cenários!$B$115:$BI$115,E$6)) -> 3247283.6
A11: Receita média por assinante hoje (ARPPU) | B11: =IFERROR(CHOOSE(Premissas!$B$6,INDEX(Cenários!$B$23:$BI$23,B$6),INDEX(Cenários!$B$69:$BI$69,B$6),INDEX(Cenários!$B$115:$BI$115,B$6))/B$9,0) -> 79.9 | C11: =IFERROR(CHOOSE(Premissas!$B$6,INDEX(Cenários!$B$23:$BI$23,C$6),INDEX(Cenários!$B$69:$BI$69,C$6),INDEX(Cenários!$B$115:$BI$115,C$6))/C$9,0) -> 79.9 | D11: =IFERROR(CHOOSE(Premissas!$B$6,INDEX(Cenários!$B$23:$BI$23,D$6),INDEX(Cenários!$B$69:$BI$69,D$6),INDEX(Cenários!$B$115:$BI$115,D$6))/D$9,0) -> 79.9 | E11: =IFERROR(CHOOSE(Premissas!$B$6,INDEX(Cenários!$B$23:$BI$23,E$6),INDEX(Cenários!$B$69:$BI$69,E$6),INDEX(Cenários!$B$115:$BI$115,E$6))/E$9,0) -> 86.192 | G11: Média do que cada assinante paga, considerando o mix de planos daquele mês.
A13: 2. CUSTO VARIÁVEL — o que cada assinante a mais custa (R$ por assinante/mês)
A14: Nuvem — do próprio assinante | B14: =INDEX(Premissas!$C$93:$G$93,INDEX(Cenários!$B$7:$BI$7,B$6)) -> 32 | C14: =INDEX(Premissas!$C$93:$G$93,INDEX(Cenários!$B$7:$BI$7,C$6)) -> 31.9 | D14: =INDEX(Premissas!$C$93:$G$93,INDEX(Cenários!$B$7:$BI$7,D$6)) -> 31.9 | E14: =INDEX(Premissas!$C$93:$G$93,INDEX(Cenários!$B$7:$BI$7,E$6)) -> 31.9 | G14: Premissas, seção 6: 'Nuvem — custo variável por usuário PAGANTE'. É o maior item variável e por isso o mais sensível: cada real aqui pede cerca de R$ 1,39 de preço.
A15: Nuvem — rateio dos usuários do plano gratuito | B15: =IFERROR((CHOOSE(Premissas!$B$6,INDEX(Cenários!$B$13:$BI$13,B$6),INDEX(Cenários!$B$59:$BI$59,B$6),INDEX(Cenários!$B$105:$BI$105,B$6))-B$9)*INDEX(Premissas!$C$94:$G$94,INDEX(Cenários!$B$7:$BI$7,B$6))/B$9,0) -> 4.0022222 | C15: =IFERROR((CHOOSE(Premissas!$B$6,INDEX(Cenários!$B$13:$BI$13,C$6),INDEX(Cenários!$B$59:$BI$59,C$6),INDEX(Cenários!$B$105:$BI$105,C$6))-C$9)*INDEX(Premissas!$C$94:$G$94,INDEX(Cenários!$B$7:$BI$7,C$6))/C$9,0) -> 0.62723017 | D15: =IFERROR((CHOOSE(Premissas!$B$6,INDEX(Cenários!$B$13:$BI$13,D$6),INDEX(Cenários!$B$59:$BI$59,D$6),INDEX(Cenários!$B$105:$BI$105,D$6))-D$9)*INDEX(Premissas!$C$94:$G$94,INDEX(Cenários!$B$7:$BI$7,D$6))/D$9,0) -> 0.62724245 | E15: =IFERROR((CHOOSE(Premissas!$B$6,INDEX(Cenários!$B$13:$BI$13,E$6),INDEX(Cenários!$B$59:$BI$59,E$6),INDEX(Cenários!$B$105:$BI$105,E$6))-E$9)*INDEX(Premissas!$C$94:$G$94,INDEX(Cenários!$B$7:$BI$7,E$6))/E$9,0) -> 0.42924711 | G15: O plano gratuito não paga e consome. Quem assina sustenta quem não assina.
A16: Nuvem — processamento do painel de dados | B16: =IFERROR(CHOOSE(Premissas!$B$6,INDEX(Cenários!$B$19:$BI$19,B$6),INDEX(Cenários!$B$65:$BI$65,B$6),INDEX(Cenários!$B$111:$BI$111,B$6))*Premissas!$B$69/B$9,0) -> 0 | C16: =IFERROR(CHOOSE(Premissas!$B$6,INDEX(Cenários!$B$19:$BI$19,C$6),INDEX(Cenários!$B$65:$BI$65,C$6),INDEX(Cenários!$B$111:$BI$111,C$6))*Premissas!$B$69/C$9,0) -> 1.6180804 | D16: =IFERROR(CHOOSE(Premissas!$B$6,INDEX(Cenários!$B$19:$BI$19,D$6),INDEX(Cenários!$B$65:$BI$65,D$6),INDEX(Cenários!$B$111:$BI$111,D$6))*Premissas!$B$69/D$9,0) -> 1.6181053 | E16: =IFERROR(CHOOSE(Premissas!$B$6,INDEX(Cenários!$B$19:$BI$19,E$6),INDEX(Cenários!$B$65:$BI$65,E$6),INDEX(Cenários!$B$111:$BI$111,E$6))*Premissas!$B$69/E$9,0) -> 1.4808242
A17: Suporte ao cliente | B17: =INDEX(Premissas!$C$95:$G$95,INDEX(Cenários!$B$7:$BI$7,B$6)) -> 0.35 | C17: =INDEX(Premissas!$C$95:$G$95,INDEX(Cenários!$B$7:$BI$7,C$6)) -> 0.35 | D17: =INDEX(Premissas!$C$95:$G$95,INDEX(Cenários!$B$7:$BI$7,D$6)) -> 0.35 | E17: =INDEX(Premissas!$C$95:$G$95,INDEX(Cenários!$B$7:$BI$7,E$6)) -> 0.25
A18: Marketing — custo de conquistar um assinante (CAC) | B18: =IFERROR((1-INDEX(Premissas!$C$59:$G$59,INDEX(Cenários!$B$7:$BI$7,B$6)))*CHOOSE(Premissas!$B$6,INDEX(Premissas!$C$56:$G$56,INDEX(Cenários!$B$7:$BI$7,B$6)),INDEX(Premissas!$C$57:$G$57,INDEX(Cenários!$B$7:$BI$7,B$6)),INDEX(Premissas!$C$58:$G$58,INDEX(Cenários!$B$7:$BI$7,B$6)))/CHOOSE(Premissas!$B$6,INDEX(Premissas!$C$52:$G$52,INDEX(Cenários!$B$7:$BI$7,B$6)),INDEX(Premissas!$C$53:$G$53,INDEX(Cenários!$B$7:$BI$7,B$6)),INDEX(Premissas!$C$54:$G$54,INDEX(Cenários!$B$7:$BI$7,B$6))),0) -> 58.333333 | C18: =IFERROR((1-INDEX(Premissas!$C$59:$G$59,INDEX(Cenários!$B$7:$BI$7,C$6)))*CHOOSE(Premissas!$B$6,INDEX(Premissas!$C$56:$G$56,INDEX(Cenários!$B$7:$BI$7,C$6)),INDEX(Premissas!$C$57:$G$57,INDEX(Cenários!$B$7:$BI$7,C$6)),INDEX(Premissas!$C$58:$G$58,INDEX(Cenários!$B$7:$BI$7,C$6)))/CHOOSE(Premissas!$B$6,INDEX(Premissas!$C$52:$G$52,INDEX(Cenários!$B$7:$BI$7,C$6)),INDEX(Premissas!$C$53:$G$53,INDEX(Cenários!$B$7:$BI$7,C$6)),INDEX(Premissas!$C$54:$G$54,INDEX(Cenários!$B$7:$BI$7,C$6))),0) -> 63.268608 | D18: =IFERROR((1-INDEX(Premissas!$C$59:$G$59,INDEX(Cenários!$B$7:$BI$7,D$6)))*CHOOSE(Premissas!$B$6,INDEX(Premissas!$C$56:$G$56,INDEX(Cenários!$B$7:$BI$7,D$6)),INDEX(Premissas!$C$57:$G$57,INDEX(Cenários!$B$7:$BI$7,D$6)),INDEX(Premissas!$C$58:$G$58,INDEX(Cenários!$B$7:$BI$7,D$6)))/CHOOSE(Premissas!$B$6,INDEX(Premissas!$C$52:$G$52,INDEX(Cenários!$B$7:$BI$7,D$6)),INDEX(Premissas!$C$53:$G$53,INDEX(Cenários!$B$7:$BI$7,D$6)),INDEX(Premissas!$C$54:$G$54,INDEX(Cenários!$B$7:$BI$7,D$6))),0) -> 63.268608 | E18: =IFERROR((1-INDEX(Premissas!$C$59:$G$59,INDEX(Cenários!$B$7:$BI$7,E$6)))*CHOOSE(Premissas!$B$6,INDEX(Premissas!$C$56:$G$56,INDEX(Cenários!$B$7:$BI$7,E$6)),INDEX(Premissas!$C$57:$G$57,INDEX(Cenários!$B$7:$BI$7,E$6)),INDEX(Premissas!$C$58:$G$58,INDEX(Cenários!$B$7:$BI$7,E$6)))/CHOOSE(Premissas!$B$6,INDEX(Premissas!$C$52:$G$52,INDEX(Cenários!$B$7:$BI$7,E$6)),INDEX(Premissas!$C$53:$G$53,INDEX(Cenários!$B$7:$BI$7,E$6)),INDEX(Premissas!$C$54:$G$54,INDEX(Cenários!$B$7:$BI$7,E$6))),0) -> 77.69847 | G18: Gasto para trazer um ASSINANTE: o CAC por usuário captado, dividido pela taxa de conversão do ano. Não é custo mensal — é de uma vez só, na entrada.
A19: Marketing — o CAC diluído na vida do assinante | B19: =B18*CHOOSE(Premissas!$B$6,INDEX(Premissas!$C$48:$G$48,INDEX(Cenários!$B$7:$BI$7,B$6)),INDEX(Premissas!$C$49:$G$49,INDEX(Cenários!$B$7:$BI$7,B$6)),INDEX(Premissas!$C$50:$G$50,INDEX(Cenários!$B$7:$BI$7,B$6))) -> 4.6666667 | C19: =C18*CHOOSE(Premissas!$B$6,INDEX(Premissas!$C$48:$G$48,INDEX(Cenários!$B$7:$BI$7,C$6)),INDEX(Premissas!$C$49:$G$49,INDEX(Cenários!$B$7:$BI$7,C$6)),INDEX(Premissas!$C$50:$G$50,INDEX(Cenários!$B$7:$BI$7,C$6))) -> 4.7577994 | D19: =D18*CHOOSE(Premissas!$B$6,INDEX(Premissas!$C$48:$G$48,INDEX(Cenários!$B$7:$BI$7,D$6)),INDEX(Premissas!$C$49:$G$49,INDEX(Cenários!$B$7:$BI$7,D$6)),INDEX(Premissas!$C$50:$G$50,INDEX(Cenários!$B$7:$BI$7,D$6))) -> 4.7577994 | E19: =E18*CHOOSE(Premissas!$B$6,INDEX(Premissas!$C$48:$G$48,INDEX(Cenários!$B$7:$BI$7,E$6)),INDEX(Premissas!$C$49:$G$49,INDEX(Cenários!$B$7:$BI$7,E$6)),INDEX(Premissas!$C$50:$G$50,INDEX(Cenários!$B$7:$BI$7,E$6))) -> 4.85304 | G19: Vida esperada do assinante = 1 ÷ churn. Multiplicar o CAC pelo churn é espalhá-lo por essa vida — é assim que ele entra num preço mensal.
A20: (=) CUSTO VARIÁVEL POR ASSINANTE | B20: =B14+B15+B16+B17+B19 -> 41.018889 | C20: =C14+C15+C16+C17+C19 -> 39.25311 | D20: =D14+D15+D16+D17+D19 -> 39.253147 | E20: =E14+E15+E16+E17+E19 -> 38.913111
A22: 3. CUSTO FIXO — o que a empresa gasta mesmo sem um assinante a mais (R$ no mês)
A23: Pessoas — equipe PJ, CLT e pró-labore | B23: =-(INDEX('Análise Fluxo'!$B$18:$BI$18,B$6)+INDEX('Análise Fluxo'!$B$19:$BI$19,B$6)+INDEX('Análise Fluxo'!$B$20:$BI$20,B$6)) -> 0 | C23: =-(INDEX('Análise Fluxo'!$B$18:$BI$18,C$6)+INDEX('Análise Fluxo'!$B$19:$BI$19,C$6)+INDEX('Análise Fluxo'!$B$20:$BI$20,C$6)) -> 42500 | D23: =-(INDEX('Análise Fluxo'!$B$18:$BI$18,D$6)+INDEX('Análise Fluxo'!$B$19:$BI$19,D$6)+INDEX('Análise Fluxo'!$B$20:$BI$20,D$6)) -> 42500 | E23: =-(INDEX('Análise Fluxo'!$B$18:$BI$18,E$6)+INDEX('Análise Fluxo'!$B$19:$BI$19,E$6)+INDEX('Análise Fluxo'!$B$20:$BI$20,E$6)) -> 374300 | G23: Da aba Pessoas, linha a linha. É o maior custo fixo em todos os meses.
A24: Nuvem — parcela fixa (ambiente, licenças, banco de dados) | B24: =IF(B7>=Premissas!$B$91,INDEX(Premissas!$C$92:$G$92,INDEX(Cenários!$B$7:$BI$7,B$6)),0) -> 600 | C24: =IF(C7>=Premissas!$B$91,INDEX(Premissas!$C$92:$G$92,INDEX(Cenários!$B$7:$BI$7,C$6)),0) -> 2500 | D24: =IF(D7>=Premissas!$B$91,INDEX(Premissas!$C$92:$G$92,INDEX(Cenários!$B$7:$BI$7,D$6)),0) -> 2500 | E24: =IF(E7>=Premissas!$B$91,INDEX(Premissas!$C$92:$G$92,INDEX(Cenários!$B$7:$BI$7,E$6)),0) -> 30000
A25: Marketing recorrente e propaganda de lançamento | B25: =-(INDEX('Análise Fluxo'!$B$22:$BI$22,B$6)+INDEX('Análise Fluxo'!$B$23:$BI$23,B$6)) -> 500 | C25: =-(INDEX('Análise Fluxo'!$B$22:$BI$22,C$6)+INDEX('Análise Fluxo'!$B$23:$BI$23,C$6)) -> 5000 | D25: =-(INDEX('Análise Fluxo'!$B$22:$BI$22,D$6)+INDEX('Análise Fluxo'!$B$23:$BI$23,D$6)) -> 5000 | E25: =-(INDEX('Análise Fluxo'!$B$22:$BI$22,E$6)+INDEX('Análise Fluxo'!$B$23:$BI$23,E$6)) -> 15000
A26: Administrativo — contabilidade, jurídico, ferramentas | B26: =-INDEX('Análise Fluxo'!$B$27:$BI$27,B$6) -> 0 | C26: =-INDEX('Análise Fluxo'!$B$27:$BI$27,C$6) -> 166.66667 | D26: =-INDEX('Análise Fluxo'!$B$27:$BI$27,D$6) -> 166.66667 | E26: =-INDEX('Análise Fluxo'!$B$27:$BI$27,E$6) -> 1666.6667 | G26: Premissas, seção 6. A célula é MENSAL. Hoje está como 2000/12, 5000/12 e assim por diante, o que dá R$ 167 por mês em 2027 — para contabilidade, jurídico e ferramentas de uma empresa no Simples isso é baixo. Vale conferir: só o contador costuma custar entre R$ 300 e R$ 800 por mês.
A27: (=) CUSTO FIXO DO MÊS | B27: =B23+B24+B25+B26 -> 1100 | C27: =C23+C24+C25+C26 -> 50166.667 | D27: =D23+D24+D25+D26 -> 50166.667 | E27: =E23+E24+E25+E26 -> 420966.67
A28: Custo fixo dividido pelos assinantes | B28: =IFERROR(B27/B$9,0) -> 12.222222 | C28: =IFERROR(C27/C$9,0) -> 11.081658 | D28: =IFERROR(D27/D$9,0) -> 7.1574642 | E28: =IFERROR(E27/E$9,0) -> 11.173634 | G28: É esta linha que faz o preço parecer impossível no lançamento e razoável depois. Não é o custo que muda — é o número de pessoas dividindo a conta.
A30: (=) CUSTO TOTAL POR ASSINANTE · variável + fixo rateado | B30: =B20+B28 -> 53.241111 | C30: =C20+C28 -> 50.334768 | D30: =D20+D28 -> 46.410611 | E30: =E20+E28 -> 50.086745
A31: ✔ Conferência do custo contra a DRE, sem o marketing (deve ser zero) | B31: =(B14+B15+B16+B17)*B$9+B27+(INDEX('Análise Fluxo'!$B$16:$BI$16,B$6)+INDEX('Análise Fluxo'!$B$17:$BI$17,B$6)+INDEX('Análise Fluxo'!$B$18:$BI$18,B$6)+INDEX('Análise Fluxo'!$B$19:$BI$19,B$6)+INDEX('Análise Fluxo'!$B$20:$BI$20,B$6)+INDEX('Análise Fluxo'!$B$22:$BI$22,B$6)+INDEX('Análise Fluxo'!$B$23:$BI$23,B$6)+INDEX('Análise Fluxo'!$B$27:$BI$27,B$6)) -> 0 | C31: =(C14+C15+C16+C17)*C$9+C27+(INDEX('Análise Fluxo'!$B$16:$BI$16,C$6)+INDEX('Análise Fluxo'!$B$17:$BI$17,C$6)+INDEX('Análise Fluxo'!$B$18:$BI$18,C$6)+INDEX('Análise Fluxo'!$B$19:$BI$19,C$6)+INDEX('Análise Fluxo'!$B$20:$BI$20,C$6)+INDEX('Análise Fluxo'!$B$22:$BI$22,C$6)+INDEX('Análise Fluxo'!$B$23:$BI$23,C$6)+INDEX('Análise Fluxo'!$B$27:$BI$27,C$6)) -> 0 | D31: =(D14+D15+D16+D17)*D$9+D27+(INDEX('Análise Fluxo'!$B$16:$BI$16,D$6)+INDEX('Análise Fluxo'!$B$17:$BI$17,D$6)+INDEX('Análise Fluxo'!$B$18:$BI$18,D$6)+INDEX('Análise Fluxo'!$B$19:$BI$19,D$6)+INDEX('Análise Fluxo'!$B$20:$BI$20,D$6)+INDEX('Análise Fluxo'!$B$22:$BI$22,D$6)+INDEX('Análise Fluxo'!$B$23:$BI$23,D$6)+INDEX('Análise Fluxo'!$B$27:$BI$27,D$6)) -> 0 | E31: =(E14+E15+E16+E17)*E$9+E27+(INDEX('Análise Fluxo'!$B$16:$BI$16,E$6)+INDEX('Análise Fluxo'!$B$17:$BI$17,E$6)+INDEX('Análise Fluxo'!$B$18:$BI$18,E$6)+INDEX('Análise Fluxo'!$B$19:$BI$19,E$6)+INDEX('Análise Fluxo'!$B$20:$BI$20,E$6)+INDEX('Análise Fluxo'!$B$22:$BI$22,E$6)+INDEX('Análise Fluxo'!$B$23:$BI$23,E$6)+INDEX('Análise Fluxo'!$B$27:$BI$27,E$6)) -> 0 | G31: Compara nuvem, suporte, pessoas, marketing recorrente e administrativo com o que a DRE gasta nos mesmos itens. O marketing de AQUISIÇÃO fica fora de propósito: aqui ele entra diluído na vida do assinante, na DRE entra no mês do desembolso.
A32: ✔ Conferência da nuvem: esta aba × assinantes − nuvem da DRE (deve ser zero) | B32: =(B14+B15+B16)*B$9+B24+INDEX('Análise Fluxo'!$B$16:$BI$16,B$6) -> 0 | C32: =(C14+C15+C16)*C$9+C24+INDEX('Análise Fluxo'!$B$16:$BI$16,C$6) -> 0 | D32: =(D14+D15+D16)*D$9+D24+INDEX('Análise Fluxo'!$B$16:$BI$16,D$6) -> 0 | E32: =(E14+E15+E16)*E$9+E24+INDEX('Análise Fluxo'!$B$16:$BI$16,E$6) -> 0 | G32: Prova que a decomposição da nuvem nesta aba é a mesma conta que a DRE usa. Se der diferente de zero, não confie no preço desta aba.
A34: 4. O QUE SAI DE CADA REAL COBRADO — antes de sobrar para pagar o custo
A35: (−) Imposto sobre a receita (Simples / Lucro Presumido) | B35: =CHOOSE(Premissas!$B$6,INDEX(Cenários!$B$30:$BI$30,B$6),INDEX(Cenários!$B$76:$BI$76,B$6),INDEX(Cenários!$B$122:$BI$122,B$6)) -> 0.155 | C35: =CHOOSE(Premissas!$B$6,INDEX(Cenários!$B$30:$BI$30,C$6),INDEX(Cenários!$B$76:$BI$76,C$6),INDEX(Cenários!$B$122:$BI$122,C$6)) -> 0.18524785 | D35: =CHOOSE(Premissas!$B$6,INDEX(Cenários!$B$30:$BI$30,D$6),INDEX(Cenários!$B$76:$BI$76,D$6),INDEX(Cenários!$B$122:$BI$122,D$6)) -> 0.15869359 | E35: =CHOOSE(Premissas!$B$6,INDEX(Cenários!$B$30:$BI$30,E$6),INDEX(Cenários!$B$76:$BI$76,E$6),INDEX(Cenários!$B$122:$BI$122,E$6)) -> 0.1633 | G35: Alíquota efetiva do mês, da tabela do Simples. Sobe conforme o faturamento dos últimos 12 meses.
A36: (−) Comissão da loja de aplicativos (Apple / Google) | B36: =Premissas!$B$62*INDEX(Premissas!$C$63:$G$63,INDEX(Cenários!$B$7:$BI$7,B$6)) -> 0.1275 | C36: =Premissas!$B$62*INDEX(Premissas!$C$63:$G$63,INDEX(Cenários!$B$7:$BI$7,C$6)) -> 0.12 | D36: =Premissas!$B$62*INDEX(Premissas!$C$63:$G$63,INDEX(Cenários!$B$7:$BI$7,D$6)) -> 0.12 | E36: =Premissas!$B$62*INDEX(Premissas!$C$63:$G$63,INDEX(Cenários!$B$7:$BI$7,E$6)) -> 0.105 | G36: 15% sobre a parte cobrada dentro do app. Cobrar fora do app evita a comissão, mas o aplicativo precisa estar nas lojas para existir.
A37: (−) Taxa do meio de pagamento (cartão, PIX, boleto) | B37: =Premissas!$B$64*(1-INDEX(Premissas!$C$63:$G$63,INDEX(Cenários!$B$7:$BI$7,B$6))) -> 0.00675 | C37: =Premissas!$B$64*(1-INDEX(Premissas!$C$63:$G$63,INDEX(Cenários!$B$7:$BI$7,C$6))) -> 0.009 | D37: =Premissas!$B$64*(1-INDEX(Premissas!$C$63:$G$63,INDEX(Cenários!$B$7:$BI$7,D$6))) -> 0.009 | E37: =Premissas!$B$64*(1-INDEX(Premissas!$C$63:$G$63,INDEX(Cenários!$B$7:$BI$7,E$6))) -> 0.0135
A38: (=) Total que sai do preço | B38: =B35+B36+B37 -> 0.28925 | C38: =C35+C36+C37 -> 0.31424785 | D38: =D35+D36+D37 -> 0.28769359 | E38: =E35+E36+E37 -> 0.2818
A39: (=) FICA PARA A EMPRESA, de cada R$ 1 cobrado | B39: =1-B38 -> 0.71075 | C39: =1-C38 -> 0.68575215 | D39: =1-D38 -> 0.71230641 | E39: =1-E38 -> 0.7182 | G39: Cobrar R$ 1 não é receber R$ 1. Todo preço desta aba é o custo dividido por esta porcentagem — é o que faz o preço subir mais do que o custo.
A41: 5. O PREÇO QUE O CUSTO EXIGE
A42: Margem EBITDA desejada | B42: =0.2 -> 0.2 | C42: =$B$42 -> 0.2 | D42: =$B$42 -> 0.2 | E42: =$B$42 -> 0.2 | G42: Digite a margem que você quer que sobre depois de pagar tudo. Com 0%, o preço apenas empata.
A43: Preço médio por assinante que apenas EMPATA (margem zero) | B43: =IFERROR(B30/B39,0) -> 74.908352 | C43: =IFERROR(C30/C39,0) -> 73.400818 | D43: =IFERROR(D30/D39,0) -> 65.155403 | E43: =IFERROR(E30/E39,0) -> 69.739272
A44: Preço médio por assinante COM a margem desejada | B44: =IFERROR(B30/(B39*(1-B42)),0) -> 93.63544 | C44: =IFERROR(C30/(C39*(1-C42)),0) -> 91.751022 | D44: =IFERROR(D30/(D39*(1-D42)),0) -> 81.444254 | E44: =IFERROR(E30/(E39*(1-E42)),0) -> 87.17409 | G44: É a ARPPU necessária: a média ponderada dos três planos. Abaixo, traduzida para o preço de cada plano.
A45: Receita média por assinante hoje (para comparar) | B45: =B11 -> 79.9 | C45: =C11 -> 79.9 | D45: =D11 -> 79.9 | E45: =E11 -> 86.192
A46: Margem EBITDA que o preço de hoje entrega | B46: =IFERROR((B11*B39-B30)/(B11*B39),0) -> 0.062473693 | C46: =IFERROR((C11*C39-C30)/(C11*C39),0) -> 0.081341457 | D46: =IFERROR((D11*D39-D30)/(D11*D39),0) -> 0.18453813 | E46: =IFERROR((E11*E39-E30)/(E11*E39),0) -> 0.19088463 | G46: Difere da margem EBITDA da DRE de propósito: aqui o marketing de aquisição entra diluído na vida do assinante, e marketplace e B2B não entram. É a margem da ASSINATURA, não a da empresa.
A48: Fator do mix (quanto a ARPPU vale em preços de Essencial) | B48: =INDEX(Premissas!$C$34:$G$34,INDEX(Cenários!$B$7:$BI$7,B$6))+INDEX(Premissas!$C$35:$G$35,INDEX(Cenários!$B$7:$BI$7,B$6))*IFERROR(Premissas!$B$30/Premissas!$B$29,0)+INDEX(Premissas!$C$36:$G$36,INDEX(Cenários!$B$7:$BI$7,B$6))*IFERROR(Premissas!$B$31/Premissas!$B$29,0) -> 1 | C48: =INDEX(Premissas!$C$34:$G$34,INDEX(Cenários!$B$7:$BI$7,C$6))+INDEX(Premissas!$C$35:$G$35,INDEX(Cenários!$B$7:$BI$7,C$6))*IFERROR(Premissas!$B$30/Premissas!$B$29,0)+INDEX(Premissas!$C$36:$G$36,INDEX(Cenários!$B$7:$BI$7,C$6))*IFERROR(Premissas!$B$31/Premissas!$B$29,0) -> 1 | D48: =INDEX(Premissas!$C$34:$G$34,INDEX(Cenários!$B$7:$BI$7,D$6))+INDEX(Premissas!$C$35:$G$35,INDEX(Cenários!$B$7:$BI$7,D$6))*IFERROR(Premissas!$B$30/Premissas!$B$29,0)+INDEX(Premissas!$C$36:$G$36,INDEX(Cenários!$B$7:$BI$7,D$6))*IFERROR(Premissas!$B$31/Premissas!$B$29,0) -> 1 | E48: =INDEX(Premissas!$C$34:$G$34,INDEX(Cenários!$B$7:$BI$7,E$6))+INDEX(Premissas!$C$35:$G$35,INDEX(Cenários!$B$7:$BI$7,E$6))*IFERROR(Premissas!$B$30/Premissas!$B$29,0)+INDEX(Premissas!$C$36:$G$36,INDEX(Cenários!$B$7:$BI$7,E$6))*IFERROR(Premissas!$B$31/Premissas!$B$29,0) -> 1.0787484 | G48: Converte a ARPPU necessária em preço do Essencial, mantendo a razão de preço atual entre os três planos. Cuidado: mexer no preço de UM plano em Premissas muda a razão, e com ela esta tradução — a ARPPU necessária, que vem do custo, não muda.
A49: Plano Essencial — preço necessário | B49: =IFERROR(B44/B48,0) -> 93.63544 | C49: =IFERROR(C44/C48,0) -> 91.751022 | D49: =IFERROR(D44/D48,0) -> 81.444254 | E49: =IFERROR(E44/E48,0) -> 80.810398
A50: Plano Premium — preço necessário | B50: =B49*IFERROR(Premissas!$B$30/Premissas!$B$29,0) -> 105.35452 | C50: =C49*IFERROR(Premissas!$B$30/Premissas!$B$29,0) -> 103.23425 | D50: =D49*IFERROR(Premissas!$B$30/Premissas!$B$29,0) -> 91.637527 | E50: =E49*IFERROR(Premissas!$B$30/Premissas!$B$29,0) -> 90.92434
A51: Plano Família — preço necessário | B51: =B49*IFERROR(Premissas!$B$31/Premissas!$B$29,0) -> 127.73796 | C51: =C49*IFERROR(Premissas!$B$31/Premissas!$B$29,0) -> 125.16723 | D51: =D49*IFERROR(Premissas!$B$31/Premissas!$B$29,0) -> 111.10668 | E51: =E49*IFERROR(Premissas!$B$31/Premissas!$B$29,0) -> 110.24197
A52: Plano Essencial — preço de hoje, em Premissas | B52: =Premissas!$B$29*(1+N(Premissas!$B$32))^(INDEX(Cenários!$B$6:$BI$6,B$6)-2026) -> 79.9 | C52: =Premissas!$B$29*(1+N(Premissas!$B$32))^(INDEX(Cenários!$B$6:$BI$6,C$6)-2026) -> 79.9 | D52: =Premissas!$B$29*(1+N(Premissas!$B$32))^(INDEX(Cenários!$B$6:$BI$6,D$6)-2026) -> 79.9 | E52: =Premissas!$B$29*(1+N(Premissas!$B$32))^(INDEX(Cenários!$B$6:$BI$6,E$6)-2026) -> 79.9
A53: Quantas vezes o preço de hoje | B53: =IFERROR(B49/B52,0) -> 1.1719079 | C53: =IFERROR(C49/C52,0) -> 1.1483232 | D53: =IFERROR(D49/D52,0) -> 1.0193273 | E53: =IFERROR(E49/E52,0) -> 1.0113942 | G53: Acima de 1,0x o preço de hoje não cobre o custo daquele mês. Acima de ~1,5x o preço deixa de ser vendável e a resposta passa a ser escala, não preço.
A55: 6. TESTAR UM PREÇO — digite o valor e veja se ele fecha
A56: Preço do Essencial que você quer testar | B56: =39.9 -> 39.9 | C56: =$B$56 -> 39.9 | D56: =$B$56 -> 39.9 | E56: =$B$56 -> 39.9 | G56: O cálculo do sócio. Premium e Família seguem a mesma proporção de hoje.
A57: Receita média por assinante a esse preço | B57: =B56*B48 -> 39.9 | C57: =C56*C48 -> 39.9 | D57: =D56*D48 -> 39.9 | E57: =E56*E48 -> 43.042063
A58: O que sobra depois de imposto, loja e meio de pagamento | B58: =B57*B39 -> 28.358925 | C58: =C57*C39 -> 27.361511 | D58: =D57*D39 -> 28.421026 | E58: =E57*E39 -> 30.912809
A59: (−) Custo total por assinante | B59: =-B30 -> -53.241111 | C59: =-C30 -> -50.334768 | D59: =-D30 -> -46.410611 | E59: =-E30 -> -50.086745
A60: (=) SOBRA POR ASSINANTE, NO MÊS | B60: =B58+B59 -> -24.882186 | C60: =C58+C59 -> -22.973258 | D60: =D58+D59 -> -17.989586 | E60: =E58+E59 -> -19.173936
A61: Margem EBITDA a esse preço | B61: =IFERROR(B60/B58,0) -> -0.8774023 | C61: =IFERROR(C60/C58,0) -> -0.83961949 | D61: =IFERROR(D60/D58,0) -> -0.6329675 | E61: =IFERROR(E60/E58,0) -> -0.62025861
A62: Assinantes necessários, a esse preço, para o mês fechar no zero | B62: =IF(B58-B20<=0,"",ROUNDUP(B27/(B58-B20),0)) | C62: =IF(C58-C20<=0,"",ROUNDUP(C27/(C58-C20),0)) | D62: =IF(D58-D20<=0,"",ROUNDUP(D27/(D58-D20),0)) | E62: =IF(E58-E20<=0,"",ROUNDUP(E27/(E58-E20),0)) | G62: Custo fixo do mês dividido pelo que cada assinante deixa depois do custo variável. Vazio significa que nenhum volume fecha: a esse preço o assinante não cobre nem o próprio custo variável.
A63: Assinantes projetados naquele mês | B63: =B$9 -> 90 | C63: =C$9 -> 4527 | D63: =D$9 -> 7009 | E63: =E$9 -> 37675
A65: Nuvem por assinante que esse preço suporta — para empatar | B65: =B58-(B15+B16+B17+B19)-B28 -> 7.1178139 | C65: =C58-(C15+C16+C17+C19)-C28 -> 8.9267425 | D65: =D58-(D15+D16+D17+D19)-D28 -> 13.910414 | E65: =E58-(E15+E16+E17+E19)-E28 -> 12.726064 | G65: A conta ao contrário: fixado o preço, quanto a nuvem pode custar por assinante. Compare com a linha 'Nuvem — do próprio assinante' no bloco 2.
A66: Nuvem por assinante que esse preço suporta — com a margem desejada | B66: =B58*(1-B42)-(B15+B16+B17+B19)-B28 -> 1.4460289 | C66: =C58*(1-C42)-(C15+C16+C17+C19)-C28 -> 3.4544404 | D66: =D58*(1-D42)-(D15+D16+D17+D19)-D28 -> 8.2262093 | E66: =E58*(1-E42)-(E15+E16+E17+E19)-E28 -> 6.5435021 | G66: Se este número ficar abaixo de zero, o preço testado não paga nem o resto do custo variável — nuvem zero não salvaria.
A67: Diferença contra a nuvem que está em Premissas hoje | B67: =B66-B14 -> -30.553971 | C67: =C66-C14 -> -28.44556 | D67: =D66-D14 -> -23.673791 | E67: =E66-E14 -> -25.356498 | G67: Negativo: a nuvem premissada é mais cara do que o preço testado suporta. Positivo: sobra folga.
A69: VEREDICTO | B69: =IF(B58-B20<=0,"✗ não fecha com nenhum volume",IF(B60>0,"✓ fecha e sobra "&TEXT(B60,"R$ 0.00")&" por assinante","✗ faltam "&TEXT(B62-B$9,"#,##0")&" assinantes")) -> ✗ não fecha com nenhum volume | C69: =IF(C58-C20<=0,"✗ não fecha com nenhum volume",IF(C60>0,"✓ fecha e sobra "&TEXT(C60,"R$ 0.00")&" por assinante","✗ faltam "&TEXT(C62-C$9,"#,##0")&" assinantes")) -> ✗ não fecha com nenhum volume | D69: =IF(D58-D20<=0,"✗ não fecha com nenhum volume",IF(D60>0,"✓ fecha e sobra "&TEXT(D60,"R$ 0.00")&" por assinante","✗ faltam "&TEXT(D62-D$9,"#,##0")&" assinantes")) -> ✗ não fecha com nenhum volume | E69: =IF(E58-E20<=0,"✗ não fecha com nenhum volume",IF(E60>0,"✓ fecha e sobra "&TEXT(E60,"R$ 0.00")&" por assinante","✗ faltam "&TEXT(E62-E$9,"#,##0")&" assinantes")) -> ✗ não fecha com nenhum volume
A72: COMO LER ESTA ABA
A73: O preço não é um número só: ele depende de quantas pessoas estão dividindo o custo fixo. Compare as quatro colunas e isso fica evidente — o custo variável por assinante quase não muda, o custo fixo por assinante despenca.
A74: Nos primeiros meses nenhum preço de mercado cobre o custo. Isso não é defeito de precificação: é a conta de uma assinatura mensal com base pequena. Esses meses são pagos por capital, não por preço. Preço alto no lançamento derruba a conversão e piora o caixa.
A75: Os dois itens que mais mexem no preço são a NUVEM POR ASSINANTE PAGANTE e a COMISSÃO DA LOJA. Cada R$ 1 de nuvem por assinante exige cerca de R$ 1,39 de preço, porque imposto, loja e meio de pagamento levam quase 30% do que se cobra.
A76: Hoje a premissa de nuvem por assinante pagante está em R$ 31,90, escrita na célula como 6,40 × 5. Nos quatro momentos da tabela, o preço de R$ 39,90 só se paga se essa nuvem ficar perto de R$ 6,40 — exatamente o número antes da multiplicação. Vale conferir de onde vem o 5: se for usuário por conta, o custo já está por assinante e não deveria ser multiplicado; se for cinco anos, é custo acumulado e não mensal.
A77: A linha de conferência da nuvem existe para você poder confiar nesta aba: ela compara a decomposição daqui com o número que a DRE usa. Se um dia ela sair de zero, alguma fórmula foi sobrescrita.

Sheet Premissas
A2: AZUL = você digita · fundo AMARELO = premissa-chave · PRETO = calculado pelo modelo. Células com marca vermelha no canto têm a fonte do número em comentário. O quadro de pessoas fica na aba Pessoas.
A4: 1. CONTROLES DO MODELO
A5: Ano → | B5: Evolução a.a. | C5: 2026 | D5: 2027 | E5: 2028 | F5: 2029 | G5: 2030
A6: Cenário ativo (1 = Conservador · 2 = Provável · 3 = Agressivo) | B6: 2 | D6: Troque este número e a planilha inteira recalcula no cenário escolhido.
A7: Cenário ativo — nome | B7: =CHOOSE($B$6,"CONSERVADOR","PROVÁVEL","AGRESSIVO") -> PROVÁVEL
A8: Considerar o plano de contratações? (1 = Sim · 0 = Não) | B8: 1 | D8: Com 0, o modelo considera só quem já está contratado (equipe do MVP).
A10: LANÇAMENTO DO APP
A11: Ano de lançamento | B11: 2026
A12: Mês de lançamento (1 = janeiro … 12 = dezembro) | B12: 12 | D12: Brief: app majoritariamente pronto em outubro.
A13: Data de lançamento (calculada) | B13: =DATE($B$11,$B$12,1) -> 46357
A14: Mês nº do lançamento na linha do tempo | B14: =($B$11-2026)*12+$B$12 -> 12
A15: Rampa de maturação da conversão (meses) | B15: 6 | D15: É isto que torna 2026 mais tímido. Coloque 1 para converter no patamar cheio desde o primeiro mês.
A17: PARÂMETROS FINANCEIROS
A18: TMA — taxa mínima de atratividade (a.a.) | B18: 0.25 | D18: Original usava 16% a.a.; 25% reflete risco de startup pré-receita.
A19: TMA equivalente mensal | B19: =(1+$B$18)^(1/12)-1 -> 0.018769265
A20: Payback desejado (meses) — critério de decisão | B20: 36 | D20: Critério Go/No-Go.
A22: 2. TRIBUTAÇÃO
A23: Regime (1 = Simples Anexo III · 2 = Simples Anexo V · 3 = Lucro Presumido) | B23: 2 | D23: ⚠ Padrão = 2 (Anexo V). O Fator R do quadro atual fica muito abaixo de 28%, então o Anexo III não está disponível. Veja a conferência na aba Pessoas.
A24: Alíquota Lucro Presumido / acima do teto do Simples | B24: 0.1633 | D24: PIS 0,65 + COFINS 3,00 + ISS 5,00 + IRPJ 4,80 + CSLL 2,88 = 16,33%
A25: Teto do Simples Nacional (RBT12) | B25: 4800000 | D25: LC 123/2006. Acima disso o modelo passa sozinho ao Lucro Presumido.
A27: 3. PREÇOS E MIX DE PLANOS
A28: • São quatro planos, conforme o backlog do produto: Free (gratuito, entra na base de usuários mas não gera receita de assinatura), Essencial, Premium e Família. Os três pagos estão abaixo; o Free é a diferença entre a base ativa e os pagantes, na aba Usuários.
A29: Plano Essencial (R$/mês) · 1 familiar, até 3 cuidadores | B29: 79.9
A30: Plano Premium (R$/mês) · 1 familiar, cuidadores ilimitados | B30: 89.9
A31: Plano Família (R$/mês) · até 4 familiares, cuidadores ilimitados | B31: 109
A32: Reajuste anual de preços (a.a.) | D32: Aplicado a partir de 2027 (IPCA projetado ~4,5%).
A33: Mix de pagantes por plano (% dos assinantes)
A34: Plano Essencial | C34: 1 | D34: 1 | E34: 0.68 | F34: 0.64 | G34: 0.6 | I34: Efeito compromisso (Simonson & Tversky, 1992) + padrão de assinatura B2C de ticket baixo.
A35: Plano Premium | C35: 0 | D35: 0 | E35: 0.24 | F35: 0.26 | G35: 0.28 | I35: Plano-ponte: cresce conforme o Premium ganha valor percebido.
A36: Plano Família | C36: 0 | D36: 0 | E36: 0.08 | F36: 0.1 | G36: 0.12 | I36: Fatia menor mas crescente — ancoragem de preço que sustenta o Intermediário.
A37: Verificação do mix (deve somar 100%) | C37: =SUM(C34:C36) -> 1 | D37: =SUM(D34:D36) -> 1 | E37: =SUM(E34:E36) -> 1 | F37: =SUM(F34:F36) -> 1 | G37: =SUM(G34:G36) -> 1
A38: ARPPU implícita (receita média por assinante pagante) | C38: =(C34*$B$29+C35*$B$30+C36*$B$31)*(1+$B$32)^(C$5-2026) -> 79.9 | D38: =(D34*$B$29+D35*$B$30+D36*$B$31)*(1+$B$32)^(D$5-2026) -> 79.9 | E38: =(E34*$B$29+E35*$B$30+E36*$B$31)*(1+$B$32)^(E$5-2026) -> 84.628 | F38: =(F34*$B$29+F35*$B$30+F36*$B$31)*(1+$B$32)^(F$5-2026) -> 85.41 | G38: =(G34*$B$29+G35*$B$30+G36*$B$31)*(1+$B$32)^(G$5-2026) -> 86.192
A40: 4. DRIVERS POR CENÁRIO
A41: • Cada driver tem 3 linhas — Conservador, Provável e Agressivo. O modelo usa a do cenário ativo.
A42: • Digite o patamar de 2026 na coluna C e a taxa de evolução anual na coluna B: 2027 a 2030 são calculados sozinhos. Quer um ano específico fora da curva? Digite por cima — a célula vira entrada manual e os anos seguintes continuam a partir dela.
A43: Novos usuários captados por mês (média do ano)
A44: Conservador | B44: 0.4 | C44: 10860 | D44: =C44*(1+$B44) -> 15204 | E44: =D44*(1+$B44) -> 21285.6 | F44: =E44*(1+$B44) -> 29799.84 | G44: =F44*(1+$B44) -> 41719.776
A45: Provável | B45: 0.5 | C45: 18100 | D45: =C45*(1+$B45) -> 27150 | E45: =D45*(1+$B45) -> 40725 | F45: =E45*(1+$B45) -> 61087.5 | G45: =F45*(1+$B45) -> 91631.25 | I45: Calibrado para a meta de ~50.000 usuários em dez/2026.
A46: Agressivo | B46: 0.6 | C46: 25340 | D46: =C46*(1+$B46) -> 40544 | E46: =D46*(1+$B46) -> 64870.4 | F46: =E46*(1+$B46) -> 103792.64 | G46: =F46*(1+$B46) -> 166068.22
A47: Churn mensal da base de usuários
A48: Conservador | B48: -0.04 | C48: 0.1 | D48: =C48*(1+$B48) -> 0.096 | E48: =D48*(1+$B48) -> 0.09216 | F48: =E48*(1+$B48) -> 0.0884736 | G48: =F48*(1+$B48) -> 0.084934656
A49: Provável | B49: -0.06 | C49: 0.08 | D49: =C49*(1+$B49) -> 0.0752 | E49: =D49*(1+$B49) -> 0.070688 | F49: =E49*(1+$B49) -> 0.06644672 | G49: =F49*(1+$B49) -> 0.062459917 | I49: Saúde & Fitness: 7–10%/mês (mediana 9,2%). Evolução negativa = churn melhorando.
A50: Agressivo | B50: -0.08 | C50: 0.06 | D50: =C50*(1+$B50) -> 0.0552 | E50: =D50*(1+$B50) -> 0.050784 | F50: =E50*(1+$B50) -> 0.04672128 | G50: =F50*(1+$B50) -> 0.042983578
A51: Taxa de conversão (pagantes ÷ base ativa) — patamar de regime
A52: Conservador | B52: 0.01 | C52: 0.01 | D52: =MIN(0.25,C52*(1+$B52)) -> 0.0101 | E52: =MIN(0.25,D52*(1+$B52)) -> 0.010201 | F52: =MIN(0.25,E52*(1+$B52)) -> 0.01030301 | G52: =MIN(0.25,F52*(1+$B52)) -> 0.01040604
A53: Provável | B53: 0.03 | C53: 0.03 | D53: =MIN(0.25,C53*(1+$B53)) -> 0.0309 | E53: =MIN(0.25,D53*(1+$B53)) -> 0.031827 | F53: =MIN(0.25,E53*(1+$B53)) -> 0.03278181 | G53: =MIN(0.25,F53*(1+$B53)) -> 0.033765264 | I53: Patamar de regime. A rampa (controle 1) segura a conversão nos primeiros meses.
A54: Agressivo | B54: 0.06 | C54: 0.06 | D54: =MIN(0.25,C54*(1+$B54)) -> 0.0636 | E54: =MIN(0.25,D54*(1+$B54)) -> 0.067416 | F54: =MIN(0.25,E54*(1+$B54)) -> 0.07146096 | G54: =MIN(0.25,F54*(1+$B54)) -> 0.075748618
A55: CAC — custo de aquisição por novo usuário (R$)
A56: Conservador | B56: 0.18 | C56: 4 | D56: =C56*(1+$B56) -> 4.72 | E56: =D56*(1+$B56) -> 5.5696 | F56: =E56*(1+$B56) -> 6.572128 | G56: =F56*(1+$B56) -> 7.755111
A57: Provável | B57: 0.15 | C57: 2.5 | D57: =C57*(1+$B57) -> 2.875 | E57: =D57*(1+$B57) -> 3.30625 | F57: =E57*(1+$B57) -> 3.8021875 | G57: =F57*(1+$B57) -> 4.3725156 | I57: CPI Brasil saúde: R$ 1,50–4,00. Sobe com a escala.
A58: Agressivo | B58: 0.15 | C58: 1.5 | D58: =C58*(1+$B58) -> 1.725 | E58: =D58*(1+$B58) -> 1.98375 | F58: =E58*(1+$B58) -> 2.2813125 | G58: =F58*(1+$B58) -> 2.6235094
A59: Aquisição orgânica (% dos novos usuários, sem custo de mídia) | C59: 0.3 | D59: 0.32 | E59: 0.35 | F59: 0.38 | G59: 0.4 | I59: Boca a boca + conteúdo da agência da Shaiane. Reduz a fatia paga com mídia.
A61: 5. MONETIZAÇÃO — CANAIS, TAXAS E RECEITA B2B
A62: Taxa das lojas de aplicativos (App Store / Google Play) | B62: 0.15 | D62: Google Play 15% desde o 1º dia; Apple 15% no Small Business Program.
A63: % da receita de assinaturas cobrada pelas lojas | C63: 0.85 | D63: 0.8 | E63: 0.75 | F63: 0.72 | G63: 0.7 | I63: Migração gradual para checkout web/PIX próprio, que não paga comissão de loja.
A64: Taxa de meio de pagamento (venda direta web/PIX) | B64: 0.045 | D64: Média ponderada de cartão (~4,99%) e PIX (~1,0%).
A65: Receita B2B de dados — o painel
A66: • O dado só vale se houver escala e consentimento. Estas três premissas definem o tamanho do painel comercializável; a tabela logo abaixo define o que se cobra por ele. Enquanto o painel não atingir o mínimo, nenhum contrato de dados gera receita, por mais que a data de início já tenha passado.
A67: % da base que consente compartilhar dados | C67: 1 | D67: 1 | E67: 1 | F67: 1 | G67: 1 | I67: ⚠ Consentimento específico e destacado, separado dos termos do app. Revogável.
A68: Base mínima do painel para ter valor comercial (usuários) | B68: 100000 | D68: Abaixo deste número, a receita de dados é zero, mesmo com contrato na tabela.
A69: Custo de processamento do painel (R$/usuário/mês) | B69: 0.05 | D69: Anonimização, agregação e entrega dos dados. Entra na linha de nuvem.
A70: Considerar iniciativas B2B EM ESTUDO? (1 = Sim · 0 = Não) | B70: 1 | D70: ⚠ Desligado. Liga as linhas marcadas como 'Em estudo' na tabela abaixo.
A71: Iniciativas de receita B2B
A72: Uma linha por iniciativa. As duas primeiras são a venda de dados, já planejada. As demais estão em branco para vocês preencherem — recompra de medicamento de uso crônico, integrações com farmácia, o que vier. Categoria separa o que aparece como 'venda de dados' do que aparece como 'outras iniciativas' na DRE.
A73: Iniciativa | B73: Categoria | C73: Status | D73: Modelo | E73: Valor | F73: Início | G73: Fim
A74: Venda de dados à indústria farmacêutica | B74: Dados | C74: Planejado | D74: Fixo mensal | E74: 3750 | F74: 46478 | G74: 47818 | I74: Modelo 'Fixo mensal': o valor é R$/mês de contrato. 'Por usuário': o valor é R$ por usuário do painel por mês.
A75: Venda de dados a redes de farmácia | B75: Dados | C75: Planejado | D75: Fixo mensal | E75: 2000 | F75: 46661 | G75: 47818
A76: Recompra de medicamento de uso crônico | B76: Outras | C76: Em estudo | D76: Fixo mensal | E76: 0 | F76: 47119 | G76: 47818
B77: Outras | C77: Em estudo | D77: Fixo mensal | E77: 0 | F77: 47119 | G77: 47818
B78: Outras | C78: Em estudo | D78: Fixo mensal | E78: 0 | F78: 47119 | G78: 47818
B79: Outras | C79: Em estudo | D79: Fixo mensal | E79: 0 | F79: 47119 | G79: 47818
B80: Outras | C80: Em estudo | D80: Fixo mensal | E80: 0 | F80: 47119 | G80: 47818
B81: Outras | C81: Em estudo | D81: Fixo mensal | E81: 0 | F81: 47119 | G81: 47818
B82: Outras | C82: Em estudo | D82: Fixo mensal | E82: 0 | F82: 47119 | G82: 47818
A85: Marketplace de dispositivos
A86: Comissão média sobre GMV | B86: 0.1 | D86: Brief: faixa de 5% a 15%. Adotado o ponto médio.
A87: Ticket médio do dispositivo (R$) | B87: 350 | D87: Oxímetro ~R$150, smartwatch de saúde ~R$400, balança/pressão ~R$250.
A88: Taxa de compra mensal (% da base ativa que compra no mês) | C88: 0 | D88: 0.0015 | E88: 0.0025 | F88: 0.004 | G88: 0.005 | I88: Marketplace só entra no ar em 2027. Compra de device é evento raro e de alto ticket.
A90: 6. CUSTOS OPERACIONAIS (exceto pessoas — ver aba Pessoas)
A91: Início dos custos de nuvem | B91: 46143 | D91: Primeiro gasto real registrado: R$ 532,29 em 04/05/2026.
A92: Nuvem — custo fixo mensal (R$) | C92: 600 | D92: 2500 | E92: 8000 | F92: 18000 | G92: 30000 | I92: Base: gasto real de R$ 532,29 em 04/05/2026.
A93: Nuvem — custo variável por usuário PAGANTE (R$/mês) | C93: =6.4*5 -> 32 | D93: 31.9 | E93: 31.9 | F93: 31.9 | G93: 31.9 | I93: Só o pagante gera histórico — premissa do brief.
A94: Nuvem — custo variável por usuário GRATUITO (R$/mês) | C94: 0.02 | D94: 0.02 | E94: 0.018 | F94: 0.015 | G94: 0.015 | I94: Não é zero: ingestão em tempo real e API consomem compute mesmo sem histórico.
A95: Suporte — ferramentas e custo variável por pagante (R$/mês) | C95: 0.35 | D95: 0.35 | E95: 0.3 | F95: 0.28 | G95: 0.25 | I95: Chatbot, help desk e base de conhecimento. As PESSOAS de suporte estão na aba Pessoas.
A96: Início das despesas administrativas | B96: 46113 | D96: A partir da constituição da empresa / primeiro aporte (16/04/2026).
A97: Administrativas (contabilidade, jurídico, ferramentas) — R$/mês | D97: =2000/12 -> 166.66667 | E97: =5000/12 -> 416.66667 | F97: =10000/12 -> 833.33333 | G97: =20000/12 -> 1666.6667 | I97: Não inclui pessoas. Escalonado com o porte da operação.
A98: Marketing recorrente — mídia de conteúdo e ferramentas (R$/mês) | C98: 500 | D98: 5000 | E98: 8000 | F98: 12000 | G98: 15000 | I98: Reduzido pela agência da Shaiane, mas não eliminado.
A99: Início do marketing recorrente | B99: 46327
A100: Propaganda de lançamento — valor único (R$) | B100: 1000
A101: Mês da propaganda de lançamento | B101: 46327
A103: 7. CAPITAL — O QUE ENTRA NA CONTA
A104: • Os investidores em si ficam na aba APORTES, em duas tabelas com linhas em branco: lançamentos de aporte, e investidores estratégicos que além de aportar trazem receita recorrente — o caso da Boston Scientific. Aqui ficam só os dois interruptores que decidem o que o modelo considera.
A105: Considerar aportes PREVISTOS? (1 = Sim · 0 = Não) | B105: 1 | D105: Hoje: R$ 120 mil de C-ioT, Martinelli e Shaiane. Desligue para ver só os fundadores.
A106: Considerar acordos EM NEGOCIAÇÃO? (1 = Sim · 0 = Não) | B106: 1 | D106: ⚠ Desligado por padrão. Ligue para incluir a Boston Scientific e qualquer outra parceria em negociação.
A108: 8. NOTAS METODOLÓGICAS
A109: • FCL (Fluxo de Caixa Livre) NÃO inclui aportes de sócios. Aporte é financiamento, não geração de caixa — incluí-lo infla VPL e TIR. A planilha original somava o aporte à receita; aqui os dois fluxos estão separados.
A110: • VPL, TIR e Payback são calculados sobre o FCL. Caixa Acumulado e Runway usam FCL + aportes.
A111: • Rendimento financeiro do caixa não é considerado (premissa conservadora).
A112: • Investimentos saem do caixa no mês do desembolso e são amortizados linearmente em 60 meses na DRE — por isso o EBITDA da DRE difere do fluxo de caixa livre.
A113: • Propaganda de lançamento é despesa de marketing, não investimento — diferente da planilha original, que a colocava em 'Projeto'.
...

Sheet DRE Projetada
A1: DRE PROJETADA — DEMONSTRAÇÃO DO RESULTADO DO EXERCÍCIO
A2: =" Cenário ativo: "&Premissas!B7 -> Cenário ativo: PROVÁVEL
A4: Linha do tempo | B4: 46023 | C4: 46054 | D4: 46082 | E4: 46113 | F4: 46143 | G4: 46174 | H4: 46204 | I4: 46235 | J4: 46266 | K4: 46296 | L4: 46327 | M4: 46357 | N4: 46388 | O4: 46419 | P4: 46447 | Q4: 46478 | R4: 46508 | S4: 46539 | T4: 46569 | U4: 46600 | V4: 46631 | W4: 46661 | X4: 46692 | Y4: 46722 | Z4: 46753 | AA4: 46784 | AB4: 46813 | AC4: 46844 | AD4: 46874 | AE4: 46905 | AF4: 46935 | AG4: 46966 | AH4: 46997 | AI4: 47027 | AJ4: 47058 | AK4: 47088 | AL4: 47119 | AM4: 47150 | AN4: 47178 | AO4: 47209 | AP4: 47239 | AQ4: 47270 | AR4: 47300 | AS4: 47331 | AT4: 47362 | AU4: 47392 | AV4: 47423 | AW4: 47453 | AX4: 47484 | AY4: 47515 | AZ4: 47543 | BA4: 47574 | BB4: 47604 | BC4: 47635 | BD4: 47665 | BE4: 47696 | BF4: 47727 | BG4: 47757 | BH4: 47788 | BI4: 47818 | BJ4: TOTAL | BK4: % / Nota
A5: Mês nº | B5: 1 | C5: 2 | D5: 3 | E5: 4 | F5: 5 | G5: 6 | H5: 7 | I5: 8 | J5: 9 | K5: 10 | L5: 11 | M5: 12 | N5: 13 | O5: 14 | P5: 15 | Q5: 16 | R5: 17 | S5: 18 | T5: 19 | U5: 20 | V5: 21 | W5: 22 | X5: 23 | Y5: 24 | Z5: 25 | AA5: 26 | AB5: 27 | AC5: 28 | AD5: 29 | AE5: 30 | AF5: 31 | AG5: 32 | AH5: 33 | AI5: 34 | AJ5: 35 | AK5: 36 | AL5: 37 | AM5: 38 | AN5: 39 | AO5: 40 | AP5: 41 | AQ5: 42 | AR5: 43 | AS5: 44 | AT5: 45 | AU5: 46 | AV5: 47 | AW5: 48 | AX5: 49 | AY5: 50 | AZ5: 51 | BA5: 52 | BB5: 53 | BC5: 54 | BD5: 55 | BE5: 56 | BF5: 57 | BG5: 58 | BH5: 59 | BI5: 60
A6: Ano | B6: =YEAR(B4) -> 2026 | C6: =YEAR(C4) -> 2026 | D6: =YEAR(D4) -> 2026 | E6: =YEAR(E4) -> 2026 | F6: =YEAR(F4) -> 2026 | G6: =YEAR(G4) -> 2026 | H6: =YEAR(H4) -> 2026 | I6: =YEAR(I4) -> 2026 | ... BI6: =YEAR(BI4) -> 2030
A7: Índice do ano (auxiliar) | B7: =MATCH(B6,Premissas!$C$5:$G$5,0) -> 1 | C7: =MATCH(C6,Premissas!$C$5:$G$5,0) -> 1 | D7: =MATCH(D6,Premissas!$C$5:$G$5,0) -> 1 | E7: =MATCH(E6,Premissas!$C$5:$G$5,0) -> 1 | F7: =MATCH(F6,Premissas!$C$5:$G$5,0) -> 1 | G7: =MATCH(G6,Premissas!$C$5:$G$5,0) -> 1 | H7: =MATCH(H6,Premissas!$C$5:$G$5,0) -> 1 | I7: =MATCH(I6,Premissas!$C$5:$G$5,0) -> 1 | ... BI7: =MATCH(BI6,Premissas!$C$5:$G$5,0) -> 5
A8: RECEITA OPERACIONAL BRUTA
A9: Assinaturas — Plano Essencial | B9: =CHOOSE(Premissas!$B$6,Cenários!B20,Cenários!B66,Cenários!B112) -> 0 | C9: =CHOOSE(Premissas!$B$6,Cenários!C20,Cenários!C66,Cenários!C112) -> 0 | D9: =CHOOSE(Premissas!$B$6,Cenários!D20,Cenários!D66,Cenários!D112) -> 0 | E9: =CHOOSE(Premissas!$B$6,Cenários!E20,Cenários!E66,Cenários!E112) -> 0 | F9: =CHOOSE(Premissas!$B$6,Cenários!F20,Cenários!F66,Cenários!F112) -> 0 | G9: =CHOOSE(Premissas!$B$6,Cenários!G20,Cenários!G66,Cenários!G112) -> 0 | H9: =CHOOSE(Premissas!$B$6,Cenários!H20,Cenários!H66,Cenários!H112) -> 0 | I9: =CHOOSE(Premissas!$B$6,Cenários!I20,Cenários!I66,Cenários!I112) -> 0 | ... BI9: =CHOOSE(Premissas!$B$6,Cenários!BI20,Cenários!BI66,Cenários!BI112) -> 1806139.5 | BJ9: =SUM(B9:BI9) -> 41960684
A10: Assinaturas — Plano Premium | B10: =CHOOSE(Premissas!$B$6,Cenários!B21,Cenários!B67,Cenários!B113) -> 0 | C10: =CHOOSE(Premissas!$B$6,Cenários!C21,Cenários!C67,Cenários!C113) -> 0 | D10: =CHOOSE(Premissas!$B$6,Cenários!D21,Cenários!D67,Cenários!D113) -> 0 | E10: =CHOOSE(Premissas!$B$6,Cenários!E21,Cenários!E67,Cenários!E113) -> 0 | F10: =CHOOSE(Premissas!$B$6,Cenários!F21,Cenários!F67,Cenários!F113) -> 0 | G10: =CHOOSE(Premissas!$B$6,Cenários!G21,Cenários!G67,Cenários!G113) -> 0 | H10: =CHOOSE(Premissas!$B$6,Cenários!H21,Cenários!H67,Cenários!H113) -> 0 | I10: =CHOOSE(Premissas!$B$6,Cenários!I21,Cenários!I67,Cenários!I113) -> 0 | ... BI10: =CHOOSE(Premissas!$B$6,Cenários!BI21,Cenários!BI67,Cenários!BI113) -> 948355.1 | BJ10: =SUM(B10:BI10) -> 18131032
A11: Assinaturas — Plano Família | B11: =CHOOSE(Premissas!$B$6,Cenários!B22,Cenários!B68,Cenários!B114) -> 0 | C11: =CHOOSE(Premissas!$B$6,Cenários!C22,Cenários!C68,Cenários!C114) -> 0 | D11: =CHOOSE(Premissas!$B$6,Cenários!D22,Cenários!D68,Cenários!D114) -> 0 | E11: =CHOOSE(Premissas!$B$6,Cenários!E22,Cenários!E68,Cenários!E114) -> 0 | F11: =CHOOSE(Premissas!$B$6,Cenários!F22,Cenários!F68,Cenários!F114) -> 0 | G11: =CHOOSE(Premissas!$B$6,Cenários!G22,Cenários!G68,Cenários!G114) -> 0 | H11: =CHOOSE(Premissas!$B$6,Cenários!H22,Cenários!H68,Cenários!H114) -> 0 | I11: =CHOOSE(Premissas!$B$6,Cenários!I22,Cenários!I68,Cenários!I114) -> 0 | ... BI11: =CHOOSE(Premissas!$B$6,Cenários!BI22,Cenários!BI68,Cenários!BI114) -> 492789 | BJ11: =SUM(B11:BI11) -> 8792594
A12: Marketplace — comissões | B12: =CHOOSE(Premissas!$B$6,Cenários!B24,Cenários!B70,Cenários!B116) -> 0 | C12: =CHOOSE(Premissas!$B$6,Cenários!C24,Cenários!C70,Cenários!C116) -> 0 | D12: =CHOOSE(Premissas!$B$6,Cenários!D24,Cenários!D70,Cenários!D116) -> 0 | E12: =CHOOSE(Premissas!$B$6,Cenários!E24,Cenários!E70,Cenários!E116) -> 0 | F12: =CHOOSE(Premissas!$B$6,Cenários!F24,Cenários!F70,Cenários!F116) -> 0 | G12: =CHOOSE(Premissas!$B$6,Cenários!G24,Cenários!G70,Cenários!G116) -> 0 | H12: =CHOOSE(Premissas!$B$6,Cenários!H24,Cenários!H70,Cenários!H116) -> 0 | I12: =CHOOSE(Premissas!$B$6,Cenários!I24,Cenários!I70,Cenários!I116) -> 0 | ... BI12: =CHOOSE(Premissas!$B$6,Cenários!BI24,Cenários!BI70,Cenários!BI116) -> 195265.12 | BJ12: =SUM(B12:BI12) -> 3470461.5
A13: B2B — parcerias estratégicas | B13: =CHOOSE(Premissas!$B$6,Cenários!B25,Cenários!B71,Cenários!B117) -> 0 | C13: =CHOOSE(Premissas!$B$6,Cenários!C25,Cenários!C71,Cenários!C117) -> 0 | D13: =CHOOSE(Premissas!$B$6,Cenários!D25,Cenários!D71,Cenários!D117) -> 0 | E13: =CHOOSE(Premissas!$B$6,Cenários!E25,Cenários!E71,Cenários!E117) -> 0 | F13: =CHOOSE(Premissas!$B$6,Cenários!F25,Cenários!F71,Cenários!F117) -> 0 | G13: =CHOOSE(Premissas!$B$6,Cenários!G25,Cenários!G71,Cenários!G117) -> 0 | H13: =CHOOSE(Premissas!$B$6,Cenários!H25,Cenários!H71,Cenários!H117) -> 0 | I13: =CHOOSE(Premissas!$B$6,Cenários!I25,Cenários!I71,Cenários!I117) -> 0 | ... BI13: =CHOOSE(Premissas!$B$6,Cenários!BI25,Cenários!BI71,Cenários!BI117) -> 5000 | BJ13: =SUM(B13:BI13) -> 230000
A14: B2B — venda de dados | B14: =CHOOSE(Premissas!$B$6,Cenários!B26,Cenários!B72,Cenários!B118) -> 0 | C14: =CHOOSE(Premissas!$B$6,Cenários!C26,Cenários!C72,Cenários!C118) -> 0 | D14: =CHOOSE(Premissas!$B$6,Cenários!D26,Cenários!D72,Cenários!D118) -> 0 | E14: =CHOOSE(Premissas!$B$6,Cenários!E26,Cenários!E72,Cenários!E118) -> 0 | F14: =CHOOSE(Premissas!$B$6,Cenários!F26,Cenários!F72,Cenários!F118) -> 0 | G14: =CHOOSE(Premissas!$B$6,Cenários!G26,Cenários!G72,Cenários!G118) -> 0 | H14: =CHOOSE(Premissas!$B$6,Cenários!H26,Cenários!H72,Cenários!H118) -> 0 | I14: =CHOOSE(Premissas!$B$6,Cenários!I26,Cenários!I72,Cenários!I118) -> 0 | ... BI14: =CHOOSE(Premissas!$B$6,Cenários!BI26,Cenários!BI72,Cenários!BI118) -> 5750 | BJ14: =SUM(B14:BI14) -> 246750 | BK14: Contratos da tabela de iniciativas B2B em Premissas, categoria Dados.
A15: B2B — outras iniciativas | B15: =CHOOSE(Premissas!$B$6,Cenários!B27,Cenários!B73,Cenários!B119) -> 0 | C15: =CHOOSE(Premissas!$B$6,Cenários!C27,Cenários!C73,Cenários!C119) -> 0 | D15: =CHOOSE(Premissas!$B$6,Cenários!D27,Cenários!D73,Cenários!D119) -> 0 | E15: =CHOOSE(Premissas!$B$6,Cenários!E27,Cenários!E73,Cenários!E119) -> 0 | F15: =CHOOSE(Premissas!$B$6,Cenários!F27,Cenários!F73,Cenários!F119) -> 0 | G15: =CHOOSE(Premissas!$B$6,Cenários!G27,Cenários!G73,Cenários!G119) -> 0 | H15: =CHOOSE(Premissas!$B$6,Cenários!H27,Cenários!H73,Cenários!H119) -> 0 | I15: =CHOOSE(Premissas!$B$6,Cenários!I27,Cenários!I73,Cenários!I119) -> 0 | ... BI15: =CHOOSE(Premissas!$B$6,Cenários!BI27,Cenários!BI73,Cenários!BI119) -> 0 | BJ15: =SUM(B15:BI15) -> 0
A16: (=) RECEITA BRUTA | B16: =SUM(B9:B15) -> 0 | C16: =SUM(C9:C15) -> 0 | D16: =SUM(D9:D15) -> 0 | E16: =SUM(E9:E15) -> 0 | F16: =SUM(F9:F15) -> 0 | G16: =SUM(G9:G15) -> 0 | H16: =SUM(H9:H15) -> 0 | I16: =SUM(I9:I15) -> 0 | ... BI16: =SUM(BI9:BI15) -> 3453298.7 | BJ16: =SUM(B16:BI16) -> 72831521
A18: DEDUÇÕES DA RECEITA BRUTA
A19: (−) Impostos sobre a receita (Simples / Lucro Presumido) | B19: =CHOOSE(Premissas!$B$6,Cenários!B31,Cenários!B77,Cenários!B123) -> 0 | C19: =CHOOSE(Premissas!$B$6,Cenários!C31,Cenários!C77,Cenários!C123) -> 0 | D19: =CHOOSE(Premissas!$B$6,Cenários!D31,Cenários!D77,Cenários!D123) -> 0 | E19: =CHOOSE(Premissas!$B$6,Cenários!E31,Cenários!E77,Cenários!E123) -> 0 | F19: =CHOOSE(Premissas!$B$6,Cenários!F31,Cenários!F77,Cenários!F123) -> 0 | G19: =CHOOSE(Premissas!$B$6,Cenários!G31,Cenários!G77,Cenários!G123) -> 0 | H19: =CHOOSE(Premissas!$B$6,Cenários!H31,Cenários!H77,Cenários!H123) -> 0 | I19: =CHOOSE(Premissas!$B$6,Cenários!I31,Cenários!I77,Cenários!I123) -> 0 | ... BI19: =CHOOSE(Premissas!$B$6,Cenários!BI31,Cenários!BI77,Cenários!BI123) -> -563923.68 | BJ19: =SUM(B19:BI19) -> -12004991 | BK19: =IFERROR(BJ19/BJ$16,0) -> -0.16483236
A20: (−) Comissão das lojas de aplicativos | B20: =CHOOSE(Premissas!$B$6,Cenários!B32,Cenários!B78,Cenários!B124) -> 0 | C20: =CHOOSE(Premissas!$B$6,Cenários!C32,Cenários!C78,Cenários!C124) -> 0 | D20: =CHOOSE(Premissas!$B$6,Cenários!D32,Cenários!D78,Cenários!D124) -> 0 | E20: =CHOOSE(Premissas!$B$6,Cenários!E32,Cenários!E78,Cenários!E124) -> 0 | F20: =CHOOSE(Premissas!$B$6,Cenários!F32,Cenários!F78,Cenários!F124) -> 0 | G20: =CHOOSE(Premissas!$B$6,Cenários!G32,Cenários!G78,Cenários!G124) -> 0 | H20: =CHOOSE(Premissas!$B$6,Cenários!H32,Cenários!H78,Cenários!H124) -> 0 | I20: =CHOOSE(Premissas!$B$6,Cenários!I32,Cenários!I78,Cenários!I124) -> 0 | ... BI20: =CHOOSE(Premissas!$B$6,Cenários!BI32,Cenários!BI78,Cenários!BI124) -> -340964.78 | BJ20: =SUM(B20:BI20) -> -7439957.6 | BK20: Apple/Google. A maior dedução isolada da receita de assinatura.
A21: (−) Taxas de meios de pagamento | B21: =CHOOSE(Premissas!$B$6,Cenários!B33,Cenários!B79,Cenários!B125) -> 0 | C21: =CHOOSE(Premissas!$B$6,Cenários!C33,Cenários!C79,Cenários!C125) -> 0 | D21: =CHOOSE(Premissas!$B$6,Cenários!D33,Cenários!D79,Cenários!D125) -> 0 | E21: =CHOOSE(Premissas!$B$6,Cenários!E33,Cenários!E79,Cenários!E125) -> 0 | F21: =CHOOSE(Premissas!$B$6,Cenários!F33,Cenários!F79,Cenários!F125) -> 0 | G21: =CHOOSE(Premissas!$B$6,Cenários!G33,Cenários!G79,Cenários!G125) -> 0 | H21: =CHOOSE(Premissas!$B$6,Cenários!H33,Cenários!H79,Cenários!H125) -> 0 | I21: =CHOOSE(Premissas!$B$6,Cenários!I33,Cenários!I79,Cenários!I125) -> 0 | ... BI21: =CHOOSE(Premissas!$B$6,Cenários!BI33,Cenários!BI79,Cenários!BI125) -> -52625.259 | BJ21: =SUM(B21:BI21) -> -1023977.4 | BK21: =IFERROR(BJ21/BJ$16,0) -> -0.014059536
A22: (=) RECEITA OPERACIONAL LÍQUIDA | B22: =B16+SUM(B19:B21) -> 0 | C22: =C16+SUM(C19:C21) -> 0 | D22: =D16+SUM(D19:D21) -> 0 | E22: =E16+SUM(E19:E21) -> 0 | F22: =F16+SUM(F19:F21) -> 0 | G22: =G16+SUM(G19:G21) -> 0 | H22: =H16+SUM(H19:H21) -> 0 | I22: =I16+SUM(I19:I21) -> 0 | ... BI22: =BI16+SUM(BI19:BI21) -> 2495785 | BJ22: =SUM(B22:BI22) -> 52362595 | BK22: =IFERROR(BJ22/BJ$16,0) -> 0.71895512
A24: CUSTO DOS SERVIÇOS PRESTADOS
A25: (−) Infraestrutura e nuvem | B25: =CHOOSE(Premissas!$B$6,Cenários!B35,Cenários!B81,Cenários!B127) -> 0 | C25: =CHOOSE(Premissas!$B$6,Cenários!C35,Cenários!C81,Cenários!C127) -> 0 | D25: =CHOOSE(Premissas!$B$6,Cenários!D35,Cenários!D81,Cenários!D127) -> 0 | E25: =CHOOSE(Premissas!$B$6,Cenários!E35,Cenários!E81,Cenários!E127) -> 0 | F25: =CHOOSE(Premissas!$B$6,Cenários!F35,Cenários!F81,Cenários!F127) -> -600 | G25: =CHOOSE(Premissas!$B$6,Cenários!G35,Cenários!G81,Cenários!G127) -> -600 | H25: =CHOOSE(Premissas!$B$6,Cenários!H35,Cenários!H81,Cenários!H127) -> -600 | I25: =CHOOSE(Premissas!$B$6,Cenários!I35,Cenários!I81,Cenários!I127) -> -600 | ... BI25: =CHOOSE(Premissas!$B$6,Cenários!BI35,Cenários!BI81,Cenários!BI127) -> -1303794.4 | BJ25: =SUM(B25:BI25) -> -28065492 | BK25: =IFERROR(BJ25/BJ$16,0) -> -0.38534816
A26: (−) Suporte ao cliente | B26: =CHOOSE(Premissas!$B$6,Cenários!B36,Cenários!B82,Cenários!B128) -> 0 | C26: =CHOOSE(Premissas!$B$6,Cenários!C36,Cenários!C82,Cenários!C128) -> 0 | D26: =CHOOSE(Premissas!$B$6,Cenários!D36,Cenários!D82,Cenários!D128) -> 0 | E26: =CHOOSE(Premissas!$B$6,Cenários!E36,Cenários!E82,Cenários!E128) -> 0 | F26: =CHOOSE(Premissas!$B$6,Cenários!F36,Cenários!F82,Cenários!F128) -> 0 | G26: =CHOOSE(Premissas!$B$6,Cenários!G36,Cenários!G82,Cenários!G128) -> 0 | H26: =CHOOSE(Premissas!$B$6,Cenários!H36,Cenários!H82,Cenários!H128) -> 0 | I26: =CHOOSE(Premissas!$B$6,Cenários!I36,Cenários!I82,Cenários!I128) -> 0 | ... BI26: =CHOOSE(Premissas!$B$6,Cenários!BI36,Cenários!BI82,Cenários!BI128) -> -9418.75 | BJ26: =SUM(B26:BI26) -> -220784.51 | BK26: =IFERROR(BJ26/BJ$16,0) -> -0.0030314417
A27: (=) LUCRO BRUTO | B27: =B22+B25+B26 -> 0 | C27: =C22+C25+C26 -> 0 | D27: =D22+D25+D26 -> 0 | E27: =E22+E25+E26 -> 0 | F27: =F22+F25+F26 -> -600 | G27: =G22+G25+G26 -> -600 | H27: =H22+H25+H26 -> -600 | I27: =I22+I25+I26 -> -600 | ... BI27: =BI22+BI25+BI26 -> 1182571.8 | BJ27: =SUM(B27:BI27) -> 24076318
A28: Margem bruta (% da receita líquida) | B28: =IFERROR(B27/B22,0) -> 0 | C28: =IFERROR(C27/C22,0) -> 0 | D28: =IFERROR(D27/D22,0) -> 0 | E28: =IFERROR(E27/E22,0) -> 0 | F28: =IFERROR(F27/F22,0) -> 0 | G28: =IFERROR(G27/G22,0) -> 0 | H28: =IFERROR(H27/H22,0) -> 0 | I28: =IFERROR(I27/I22,0) -> 0 | ... BJ28: =IFERROR(BJ27/BJ22,0) -> 0.45979994
A30: DESPESAS OPERACIONAIS
A31: (−) Pessoal — equipe PJ, CLT e pró-labore | B31: ='Análise Fluxo'!B18+'Análise Fluxo'!B19+'Análise Fluxo'!B20 -> 0 | C31: ='Análise Fluxo'!C18+'Análise Fluxo'!C19+'Análise Fluxo'!C20 -> 0 | D31: ='Análise Fluxo'!D18+'Análise Fluxo'!D19+'Análise Fluxo'!D20 -> 0 | E31: ='Análise Fluxo'!E18+'Análise Fluxo'!E19+'Análise Fluxo'!E20 -> 0 | F31: ='Análise Fluxo'!F18+'Análise Fluxo'!F19+'Análise Fluxo'!F20 -> 0 | G31: ='Análise Fluxo'!G18+'Análise Fluxo'!G19+'Análise Fluxo'!G20 -> 0 | H31: ='Análise Fluxo'!H18+'Análise Fluxo'!H19+'Análise Fluxo'!H20 -> 0 | I31: ='Análise Fluxo'!I18+'Análise Fluxo'!I19+'Análise Fluxo'!I20 -> 0 | ... BI31: ='Análise Fluxo'!BI18+'Análise Fluxo'!BI19+'Análise Fluxo'!BI20 -> -374300 | BJ31: =SUM(B31:BI31) -> -9451200 | BK31: =IFERROR(BJ31/BJ$16,0) -> -0.12976799
A32: (−) Marketing e aquisição | B32: ='Análise Fluxo'!B21+'Análise Fluxo'!B22+'Análise Fluxo'!B23 -> 0 | C32: ='Análise Fluxo'!C21+'Análise Fluxo'!C22+'Análise Fluxo'!C23 -> 0 | D32: ='Análise Fluxo'!D21+'Análise Fluxo'!D22+'Análise Fluxo'!D23 -> 0 | E32: ='Análise Fluxo'!E21+'Análise Fluxo'!E22+'Análise Fluxo'!E23 -> 0 | F32: ='Análise Fluxo'!F21+'Análise Fluxo'!F22+'Análise Fluxo'!F23 -> 0 | G32: ='Análise Fluxo'!G21+'Análise Fluxo'!G22+'Análise Fluxo'!G23 -> 0 | H32: ='Análise Fluxo'!H21+'Análise Fluxo'!H22+'Análise Fluxo'!H23 -> 0 | I32: ='Análise Fluxo'!I21+'Análise Fluxo'!I22+'Análise Fluxo'!I23 -> 0 | ... BI32: ='Análise Fluxo'!BI21+'Análise Fluxo'!BI22+'Análise Fluxo'!BI23 -> -255395.44 | BJ32: =SUM(B32:BI32) -> -6813666.2 | BK32: Inclui a propaganda de lançamento, tratada como despesa e não como investimento.
A33: (−) Despesas administrativas | B33: ='Análise Fluxo'!B27 -> 0 | C33: ='Análise Fluxo'!C27 -> 0 | D33: ='Análise Fluxo'!D27 -> 0 | E33: ='Análise Fluxo'!E27 -> 0 | F33: ='Análise Fluxo'!F27 -> 0 | G33: ='Análise Fluxo'!G27 -> 0 | H33: ='Análise Fluxo'!H27 -> 0 | I33: ='Análise Fluxo'!I27 -> 0 | ... BI33: ='Análise Fluxo'!BI27 -> -1666.6667 | BJ33: =SUM(B33:BI33) -> -37000 | BK33: =IFERROR(BJ33/BJ$16,0) -> -0.00050802179
A34: (=) EBITDA | B34: =B27+SUM(B31:B33) -> 0 | C34: =C27+SUM(C31:C33) -> 0 | D34: =D27+SUM(D31:D33) -> 0 | E34: =E27+SUM(E31:E33) -> 0 | F34: =F27+SUM(F31:F33) -> -600 | G34: =G27+SUM(G31:G33) -> -600 | H34: =H27+SUM(H31:H33) -> -600 | I34: =I27+SUM(I31:I33) -> -600 | ... BI34: =BI27+SUM(BI31:BI33) -> 551209.7 | BJ34: =SUM(B34:BI34) -> 7774451.7
A35: Margem EBITDA (% da receita líquida) | B35: =IFERROR(B34/B22,0) -> 0 | C35: =IFERROR(C34/C22,0) -> 0 | D35: =IFERROR(D34/D22,0) -> 0 | E35: =IFERROR(E34/E22,0) -> 0 | F35: =IFERROR(F34/F22,0) -> 0 | G35: =IFERROR(G34/G22,0) -> 0 | H35: =IFERROR(H34/H22,0) -> 0 | I35: =IFERROR(I34/I22,0) -> 0 | ... BJ35: =IFERROR(BJ34/BJ22,0) -> 0.14847339
A37: RESULTADO
A38: (−) Depreciação e amortização | B38: =-Investimentos!B30 -> 0 | C38: =-Investimentos!C30 -> 0 | D38: =-Investimentos!D30 -> 0 | E38: =-Investimentos!E30 -> 0 | F38: =-Investimentos!F30 -> 0 | G38: =-Investimentos!G30 -> -100 | H38: =-Investimentos!H30 -> -100 | I38: =-Investimentos!I30 -> -100 | ... BI38: =-Investimentos!BI30 -> -2068.797 | BJ38: =SUM(B38:BI38) -> -62285.777 | BK38: Investimentos amortizados linearmente em 60 meses.
A39: (=) EBIT — resultado operacional | B39: =B34+B38 -> 0 | C39: =C34+C38 -> 0 | D39: =D34+D38 -> 0 | E39: =E34+E38 -> 0 | F39: =F34+F38 -> -600 | G39: =G34+G38 -> -700 | H39: =H34+H38 -> -700 | I39: =I34+I38 -> -700 | ... BI39: =BI34+BI38 -> 549140.91 | BJ39: =SUM(B39:BI39) -> 7712166
A40: (+/−) Resultado financeiro | B40: =0 -> 0 | C40: =0 -> 0 | D40: =0 -> 0 | E40: =0 -> 0 | F40: =0 -> 0 | G40: =0 -> 0 | H40: =0 -> 0 | I40: =0 -> 0 | ... BI40: =0 -> 0 | BJ40: =SUM(B40:BI40) -> 0 | BK40: Rendimento do caixa não considerado (premissa conservadora).
A41: (=) RESULTADO ANTES DO IR | B41: =B39+B40 -> 0 | C41: =C39+C40 -> 0 | D41: =D39+D40 -> 0 | E41: =E39+E40 -> 0 | F41: =F39+F40 -> -600 | G41: =G39+G40 -> -700 | H41: =H39+H40 -> -700 | I41: =I39+I40 -> -700 | ... BI41: =BI39+BI40 -> 549140.91 | BJ41: =SUM(B41:BI41) -> 7712166
A42: (−) IRPJ e CSLL | B42: =0 -> 0 | C42: =0 -> 0 | D42: =0 -> 0 | E42: =0 -> 0 | F42: =0 -> 0 | G42: =0 -> 0 | H42: =0 -> 0 | I42: =0 -> 0 | ... BI42: =0 -> 0 | BJ42: =SUM(B42:BI42) -> 0 | BK42: Já incluídos na linha de impostos sobre a receita (DAS do Simples ou Lucro Presumido).
A43: (=) LUCRO LÍQUIDO DO EXERCÍCIO | B43: =B41+B42 -> 0 | C43: =C41+C42 -> 0 | D43: =D41+D42 -> 0 | E43: =E41+E42 -> 0 | F43: =F41+F42 -> -600 | G43: =G41+G42 -> -700 | H43: =H41+H42 -> -700 | I43: =I41+I42 -> -700 | ... BI43: =BI41+BI42 -> 549140.91 | BJ43: =SUM(B43:BI43) -> 7712166
A44: Margem líquida (% da receita líquida) | B44: =IFERROR(B43/B22,0) -> 0 | C44: =IFERROR(C43/C22,0) -> 0 | D44: =IFERROR(D43/D22,0) -> 0 | E44: =IFERROR(E43/E22,0) -> 0 | F44: =IFERROR(F43/F22,0) -> 0 | G44: =IFERROR(G43/G22,0) -> 0 | H44: =IFERROR(H43/H22,0) -> 0 | I44: =IFERROR(I43/I22,0) -> 0 | ... BJ44: =IFERROR(BJ43/BJ22,0) -> 0.14728388
A45: Lucro líquido acumulado | B45: =B43 -> 0 | C45: =B45+C43 -> 0 | D45: =C45+D43 -> 0 | E45: =D45+E43 -> 0 | F45: =E45+F43 -> -600 | G45: =F45+G43 -> -1300 | H45: =G45+H43 -> -2000 | I45: =H45+I43 -> -2700 | J45: =I45+J43 -> -3552.1303 | ... BI45: =BH45+BI43 -> 7712166
A47: DRE ANUAL CONSOLIDADA
A48: Demonstração do Resultado | B48: 2026 | C48: 2027 | D48: 2028 | E48: 2029 | F48: 2030 | G48: 5 ANOS
A49: RECEITA BRUTA | B49: =SUMIFS($B$16:$BI$16,$B$6:$BI$6,B$48) -> 7191 | C49: =SUMIFS($B$16:$BI$16,$B$6:$BI$6,C$48) -> 4266370.6 | D49: =SUMIFS($B$16:$BI$16,$B$6:$BI$6,D$48) -> 11883042 | E49: =SUMIFS($B$16:$BI$16,$B$6:$BI$6,E$48) -> 21235019 | F49: =SUMIFS($B$16:$BI$16,$B$6:$BI$6,F$48) -> 35439898 | G49: =SUM(B49:F49) -> 72831521
A50: (−) Impostos sobre a receita | B50: =SUMIFS($B$19:$BI$19,$B$6:$BI$6,B$48) -> -1114.605 | C50: =SUMIFS($B$19:$BI$19,$B$6:$BI$6,C$48) -> -797617.1 | D50: =SUMIFS($B$19:$BI$19,$B$6:$BI$6,D$48) -> -1951245.6 | E50: =SUMIFS($B$19:$BI$19,$B$6:$BI$6,E$48) -> -3467678.6 | F50: =SUMIFS($B$19:$BI$19,$B$6:$BI$6,F$48) -> -5787335.4 | G50: =SUM(B50:F50) -> -12004991
A51: (−) Comissão das lojas de aplicativos | B51: =SUMIFS($B$20:$BI$20,$B$6:$BI$6,B$48) -> -916.8525 | C51: =SUMIFS($B$20:$BI$20,$B$6:$BI$6,C$48) -> -490071.44 | D51: =SUMIFS($B$20:$BI$20,$B$6:$BI$6,D$48) -> -1280724 | E51: =SUMIFS($B$20:$BI$20,$B$6:$BI$6,E$48) -> -2170901.1 | F51: =SUMIFS($B$20:$BI$20,$B$6:$BI$6,F$48) -> -3497344.2 | G51: =SUM(B51:F51) -> -7439957.6
A52: (−) Taxas de meios de pagamento | B52: =SUMIFS($B$21:$BI$21,$B$6:$BI$6,B$48) -> -48.53925 | C52: =SUMIFS($B$21:$BI$21,$B$6:$BI$6,C$48) -> -40926.493 | D52: =SUMIFS($B$21:$BI$21,$B$6:$BI$6,D$48) -> -144714.72 | E52: =SUMIFS($B$21:$BI$21,$B$6:$BI$6,E$48) -> -298500.5 | F52: =SUMIFS($B$21:$BI$21,$B$6:$BI$6,F$48) -> -539787.15 | G52: =SUM(B52:F52) -> -1023977.4
A53: (=) RECEITA LÍQUIDA | B53: =SUMIFS($B$22:$BI$22,$B$6:$BI$6,B$48) -> 5111.0032 | C53: =SUMIFS($B$22:$BI$22,$B$6:$BI$6,C$48) -> 2937755.6 | D53: =SUMIFS($B$22:$BI$22,$B$6:$BI$6,D$48) -> 8506358.2 | E53: =SUMIFS($B$22:$BI$22,$B$6:$BI$6,E$48) -> 15297939 | F53: =SUMIFS($B$22:$BI$22,$B$6:$BI$6,F$48) -> 25615431 | G53: =SUM(B53:F53) -> 52362595
A54: (−) Infraestrutura e nuvem | B54: =SUMIFS($B$25:$BI$25,$B$6:$BI$6,B$48) -> -8040.2 | C54: =SUMIFS($B$25:$BI$25,$B$6:$BI$6,C$48) -> -1773000.6 | D54: =SUMIFS($B$25:$BI$25,$B$6:$BI$6,D$48) -> -4672208.9 | E54: =SUMIFS($B$25:$BI$25,$B$6:$BI$6,E$48) -> -8186684.4 | F54: =SUMIFS($B$25:$BI$25,$B$6:$BI$6,F$48) -> -13425558 | G54: =SUM(B54:F54) -> -28065492
A55: (−) Suporte ao cliente | B55: =SUMIFS($B$26:$BI$26,$B$6:$BI$6,B$48) -> -31.5 | C55: =SUMIFS($B$26:$BI$26,$B$6:$BI$6,C$48) -> -17889.55 | D55: =SUMIFS($B$26:$BI$26,$B$6:$BI$6,D$48) -> -40356.3 | E55: =SUMIFS($B$26:$BI$26,$B$6:$BI$6,E$48) -> -65897.16 | F55: =SUMIFS($B$26:$BI$26,$B$6:$BI$6,F$48) -> -96610 | G55: =SUM(B55:F55) -> -220784.51
A56: (=) LUCRO BRUTO | B56: =SUMIFS($B$27:$BI$27,$B$6:$BI$6,B$48) -> -2960.6968 | C56: =SUMIFS($B$27:$BI$27,$B$6:$BI$6,C$48) -> 1146865.4 | D56: =SUMIFS($B$27:$BI$27,$B$6:$BI$6,D$48) -> 3793793.1 | E56: =SUMIFS($B$27:$BI$27,$B$6:$BI$6,E$48) -> 7045356.9 | F56: =SUMIFS($B$27:$BI$27,$B$6:$BI$6,F$48) -> 12093263 | G56: =SUM(B56:F56) -> 24076318
A57: Margem bruta | B57: =IFERROR(B56/B53,0) -> -0.57927898 | C57: =IFERROR(C56/C53,0) -> 0.39038829 | D57: =IFERROR(D56/D53,0) -> 0.44599498 | E57: =IFERROR(E56/E53,0) -> 0.4605429 | F57: =IFERROR(F56/F53,0) -> 0.47210851 | G57: =IFERROR(G56/G53,0) -> 0.45979994
A58: (−) Pessoal | B58: =SUMIFS($B$31:$BI$31,$B$6:$BI$6,B$48) -> 0 | C58: =SUMIFS($B$31:$BI$31,$B$6:$BI$6,C$48) -> -510000 | D58: =SUMIFS($B$31:$BI$31,$B$6:$BI$6,D$48) -> -1410000 | E58: =SUMIFS($B$31:$BI$31,$B$6:$BI$6,E$48) -> -3039600 | F58: =SUMIFS($B$31:$BI$31,$B$6:$BI$6,F$48) -> -4491600 | G58: =SUM(B58:F58) -> -9451200
A59: (−) Marketing e aquisição | B59: =SUMIFS($B$32:$BI$32,$B$6:$BI$6,B$48) -> -33675 | C59: =SUMIFS($B$32:$BI$32,$B$6:$BI$6,C$48) -> -696939 | D59: =SUMIFS($B$32:$BI$32,$B$6:$BI$6,D$48) -> -1146246.8 | E59: =SUMIFS($B$32:$BI$32,$B$6:$BI$6,E$48) -> -1872060 | F59: =SUMIFS($B$32:$BI$32,$B$6:$BI$6,F$48) -> -3064745.3 | G59: =SUM(B59:F59) -> -6813666.2
A60: (−) Despesas administrativas | B60: =SUMIFS($B$33:$BI$33,$B$6:$BI$6,B$48) -> 0 | C60: =SUMIFS($B$33:$BI$33,$B$6:$BI$6,C$48) -> -2000 | D60: =SUMIFS($B$33:$BI$33,$B$6:$BI$6,D$48) -> -5000 | E60: =SUMIFS($B$33:$BI$33,$B$6:$BI$6,E$48) -> -10000 | F60: =SUMIFS($B$33:$BI$33,$B$6:$BI$6,F$48) -> -20000 | G60: =SUM(B60:F60) -> -37000
A61: (=) EBITDA | B61: =SUMIFS($B$34:$BI$34,$B$6:$BI$6,B$48) -> -36635.697 | C61: =SUMIFS($B$34:$BI$34,$B$6:$BI$6,C$48) -> -62073.633 | D61: =SUMIFS($B$34:$BI$34,$B$6:$BI$6,D$48) -> 1232546.2 | E61: =SUMIFS($B$34:$BI$34,$B$6:$BI$6,E$48) -> 2123696.9 | F61: =SUMIFS($B$34:$BI$34,$B$6:$BI$6,F$48) -> 4516917.9 | G61: =SUM(B61:F61) -> 7774451.7
A62: Margem EBITDA | B62: =IFERROR(B61/B53,0) -> -7.168005 | C62: =IFERROR(C61/C53,0) -> -0.021129611 | D62: =IFERROR(D61/D53,0) -> 0.14489705 | E62: =IFERROR(E61/E53,0) -> 0.13882243 | F62: =IFERROR(F61/F53,0) -> 0.17633581 | G62: =IFERROR(G61/G53,0) -> 0.14847339
A63: (−) Depreciação e amortização | B63: =SUMIFS($B$38:$BI$38,$B$6:$BI$6,B$48) -> -2183.5213 | C63: =SUMIFS($B$38:$BI$38,$B$6:$BI$6,C$48) -> -9625.564 | D63: =SUMIFS($B$38:$BI$38,$B$6:$BI$6,D$48) -> -12325.564 | E63: =SUMIFS($B$38:$BI$38,$B$6:$BI$6,E$48) -> -16325.564 | F63: =SUMIFS($B$38:$BI$38,$B$6:$BI$6,F$48) -> -21825.564 | G63: =SUM(B63:F63) -> -62285.777
A64: (=) EBIT | B64: =SUMIFS($B$39:$BI$39,$B$6:$BI$6,B$48) -> -38819.218 | C64: =SUMIFS($B$39:$BI$39,$B$6:$BI$6,C$48) -> -71699.197 | D64: =SUMIFS($B$39:$BI$39,$B$6:$BI$6,D$48) -> 1220220.7 | E64: =SUMIFS($B$39:$BI$39,$B$6:$BI$6,E$48) -> 2107371.4 | F64: =SUMIFS($B$39:$BI$39,$B$6:$BI$6,F$48) -> 4495092.4 | G64: =SUM(B64:F64) -> 7712166
A65: (=) LUCRO LÍQUIDO | B65: =SUMIFS($B$43:$BI$43,$B$6:$BI$6,B$48) -> -38819.218 | C65: =SUMIFS($B$43:$BI$43,$B$6:$BI$6,C$48) -> -71699.197 | D65: =SUMIFS($B$43:$BI$43,$B$6:$BI$6,D$48) -> 1220220.7 | E65: =SUMIFS($B$43:$BI$43,$B$6:$BI$6,E$48) -> 2107371.4 | F65: =SUMIFS($B$43:$BI$43,$B$6:$BI$6,F$48) -> 4495092.4 | G65: =SUM(B65:F65) -> 7712166
A66: Margem líquida | B66: =IFERROR(B65/B53,0) -> -7.5952247 | C66: =IFERROR(C65/C53,0) -> -0.024406114 | D66: =IFERROR(D65/D53,0) -> 0.14344807 | E66: =IFERROR(E65/E53,0) -> 0.13775525 | F66: =IFERROR(F65/F53,0) -> 0.17548377 | G66: =IFERROR(G65/G53,0) -> 0.14728388

Sheet Análise Fluxo
A1: ANÁLISE DE FLUXO DE CAIXA E VIABILIDADE
A2: =" Cenário ativo: "&Premissas!B7 -> Cenário ativo: PROVÁVEL
A4: Linha do tempo | B4: 46023 | C4: 46054 | D4: 46082 | E4: 46113 | F4: 46143 | G4: 46174 | H4: 46204 | I4: 46235 | J4: 46266 | K4: 46296 | L4: 46327 | M4: 46357 | N4: 46388 | O4: 46419 | P4: 46447 | Q4: 46478 | R4: 46508 | S4: 46539 | T4: 46569 | U4: 46600 | V4: 46631 | W4: 46661 | X4: 46692 | Y4: 46722 | Z4: 46753 | AA4: 46784 | AB4: 46813 | AC4: 46844 | AD4: 46874 | AE4: 46905 | AF4: 46935 | AG4: 46966 | AH4: 46997 | AI4: 47027 | AJ4: 47058 | AK4: 47088 | AL4: 47119 | AM4: 47150 | AN4: 47178 | AO4: 47209 | AP4: 47239 | AQ4: 47270 | AR4: 47300 | AS4: 47331 | AT4: 47362 | AU4: 47392 | AV4: 47423 | AW4: 47453 | AX4: 47484 | AY4: 47515 | AZ4: 47543 | BA4: 47574 | BB4: 47604 | BC4: 47635 | BD4: 47665 | BE4: 47696 | BF4: 47727 | BG4: 47757 | BH4: 47788 | BI4: 47818 | BJ4: TOTAL | BK4: % / Nota
A5: Mês nº | B5: 1 | C5: 2 | D5: 3 | E5: 4 | F5: 5 | G5: 6 | H5: 7 | I5: 8 | J5: 9 | K5: 10 | L5: 11 | M5: 12 | N5: 13 | O5: 14 | P5: 15 | Q5: 16 | R5: 17 | S5: 18 | T5: 19 | U5: 20 | V5: 21 | W5: 22 | X5: 23 | Y5: 24 | Z5: 25 | AA5: 26 | AB5: 27 | AC5: 28 | AD5: 29 | AE5: 30 | AF5: 31 | AG5: 32 | AH5: 33 | AI5: 34 | AJ5: 35 | AK5: 36 | AL5: 37 | AM5: 38 | AN5: 39 | AO5: 40 | AP5: 41 | AQ5: 42 | AR5: 43 | AS5: 44 | AT5: 45 | AU5: 46 | AV5: 47 | AW5: 48 | AX5: 49 | AY5: 50 | AZ5: 51 | BA5: 52 | BB5: 53 | BC5: 54 | BD5: 55 | BE5: 56 | BF5: 57 | BG5: 58 | BH5: 59 | BI5: 60
A6: Ano | B6: =YEAR(B4) -> 2026 | C6: =YEAR(C4) -> 2026 | D6: =YEAR(D4) -> 2026 | E6: =YEAR(E4) -> 2026 | F6: =YEAR(F4) -> 2026 | G6: =YEAR(G4) -> 2026 | H6: =YEAR(H4) -> 2026 | I6: =YEAR(I4) -> 2026 | ... BI6: =YEAR(BI4) -> 2030
A7: Índice do ano (auxiliar) | B7: =MATCH(B6,Premissas!$C$5:$G$5,0) -> 1 | C7: =MATCH(C6,Premissas!$C$5:$G$5,0) -> 1 | D7: =MATCH(D6,Premissas!$C$5:$G$5,0) -> 1 | E7: =MATCH(E6,Premissas!$C$5:$G$5,0) -> 1 | F7: =MATCH(F6,Premissas!$C$5:$G$5,0) -> 1 | G7: =MATCH(G6,Premissas!$C$5:$G$5,0) -> 1 | H7: =MATCH(H6,Premissas!$C$5:$G$5,0) -> 1 | I7: =MATCH(I6,Premissas!$C$5:$G$5,0) -> 1 | ... BI7: =MATCH(BI6,Premissas!$C$5:$G$5,0) -> 5
A8: PROJETO — INVESTIMENTOS
A9: Desenvolvimento do app (pessoal capitalizado) | B9: =-Investimentos!B24 -> 0 | C9: =-Investimentos!C24 -> 0 | D9: =-Investimentos!D24 -> 0 | E9: =-Investimentos!E24 -> 0 | F9: =-Investimentos!F24 -> 0 | G9: =-Investimentos!G24 -> 0 | H9: =-Investimentos!H24 -> 0 | I9: =-Investimentos!I24 -> 0 | ... BI9: =-Investimentos!BI24 -> 0 | BJ9: =SUM(B9:BI9) -> -21000 | BK9: =IFERROR(BJ9/BJ$13,0) -> 0.16918045
A10: Equipamentos | B10: =-Investimentos!B21 -> 0 | C10: =-Investimentos!C21 -> 0 | D10: =-Investimentos!D21 -> 0 | E10: =-Investimentos!E21 -> 0 | F10: =-Investimentos!F21 -> 0 | G10: =-Investimentos!G21 -> 0 | H10: =-Investimentos!H21 -> 0 | I10: =-Investimentos!I21 -> -9127.82 | ... BI10: =-Investimentos!BI21 -> 0 | BJ10: =SUM(B10:BI10) -> -85127.82 | BK10: =IFERROR(BJ10/BJ$13,0) -> 0.68580774
A11: Constituição, marca e jurídico | B11: =-Investimentos!B22 -> 0 | C11: =-Investimentos!C22 -> 0 | D11: =-Investimentos!D22 -> 0 | E11: =-Investimentos!E22 -> 0 | F11: =-Investimentos!F22 -> -6000 | G11: =-Investimentos!G22 -> 0 | H11: =-Investimentos!H22 -> 0 | I11: =-Investimentos!I22 -> 0 | ... BI11: =-Investimentos!BI22 -> 0 | BJ11: =SUM(B11:BI11) -> -6000 | BK11: =IFERROR(BJ11/BJ$13,0) -> 0.04833727
A12: Certificações e conformidade | B12: =-Investimentos!B23 -> 0 | C12: =-Investimentos!C23 -> 0 | D12: =-Investimentos!D23 -> 0 | E12: =-Investimentos!E23 -> 0 | F12: =-Investimentos!F23 -> 0 | G12: =-Investimentos!G23 -> 0 | H12: =-Investimentos!H23 -> 0 | I12: =-Investimentos!I23 -> 0 | ... BI12: =-Investimentos!BI23 -> 0 | BJ12: =SUM(B12:BI12) -> -12000 | BK12: =IFERROR(BJ12/BJ$13,0) -> 0.096674541
A13: TOTAL PROJETO | B13: =SUM(B9:B12) -> 0 | C13: =SUM(C9:C12) -> 0 | D13: =SUM(D9:D12) -> 0 | E13: =SUM(E9:E12) -> 0 | F13: =SUM(F9:F12) -> -6000 | G13: =SUM(G9:G12) -> 0 | H13: =SUM(H9:H12) -> 0 | I13: =SUM(I9:I12) -> -9127.82 | ... BI13: =SUM(BI9:BI12) -> 0 | BJ13: =SUM(B13:BI13) -> -124127.82
A15: OPERACIONAIS
A16: Infraestrutura e nuvem | B16: =CHOOSE(Premissas!$B$6,Cenários!B35,Cenários!B81,Cenários!B127) -> 0 | C16: =CHOOSE(Premissas!$B$6,Cenários!C35,Cenários!C81,Cenários!C127) -> 0 | D16: =CHOOSE(Premissas!$B$6,Cenários!D35,Cenários!D81,Cenários!D127) -> 0 | E16: =CHOOSE(Premissas!$B$6,Cenários!E35,Cenários!E81,Cenários!E127) -> 0 | F16: =CHOOSE(Premissas!$B$6,Cenários!F35,Cenários!F81,Cenários!F127) -> -600 | G16: =CHOOSE(Premissas!$B$6,Cenários!G35,Cenários!G81,Cenários!G127) -> -600 | H16: =CHOOSE(Premissas!$B$6,Cenários!H35,Cenários!H81,Cenários!H127) -> -600 | I16: =CHOOSE(Premissas!$B$6,Cenários!I35,Cenários!I81,Cenários!I127) -> -600 | ... BI16: =CHOOSE(Premissas!$B$6,Cenários!BI35,Cenários!BI81,Cenários!BI127) -> -1303794.4 | BJ16: =SUM(B16:BI16) -> -28065492 | BK16: =IFERROR(BJ16/BJ$28,0) -> 0.43139804
A17: Suporte ao cliente | B17: =CHOOSE(Premissas!$B$6,Cenários!B36,Cenários!B82,Cenários!B128) -> 0 | C17: =CHOOSE(Premissas!$B$6,Cenários!C36,Cenários!C82,Cenários!C128) -> 0 | D17: =CHOOSE(Premissas!$B$6,Cenários!D36,Cenários!D82,Cenários!D128) -> 0 | E17: =CHOOSE(Premissas!$B$6,Cenários!E36,Cenários!E82,Cenários!E128) -> 0 | F17: =CHOOSE(Premissas!$B$6,Cenários!F36,Cenários!F82,Cenários!F128) -> 0 | G17: =CHOOSE(Premissas!$B$6,Cenários!G36,Cenários!G82,Cenários!G128) -> 0 | H17: =CHOOSE(Premissas!$B$6,Cenários!H36,Cenários!H82,Cenários!H128) -> 0 | I17: =CHOOSE(Premissas!$B$6,Cenários!I36,Cenários!I82,Cenários!I128) -> 0 | ... BI17: =CHOOSE(Premissas!$B$6,Cenários!BI36,Cenários!BI82,Cenários!BI128) -> -9418.75 | BJ17: =SUM(B17:BI17) -> -220784.51 | BK17: =IFERROR(BJ17/BJ$28,0) -> 0.0033937051
A18: Equipe PJ | B18: =-Pessoas!B42 -> 0 | C18: =-Pessoas!C42 -> 0 | D18: =-Pessoas!D42 -> 0 | E18: =-Pessoas!E42 -> 0 | F18: =-Pessoas!F42 -> 0 | G18: =-Pessoas!G42 -> 0 | H18: =-Pessoas!H42 -> 0 | I18: =-Pessoas!I42 -> 0 | ... BI18: =-Pessoas!BI42 -> -342300 | BJ18: =SUM(B18:BI18) -> -8323200 | BK18: =IFERROR(BJ18/BJ$28,0) -> 0.1279369
A19: Equipe CLT (salários e encargos) | B19: =-Pessoas!B43 -> 0 | C19: =-Pessoas!C43 -> 0 | D19: =-Pessoas!D43 -> 0 | E19: =-Pessoas!E43 -> 0 | F19: =-Pessoas!F43 -> 0 | G19: =-Pessoas!G43 -> 0 | H19: =-Pessoas!H43 -> 0 | I19: =-Pessoas!I43 -> 0 | ... BI19: =-Pessoas!BI43 -> 0 | BJ19: =SUM(B19:BI19) -> 0 | BK19: =IFERROR(BJ19/BJ$28,0) -> 0
A20: Pró-labore dos sócios | B20: =-Pessoas!B44 -> 0 | C20: =-Pessoas!C44 -> 0 | D20: =-Pessoas!D44 -> 0 | E20: =-Pessoas!E44 -> 0 | F20: =-Pessoas!F44 -> 0 | G20: =-Pessoas!G44 -> 0 | H20: =-Pessoas!H44 -> 0 | I20: =-Pessoas!I44 -> 0 | ... BI20: =-Pessoas!BI44 -> -32000 | BJ20: =SUM(B20:BI20) -> -1128000 | BK20: =IFERROR(BJ20/BJ$28,0) -> 0.017338623
A21: Marketing de performance (aquisição) | B21: {=-CHOOSE(Premissas!$B$6,Cenários!B10,Cenários!B56,Cenários!B102)*(1-INDEX(Premissas!$C$59:$G$59,B$7))*CHOOSE(Premissas!$B$6,INDEX(Premissas!$C$56:$G$56,B$7),INDEX(Premissas!$C$57:$G$57,B$7),INDEX(Premissas!$C$58:$G$58,B$7))} -> 0 | C21: {=-CHOOSE(Premissas!$B$6,Cenários!C10,Cenários!C56,Cenários!C102)*(1-INDEX(Premissas!$C$59:$G$59,C$7))*CHOOSE(Premissas!$B$6,INDEX(Premissas!$C$56:$G$56,C$7),INDEX(Premissas!$C$57:$G$57,C$7),INDEX(Premissas!$C$58:$G$58,C$7))} -> 0 | D21: {=-CHOOSE(Premissas!$B$6,Cenários!D10,Cenários!D56,Cenários!D102)*(1-INDEX(Premissas!$C$59:$G$59,D$7))*CHOOSE(Premissas!$B$6,INDEX(Premissas!$C$56:$G$56,D$7),INDEX(Premissas!$C$57:$G$57,D$7),INDEX(Premissas!$C$58:$G$58,D$7))} -> 0 | E21: {=-CHOOSE(Premissas!$B$6,Cenários!E10,Cenários!E56,Cenários!E102)*(1-INDEX(Premissas!$C$59:$G$59,E$7))*CHOOSE(Premissas!$B$6,INDEX(Premissas!$C$56:$G$56,E$7),INDEX(Premissas!$C$57:$G$57,E$7),INDEX(Premissas!$C$58:$G$58,E$7))} -> 0 | F21: {=-CHOOSE(Premissas!$B$6,Cenários!F10,Cenários!F56,Cenários!F102)*(1-INDEX(Premissas!$C$59:$G$59,F$7))*CHOOSE(Premissas!$B$6,INDEX(Premissas!$C$56:$G$56,F$7),INDEX(Premissas!$C$57:$G$57,F$7),INDEX(Premissas!$C$58:$G$58,F$7))} -> 0 | G21: {=-CHOOSE(Premissas!$B$6,Cenários!G10,Cenários!G56,Cenários!G102)*(1-INDEX(Premissas!$C$59:$G$59,G$7))*CHOOSE(Premissas!$B$6,INDEX(Premissas!$C$56:$G$56,G$7),INDEX(Premissas!$C$57:$G$57,G$7),INDEX(Premissas!$C$58:$G$58,G$7))} -> 0 | H21: {=-CHOOSE(Premissas!$B$6,Cenários!H10,Cenários!H56,Cenários!H102)*(1-INDEX(Premissas!$C$59:$G$59,H$7))*CHOOSE(Premissas!$B$6,INDEX(Premissas!$C$56:$G$56,H$7),INDEX(Premissas!$C$57:$G$57,H$7),INDEX(Premissas!$C$58:$G$58,H$7))} -> 0 | I21: {=-CHOOSE(Premissas!$B$6,Cenários!I10,Cenários!I56,Cenários!I102)*(1-INDEX(Premissas!$C$59:$G$59,I$7))*CHOOSE(Premissas!$B$6,INDEX(Premissas!$C$56:$G$56,I$7),INDEX(Premissas!$C$57:$G$57,I$7),INDEX(Premissas!$C$58:$G$58,I$7))} -> 0 | ... BI21: {=-CHOOSE(Premissas!$B$6,Cenários!BI10,Cenários!BI56,Cenários!BI102)*(1-INDEX(Premissas!$C$59:$G$59,BI$7))*CHOOSE(Premissas!$B$6,INDEX(Premissas!$C$56:$G$56,BI$7),INDEX(Premissas!$C$57:$G$57,BI$7),INDEX(Premissas!$C$58:$G$58,BI$7))} -> -240395.44 | BJ21: =SUM(B21:BI21) -> -6331666.2 | BK21: =IFERROR(BJ21/BJ$28,0) -> 0.097324799
A22: Marketing recorrente (agência e conteúdo) | B22: {=-IF(B$4>=Premissas!$B$99,INDEX(Premissas!$C$98:$G$98,B$7),0)} -> 0 | C22: {=-IF(C$4>=Premissas!$B$99,INDEX(Premissas!$C$98:$G$98,C$7),0)} -> 0 | D22: {=-IF(D$4>=Premissas!$B$99,INDEX(Premissas!$C$98:$G$98,D$7),0)} -> 0 | E22: {=-IF(E$4>=Premissas!$B$99,INDEX(Premissas!$C$98:$G$98,E$7),0)} -> 0 | F22: {=-IF(F$4>=Premissas!$B$99,INDEX(Premissas!$C$98:$G$98,F$7),0)} -> 0 | G22: {=-IF(G$4>=Premissas!$B$99,INDEX(Premissas!$C$98:$G$98,G$7),0)} -> 0 | H22: {=-IF(H$4>=Premissas!$B$99,INDEX(Premissas!$C$98:$G$98,H$7),0)} -> 0 | I22: {=-IF(I$4>=Premissas!$B$99,INDEX(Premissas!$C$98:$G$98,I$7),0)} -> 0 | ... BI22: {=-IF(BI$4>=Premissas!$B$99,INDEX(Premissas!$C$98:$G$98,BI$7),0)} -> -15000 | BJ22: =SUM(B22:BI22) -> -481000 | BK22: =IFERROR(BJ22/BJ$28,0) -> 0.0073935086
A23: Propaganda de lançamento | B23: =-IF(B$4=DATE(YEAR(Premissas!$B$101),MONTH(Premissas!$B$101),1),Premissas!$B$100,0) -> 0 | C23: =-IF(C$4=DATE(YEAR(Premissas!$B$101),MONTH(Premissas!$B$101),1),Premissas!$B$100,0) -> 0 | D23: =-IF(D$4=DATE(YEAR(Premissas!$B$101),MONTH(Premissas!$B$101),1),Premissas!$B$100,0) -> 0 | E23: =-IF(E$4=DATE(YEAR(Premissas!$B$101),MONTH(Premissas!$B$101),1),Premissas!$B$100,0) -> 0 | F23: =-IF(F$4=DATE(YEAR(Premissas!$B$101),MONTH(Premissas!$B$101),1),Premissas!$B$100,0) -> 0 | G23: =-IF(G$4=DATE(YEAR(Premissas!$B$101),MONTH(Premissas!$B$101),1),Premissas!$B$100,0) -> 0 | H23: =-IF(H$4=DATE(YEAR(Premissas!$B$101),MONTH(Premissas!$B$101),1),Premissas!$B$100,0) -> 0 | I23: =-IF(I$4=DATE(YEAR(Premissas!$B$101),MONTH(Premissas!$B$101),1),Premissas!$B$100,0) -> 0 | ... BI23: =-IF(BI$4=DATE(YEAR(Premissas!$B$101),MONTH(Premissas!$B$101),1),Premissas!$B$100,0) -> 0 | BJ23: =SUM(B23:BI23) -> -1000 | BK23: =IFERROR(BJ23/BJ$28,0) -> 1.537112e-05
A24: Comissão das lojas de aplicativos | B24: =CHOOSE(Premissas!$B$6,Cenários!B32,Cenários!B78,Cenários!B124) -> 0 | C24: =CHOOSE(Premissas!$B$6,Cenários!C32,Cenários!C78,Cenários!C124) -> 0 | D24: =CHOOSE(Premissas!$B$6,Cenários!D32,Cenários!D78,Cenários!D124) -> 0 | E24: =CHOOSE(Premissas!$B$6,Cenários!E32,Cenários!E78,Cenários!E124) -> 0 | F24: =CHOOSE(Premissas!$B$6,Cenários!F32,Cenários!F78,Cenários!F124) -> 0 | G24: =CHOOSE(Premissas!$B$6,Cenários!G32,Cenários!G78,Cenários!G124) -> 0 | H24: =CHOOSE(Premissas!$B$6,Cenários!H32,Cenários!H78,Cenários!H124) -> 0 | I24: =CHOOSE(Premissas!$B$6,Cenários!I32,Cenários!I78,Cenários!I124) -> 0 | ... BI24: =CHOOSE(Premissas!$B$6,Cenários!BI32,Cenários!BI78,Cenários!BI124) -> -340964.78 | BJ24: =SUM(B24:BI24) -> -7439957.6 | BK24: =IFERROR(BJ24/BJ$28,0) -> 0.11436048
A25: Taxas de meios de pagamento | B25: =CHOOSE(Premissas!$B$6,Cenários!B33,Cenários!B79,Cenários!B125) -> 0 | C25: =CHOOSE(Premissas!$B$6,Cenários!C33,Cenários!C79,Cenários!C125) -> 0 | D25: =CHOOSE(Premissas!$B$6,Cenários!D33,Cenários!D79,Cenários!D125) -> 0 | E25: =CHOOSE(Premissas!$B$6,Cenários!E33,Cenários!E79,Cenários!E125) -> 0 | F25: =CHOOSE(Premissas!$B$6,Cenários!F33,Cenários!F79,Cenários!F125) -> 0 | G25: =CHOOSE(Premissas!$B$6,Cenários!G33,Cenários!G79,Cenários!G125) -> 0 | H25: =CHOOSE(Premissas!$B$6,Cenários!H33,Cenários!H79,Cenários!H125) -> 0 | I25: =CHOOSE(Premissas!$B$6,Cenários!I33,Cenários!I79,Cenários!I125) -> 0 | ... BI25: =CHOOSE(Premissas!$B$6,Cenários!BI33,Cenários!BI79,Cenários!BI125) -> -52625.259 | BJ25: =SUM(B25:BI25) -> -1023977.4 | BK25: =IFERROR(BJ25/BJ$28,0) -> 0.015739679
A26: Impostos sobre a receita | B26: =CHOOSE(Premissas!$B$6,Cenários!B31,Cenários!B77,Cenários!B123) -> 0 | C26: =CHOOSE(Premissas!$B$6,Cenários!C31,Cenários!C77,Cenários!C123) -> 0 | D26: =CHOOSE(Premissas!$B$6,Cenários!D31,Cenários!D77,Cenários!D123) -> 0 | E26: =CHOOSE(Premissas!$B$6,Cenários!E31,Cenários!E77,Cenários!E123) -> 0 | F26: =CHOOSE(Premissas!$B$6,Cenários!F31,Cenários!F77,Cenários!F123) -> 0 | G26: =CHOOSE(Premissas!$B$6,Cenários!G31,Cenários!G77,Cenários!G123) -> 0 | H26: =CHOOSE(Premissas!$B$6,Cenários!H31,Cenários!H77,Cenários!H123) -> 0 | I26: =CHOOSE(Premissas!$B$6,Cenários!I31,Cenários!I77,Cenários!I123) -> 0 | ... BI26: =CHOOSE(Premissas!$B$6,Cenários!BI31,Cenários!BI77,Cenários!BI123) -> -563923.68 | BJ26: =SUM(B26:BI26) -> -12004991 | BK26: =IFERROR(BJ26/BJ$28,0) -> 0.18453016
A27: Despesas administrativas | B27: {=-IF(B$4>=Premissas!$B$96,INDEX(Premissas!$C$97:$G$97,B$7),0)} -> 0 | C27: {=-IF(C$4>=Premissas!$B$96,INDEX(Premissas!$C$97:$G$97,C$7),0)} -> 0 | D27: {=-IF(D$4>=Premissas!$B$96,INDEX(Premissas!$C$97:$G$97,D$7),0)} -> 0 | E27: {=-IF(E$4>=Premissas!$B$96,INDEX(Premissas!$C$97:$G$97,E$7),0)} -> 0 | F27: {=-IF(F$4>=Premissas!$B$96,INDEX(Premissas!$C$97:$G$97,F$7),0)} -> 0 | G27: {=-IF(G$4>=Premissas!$B$96,INDEX(Premissas!$C$97:$G$97,G$7),0)} -> 0 | H27: {=-IF(H$4>=Premissas!$B$96,INDEX(Premissas!$C$97:$G$97,H$7),0)} -> 0 | I27: {=-IF(I$4>=Premissas!$B$96,INDEX(Premissas!$C$97:$G$97,I$7),0)} -> 0 | ... BI27: {=-IF(BI$4>=Premissas!$B$96,INDEX(Premissas!$C$97:$G$97,BI$7),0)} -> -1666.6667 | BJ27: =SUM(B27:BI27) -> -37000 | BK27: =IFERROR(BJ27/BJ$28,0) -> 0.00056873143
A28: TOTAL OPERACIONAIS | B28: =SUM(B16:B27) -> 0 | C28: =SUM(C16:C27) -> 0 | D28: =SUM(D16:D27) -> 0 | E28: =SUM(E16:E27) -> 0 | F28: =SUM(F16:F27) -> -600 | G28: =SUM(G16:G27) -> -600 | H28: =SUM(H16:H27) -> -600 | I28: =SUM(I16:I27) -> -600 | ... BI28: =SUM(BI16:BI27) -> -2902089 | BJ28: =SUM(B28:BI28) -> -65057069
A30: FLUXO DE CAIXA
A31: Receita bruta total | B31: =CHOOSE(Premissas!$B$6,Cenários!B28,Cenários!B74,Cenários!B120) -> 0 | C31: =CHOOSE(Premissas!$B$6,Cenários!C28,Cenários!C74,Cenários!C120) -> 0 | D31: =CHOOSE(Premissas!$B$6,Cenários!D28,Cenários!D74,Cenários!D120) -> 0 | E31: =CHOOSE(Premissas!$B$6,Cenários!E28,Cenários!E74,Cenários!E120) -> 0 | F31: =CHOOSE(Premissas!$B$6,Cenários!F28,Cenários!F74,Cenários!F120) -> 0 | G31: =CHOOSE(Premissas!$B$6,Cenários!G28,Cenários!G74,Cenários!G120) -> 0 | H31: =CHOOSE(Premissas!$B$6,Cenários!H28,Cenários!H74,Cenários!H120) -> 0 | I31: =CHOOSE(Premissas!$B$6,Cenários!I28,Cenários!I74,Cenários!I120) -> 0 | ... BI31: =CHOOSE(Premissas!$B$6,Cenários!BI28,Cenários!BI74,Cenários!BI120) -> 3453298.7 | BJ31: =SUM(B31:BI31) -> 72831521
A32: FLUXO DE CAIXA LIVRE (FCL) | B32: =B31+B13+B28 -> 0 | C32: =C31+C13+C28 -> 0 | D32: =D31+D13+D28 -> 0 | E32: =E31+E13+E28 -> 0 | F32: =F31+F13+F28 -> -6600 | G32: =G31+G13+G28 -> -600 | H32: =H31+H13+H28 -> -600 | I32: =I31+I13+I28 -> -9727.82 | ... BI32: =BI31+BI13+BI28 -> 551209.7 | BJ32: =SUM(B32:BI32) -> 7650323.9 | BK32: Sem aportes — aporte é financiamento, não geração de caixa.
A33: FCL descontado | B33: =B32/(1+Premissas!$B$19)^B$5 -> 0 | C33: =C32/(1+Premissas!$B$19)^C$5 -> 0 | D33: =D32/(1+Premissas!$B$19)^D$5 -> 0 | E33: =E32/(1+Premissas!$B$19)^E$5 -> 0 | F33: =F32/(1+Premissas!$B$19)^F$5 -> -6014.0186 | G33: =G32/(1+Premissas!$B$19)^G$5 -> -536.65631 | H33: =H32/(1+Premissas!$B$19)^H$5 -> -526.76924 | I33: =I32/(1+Premissas!$B$19)^I$5 -> -8383.1811 | ... BI33: =BI32/(1+Premissas!$B$19)^BI$5 -> 180620.4 | BJ33: =SUM(B33:BI33) -> 3051853.8
A34: FCL descontado acumulado | B34: =B33 -> 0 | C34: =B34+C33 -> 0 | D34: =C34+D33 -> 0 | E34: =D34+E33 -> 0 | F34: =E34+F33 -> -6014.0186 | G34: =F34+G33 -> -6550.6749 | H34: =G34+H33 -> -7077.4441 | I34: =H34+I33 -> -15460.625 | J34: =I34+J33 -> -24850.082 | ... BI34: =BH34+BI33 -> 3051853.8
A35: FCL acumulado (nominal) | B35: =B32 -> 0 | C35: =B35+C32 -> 0 | D35: =C35+D32 -> 0 | E35: =D35+E32 -> 0 | F35: =E35+F32 -> -6600 | G35: =F35+G32 -> -7200 | H35: =G35+H32 -> -7800 | I35: =H35+I32 -> -17527.82 | J35: =I35+J32 -> -28627.82 | ... BI35: =BH35+BI32 -> 7650323.9
A37: (+) Aportes de sócios | B37: =Aportes!B96 -> 0 | C37: =Aportes!C96 -> 0 | D37: =Aportes!D96 -> 0 | E37: =Aportes!E96 -> 10000 | F37: =Aportes!F96 -> 0 | G37: =Aportes!G96 -> 0 | H37: =Aportes!H96 -> 5000 | I37: =Aportes!I96 -> 18000 | ... BI37: =Aportes!BI96 -> 0 | BJ37: =SUM(B37:BI37) -> 317000
A38: Fluxo de caixa do período (FCL + aportes) | B38: =B32+B37 -> 0 | C38: =C32+C37 -> 0 | D38: =D32+D37 -> 0 | E38: =E32+E37 -> 10000 | F38: =F32+F37 -> -6600 | G38: =G32+G37 -> -600 | H38: =H32+H37 -> 4400 | I38: =I32+I37 -> 8272.18 | ... BI38: =BI32+BI37 -> 551209.7 | BJ38: =SUM(B38:BI38) -> 7967323.9
A39: CAIXA ACUMULADO | B39: =B38 -> 0 | C39: =B39+C38 -> 0 | D39: =C39+D38 -> 0 | E39: =D39+E38 -> 10000 | F39: =E39+F38 -> 3400 | G39: =F39+G38 -> 2800 | H39: =G39+H38 -> 7200 | I39: =H39+I38 -> 15472.18 | J39: =I39+J38 -> 8372.18 | ... BI39: =BH39+BI38 -> 7967323.9
A40: Auxiliar — mês com FCL acumulado negativo | B40: =IF(B35<0,B$5,0) -> 0 | C40: =IF(C35<0,C$5,0) -> 0 | D40: =IF(D35<0,D$5,0) -> 0 | E40: =IF(E35<0,E$5,0) -> 0 | F40: =IF(F35<0,F$5,0) -> 5 | G40: =IF(G35<0,G$5,0) -> 6 | H40: =IF(H35<0,H$5,0) -> 7 | I40: =IF(I35<0,I$5,0) -> 8 | ... BI40: =IF(BI35<0,BI$5,0) -> 0 | BK40: Guarda o nº do mês enquanto o acumulado está negativo. O payback é o maior valor desta linha, mais um.
A41: Auxiliar — mês com FCL descontado acumulado negativo | B41: =IF(B34<0,B$5,0) -> 0 | C41: =IF(C34<0,C$5,0) -> 0 | D41: =IF(D34<0,D$5,0) -> 0 | E41: =IF(E34<0,E$5,0) -> 0 | F41: =IF(F34<0,F$5,0) -> 5 | G41: =IF(G34<0,G$5,0) -> 6 | H41: =IF(H34<0,H$5,0) -> 7 | I41: =IF(I34<0,I$5,0) -> 8 | ... BI41: =IF(BI34<0,BI$5,0) -> 0
A42: ✔ Verificação: FCL desta aba − FCL do motor (deve ser zero) | B42: =ROUND(B32-CHOOSE(Premissas!$B$6,Cenários!B42,Cenários!B88,Cenários!B134),2) -> 0 | C42: =ROUND(C32-CHOOSE(Premissas!$B$6,Cenários!C42,Cenários!C88,Cenários!C134),2) -> 0 | D42: =ROUND(D32-CHOOSE(Premissas!$B$6,Cenários!D42,Cenários!D88,Cenários!D134),2) -> 0 | E42: =ROUND(E32-CHOOSE(Premissas!$B$6,Cenários!E42,Cenários!E88,Cenários!E134),2) -> 0 | F42: =ROUND(F32-CHOOSE(Premissas!$B$6,Cenários!F42,Cenários!F88,Cenários!F134),2) -> 0 | G42: =ROUND(G32-CHOOSE(Premissas!$B$6,Cenários!G42,Cenários!G88,Cenários!G134),2) -> 0 | H42: =ROUND(H32-CHOOSE(Premissas!$B$6,Cenários!H42,Cenários!H88,Cenários!H134),2) -> 0 | I42: =ROUND(I32-CHOOSE(Premissas!$B$6,Cenários!I42,Cenários!I88,Cenários!I134),2) -> 0 | ... BI42: =ROUND(BI32-CHOOSE(Premissas!$B$6,Cenários!BI42,Cenários!BI88,Cenários!BI134),2) -> 0 | BJ42: =SUM(B42:BI42) -> 0 | BK42: Zero confirma que o detalhamento reconcilia com o motor de cenários.
A44: INDICADORES DE VIABILIDADE — CENÁRIO SELECIONADO
A45: VPL — Valor Presente Líquido | B45: {=NPV(Premissas!$B$19,B32:BI32)} -> 3051853.8 | D45: Soma do FCL trazido a valor presente pela TMA. Positivo = cria valor.
A46: TIR mensal | B46: =IFERROR(IRR(B32:BI32),"n/d") -> 0.11586217 | D46: Taxa que zera o VPL.
A47: TIR anual | B47: =IFERROR((1+$B46)^12-1,"n/d") -> 2.7267192 | D47: Compare com a TMA. Acima dela, o projeto remunera o risco.
A48: Payback simples (meses) | B48: =IF(BI35<0,"> 60 meses",MAX(B40:BI40)+1) -> 28 | D48: Mês em que o FCL acumulado passa a positivo e não volta mais.
A49: Payback descontado (meses) | B49: =IF(BI34<0,"> 60 meses",MAX(B41:BI41)+1) -> 29 | D49: Idem, com o dinheiro trazido a valor presente.
A50: Capital requerido (pico de caixa negativo) | B50: =-MIN(B35:BI35) -> 343862.1 | D50: Quanto de capital o projeto precisa antes de se sustentar.
A51: Caixa mínimo ao longo do período | B51: =MIN(B39:BI39) -> -46752.641 | D51: Se negativo, o capital planejado não é suficiente.
A52: Investimento total (CAPEX) | B52: =-BJ13 -> 124127.82
A53: Receita bruta acumulada | B53: =BJ31 -> 72831521
A54: FCL acumulado no período | B54: =BJ32 -> 7650323.9
A55: Retorno sobre o capital requerido (múltiplo) | B55: =IFERROR(BJ32/$B50,0) -> 22.248232 | D55: FCL acumulado ÷ capital requerido. É um múltiplo, não um percentual: 3,0x significa que o projeto devolve três vezes o capital que precisou.
A56: TMA utilizada (a.a.) | B56: =Premissas!$B$18 -> 0.25
A57: Alíquota efetiva média de impostos | B57: =IFERROR(-BJ26/BJ31,0) -> 0.16483236
A59: PREMISSAS — RESUMO (editar na aba Premissas)
A60: Plano Essencial (R$/mês) | B60: =Premissas!$B$29 -> 79.9
A61: Plano Premium (R$/mês) | B61: =Premissas!$B$30 -> 89.9
A62: Plano Família (R$/mês) | B62: =Premissas!$B$31 -> 109
A63: Taxa das lojas de aplicativos | B63: =Premissas!$B$62 -> 0.15
A64: Comissão do marketplace | B64: =Premissas!$B$86 -> 0.1
A65: TMA (a.a.) | B65: =Premissas!$B$18 -> 0.25
A66: Payback desejado (meses) | B66: =Premissas!$B$20 -> 36
A67: Rampa de conversão (meses) | B67: =Premissas!$B$15 -> 6

Sheet Pessoas
A1: PESSOAS — QUADRO DE PESSOAL
A2: Uma linha por papel. Edite quantidade, custo, início e fim livremente. Status 'Contratado' entra sempre; 'Plano' só entra se o controle 1 de Premissas estiver em 1. Todo o custo de pessoal do modelo sai daqui.
A3: ⚠ ABA DE AJUSTE · o time muda; revise as datas de entrada e saída e o custo de cada pessoa sempre que houver contratação ou saída.
A4: QUADRO — edite livremente, inclusive as linhas em branco no fim
A5: Função / papel | B5: Tipo | C5: Status | D5: Qtd | E5: Custo mensal por pessoa | F5: Encargos (% sobre CLT) | G5: Custo total mensal | H5: Início | I5: Fim | J5: Classificação
A6: Equipe PJ — desenvolvimento do MVP | B6: PJ | C6: Contratado | D6: 1 | E6: 10500 | F6: 0 | G6: =$D6*$E6*(1+$F6) -> 10500 | H6: 46266 | I6: 46296 | J6: Investimento
A7: Desenvolvimento — time base | B7: PJ | C7: Plano | D7: 2 | E7: 9000 | F7: 0 | G7: =$D7*$E7*(1+$F7) -> 18000 | H7: 46388 | I7: 47818 | J7: Despesa
A8: Desenvolvimento — ampliação 2028 (adicional) | B8: PJ | C8: Plano | D8: 3 | E8: 9500 | F8: 0 | G8: =$D8*$E8*(1+$F8) -> 28500 | H8: 46753 | I8: 47818 | J8: Despesa
A9: Desenvolvimento — ampliação 2029 (adicional) | B9: PJ | C9: Plano | D9: 5 | E9: 10000 | F9: 0 | G9: =$D9*$E9*(1+$F9) -> 50000 | H9: 47119 | I9: 47818 | J9: Despesa
A10: Desenvolvimento — ampliação 2030 (adicional) | B10: PJ | C10: Plano | D10: 6 | E10: 10500 | F10: 0 | G10: =$D10*$E10*(1+$F10) -> 63000 | H10: 47484 | I10: 47818 | J10: Despesa
A11: Suporte ao cliente — time base | B11: PJ | C11: Plano | D11: 1 | E11: 3500 | F11: 0 | G11: =$D11*$E11*(1+$F11) -> 3500 | H11: 46388 | I11: 47818 | J11: Despesa
A12: Suporte — ampliação 2028 (adicional) | B12: PJ | C12: Plano | D12: 3 | E12: 3500 | F12: 0 | G12: =$D12*$E12*(1+$F12) -> 10500 | H12: 46753 | I12: 47818 | J12: Despesa
A13: Suporte — ampliação 2029 (adicional) | B13: PJ | C13: Plano | D13: 6 | E13: 3800 | F13: 0 | G13: =$D13*$E13*(1+$F13) -> 22800 | H13: 47119 | I13: 47818 | J13: Despesa
A14: Suporte — ampliação 2030 (adicional) | B14: PJ | C14: Plano | D14: 8 | E14: 4000 | F14: 0 | G14: =$D14*$E14*(1+$F14) -> 32000 | H14: 47484 | I14: 47818 | J14: Despesa
A15: Growth e marketing | B15: PJ | C15: Plano | D15: 1 | E15: 6000 | F15: 0 | G15: =$D15*$E15*(1+$F15) -> 6000 | H15: 46388 | I15: 47818 | J15: Despesa
A16: Growth — ampliação 2028 (adicional) | B16: PJ | C16: Plano | D16: 2 | E16: 7000 | F16: 0 | G16: =$D16*$E16*(1+$F16) -> 14000 | H16: 46753 | I16: 47818 | J16: Despesa
A17: Growth — ampliação 2029 (adicional) | B17: PJ | C17: Plano | D17: 3 | E17: 8000 | F17: 0 | G17: =$D17*$E17*(1+$F17) -> 24000 | H17: 47119 | I17: 47818 | J17: Despesa
... A24: (exemplo) Contratação CLT | B24: CLT | C24: Plano | D24: 0 | E24: 8000 | F24: 0.7 | G24: =$D24*$E24*(1+$F24) -> 0 | H24: 46753 | I24: 47818 | J24: Despesa
B25: PJ | C25: Plano | D25: 0 | E25: 0 | F25: 0 | G25: =$D25*$E25*(1+$F25) -> 0 | H25: 46388 | I25: 47818 | J25: Despesa
B26: PJ | C26: Plano | D26: 0 | E26: 0 | F26: 0 | G26: =$D26*$E26*(1+$F26) -> 0 | H26: 46388 | I26: 47818 | J26: Despesa
B27: PJ | C27: Plano | D27: 0 | E27: 0 | F27: 0 | G27: =$D27*$E27*(1+$F27) -> 0 | H27: 46388 | I27: 47818 | J27: Despesa
B28: PJ | C28: Plano | D28: 0 | E28: 0 | F28: 0 | G28: =$D28*$E28*(1+$F28) -> 0 | H28: 46388 | I28: 47818 | J28: Despesa
B29: PJ | C29: Plano | D29: 0 | E29: 0 | F29: 0 | G29: =$D29*$E29*(1+$F29) -> 0 | H29: 46388 | I29: 47818 | J29: Despesa
B30: PJ | C30: Plano | D30: 0 | E30: 0 | F30: 0 | G30: =$D30*$E30*(1+$F30) -> 0 | H30: 46388 | I30: 47818 | J30: Despesa
B31: PJ | C31: Plano | D31: 0 | E31: 0 | F31: 0 | G31: =$D31*$E31*(1+$F31) -> 0 | H31: 46388 | I31: 47818 | J31: Despesa
B32: PJ | C32: Plano | D32: 0 | E32: 0 | F32: 0 | G32: =$D32*$E32*(1+$F32) -> 0 | H32: 46388 | I32: 47818 | J32: Despesa
A33: TOTAL DO QUADRO (custo mensal se todas as linhas estivessem ativas) | G33: =SUM(G6:G32) -> 399800
A34: Azul-escuro/verde = já contratado · azul-claro = plano sugerido, a validar. Coluna 'Custo total mensal' é calculada.
A36: Linha do tempo | B36: 46023 | C36: 46054 | D36: 46082 | E36: 46113 | F36: 46143 | G36: 46174 | H36: 46204 | I36: 46235 | J36: 46266 | K36: 46296 | L36: 46327 | M36: 46357 | N36: 46388 | O36: 46419 | P36: 46447 | Q36: 46478 | R36: 46508 | S36: 46539 | T36: 46569 | U36: 46600 | V36: 46631 | W36: 46661 | X36: 46692 | Y36: 46722 | Z36: 46753 | AA36: 46784 | AB36: 46813 | AC36: 46844 | AD36: 46874 | AE36: 46905 | AF36: 46935 | AG36: 46966 | AH36: 46997 | AI36: 47027 | AJ36: 47058 | AK36: 47088 | AL36: 47119 | AM36: 47150 | AN36: 47178 | AO36: 47209 | AP36: 47239 | AQ36: 47270 | AR36: 47300 | AS36: 47331 | AT36: 47362 | AU36: 47392 | AV36: 47423 | AW36: 47453 | AX36: 47484 | AY36: 47515 | AZ36: 47543 | BA36: 47574 | BB36: 47604 | BC36: 47635 | BD36: 47665 | BE36: 47696 | BF36: 47727 | BG36: 47757 | BH36: 47788 | BI36: 47818 | BJ36: TOTAL | BK36: % / Nota
A37: Mês nº | B37: 1 | C37: 2 | D37: 3 | E37: 4 | F37: 5 | G37: 6 | H37: 7 | I37: 8 | J37: 9 | K37: 10 | L37: 11 | M37: 12 | N37: 13 | O37: 14 | P37: 15 | Q37: 16 | R37: 17 | S37: 18 | T37: 19 | U37: 20 | V37: 21 | W37: 22 | X37: 23 | Y37: 24 | Z37: 25 | AA37: 26 | AB37: 27 | AC37: 28 | AD37: 29 | AE37: 30 | AF37: 31 | AG37: 32 | AH37: 33 | AI37: 34 | AJ37: 35 | AK37: 36 | AL37: 37 | AM37: 38 | AN37: 39 | AO37: 40 | AP37: 41 | AQ37: 42 | AR37: 43 | AS37: 44 | AT37: 45 | AU37: 46 | AV37: 47 | AW37: 48 | AX37: 49 | AY37: 50 | AZ37: 51 | BA37: 52 | BB37: 53 | BC37: 54 | BD37: 55 | BE37: 56 | BF37: 57 | BG37: 58 | BH37: 59 | BI37: 60
A38: Ano | B38: =YEAR(B36) -> 2026 | C38: =YEAR(C36) -> 2026 | D38: =YEAR(D36) -> 2026 | E38: =YEAR(E36) -> 2026 | F38: =YEAR(F36) -> 2026 | G38: =YEAR(G36) -> 2026 | H38: =YEAR(H36) -> 2026 | I38: =YEAR(I36) -> 2026 | ... BI38: =YEAR(BI36) -> 2030
A39: Índice do ano (auxiliar) | B39: =MATCH(B38,Premissas!$C$5:$G$5,0) -> 1 | C39: =MATCH(C38,Premissas!$C$5:$G$5,0) -> 1 | D39: =MATCH(D38,Premissas!$C$5:$G$5,0) -> 1 | E39: =MATCH(E38,Premissas!$C$5:$G$5,0) -> 1 | F39: =MATCH(F38,Premissas!$C$5:$G$5,0) -> 1 | G39: =MATCH(G38,Premissas!$C$5:$G$5,0) -> 1 | H39: =MATCH(H38,Premissas!$C$5:$G$5,0) -> 1 | I39: =MATCH(I38,Premissas!$C$5:$G$5,0) -> 1 | ... BI39: =MATCH(BI38,Premissas!$C$5:$G$5,0) -> 5
A40: CUSTO MENSAL DE PESSOAL
A41: Pessoas ativas no mês (headcount) | B41: =SUMPRODUCT(($H$6:$H$32<=B$36)*($I$6:$I$32>=B$36)*(($C$6:$C$32="Contratado")+($C$6:$C$32="Plano")*Premissas!$B$8)*$D$6:$D$32) -> 0 | C41: =SUMPRODUCT(($H$6:$H$32<=C$36)*($I$6:$I$32>=C$36)*(($C$6:$C$32="Contratado")+($C$6:$C$32="Plano")*Premissas!$B$8)*$D$6:$D$32) -> 0 | D41: =SUMPRODUCT(($H$6:$H$32<=D$36)*($I$6:$I$32>=D$36)*(($C$6:$C$32="Contratado")+($C$6:$C$32="Plano")*Premissas!$B$8)*$D$6:$D$32) -> 0 | E41: =SUMPRODUCT(($H$6:$H$32<=E$36)*($I$6:$I$32>=E$36)*(($C$6:$C$32="Contratado")+($C$6:$C$32="Plano")*Premissas!$B$8)*$D$6:$D$32) -> 0 | F41: =SUMPRODUCT(($H$6:$H$32<=F$36)*($I$6:$I$32>=F$36)*(($C$6:$C$32="Contratado")+($C$6:$C$32="Plano")*Premissas!$B$8)*$D$6:$D$32) -> 0 | G41: =SUMPRODUCT(($H$6:$H$32<=G$36)*($I$6:$I$32>=G$36)*(($C$6:$C$32="Contratado")+($C$6:$C$32="Plano")*Premissas!$B$8)*$D$6:$D$32) -> 0 | H41: =SUMPRODUCT(($H$6:$H$32<=H$36)*($I$6:$I$32>=H$36)*(($C$6:$C$32="Contratado")+($C$6:$C$32="Plano")*Premissas!$B$8)*$D$6:$D$32) -> 0 | I41: =SUMPRODUCT(($H$6:$H$32<=I$36)*($I$6:$I$32>=I$36)*(($C$6:$C$32="Contratado")+($C$6:$C$32="Plano")*Premissas!$B$8)*$D$6:$D$32) -> 0 | ... BI41: =SUMPRODUCT(($H$6:$H$32<=BI$36)*($I$6:$I$32>=BI$36)*(($C$6:$C$32="Contratado")+($C$6:$C$32="Plano")*Premissas!$B$8)*$D$6:$D$32) -> 50 | BJ41: =BI41 -> 50 | BK41: Quadro em dez/2030, não soma.
A42: Equipe PJ (despesa) | B42: =SUMPRODUCT(($B$6:$B$32="PJ")*($J$6:$J$32="Despesa")*($H$6:$H$32<=B$36)*($I$6:$I$32>=B$36)*(($C$6:$C$32="Contratado")+($C$6:$C$32="Plano")*Premissas!$B$8)*$G$6:$G$32) -> 0 | C42: =SUMPRODUCT(($B$6:$B$32="PJ")*($J$6:$J$32="Despesa")*($H$6:$H$32<=C$36)*($I$6:$I$32>=C$36)*(($C$6:$C$32="Contratado")+($C$6:$C$32="Plano")*Premissas!$B$8)*$G$6:$G$32) -> 0 | D42: =SUMPRODUCT(($B$6:$B$32="PJ")*($J$6:$J$32="Despesa")*($H$6:$H$32<=D$36)*($I$6:$I$32>=D$36)*(($C$6:$C$32="Contratado")+($C$6:$C$32="Plano")*Premissas!$B$8)*$G$6:$G$32) -> 0 | E42: =SUMPRODUCT(($B$6:$B$32="PJ")*($J$6:$J$32="Despesa")*($H$6:$H$32<=E$36)*($I$6:$I$32>=E$36)*(($C$6:$C$32="Contratado")+($C$6:$C$32="Plano")*Premissas!$B$8)*$G$6:$G$32) -> 0 | F42: =SUMPRODUCT(($B$6:$B$32="PJ")*($J$6:$J$32="Despesa")*($H$6:$H$32<=F$36)*($I$6:$I$32>=F$36)*(($C$6:$C$32="Contratado")+($C$6:$C$32="Plano")*Premissas!$B$8)*$G$6:$G$32) -> 0 | G42: =SUMPRODUCT(($B$6:$B$32="PJ")*($J$6:$J$32="Despesa")*($H$6:$H$32<=G$36)*($I$6:$I$32>=G$36)*(($C$6:$C$32="Contratado")+($C$6:$C$32="Plano")*Premissas!$B$8)*$G$6:$G$32) -> 0 | H42: =SUMPRODUCT(($B$6:$B$32="PJ")*($J$6:$J$32="Despesa")*($H$6:$H$32<=H$36)*($I$6:$I$32>=H$36)*(($C$6:$C$32="Contratado")+($C$6:$C$32="Plano")*Premissas!$B$8)*$G$6:$G$32) -> 0 | I42: =SUMPRODUCT(($B$6:$B$32="PJ")*($J$6:$J$32="Despesa")*($H$6:$H$32<=I$36)*($I$6:$I$32>=I$36)*(($C$6:$C$32="Contratado")+($C$6:$C$32="Plano")*Premissas!$B$8)*$G$6:$G$32) -> 0 | ... BI42: =SUMPRODUCT(($B$6:$B$32="PJ")*($J$6:$J$32="Despesa")*($H$6:$H$32<=BI$36)*($I$6:$I$32>=BI$36)*(($C$6:$C$32="Contratado")+($C$6:$C$32="Plano")*Premissas!$B$8)*$G$6:$G$32) -> 342300 | BJ42: =SUM(B42:BI42) -> 8323200
A43: Equipe CLT — salários e encargos (despesa) | B43: =SUMPRODUCT(($B$6:$B$32="CLT")*($J$6:$J$32="Despesa")*($H$6:$H$32<=B$36)*($I$6:$I$32>=B$36)*(($C$6:$C$32="Contratado")+($C$6:$C$32="Plano")*Premissas!$B$8)*$G$6:$G$32) -> 0 | C43: =SUMPRODUCT(($B$6:$B$32="CLT")*($J$6:$J$32="Despesa")*($H$6:$H$32<=C$36)*($I$6:$I$32>=C$36)*(($C$6:$C$32="Contratado")+($C$6:$C$32="Plano")*Premissas!$B$8)*$G$6:$G$32) -> 0 | D43: =SUMPRODUCT(($B$6:$B$32="CLT")*($J$6:$J$32="Despesa")*($H$6:$H$32<=D$36)*($I$6:$I$32>=D$36)*(($C$6:$C$32="Contratado")+($C$6:$C$32="Plano")*Premissas!$B$8)*$G$6:$G$32) -> 0 | E43: =SUMPRODUCT(($B$6:$B$32="CLT")*($J$6:$J$32="Despesa")*($H$6:$H$32<=E$36)*($I$6:$I$32>=E$36)*(($C$6:$C$32="Contratado")+($C$6:$C$32="Plano")*Premissas!$B$8)*$G$6:$G$32) -> 0 | F43: =SUMPRODUCT(($B$6:$B$32="CLT")*($J$6:$J$32="Despesa")*($H$6:$H$32<=F$36)*($I$6:$I$32>=F$36)*(($C$6:$C$32="Contratado")+($C$6:$C$32="Plano")*Premissas!$B$8)*$G$6:$G$32) -> 0 | G43: =SUMPRODUCT(($B$6:$B$32="CLT")*($J$6:$J$32="Despesa")*($H$6:$H$32<=G$36)*($I$6:$I$32>=G$36)*(($C$6:$C$32="Contratado")+($C$6:$C$32="Plano")*Premissas!$B$8)*$G$6:$G$32) -> 0 | H43: =SUMPRODUCT(($B$6:$B$32="CLT")*($J$6:$J$32="Despesa")*($H$6:$H$32<=H$36)*($I$6:$I$32>=H$36)*(($C$6:$C$32="Contratado")+($C$6:$C$32="Plano")*Premissas!$B$8)*$G$6:$G$32) -> 0 | I43: =SUMPRODUCT(($B$6:$B$32="CLT")*($J$6:$J$32="Despesa")*($H$6:$H$32<=I$36)*($I$6:$I$32>=I$36)*(($C$6:$C$32="Contratado")+($C$6:$C$32="Plano")*Premissas!$B$8)*$G$6:$G$32) -> 0 | ... BI43: =SUMPRODUCT(($B$6:$B$32="CLT")*($J$6:$J$32="Despesa")*($H$6:$H$32<=BI$36)*($I$6:$I$32>=BI$36)*(($C$6:$C$32="Contratado")+($C$6:$C$32="Plano")*Premissas!$B$8)*$G$6:$G$32) -> 0 | BJ43: =SUM(B43:BI43) -> 0
A44: Pró-labore dos sócios (despesa) | B44: =SUMPRODUCT(($B$6:$B$32="Sócio")*($J$6:$J$32="Despesa")*($H$6:$H$32<=B$36)*($I$6:$I$32>=B$36)*(($C$6:$C$32="Contratado")+($C$6:$C$32="Plano")*Premissas!$B$8)*$G$6:$G$32) -> 0 | C44: =SUMPRODUCT(($B$6:$B$32="Sócio")*($J$6:$J$32="Despesa")*($H$6:$H$32<=C$36)*($I$6:$I$32>=C$36)*(($C$6:$C$32="Contratado")+($C$6:$C$32="Plano")*Premissas!$B$8)*$G$6:$G$32) -> 0 | D44: =SUMPRODUCT(($B$6:$B$32="Sócio")*($J$6:$J$32="Despesa")*($H$6:$H$32<=D$36)*($I$6:$I$32>=D$36)*(($C$6:$C$32="Contratado")+($C$6:$C$32="Plano")*Premissas!$B$8)*$G$6:$G$32) -> 0 | E44: =SUMPRODUCT(($B$6:$B$32="Sócio")*($J$6:$J$32="Despesa")*($H$6:$H$32<=E$36)*($I$6:$I$32>=E$36)*(($C$6:$C$32="Contratado")+($C$6:$C$32="Plano")*Premissas!$B$8)*$G$6:$G$32) -> 0 | F44: =SUMPRODUCT(($B$6:$B$32="Sócio")*($J$6:$J$32="Despesa")*($H$6:$H$32<=F$36)*($I$6:$I$32>=F$36)*(($C$6:$C$32="Contratado")+($C$6:$C$32="Plano")*Premissas!$B$8)*$G$6:$G$32) -> 0 | G44: =SUMPRODUCT(($B$6:$B$32="Sócio")*($J$6:$J$32="Despesa")*($H$6:$H$32<=G$36)*($I$6:$I$32>=G$36)*(($C$6:$C$32="Contratado")+($C$6:$C$32="Plano")*Premissas!$B$8)*$G$6:$G$32) -> 0 | H44: =SUMPRODUCT(($B$6:$B$32="Sócio")*($J$6:$J$32="Despesa")*($H$6:$H$32<=H$36)*($I$6:$I$32>=H$36)*(($C$6:$C$32="Contratado")+($C$6:$C$32="Plano")*Premissas!$B$8)*$G$6:$G$32) -> 0 | I44: =SUMPRODUCT(($B$6:$B$32="Sócio")*($J$6:$J$32="Despesa")*($H$6:$H$32<=I$36)*($I$6:$I$32>=I$36)*(($C$6:$C$32="Contratado")+($C$6:$C$32="Plano")*Premissas!$B$8)*$G$6:$G$32) -> 0 | ... BI44: =SUMPRODUCT(($B$6:$B$32="Sócio")*($J$6:$J$32="Despesa")*($H$6:$H$32<=BI$36)*($I$6:$I$32>=BI$36)*(($C$6:$C$32="Contratado")+($C$6:$C$32="Plano")*Premissas!$B$8)*$G$6:$G$32) -> 32000 | BJ44: =SUM(B44:BI44) -> 1128000
A45: TOTAL DE PESSOAL — DESPESA | B45: =SUMPRODUCT(($J$6:$J$32="Despesa")*($H$6:$H$32<=B$36)*($I$6:$I$32>=B$36)*(($C$6:$C$32="Contratado")+($C$6:$C$32="Plano")*Premissas!$B$8)*$G$6:$G$32) -> 0 | C45: =SUMPRODUCT(($J$6:$J$32="Despesa")*($H$6:$H$32<=C$36)*($I$6:$I$32>=C$36)*(($C$6:$C$32="Contratado")+($C$6:$C$32="Plano")*Premissas!$B$8)*$G$6:$G$32) -> 0 | D45: =SUMPRODUCT(($J$6:$J$32="Despesa")*($H$6:$H$32<=D$36)*($I$6:$I$32>=D$36)*(($C$6:$C$32="Contratado")+($C$6:$C$32="Plano")*Premissas!$B$8)*$G$6:$G$32) -> 0 | E45: =SUMPRODUCT(($J$6:$J$32="Despesa")*($H$6:$H$32<=E$36)*($I$6:$I$32>=E$36)*(($C$6:$C$32="Contratado")+($C$6:$C$32="Plano")*Premissas!$B$8)*$G$6:$G$32) -> 0 | F45: =SUMPRODUCT(($J$6:$J$32="Despesa")*($H$6:$H$32<=F$36)*($I$6:$I$32>=F$36)*(($C$6:$C$32="Contratado")+($C$6:$C$32="Plano")*Premissas!$B$8)*$G$6:$G$32) -> 0 | G45: =SUMPRODUCT(($J$6:$J$32="Despesa")*($H$6:$H$32<=G$36)*($I$6:$I$32>=G$36)*(($C$6:$C$32="Contratado")+($C$6:$C$32="Plano")*Premissas!$B$8)*$G$6:$G$32) -> 0 | H45: =SUMPRODUCT(($J$6:$J$32="Despesa")*($H$6:$H$32<=H$36)*($I$6:$I$32>=H$36)*(($C$6:$C$32="Contratado")+($C$6:$C$32="Plano")*Premissas!$B$8)*$G$6:$G$32) -> 0 | I45: =SUMPRODUCT(($J$6:$J$32="Despesa")*($H$6:$H$32<=I$36)*($I$6:$I$32>=I$36)*(($C$6:$C$32="Contratado")+($C$6:$C$32="Plano")*Premissas!$B$8)*$G$6:$G$32) -> 0 | ... BI45: =SUMPRODUCT(($J$6:$J$32="Despesa")*($H$6:$H$32<=BI$36)*($I$6:$I$32>=BI$36)*(($C$6:$C$32="Contratado")+($C$6:$C$32="Plano")*Premissas!$B$8)*$G$6:$G$32) -> 374300 | BJ45: =SUM(B45:BI45) -> 9451200
A46: Pessoal capitalizado — INVESTIMENTO | B46: =SUMPRODUCT(($J$6:$J$32="Investimento")*($H$6:$H$32<=B$36)*($I$6:$I$32>=B$36)*(($C$6:$C$32="Contratado")+($C$6:$C$32="Plano")*Premissas!$B$8)*$G$6:$G$32) -> 0 | C46: =SUMPRODUCT(($J$6:$J$32="Investimento")*($H$6:$H$32<=C$36)*($I$6:$I$32>=C$36)*(($C$6:$C$32="Contratado")+($C$6:$C$32="Plano")*Premissas!$B$8)*$G$6:$G$32) -> 0 | D46: =SUMPRODUCT(($J$6:$J$32="Investimento")*($H$6:$H$32<=D$36)*($I$6:$I$32>=D$36)*(($C$6:$C$32="Contratado")+($C$6:$C$32="Plano")*Premissas!$B$8)*$G$6:$G$32) -> 0 | E46: =SUMPRODUCT(($J$6:$J$32="Investimento")*($H$6:$H$32<=E$36)*($I$6:$I$32>=E$36)*(($C$6:$C$32="Contratado")+($C$6:$C$32="Plano")*Premissas!$B$8)*$G$6:$G$32) -> 0 | F46: =SUMPRODUCT(($J$6:$J$32="Investimento")*($H$6:$H$32<=F$36)*($I$6:$I$32>=F$36)*(($C$6:$C$32="Contratado")+($C$6:$C$32="Plano")*Premissas!$B$8)*$G$6:$G$32) -> 0 | G46: =SUMPRODUCT(($J$6:$J$32="Investimento")*($H$6:$H$32<=G$36)*($I$6:$I$32>=G$36)*(($C$6:$C$32="Contratado")+($C$6:$C$32="Plano")*Premissas!$B$8)*$G$6:$G$32) -> 0 | H46: =SUMPRODUCT(($J$6:$J$32="Investimento")*($H$6:$H$32<=H$36)*($I$6:$I$32>=H$36)*(($C$6:$C$32="Contratado")+($C$6:$C$32="Plano")*Premissas!$B$8)*$G$6:$G$32) -> 0 | I46: =SUMPRODUCT(($J$6:$J$32="Investimento")*($H$6:$H$32<=I$36)*($I$6:$I$32>=I$36)*(($C$6:$C$32="Contratado")+($C$6:$C$32="Plano")*Premissas!$B$8)*$G$6:$G$32) -> 0 | ... BI46: =SUMPRODUCT(($J$6:$J$32="Investimento")*($H$6:$H$32<=BI$36)*($I$6:$I$32>=BI$36)*(($C$6:$C$32="Contratado")+($C$6:$C$32="Plano")*Premissas!$B$8)*$G$6:$G$32) -> 0 | BJ46: =SUM(B46:BI46) -> 21000 | BK46: Vai para a aba Investimentos e é amortizado em 60 meses.
A47: Folha que conta para o Fator R (CLT + pró-labore) | B47: =SUMPRODUCT((($B$6:$B$32="CLT")+($B$6:$B$32="Sócio"))*($H$6:$H$32<=B$36)*($I$6:$I$32>=B$36)*(($C$6:$C$32="Contratado")+($C$6:$C$32="Plano")*Premissas!$B$8)*$G$6:$G$32) -> 0 | C47: =SUMPRODUCT((($B$6:$B$32="CLT")+($B$6:$B$32="Sócio"))*($H$6:$H$32<=C$36)*($I$6:$I$32>=C$36)*(($C$6:$C$32="Contratado")+($C$6:$C$32="Plano")*Premissas!$B$8)*$G$6:$G$32) -> 0 | D47: =SUMPRODUCT((($B$6:$B$32="CLT")+($B$6:$B$32="Sócio"))*($H$6:$H$32<=D$36)*($I$6:$I$32>=D$36)*(($C$6:$C$32="Contratado")+($C$6:$C$32="Plano")*Premissas!$B$8)*$G$6:$G$32) -> 0 | E47: =SUMPRODUCT((($B$6:$B$32="CLT")+($B$6:$B$32="Sócio"))*($H$6:$H$32<=E$36)*($I$6:$I$32>=E$36)*(($C$6:$C$32="Contratado")+($C$6:$C$32="Plano")*Premissas!$B$8)*$G$6:$G$32) -> 0 | F47: =SUMPRODUCT((($B$6:$B$32="CLT")+($B$6:$B$32="Sócio"))*($H$6:$H$32<=F$36)*($I$6:$I$32>=F$36)*(($C$6:$C$32="Contratado")+($C$6:$C$32="Plano")*Premissas!$B$8)*$G$6:$G$32) -> 0 | G47: =SUMPRODUCT((($B$6:$B$32="CLT")+($B$6:$B$32="Sócio"))*($H$6:$H$32<=G$36)*($I$6:$I$32>=G$36)*(($C$6:$C$32="Contratado")+($C$6:$C$32="Plano")*Premissas!$B$8)*$G$6:$G$32) -> 0 | H47: =SUMPRODUCT((($B$6:$B$32="CLT")+($B$6:$B$32="Sócio"))*($H$6:$H$32<=H$36)*($I$6:$I$32>=H$36)*(($C$6:$C$32="Contratado")+($C$6:$C$32="Plano")*Premissas!$B$8)*$G$6:$G$32) -> 0 | I47: =SUMPRODUCT((($B$6:$B$32="CLT")+($B$6:$B$32="Sócio"))*($H$6:$H$32<=I$36)*($I$6:$I$32>=I$36)*(($C$6:$C$32="Contratado")+($C$6:$C$32="Plano")*Premissas!$B$8)*$G$6:$G$32) -> 0 | ... BI47: =SUMPRODUCT((($B$6:$B$32="CLT")+($B$6:$B$32="Sócio"))*($H$6:$H$32<=BI$36)*($I$6:$I$32>=BI$36)*(($C$6:$C$32="Contratado")+($C$6:$C$32="Plano")*Premissas!$B$8)*$G$6:$G$32) -> 32000 | BJ47: =SUM(B47:BI47) -> 1128000 | BK47: Pagamento a PJ não entra no Fator R.
A49: RESUMO ANUAL E FATOR R
B50: 2026 | C50: 2027 | D50: 2028 | E50: 2029 | F50: 2030
A51: Custo total de pessoal (despesa) | B51: =SUMIFS($B$45:$BI$45,$B$38:$BI$38,B$50) -> 0 | C51: =SUMIFS($B$45:$BI$45,$B$38:$BI$38,C$50) -> 510000 | D51: =SUMIFS($B$45:$BI$45,$B$38:$BI$38,D$50) -> 1410000 | E51: =SUMIFS($B$45:$BI$45,$B$38:$BI$38,E$50) -> 3039600 | F51: =SUMIFS($B$45:$BI$45,$B$38:$BI$38,F$50) -> 4491600
A52: Pessoal capitalizado (investimento) | B52: =SUMIFS($B$46:$BI$46,$B$38:$BI$38,B$50) -> 21000 | C52: =SUMIFS($B$46:$BI$46,$B$38:$BI$38,C$50) -> 0 | D52: =SUMIFS($B$46:$BI$46,$B$38:$BI$38,D$50) -> 0 | E52: =SUMIFS($B$46:$BI$46,$B$38:$BI$38,E$50) -> 0 | F52: =SUMIFS($B$46:$BI$46,$B$38:$BI$38,F$50) -> 0
A53: Folha do Fator R (CLT + pró-labore) | B53: =SUMIFS($B$47:$BI$47,$B$38:$BI$38,B$50) -> 0 | C53: =SUMIFS($B$47:$BI$47,$B$38:$BI$38,C$50) -> 180000 | D53: =SUMIFS($B$47:$BI$47,$B$38:$BI$38,D$50) -> 180000 | E53: =SUMIFS($B$47:$BI$47,$B$38:$BI$38,E$50) -> 384000 | F53: =SUMIFS($B$47:$BI$47,$B$38:$BI$38,F$50) -> 384000
A54: Pessoas ativas em dezembro | B54: =M41 -> 0 | C54: =Y41 -> 7 | D54: =AK41 -> 17 | E54: =AW41 -> 34 | F54: =BI41 -> 50
A55: Receita bruta do ano (cenário ativo) | B55: =SUMIFS(Faturamento!$B$16:$BI$16,Faturamento!$B$6:$BI$6,B$50) -> 7191 | C55: =SUMIFS(Faturamento!$B$16:$BI$16,Faturamento!$B$6:$BI$6,C$50) -> 4266370.6 | D55: =SUMIFS(Faturamento!$B$16:$BI$16,Faturamento!$B$6:$BI$6,D$50) -> 11883042 | E55: =SUMIFS(Faturamento!$B$16:$BI$16,Faturamento!$B$6:$BI$6,E$50) -> 21235019 | F55: =SUMIFS(Faturamento!$B$16:$BI$16,Faturamento!$B$6:$BI$6,F$50) -> 35439898
A56: FATOR R (folha ÷ receita bruta) | B56: =IFERROR(B53/B55,0) -> 0 | C56: =IFERROR(C53/C55,0) -> 0.042190428 | D56: =IFERROR(D53/D55,0) -> 0.015147636 | E56: =IFERROR(E53/E55,0) -> 0.018083337 | F56: =IFERROR(F53/F55,0) -> 0.010835246
A57: Anexo aplicável | B57: =IF(B56>=0.28,"Anexo III","Anexo V") -> Anexo V | C57: =IF(C56>=0.28,"Anexo III","Anexo V") -> Anexo V | D57: =IF(D56>=0.28,"Anexo III","Anexo V") -> Anexo V | E57: =IF(E56>=0.28,"Anexo III","Anexo V") -> Anexo V | F57: =IF(F56>=0.28,"Anexo III","Anexo V") -> Anexo V
A58: Regime escolhido em Premissas | B58: =CHOOSE(Premissas!$B$23,"Anexo III","Anexo V","Lucro Presumido") -> Anexo V | C58: =CHOOSE(Premissas!$B$23,"Anexo III","Anexo V","Lucro Presumido") -> Anexo V | D58: =CHOOSE(Premissas!$B$23,"Anexo III","Anexo V","Lucro Presumido") -> Anexo V | E58: =CHOOSE(Premissas!$B$23,"Anexo III","Anexo V","Lucro Presumido") -> Anexo V | F58: =CHOOSE(Premissas!$B$23,"Anexo III","Anexo V","Lucro Presumido") -> Anexo V
A59: Escolha compatível com o Fator R? | B59: =IF(Premissas!$B$23=3,"n/a",IF(B58=B57,"✔ SIM","⚠ NÃO")) -> ✔ SIM | C59: =IF(Premissas!$B$23=3,"n/a",IF(C58=C57,"✔ SIM","⚠ NÃO")) -> ✔ SIM | D59: =IF(Premissas!$B$23=3,"n/a",IF(D58=D57,"✔ SIM","⚠ NÃO")) -> ✔ SIM | E59: =IF(Premissas!$B$23=3,"n/a",IF(E58=E57,"✔ SIM","⚠ NÃO")) -> ✔ SIM | F59: =IF(Premissas!$B$23=3,"n/a",IF(F58=F57,"✔ SIM","⚠ NÃO")) -> ✔ SIM
A60: Custo de pessoal ÷ receita bruta | B60: =IFERROR(B51/B55,0) -> 0 | C60: =IFERROR(C51/C55,0) -> 0.11953955 | D60: =IFERROR(D51/D55,0) -> 0.11865648 | E60: =IFERROR(E51/E55,0) -> 0.14314091 | F60: =IFERROR(F51/F55,0) -> 0.12673851
A62: ▸ Como o Fator R funciona
A63: Fator R = (folha CLT + pró-labore dos últimos 12 meses) ÷ receita bruta dos últimos 12 meses. Igual ou acima de 28%, a empresa fica no Anexo III do Simples (alíquota efetiva a partir de 6%). Abaixo, cai no Anexo V (a partir de 15,5%). Pagamento a equipe PJ NÃO entra na conta.
A64: ▸ Por que isso importa para a Oppa
A65: Com o quadro atual — equipe PJ e pró-labore modesto — o Fator R fica bem abaixo de 28%, o que leva ao Anexo V. Migrar parte do time para CLT ou aumentar o pró-labore eleva o custo de folha, mas pode reduzir mais imposto do que custa. Use a linha de exemplo CLT e a aba Tributos para comparar os dois efeitos antes de decidir.
A66: ▸ O que está de fato contratado
A67: Só a equipe PJ do MVP, de setembro a outubro de 2026, R$ 21.000 no total. Todo o resto é plano — desligue no controle 1 de Premissas para ver o modelo sem nenhuma contratação futura.

Sheet Aportes
A1: APORTES E INVESTIDORES
A2: Todo o capital da Oppa entra por esta aba. Há linhas em branco em todas as tabelas: para incluir um investidor novo, basta preencher uma delas — o modelo inteiro recalcula sozinho, sem mexer em fórmula nenhuma.
A3: ⚠ ABA DE AJUSTE · cada aporte tem um STATUS, e o status decide se ele entra no modelo. Realizado e Compromisso entram sempre; Previsto e Em negociação só com o interruptor ligado na seção 7 de Premissas.
A4: 1. LANÇAMENTOS DE APORTE — quem colocou (ou colocará) dinheiro, e quando
A5: Data | B5: Sócio / Investidor | C5: Valor | D5: Status | E5: Tipo | F5: Observação
A6: 46128 | B6: Paulo Kapp | C6: 10000 | D6: Realizado | E6: Fundador
A7: 46207 | B7: Lucas Medina | C7: 5000 | D7: Realizado | E7: Fundador
A8: 46254 | B8: Paulo Kapp | C8: 10000 | D8: Realizado | E8: Fundador | F8: Completa os R$ 20.000 de compromisso.
A9: 46254 | B9: Felipe Toescher | C9: 3000 | D9: Realizado | E9: Fundador
A10: 46254 | B10: Lucas Iung | C10: 2000 | D10: Realizado | E10: Fundador
A11: 46263 | B11: Lucas Iung | C11: 3000 | D11: Realizado | E11: Fundador
A12: 46269 | B12: Felipe Toescher | C12: 2000 | D12: Realizado | E12: Fundador
A13: 46281 | B13: Lucas Iung | C13: 1000 | D13: Realizado | E13: Fundador
A14: 46281 | B14: Lucas Medina | C14: 1000 | D14: Realizado | E14: Fundador
A15: 46310 | B15: C-ioT | C15: 40000 | D15: Em negociação | E15: Novo sócio | F15: Negociação em curso, sem assinatura.
A16: 46310 | B16: Felipe Martinelli | C16: 40000 | D16: Em negociação | E16: Novo sócio | F16: Negociação em curso, sem assinatura.
B36: TOTAL LANÇADO (conforme os controles de status) | C36: =SUMPRODUCT((($D$6:$D$35="Realizado")+($D$6:$D$35="Compromisso")+($D$6:$D$35="Previsto")*Premissas!$B$105+($D$6:$D$35="Em negociação")*Premissas!$B$106)*$C$6:$C$35) -> 117000
A38: 2. INVESTIDORES ESTRATÉGICOS E PARCERIAS — aporte mais receita recorrente
A39: Use esta tabela para investidor que, além de aportar, traz receita — como a Boston Scientific. Preencha uma linha em branco para incluir outro. O aporte entra no caixa no mês indicado; a receita recorrente entra na DRE como receita B2B, todo mês, entre as datas de início e fim.
A40: Investidor | B40: Status | C40: Aporte (R$) | D40: Mês do aporte | E40: Receita B2B (R$/mês) | F40: Início da receita | G40: Fim da receita | H40: Observação
A41: Boston Scientific | B41: Em negociação | C41: 200000 | D41: 46419 | E41: 5000 | F41: 46447 | G41: 47818 | H41: Monitoramento de pacientes pós-operatórios. Aporte na casa dos seis dígitos, não confirmado — adotado o ponto médio da faixa. Contrapartida esperada: exclusividade B2B hospitalar por um período longo.
B42: Em negociação | C42: 0 | D42: 46753 | E42: 0 | F42: 46753 | G42: 47818
B43: Em negociação | C43: 0 | D43: 46753 | E43: 0 | F43: 46753 | G43: 47818
B44: Em negociação | C44: 0 | D44: 46753 | E44: 0 | F44: 46753 | G44: 47818
B45: Em negociação | C45: 0 | D45: 46753 | E45: 0 | F45: 46753 | G45: 47818
B46: Em negociação | C46: 0 | D46: 46753 | E46: 0 | F46: 46753 | G46: 47818
B47: Em negociação | C47: 0 | D47: 46753 | E47: 0 | F47: 46753 | G47: 47818
B48: Em negociação | C48: 0 | D48: 46753 | E48: 0 | F48: 46753 | G48: 47818
A49: TOTAL | C49: =SUMPRODUCT((($B$41:$B$48="Confirmado")+($B$41:$B$48="Em negociação")*Premissas!$B$106)*$C$41:$C$48) -> 200000 | E49: =SUMPRODUCT((($B$41:$B$48="Confirmado")+($B$41:$B$48="Em negociação")*Premissas!$B$106)*$E$41:$E$48) -> 5000 | I49: Receita B2B mensal somada de todas as parcerias ativas.
A51: 3. RESUMO DO CAPITAL
B52: Realizado — dinheiro que já entrou | C52: =SUMIFS($C$6:$C$35,$D$6:$D$35,"Realizado") -> 37000
B53: Compromisso dos fundadores a integralizar | C53: =SUMIFS($C$6:$C$35,$D$6:$D$35,"Compromisso") -> 0
B54: Previsto — negociação em curso, sem assinatura | C54: =SUMIFS($C$6:$C$35,$D$6:$D$35,"Previsto")*Premissas!$B$105 -> 0
B55: Em negociação — lançamentos | C55: =SUMIFS($C$6:$C$35,$D$6:$D$35,"Em negociação")*Premissas!$B$106 -> 80000
B56: Investidores estratégicos | C56: =SUMPRODUCT((($B$41:$B$48="Confirmado")+($B$41:$B$48="Em negociação")*Premissas!$B$106)*$C$41:$C$48) -> 200000
B57: CAPITAL TOTAL CONSIDERADO NO MODELO | C57: =C36+C49 -> 317000 | E57: Os controles que ligam e desligam 'Previsto' e 'Em negociação' estão na aba Premissas, seção 7.
A60: 4. COMPROMISSO DOS FUNDADORES — R$ 20.000 cada, sendo R$ 10.000 ainda em 2026
A61: Fundador | B61: Meta total | C61: Aportado até 2026 | D61: Aportado total | E61: Falta em 2026 | F61: Falta total
A62: Paulo Kapp | B62: 20000 | C62: =SUMIFS($C$6:$C$35,$B$6:$B$35,$A62,$A$6:$A$35,"<="&DATE(2026,12,31)) -> 20000 | D62: =SUMIFS($C$6:$C$35,$B$6:$B$35,$A62) -> 20000 | E62: =MAX(0,10000-$C62) -> 0 | F62: =MAX(0,$B62-$D62) -> 0 | H62: Paulo Kapp já integralizou os R$ 20.000. Os demais têm saldo a aportar.
A63: Lucas Medina | B63: 20000 | C63: =SUMIFS($C$6:$C$35,$B$6:$B$35,$A63,$A$6:$A$35,"<="&DATE(2026,12,31)) -> 6000 | D63: =SUMIFS($C$6:$C$35,$B$6:$B$35,$A63) -> 6000 | E63: =MAX(0,10000-$C63) -> 4000 | F63: =MAX(0,$B63-$D63) -> 14000
A64: Felipe Toescher | B64: 20000 | C64: =SUMIFS($C$6:$C$35,$B$6:$B$35,$A64,$A$6:$A$35,"<="&DATE(2026,12,31)) -> 5000 | D64: =SUMIFS($C$6:$C$35,$B$6:$B$35,$A64) -> 5000 | E64: =MAX(0,10000-$C64) -> 5000 | F64: =MAX(0,$B64-$D64) -> 15000
A65: Lucas Iung | B65: 20000 | C65: =SUMIFS($C$6:$C$35,$B$6:$B$35,$A65,$A$6:$A$35,"<="&DATE(2026,12,31)) -> 6000 | D65: =SUMIFS($C$6:$C$35,$B$6:$B$35,$A65) -> 6000 | E65: =MAX(0,10000-$C65) -> 4000 | F65: =MAX(0,$B65-$D65) -> 14000
A68: 5. PARTICIPAÇÃO PROPORCIONAL AO CAPITAL APORTADO — inclua aqui o nome de todo investidor novo
A69: Leia com cuidado: isto é a proporção do dinheiro colocado, não a participação societária. Percentual de sociedade depende do valuation acordado em cada rodada e de outras condições — no caso de um investidor estratégico como a Boston, a contrapartida pode ser exclusividade comercial em vez de mais equity. Use esta tabela como ponto de partida da conversa, não como resultado.
A70: Sócio / Investidor | B70: Capital aportado | C70: Proporção
A71: Paulo Kapp | B71: =IF($A71="",0,SUMPRODUCT((($D$6:$D$35="Realizado")+($D$6:$D$35="Compromisso")+($D$6:$D$35="Previsto")*Premissas!$B$105+($D$6:$D$35="Em negociação")*Premissas!$B$106)*($B$6:$B$35=$A71)*$C$6:$C$35)+SUMPRODUCT((($B$41:$B$48="Confirmado")+($B$41:$B$48="Em negociação")*Premissas!$B$106)*($A$41:$A$48=$A71)*$C$41:$C$48)) -> 20000 | C71: =IFERROR($B71/$B$84,0) -> 0.17094017
A72: Lucas Medina | B72: =IF($A72="",0,SUMPRODUCT((($D$6:$D$35="Realizado")+($D$6:$D$35="Compromisso")+($D$6:$D$35="Previsto")*Premissas!$B$105+($D$6:$D$35="Em negociação")*Premissas!$B$106)*($B$6:$B$35=$A72)*$C$6:$C$35)+SUMPRODUCT((($B$41:$B$48="Confirmado")+($B$41:$B$48="Em negociação")*Premissas!$B$106)*($A$41:$A$48=$A72)*$C$41:$C$48)) -> 6000 | C72: =IFERROR($B72/$B$84,0) -> 0.051282051
A73: Felipe Toescher | B73: =IF($A73="",0,SUMPRODUCT((($D$6:$D$35="Realizado")+($D$6:$D$35="Compromisso")+($D$6:$D$35="Previsto")*Premissas!$B$105+($D$6:$D$35="Em negociação")*Premissas!$B$106)*($B$6:$B$35=$A73)*$C$6:$C$35)+SUMPRODUCT((($B$41:$B$48="Confirmado")+($B$41:$B$48="Em negociação")*Premissas!$B$106)*($A$41:$A$48=$A73)*$C$41:$C$48)) -> 5000 | C73: =IFERROR($B73/$B$84,0) -> 0.042735043
A74: Lucas Iung | B74: =IF($A74="",0,SUMPRODUCT((($D$6:$D$35="Realizado")+($D$6:$D$35="Compromisso")+($D$6:$D$35="Previsto")*Premissas!$B$105+($D$6:$D$35="Em negociação")*Premissas!$B$106)*($B$6:$B$35=$A74)*$C$6:$C$35)+SUMPRODUCT((($B$41:$B$48="Confirmado")+($B$41:$B$48="Em negociação")*Premissas!$B$106)*($A$41:$A$48=$A74)*$C$41:$C$48)) -> 6000 | C74: =IFERROR($B74/$B$84,0) -> 0.051282051
A75: C-ioT | B75: =IF($A75="",0,SUMPRODUCT((($D$6:$D$35="Realizado")+($D$6:$D$35="Compromisso")+($D$6:$D$35="Previsto")*Premissas!$B$105+($D$6:$D$35="Em negociação")*Premissas!$B$106)*($B$6:$B$35=$A75)*$C$6:$C$35)+SUMPRODUCT((($B$41:$B$48="Confirmado")+($B$41:$B$48="Em negociação")*Premissas!$B$106)*($A$41:$A$48=$A75)*$C$41:$C$48)) -> 40000 | C75: =IFERROR($B75/$B$84,0) -> 0.34188034
A76: Felipe Martinelli | B76: =IF($A76="",0,SUMPRODUCT((($D$6:$D$35="Realizado")+($D$6:$D$35="Compromisso")+($D$6:$D$35="Previsto")*Premissas!$B$105+($D$6:$D$35="Em negociação")*Premissas!$B$106)*($B$6:$B$35=$A76)*$C$6:$C$35)+SUMPRODUCT((($B$41:$B$48="Confirmado")+($B$41:$B$48="Em negociação")*Premissas!$B$106)*($A$41:$A$48=$A76)*$C$41:$C$48)) -> 40000 | C76: =IFERROR($B76/$B$84,0) -> 0.34188034
A77: Shaiane | B77: =IF($A77="",0,SUMPRODUCT((($D$6:$D$35="Realizado")+($D$6:$D$35="Compromisso")+($D$6:$D$35="Previsto")*Premissas!$B$105+($D$6:$D$35="Em negociação")*Premissas!$B$106)*($B$6:$B$35=$A77)*$C$6:$C$35)+SUMPRODUCT((($B$41:$B$48="Confirmado")+($B$41:$B$48="Em negociação")*Premissas!$B$106)*($A$41:$A$48=$A77)*$C$41:$C$48)) -> 0 | C77: =IFERROR($B77/$B$84,0) -> 0
B78: =IF($A78="",0,SUMPRODUCT((($D$6:$D$35="Realizado")+($D$6:$D$35="Compromisso")+($D$6:$D$35="Previsto")*Premissas!$B$105+($D$6:$D$35="Em negociação")*Premissas!$B$106)*($B$6:$B$35=$A78)*$C$6:$C$35)+SUMPRODUCT((($B$41:$B$48="Confirmado")+($B$41:$B$48="Em negociação")*Premissas!$B$106)*($A$41:$A$48=$A78)*$C$41:$C$48)) -> 0 | C78: =IFERROR($B78/$B$84,0) -> 0
B79: =IF($A79="",0,SUMPRODUCT((($D$6:$D$35="Realizado")+($D$6:$D$35="Compromisso")+($D$6:$D$35="Previsto")*Premissas!$B$105+($D$6:$D$35="Em negociação")*Premissas!$B$106)*($B$6:$B$35=$A79)*$C$6:$C$35)+SUMPRODUCT((($B$41:$B$48="Confirmado")+($B$41:$B$48="Em negociação")*Premissas!$B$106)*($A$41:$A$48=$A79)*$C$41:$C$48)) -> 0 | C79: =IFERROR($B79/$B$84,0) -> 0
B80: =IF($A80="",0,SUMPRODUCT((($D$6:$D$35="Realizado")+($D$6:$D$35="Compromisso")+($D$6:$D$35="Previsto")*Premissas!$B$105+($D$6:$D$35="Em negociação")*Premissas!$B$106)*($B$6:$B$35=$A80)*$C$6:$C$35)+SUMPRODUCT((($B$41:$B$48="Confirmado")+($B$41:$B$48="Em negociação")*Premissas!$B$106)*($A$41:$A$48=$A80)*$C$41:$C$48)) -> 0 | C80: =IFERROR($B80/$B$84,0) -> 0
B81: =IF($A81="",0,SUMPRODUCT((($D$6:$D$35="Realizado")+($D$6:$D$35="Compromisso")+($D$6:$D$35="Previsto")*Premissas!$B$105+($D$6:$D$35="Em negociação")*Premissas!$B$106)*($B$6:$B$35=$A81)*$C$6:$C$35)+SUMPRODUCT((($B$41:$B$48="Confirmado")+($B$41:$B$48="Em negociação")*Premissas!$B$106)*($A$41:$A$48=$A81)*$C$41:$C$48)) -> 0 | C81: =IFERROR($B81/$B$84,0) -> 0
B82: =IF($A82="",0,SUMPRODUCT((($D$6:$D$35="Realizado")+($D$6:$D$35="Compromisso")+($D$6:$D$35="Previsto")*Premissas!$B$105+($D$6:$D$35="Em negociação")*Premissas!$B$106)*($B$6:$B$35=$A82)*$C$6:$C$35)+SUMPRODUCT((($B$41:$B$48="Confirmado")+($B$41:$B$48="Em negociação")*Premissas!$B$106)*($A$41:$A$48=$A82)*$C$41:$C$48)) -> 0 | C82: =IFERROR($B82/$B$84,0) -> 0
B83: =IF($A83="",0,SUMPRODUCT((($D$6:$D$35="Realizado")+($D$6:$D$35="Compromisso")+($D$6:$D$35="Previsto")*Premissas!$B$105+($D$6:$D$35="Em negociação")*Premissas!$B$106)*($B$6:$B$35=$A83)*$C$6:$C$35)+SUMPRODUCT((($B$41:$B$48="Confirmado")+($B$41:$B$48="Em negociação")*Premissas!$B$106)*($A$41:$A$48=$A83)*$C$41:$C$48)) -> 0 | C83: =IFERROR($B83/$B$84,0) -> 0
A84: TOTAL | B84: =SUM(B71:B83) -> 117000 | C84: =SUM(C71:C83) -> 1
A85: Capital não atribuído nesta tabela | B85: =C36+C49-B84 -> 200000 | C85: =IF(ROUND(B85,2)=0,"✔ tudo atribuído","⚠ acrescente o nome que falta") -> ⚠ acrescente o nome que falta | E85: Se aparecer valor diferente de zero, algum investidor foi lançado nas tabelas 1 ou 2 e não foi acrescentado aqui. Digite o nome dele numa linha em branco acima — exatamente como está escrito no lançamento.
A87: 6. CRONOGRAMA MENSAL DE ENTRADA DE CAPITAL
A88: Linha do tempo | B88: 46023 | C88: 46054 | D88: 46082 | E88: 46113 | F88: 46143 | G88: 46174 | H88: 46204 | I88: 46235 | J88: 46266 | K88: 46296 | L88: 46327 | M88: 46357 | N88: 46388 | O88: 46419 | P88: 46447 | Q88: 46478 | R88: 46508 | S88: 46539 | T88: 46569 | U88: 46600 | V88: 46631 | W88: 46661 | X88: 46692 | Y88: 46722 | Z88: 46753 | AA88: 46784 | AB88: 46813 | AC88: 46844 | AD88: 46874 | AE88: 46905 | AF88: 46935 | AG88: 46966 | AH88: 46997 | AI88: 47027 | AJ88: 47058 | AK88: 47088 | AL88: 47119 | AM88: 47150 | AN88: 47178 | AO88: 47209 | AP88: 47239 | AQ88: 47270 | AR88: 47300 | AS88: 47331 | AT88: 47362 | AU88: 47392 | AV88: 47423 | AW88: 47453 | AX88: 47484 | AY88: 47515 | AZ88: 47543 | BA88: 47574 | BB88: 47604 | BC88: 47635 | BD88: 47665 | BE88: 47696 | BF88: 47727 | BG88: 47757 | BH88: 47788 | BI88: 47818 | BJ88: TOTAL | BK88: % / Nota
A89: Mês nº | B89: 1 | C89: 2 | D89: 3 | E89: 4 | F89: 5 | G89: 6 | H89: 7 | I89: 8 | J89: 9 | K89: 10 | L89: 11 | M89: 12 | N89: 13 | O89: 14 | P89: 15 | Q89: 16 | R89: 17 | S89: 18 | T89: 19 | U89: 20 | V89: 21 | W89: 22 | X89: 23 | Y89: 24 | Z89: 25 | AA89: 26 | AB89: 27 | AC89: 28 | AD89: 29 | AE89: 30 | AF89: 31 | AG89: 32 | AH89: 33 | AI89: 34 | AJ89: 35 | AK89: 36 | AL89: 37 | AM89: 38 | AN89: 39 | AO89: 40 | AP89: 41 | AQ89: 42 | AR89: 43 | AS89: 44 | AT89: 45 | AU89: 46 | AV89: 47 | AW89: 48 | AX89: 49 | AY89: 50 | AZ89: 51 | BA89: 52 | BB89: 53 | BC89: 54 | BD89: 55 | BE89: 56 | BF89: 57 | BG89: 58 | BH89: 59 | BI89: 60
A90: Ano | B90: =YEAR(B88) -> 2026 | C90: =YEAR(C88) -> 2026 | D90: =YEAR(D88) -> 2026 | E90: =YEAR(E88) -> 2026 | F90: =YEAR(F88) -> 2026 | G90: =YEAR(G88) -> 2026 | H90: =YEAR(H88) -> 2026 | I90: =YEAR(I88) -> 2026 | ... BI90: =YEAR(BI88) -> 2030
A91: Índice do ano (auxiliar) | B91: =MATCH(B90,Premissas!$C$5:$G$5,0) -> 1 | C91: =MATCH(C90,Premissas!$C$5:$G$5,0) -> 1 | D91: =MATCH(D90,Premissas!$C$5:$G$5,0) -> 1 | E91: =MATCH(E90,Premissas!$C$5:$G$5,0) -> 1 | F91: =MATCH(F90,Premissas!$C$5:$G$5,0) -> 1 | G91: =MATCH(G90,Premissas!$C$5:$G$5,0) -> 1 | H91: =MATCH(H90,Premissas!$C$5:$G$5,0) -> 1 | I91: =MATCH(I90,Premissas!$C$5:$G$5,0) -> 1 | ... BI91: =MATCH(BI90,Premissas!$C$5:$G$5,0) -> 5
A92: Aportes de fundadores | B92: =SUMPRODUCT(($E$6:$E$35="Fundador")*(($D$6:$D$35="Realizado")+($D$6:$D$35="Compromisso")+($D$6:$D$35="Previsto")*Premissas!$B$105+($D$6:$D$35="Em negociação")*Premissas!$B$106)*($A$6:$A$35>=B$88)*($A$6:$A$35<=EOMONTH(B$88,0))*$C$6:$C$35) -> 0 | C92: =SUMPRODUCT(($E$6:$E$35="Fundador")*(($D$6:$D$35="Realizado")+($D$6:$D$35="Compromisso")+($D$6:$D$35="Previsto")*Premissas!$B$105+($D$6:$D$35="Em negociação")*Premissas!$B$106)*($A$6:$A$35>=C$88)*($A$6:$A$35<=EOMONTH(C$88,0))*$C$6:$C$35) -> 0 | D92: =SUMPRODUCT(($E$6:$E$35="Fundador")*(($D$6:$D$35="Realizado")+($D$6:$D$35="Compromisso")+($D$6:$D$35="Previsto")*Premissas!$B$105+($D$6:$D$35="Em negociação")*Premissas!$B$106)*($A$6:$A$35>=D$88)*($A$6:$A$35<=EOMONTH(D$88,0))*$C$6:$C$35) -> 0 | E92: =SUMPRODUCT(($E$6:$E$35="Fundador")*(($D$6:$D$35="Realizado")+($D$6:$D$35="Compromisso")+($D$6:$D$35="Previsto")*Premissas!$B$105+($D$6:$D$35="Em negociação")*Premissas!$B$106)*($A$6:$A$35>=E$88)*($A$6:$A$35<=EOMONTH(E$88,0))*$C$6:$C$35) -> 10000 | F92: =SUMPRODUCT(($E$6:$E$35="Fundador")*(($D$6:$D$35="Realizado")+($D$6:$D$35="Compromisso")+($D$6:$D$35="Previsto")*Premissas!$B$105+($D$6:$D$35="Em negociação")*Premissas!$B$106)*($A$6:$A$35>=F$88)*($A$6:$A$35<=EOMONTH(F$88,0))*$C$6:$C$35) -> 0 | G92: =SUMPRODUCT(($E$6:$E$35="Fundador")*(($D$6:$D$35="Realizado")+($D$6:$D$35="Compromisso")+($D$6:$D$35="Previsto")*Premissas!$B$105+($D$6:$D$35="Em negociação")*Premissas!$B$106)*($A$6:$A$35>=G$88)*($A$6:$A$35<=EOMONTH(G$88,0))*$C$6:$C$35) -> 0 | H92: =SUMPRODUCT(($E$6:$E$35="Fundador")*(($D$6:$D$35="Realizado")+($D$6:$D$35="Compromisso")+($D$6:$D$35="Previsto")*Premissas!$B$105+($D$6:$D$35="Em negociação")*Premissas!$B$106)*($A$6:$A$35>=H$88)*($A$6:$A$35<=EOMONTH(H$88,0))*$C$6:$C$35) -> 5000 | I92: =SUMPRODUCT(($E$6:$E$35="Fundador")*(($D$6:$D$35="Realizado")+($D$6:$D$35="Compromisso")+($D$6:$D$35="Previsto")*Premissas!$B$105+($D$6:$D$35="Em negociação")*Premissas!$B$106)*($A$6:$A$35>=I$88)*($A$6:$A$35<=EOMONTH(I$88,0))*$C$6:$C$35) -> 18000 | ... BI92: =SUMPRODUCT(($E$6:$E$35="Fundador")*(($D$6:$D$35="Realizado")+($D$6:$D$35="Compromisso")+($D$6:$D$35="Previsto")*Premissas!$B$105+($D$6:$D$35="Em negociação")*Premissas!$B$106)*($A$6:$A$35>=BI$88)*($A$6:$A$35<=EOMONTH(BI$88,0))*$C$6:$C$35) -> 0 | BJ92: =SUM(B92:BI92) -> 37000
A93: Aportes de novos sócios | B93: =SUMPRODUCT(($E$6:$E$35="Novo sócio")*(($D$6:$D$35="Realizado")+($D$6:$D$35="Compromisso")+($D$6:$D$35="Previsto")*Premissas!$B$105+($D$6:$D$35="Em negociação")*Premissas!$B$106)*($A$6:$A$35>=B$88)*($A$6:$A$35<=EOMONTH(B$88,0))*$C$6:$C$35) -> 0 | C93: =SUMPRODUCT(($E$6:$E$35="Novo sócio")*(($D$6:$D$35="Realizado")+($D$6:$D$35="Compromisso")+($D$6:$D$35="Previsto")*Premissas!$B$105+($D$6:$D$35="Em negociação")*Premissas!$B$106)*($A$6:$A$35>=C$88)*($A$6:$A$35<=EOMONTH(C$88,0))*$C$6:$C$35) -> 0 | D93: =SUMPRODUCT(($E$6:$E$35="Novo sócio")*(($D$6:$D$35="Realizado")+($D$6:$D$35="Compromisso")+($D$6:$D$35="Previsto")*Premissas!$B$105+($D$6:$D$35="Em negociação")*Premissas!$B$106)*($A$6:$A$35>=D$88)*($A$6:$A$35<=EOMONTH(D$88,0))*$C$6:$C$35) -> 0 | E93: =SUMPRODUCT(($E$6:$E$35="Novo sócio")*(($D$6:$D$35="Realizado")+($D$6:$D$35="Compromisso")+($D$6:$D$35="Previsto")*Premissas!$B$105+($D$6:$D$35="Em negociação")*Premissas!$B$106)*($A$6:$A$35>=E$88)*($A$6:$A$35<=EOMONTH(E$88,0))*$C$6:$C$35) -> 0 | F93: =SUMPRODUCT(($E$6:$E$35="Novo sócio")*(($D$6:$D$35="Realizado")+($D$6:$D$35="Compromisso")+($D$6:$D$35="Previsto")*Premissas!$B$105+($D$6:$D$35="Em negociação")*Premissas!$B$106)*($A$6:$A$35>=F$88)*($A$6:$A$35<=EOMONTH(F$88,0))*$C$6:$C$35) -> 0 | G93: =SUMPRODUCT(($E$6:$E$35="Novo sócio")*(($D$6:$D$35="Realizado")+($D$6:$D$35="Compromisso")+($D$6:$D$35="Previsto")*Premissas!$B$105+($D$6:$D$35="Em negociação")*Premissas!$B$106)*($A$6:$A$35>=G$88)*($A$6:$A$35<=EOMONTH(G$88,0))*$C$6:$C$35) -> 0 | H93: =SUMPRODUCT(($E$6:$E$35="Novo sócio")*(($D$6:$D$35="Realizado")+($D$6:$D$35="Compromisso")+($D$6:$D$35="Previsto")*Premissas!$B$105+($D$6:$D$35="Em negociação")*Premissas!$B$106)*($A$6:$A$35>=H$88)*($A$6:$A$35<=EOMONTH(H$88,0))*$C$6:$C$35) -> 0 | I93: =SUMPRODUCT(($E$6:$E$35="Novo sócio")*(($D$6:$D$35="Realizado")+($D$6:$D$35="Compromisso")+($D$6:$D$35="Previsto")*Premissas!$B$105+($D$6:$D$35="Em negociação")*Premissas!$B$106)*($A$6:$A$35>=I$88)*($A$6:$A$35<=EOMONTH(I$88,0))*$C$6:$C$35) -> 0 | ... BI93: =SUMPRODUCT(($E$6:$E$35="Novo sócio")*(($D$6:$D$35="Realizado")+($D$6:$D$35="Compromisso")+($D$6:$D$35="Previsto")*Premissas!$B$105+($D$6:$D$35="Em negociação")*Premissas!$B$106)*($A$6:$A$35>=BI$88)*($A$6:$A$35<=EOMONTH(BI$88,0))*$C$6:$C$35) -> 0 | BJ93: =SUM(B93:BI93) -> 80000
A94: Aportes de investidores estratégicos (lançamentos) | B94: =SUMPRODUCT(($E$6:$E$35="Investidor estratégico")*(($D$6:$D$35="Realizado")+($D$6:$D$35="Compromisso")+($D$6:$D$35="Previsto")*Premissas!$B$105+($D$6:$D$35="Em negociação")*Premissas!$B$106)*($A$6:$A$35>=B$88)*($A$6:$A$35<=EOMONTH(B$88,0))*$C$6:$C$35) -> 0 | C94: =SUMPRODUCT(($E$6:$E$35="Investidor estratégico")*(($D$6:$D$35="Realizado")+($D$6:$D$35="Compromisso")+($D$6:$D$35="Previsto")*Premissas!$B$105+($D$6:$D$35="Em negociação")*Premissas!$B$106)*($A$6:$A$35>=C$88)*($A$6:$A$35<=EOMONTH(C$88,0))*$C$6:$C$35) -> 0 | D94: =SUMPRODUCT(($E$6:$E$35="Investidor estratégico")*(($D$6:$D$35="Realizado")+($D$6:$D$35="Compromisso")+($D$6:$D$35="Previsto")*Premissas!$B$105+($D$6:$D$35="Em negociação")*Premissas!$B$106)*($A$6:$A$35>=D$88)*($A$6:$A$35<=EOMONTH(D$88,0))*$C$6:$C$35) -> 0 | E94: =SUMPRODUCT(($E$6:$E$35="Investidor estratégico")*(($D$6:$D$35="Realizado")+($D$6:$D$35="Compromisso")+($D$6:$D$35="Previsto")*Premissas!$B$105+($D$6:$D$35="Em negociação")*Premissas!$B$106)*($A$6:$A$35>=E$88)*($A$6:$A$35<=EOMONTH(E$88,0))*$C$6:$C$35) -> 0 | F94: =SUMPRODUCT(($E$6:$E$35="Investidor estratégico")*(($D$6:$D$35="Realizado")+($D$6:$D$35="Compromisso")+($D$6:$D$35="Previsto")*Premissas!$B$105+($D$6:$D$35="Em negociação")*Premissas!$B$106)*($A$6:$A$35>=F$88)*($A$6:$A$35<=EOMONTH(F$88,0))*$C$6:$C$35) -> 0 | G94: =SUMPRODUCT(($E$6:$E$35="Investidor estratégico")*(($D$6:$D$35="Realizado")+($D$6:$D$35="Compromisso")+($D$6:$D$35="Previsto")*Premissas!$B$105+($D$6:$D$35="Em negociação")*Premissas!$B$106)*($A$6:$A$35>=G$88)*($A$6:$A$35<=EOMONTH(G$88,0))*$C$6:$C$35) -> 0 | H94: =SUMPRODUCT(($E$6:$E$35="Investidor estratégico")*(($D$6:$D$35="Realizado")+($D$6:$D$35="Compromisso")+($D$6:$D$35="Previsto")*Premissas!$B$105+($D$6:$D$35="Em negociação")*Premissas!$B$106)*($A$6:$A$35>=H$88)*($A$6:$A$35<=EOMONTH(H$88,0))*$C$6:$C$35) -> 0 | I94: =SUMPRODUCT(($E$6:$E$35="Investidor estratégico")*(($D$6:$D$35="Realizado")+($D$6:$D$35="Compromisso")+($D$6:$D$35="Previsto")*Premissas!$B$105+($D$6:$D$35="Em negociação")*Premissas!$B$106)*($A$6:$A$35>=I$88)*($A$6:$A$35<=EOMONTH(I$88,0))*$C$6:$C$35) -> 0 | ... BI94: =SUMPRODUCT(($E$6:$E$35="Investidor estratégico")*(($D$6:$D$35="Realizado")+($D$6:$D$35="Compromisso")+($D$6:$D$35="Previsto")*Premissas!$B$105+($D$6:$D$35="Em negociação")*Premissas!$B$106)*($A$6:$A$35>=BI$88)*($A$6:$A$35<=EOMONTH(BI$88,0))*$C$6:$C$35) -> 0 | BJ94: =SUM(B94:BI94) -> 0
A95: Aportes da tabela de parcerias estratégicas | B95: =SUMPRODUCT((($B$41:$B$48="Confirmado")+($B$41:$B$48="Em negociação")*Premissas!$B$106)*($D$41:$D$48>=B$88)*($D$41:$D$48<=EOMONTH(B$88,0))*$C$41:$C$48) -> 0 | C95: =SUMPRODUCT((($B$41:$B$48="Confirmado")+($B$41:$B$48="Em negociação")*Premissas!$B$106)*($D$41:$D$48>=C$88)*($D$41:$D$48<=EOMONTH(C$88,0))*$C$41:$C$48) -> 0 | D95: =SUMPRODUCT((($B$41:$B$48="Confirmado")+($B$41:$B$48="Em negociação")*Premissas!$B$106)*($D$41:$D$48>=D$88)*($D$41:$D$48<=EOMONTH(D$88,0))*$C$41:$C$48) -> 0 | E95: =SUMPRODUCT((($B$41:$B$48="Confirmado")+($B$41:$B$48="Em negociação")*Premissas!$B$106)*($D$41:$D$48>=E$88)*($D$41:$D$48<=EOMONTH(E$88,0))*$C$41:$C$48) -> 0 | F95: =SUMPRODUCT((($B$41:$B$48="Confirmado")+($B$41:$B$48="Em negociação")*Premissas!$B$106)*($D$41:$D$48>=F$88)*($D$41:$D$48<=EOMONTH(F$88,0))*$C$41:$C$48) -> 0 | G95: =SUMPRODUCT((($B$41:$B$48="Confirmado")+($B$41:$B$48="Em negociação")*Premissas!$B$106)*($D$41:$D$48>=G$88)*($D$41:$D$48<=EOMONTH(G$88,0))*$C$41:$C$48) -> 0 | H95: =SUMPRODUCT((($B$41:$B$48="Confirmado")+($B$41:$B$48="Em negociação")*Premissas!$B$106)*($D$41:$D$48>=H$88)*($D$41:$D$48<=EOMONTH(H$88,0))*$C$41:$C$48) -> 0 | I95: =SUMPRODUCT((($B$41:$B$48="Confirmado")+($B$41:$B$48="Em negociação")*Premissas!$B$106)*($D$41:$D$48>=I$88)*($D$41:$D$48<=EOMONTH(I$88,0))*$C$41:$C$48) -> 0 | ... BI95: =SUMPRODUCT((($B$41:$B$48="Confirmado")+($B$41:$B$48="Em negociação")*Premissas!$B$106)*($D$41:$D$48>=BI$88)*($D$41:$D$48<=EOMONTH(BI$88,0))*$C$41:$C$48) -> 0 | BJ95: =SUM(B95:BI95) -> 200000
A96: TOTAL DE APORTES NO MÊS | B96: =SUM(B92:B95) -> 0 | C96: =SUM(C92:C95) -> 0 | D96: =SUM(D92:D95) -> 0 | E96: =SUM(E92:E95) -> 10000 | F96: =SUM(F92:F95) -> 0 | G96: =SUM(G92:G95) -> 0 | H96: =SUM(H92:H95) -> 5000 | I96: =SUM(I92:I95) -> 18000 | ... BI96: =SUM(BI92:BI95) -> 0 | BJ96: =SUM(B96:BI96) -> 317000
A97: Capital acumulado | B97: =B96 -> 0 | C97: =B97+C96 -> 0 | D97: =C97+D96 -> 0 | E97: =D97+E96 -> 10000 | F97: =E97+F96 -> 10000 | G97: =F97+G96 -> 10000 | H97: =G97+H96 -> 15000 | I97: =H97+I96 -> 33000 | J97: =I97+J96 -> 37000 | ... BI97: =BH97+BI96 -> 317000
A98: Receita B2B das parcerias estratégicas | B98: =SUMPRODUCT((($B$41:$B$48="Confirmado")+($B$41:$B$48="Em negociação")*Premissas!$B$106)*($F$41:$F$48<=B$88)*($G$41:$G$48>=B$88)*$E$41:$E$48) -> 0 | C98: =SUMPRODUCT((($B$41:$B$48="Confirmado")+($B$41:$B$48="Em negociação")*Premissas!$B$106)*($F$41:$F$48<=C$88)*($G$41:$G$48>=C$88)*$E$41:$E$48) -> 0 | D98: =SUMPRODUCT((($B$41:$B$48="Confirmado")+($B$41:$B$48="Em negociação")*Premissas!$B$106)*($F$41:$F$48<=D$88)*($G$41:$G$48>=D$88)*$E$41:$E$48) -> 0 | E98: =SUMPRODUCT((($B$41:$B$48="Confirmado")+($B$41:$B$48="Em negociação")*Premissas!$B$106)*($F$41:$F$48<=E$88)*($G$41:$G$48>=E$88)*$E$41:$E$48) -> 0 | F98: =SUMPRODUCT((($B$41:$B$48="Confirmado")+($B$41:$B$48="Em negociação")*Premissas!$B$106)*($F$41:$F$48<=F$88)*($G$41:$G$48>=F$88)*$E$41:$E$48) -> 0 | G98: =SUMPRODUCT((($B$41:$B$48="Confirmado")+($B$41:$B$48="Em negociação")*Premissas!$B$106)*($F$41:$F$48<=G$88)*($G$41:$G$48>=G$88)*$E$41:$E$48) -> 0 | H98: =SUMPRODUCT((($B$41:$B$48="Confirmado")+($B$41:$B$48="Em negociação")*Premissas!$B$106)*($F$41:$F$48<=H$88)*($G$41:$G$48>=H$88)*$E$41:$E$48) -> 0 | I98: =SUMPRODUCT((($B$41:$B$48="Confirmado")+($B$41:$B$48="Em negociação")*Premissas!$B$106)*($F$41:$F$48<=I$88)*($G$41:$G$48>=I$88)*$E$41:$E$48) -> 0 | ... BI98: =SUMPRODUCT((($B$41:$B$48="Confirmado")+($B$41:$B$48="Em negociação")*Premissas!$B$106)*($F$41:$F$48<=BI$88)*($G$41:$G$48>=BI$88)*$E$41:$E$48) -> 5000 | BJ98: =SUM(B98:BI98) -> 230000 | BK98: Entra na DRE como receita B2B. Some outra parceria na tabela 2 e ela aparece aqui.

Sheet Investimentos
A1: INVESTIMENTOS (CAPEX) — CRONOGRAMA E AMORTIZAÇÃO
A2: Desembolsos de capital. Saem do caixa no mês do lançamento (aba Análise Fluxo) e são amortizados linearmente em 60 meses na DRE. Verde = já realizado.
A3: ⚠ ABA DE AJUSTE · cronograma de desembolso. Investimento sai do caixa no mês da data e é amortizado em 60 meses na DRE — não é despesa do mês.
A4: LANÇAMENTOS DE INVESTIMENTO
A5: Data | B5: Item | C5: Categoria | D5: Valor | E5: Status
A6: 46146 | B6: Constituição da empresa, registro de marca e assessoria jurídica | C6: Marca e jurídico | D6: 6000 | E6: Previsto
A7: 46254 | B7: 2 notebooks Lenovo | C7: Equipamentos | D7: 9127.82 | E7: Realizado | F7: Fatos do brief: 2 notebooks Lenovo por R$ 9.127,82.
A8: 46477 | B8: Adequação LGPD e segurança da informação | C8: Certificações | D8: 12000 | E8: Previsto
A9: 46568 | B9: Equipamentos — expansão da equipe | C9: Equipamentos | D9: 6000 | E9: Previsto
A10: 46934 | B10: Equipamentos | C10: Equipamentos | D10: 15000 | E10: Previsto
A11: 47299 | B11: Equipamentos | C11: Equipamentos | D11: 25000 | E11: Previsto
A12: 47664 | B12: Equipamentos | C12: Equipamentos | D12: 30000 | E12: Previsto
C14: TOTAL | D14: =SUM(D6:D13) -> 103127.82
A16: Linha do tempo | B16: 46023 | C16: 46054 | D16: 46082 | E16: 46113 | F16: 46143 | G16: 46174 | H16: 46204 | I16: 46235 | J16: 46266 | K16: 46296 | L16: 46327 | M16: 46357 | N16: 46388 | O16: 46419 | P16: 46447 | Q16: 46478 | R16: 46508 | S16: 46539 | T16: 46569 | U16: 46600 | V16: 46631 | W16: 46661 | X16: 46692 | Y16: 46722 | Z16: 46753 | AA16: 46784 | AB16: 46813 | AC16: 46844 | AD16: 46874 | AE16: 46905 | AF16: 46935 | AG16: 46966 | AH16: 46997 | AI16: 47027 | AJ16: 47058 | AK16: 47088 | AL16: 47119 | AM16: 47150 | AN16: 47178 | AO16: 47209 | AP16: 47239 | AQ16: 47270 | AR16: 47300 | AS16: 47331 | AT16: 47362 | AU16: 47392 | AV16: 47423 | AW16: 47453 | AX16: 47484 | AY16: 47515 | AZ16: 47543 | BA16: 47574 | BB16: 47604 | BC16: 47635 | BD16: 47665 | BE16: 47696 | BF16: 47727 | BG16: 47757 | BH16: 47788 | BI16: 47818 | BJ16: TOTAL | BK16: % / Nota
A17: Mês nº | B17: 1 | C17: 2 | D17: 3 | E17: 4 | F17: 5 | G17: 6 | H17: 7 | I17: 8 | J17: 9 | K17: 10 | L17: 11 | M17: 12 | N17: 13 | O17: 14 | P17: 15 | Q17: 16 | R17: 17 | S17: 18 | T17: 19 | U17: 20 | V17: 21 | W17: 22 | X17: 23 | Y17: 24 | Z17: 25 | AA17: 26 | AB17: 27 | AC17: 28 | AD17: 29 | AE17: 30 | AF17: 31 | AG17: 32 | AH17: 33 | AI17: 34 | AJ17: 35 | AK17: 36 | AL17: 37 | AM17: 38 | AN17: 39 | AO17: 40 | AP17: 41 | AQ17: 42 | AR17: 43 | AS17: 44 | AT17: 45 | AU17: 46 | AV17: 47 | AW17: 48 | AX17: 49 | AY17: 50 | AZ17: 51 | BA17: 52 | BB17: 53 | BC17: 54 | BD17: 55 | BE17: 56 | BF17: 57 | BG17: 58 | BH17: 59 | BI17: 60
A18: Ano | B18: =YEAR(B16) -> 2026 | C18: =YEAR(C16) -> 2026 | D18: =YEAR(D16) -> 2026 | E18: =YEAR(E16) -> 2026 | F18: =YEAR(F16) -> 2026 | G18: =YEAR(G16) -> 2026 | H18: =YEAR(H16) -> 2026 | I18: =YEAR(I16) -> 2026 | ... BI18: =YEAR(BI16) -> 2030
A20: CRONOGRAMA MENSAL DE DESEMBOLSO
A21: Equipamentos | B21: =SUMIFS($D$6:$D$13,$C$6:$C$13,"Equipamentos",$A$6:$A$13,">="&B$16,$A$6:$A$13,"<="&EOMONTH(B$16,0)) -> 0 | C21: =SUMIFS($D$6:$D$13,$C$6:$C$13,"Equipamentos",$A$6:$A$13,">="&C$16,$A$6:$A$13,"<="&EOMONTH(C$16,0)) -> 0 | D21: =SUMIFS($D$6:$D$13,$C$6:$C$13,"Equipamentos",$A$6:$A$13,">="&D$16,$A$6:$A$13,"<="&EOMONTH(D$16,0)) -> 0 | E21: =SUMIFS($D$6:$D$13,$C$6:$C$13,"Equipamentos",$A$6:$A$13,">="&E$16,$A$6:$A$13,"<="&EOMONTH(E$16,0)) -> 0 | F21: =SUMIFS($D$6:$D$13,$C$6:$C$13,"Equipamentos",$A$6:$A$13,">="&F$16,$A$6:$A$13,"<="&EOMONTH(F$16,0)) -> 0 | G21: =SUMIFS($D$6:$D$13,$C$6:$C$13,"Equipamentos",$A$6:$A$13,">="&G$16,$A$6:$A$13,"<="&EOMONTH(G$16,0)) -> 0 | H21: =SUMIFS($D$6:$D$13,$C$6:$C$13,"Equipamentos",$A$6:$A$13,">="&H$16,$A$6:$A$13,"<="&EOMONTH(H$16,0)) -> 0 | I21: =SUMIFS($D$6:$D$13,$C$6:$C$13,"Equipamentos",$A$6:$A$13,">="&I$16,$A$6:$A$13,"<="&EOMONTH(I$16,0)) -> 9127.82 | ... BI21: =SUMIFS($D$6:$D$13,$C$6:$C$13,"Equipamentos",$A$6:$A$13,">="&BI$16,$A$6:$A$13,"<="&EOMONTH(BI$16,0)) -> 0 | BJ21: =SUM(B21:BI21) -> 85127.82 | BK21: =IFERROR(BJ21/BJ$25,0) -> 0.68580774
A22: Marca e jurídico | B22: =SUMIFS($D$6:$D$13,$C$6:$C$13,"Marca e jurídico",$A$6:$A$13,">="&B$16,$A$6:$A$13,"<="&EOMONTH(B$16,0)) -> 0 | C22: =SUMIFS($D$6:$D$13,$C$6:$C$13,"Marca e jurídico",$A$6:$A$13,">="&C$16,$A$6:$A$13,"<="&EOMONTH(C$16,0)) -> 0 | D22: =SUMIFS($D$6:$D$13,$C$6:$C$13,"Marca e jurídico",$A$6:$A$13,">="&D$16,$A$6:$A$13,"<="&EOMONTH(D$16,0)) -> 0 | E22: =SUMIFS($D$6:$D$13,$C$6:$C$13,"Marca e jurídico",$A$6:$A$13,">="&E$16,$A$6:$A$13,"<="&EOMONTH(E$16,0)) -> 0 | F22: =SUMIFS($D$6:$D$13,$C$6:$C$13,"Marca e jurídico",$A$6:$A$13,">="&F$16,$A$6:$A$13,"<="&EOMONTH(F$16,0)) -> 6000 | G22: =SUMIFS($D$6:$D$13,$C$6:$C$13,"Marca e jurídico",$A$6:$A$13,">="&G$16,$A$6:$A$13,"<="&EOMONTH(G$16,0)) -> 0 | H22: =SUMIFS($D$6:$D$13,$C$6:$C$13,"Marca e jurídico",$A$6:$A$13,">="&H$16,$A$6:$A$13,"<="&EOMONTH(H$16,0)) -> 0 | I22: =SUMIFS($D$6:$D$13,$C$6:$C$13,"Marca e jurídico",$A$6:$A$13,">="&I$16,$A$6:$A$13,"<="&EOMONTH(I$16,0)) -> 0 | ... BI22: =SUMIFS($D$6:$D$13,$C$6:$C$13,"Marca e jurídico",$A$6:$A$13,">="&BI$16,$A$6:$A$13,"<="&EOMONTH(BI$16,0)) -> 0 | BJ22: =SUM(B22:BI22) -> 6000 | BK22: =IFERROR(BJ22/BJ$25,0) -> 0.04833727
A23: Certificações | B23: =SUMIFS($D$6:$D$13,$C$6:$C$13,"Certificações",$A$6:$A$13,">="&B$16,$A$6:$A$13,"<="&EOMONTH(B$16,0)) -> 0 | C23: =SUMIFS($D$6:$D$13,$C$6:$C$13,"Certificações",$A$6:$A$13,">="&C$16,$A$6:$A$13,"<="&EOMONTH(C$16,0)) -> 0 | D23: =SUMIFS($D$6:$D$13,$C$6:$C$13,"Certificações",$A$6:$A$13,">="&D$16,$A$6:$A$13,"<="&EOMONTH(D$16,0)) -> 0 | E23: =SUMIFS($D$6:$D$13,$C$6:$C$13,"Certificações",$A$6:$A$13,">="&E$16,$A$6:$A$13,"<="&EOMONTH(E$16,0)) -> 0 | F23: =SUMIFS($D$6:$D$13,$C$6:$C$13,"Certificações",$A$6:$A$13,">="&F$16,$A$6:$A$13,"<="&EOMONTH(F$16,0)) -> 0 | G23: =SUMIFS($D$6:$D$13,$C$6:$C$13,"Certificações",$A$6:$A$13,">="&G$16,$A$6:$A$13,"<="&EOMONTH(G$16,0)) -> 0 | H23: =SUMIFS($D$6:$D$13,$C$6:$C$13,"Certificações",$A$6:$A$13,">="&H$16,$A$6:$A$13,"<="&EOMONTH(H$16,0)) -> 0 | I23: =SUMIFS($D$6:$D$13,$C$6:$C$13,"Certificações",$A$6:$A$13,">="&I$16,$A$6:$A$13,"<="&EOMONTH(I$16,0)) -> 0 | ... BI23: =SUMIFS($D$6:$D$13,$C$6:$C$13,"Certificações",$A$6:$A$13,">="&BI$16,$A$6:$A$13,"<="&EOMONTH(BI$16,0)) -> 0 | BJ23: =SUM(B23:BI23) -> 12000 | BK23: =IFERROR(BJ23/BJ$25,0) -> 0.096674541
A24: Desenvolvimento do app (pessoal capitalizado) | B24: =Pessoas!B46 -> 0 | C24: =Pessoas!C46 -> 0 | D24: =Pessoas!D46 -> 0 | E24: =Pessoas!E46 -> 0 | F24: =Pessoas!F46 -> 0 | G24: =Pessoas!G46 -> 0 | H24: =Pessoas!H46 -> 0 | I24: =Pessoas!I46 -> 0 | ... BI24: =Pessoas!BI46 -> 0 | BJ24: =SUM(B24:BI24) -> 21000 | BK24: =IFERROR(BJ24/BJ$25,0) -> 0.16918045
A25: TOTAL DE INVESTIMENTOS | B25: =SUM(B21:B24) -> 0 | C25: =SUM(C21:C24) -> 0 | D25: =SUM(D21:D24) -> 0 | E25: =SUM(E21:E24) -> 0 | F25: =SUM(F21:F24) -> 6000 | G25: =SUM(G21:G24) -> 0 | H25: =SUM(H21:H24) -> 0 | I25: =SUM(I21:I24) -> 9127.82 | ... BI25: =SUM(BI21:BI24) -> 0 | BJ25: =SUM(B25:BI25) -> 124127.82
A27: DEPRECIAÇÃO E AMORTIZAÇÃO (linear, 60 meses)
A28: Vida útil adotada (meses) | B28: 60 | D28: Equipamentos de informática: 5 anos (20% a.a., IN RFB 1.700). Software e intangíveis amortizados no mesmo prazo.
A29: Investimento acumulado (base amortizável) | B29: =SUM($B25:B25) -> 0 | C29: =SUM($B25:C25) -> 0 | D29: =SUM($B25:D25) -> 0 | E29: =SUM($B25:E25) -> 0 | F29: =SUM($B25:F25) -> 6000 | G29: =SUM($B25:G25) -> 6000 | H29: =SUM($B25:H25) -> 6000 | I29: =SUM($B25:I25) -> 15127.82 | ... BI29: =SUM($B25:BI25) -> 124127.82 | BJ29: =SUM(B29:BI29) -> 3861274.5
A30: Depreciação e amortização do mês | B30: =0 -> 0 | C30: =B29/$B$28 -> 0 | D30: =C29/$B$28 -> 0 | E30: =D29/$B$28 -> 0 | F30: =E29/$B$28 -> 0 | G30: =F29/$B$28 -> 100 | H30: =G29/$B$28 -> 100 | I30: =H29/$B$28 -> 100 | J30: =I29/$B$28 -> 252.13033 | ... BI30: =BH29/$B$28 -> 2068.797 | BJ30: =SUM(B30:BI30) -> 62285.777 | BK30: Cada item começa a amortizar no mês seguinte ao desembolso.
A31: Saldo contábil do ativo (imobilizado + intangível) | B31: =B25 -> 0 | C31: =B31+C25-C30 -> 0 | D31: =C31+D25-D30 -> 0 | E31: =D31+E25-E30 -> 0 | F31: =E31+F25-F30 -> 6000 | G31: =F31+G25-G30 -> 5900 | H31: =G31+H25-H30 -> 5800 | I31: =H31+I25-I30 -> 14827.82 | J31: =I31+J25-J30 -> 25075.69 | ... BI31: =BH31+BI25-BI30 -> 61842.043

Sheet Sócios
A1: SÓCIOS — QUANTO SOBRA PARA DIVIDIR
A2: Quanto o negócio gera de lucro, quanto disso pode virar dinheiro no bolso dos sócios, e quanto cabe a cada um. Os percentuais de participação são PLACEHOLDER — troque pelos reais quando o quadro societário estiver fechado.
A3: ⚠ ABA DE AJUSTE · os percentuais de participação ainda são provisórios. Troque-os e todo o rateio recalcula. Participação societária depende do valuation de cada rodada, não da proporção do capital aportado.
A4: 1. QUADRO SOCIETÁRIO — preencha quando os percentuais estiverem fechados
A6: Sócio | B6: Tipo | C6: Participação societária | D6: Fatia do pró-labore | E6: Capital aportado | F6: Proporção do capital | G6: Prêmio sobre o capital
A7: Paulo Kapp | B7: Fundador | C7: =0.5/6 -> 0.083333333 | D7: 0.25 | E7: =IF($A7="",0,SUMIFS(Aportes!$C$6:$C$35,Aportes!$B$6:$B$35,$A7)+SUMIFS(Aportes!$C$41:$C$48,Aportes!$A$41:$A$48,$A7)) -> 20000 | F7: =IFERROR($E7/$E$20,0) -> 0.25974026 | G7: =$C7-$F7 -> -0.17640693
A8: Lucas Medina | B8: Fundador | C8: =0.5/6 -> 0.083333333 | D8: 0.25 | E8: =IF($A8="",0,SUMIFS(Aportes!$C$6:$C$35,Aportes!$B$6:$B$35,$A8)+SUMIFS(Aportes!$C$41:$C$48,Aportes!$A$41:$A$48,$A8)) -> 6000 | F8: =IFERROR($E8/$E$20,0) -> 0.077922078 | G8: =$C8-$F8 -> 0.0054112554
A9: Felipe Toescher | B9: Fundador | C9: =0.5/6 -> 0.083333333 | D9: 0.25 | E9: =IF($A9="",0,SUMIFS(Aportes!$C$6:$C$35,Aportes!$B$6:$B$35,$A9)+SUMIFS(Aportes!$C$41:$C$48,Aportes!$A$41:$A$48,$A9)) -> 5000 | F9: =IFERROR($E9/$E$20,0) -> 0.064935065 | G9: =$C9-$F9 -> 0.018398268
A10: Lucas Iung | B10: Fundador | C10: =0.5/6 -> 0.083333333 | D10: 0.25 | E10: =IF($A10="",0,SUMIFS(Aportes!$C$6:$C$35,Aportes!$B$6:$B$35,$A10)+SUMIFS(Aportes!$C$41:$C$48,Aportes!$A$41:$A$48,$A10)) -> 6000 | F10: =IFERROR($E10/$E$20,0) -> 0.077922078 | G10: =$C10-$F10 -> 0.0054112554
A11: Felipe Martinelli | B11: Investidor | C11: =0.5/6 -> 0.083333333 | D11: 0 | E11: =IF($A11="",0,SUMIFS(Aportes!$C$6:$C$35,Aportes!$B$6:$B$35,$A11)+SUMIFS(Aportes!$C$41:$C$48,Aportes!$A$41:$A$48,$A11)) -> 40000 | F11: =IFERROR($E11/$E$20,0) -> 0.51948052 | G11: =$C11-$F11 -> -0.43614719
A12: CioT | B12: Investidor | C12: =0.5/6 -> 0.083333333 | D12: 0 | E12: =IF($A12="",0,SUMIFS(Aportes!$C$6:$C$35,Aportes!$B$6:$B$35,$A12)+SUMIFS(Aportes!$C$41:$C$48,Aportes!$A$41:$A$48,$A12)) -> 0 | F12: =IFERROR($E12/$E$20,0) -> 0 | G12: =$C12-$F12 -> 0.083333333
A13: Tesouraria | B13: Fundador | C13: 0.5 | D13: 0 | E13: =IF($A13="",0,SUMIFS(Aportes!$C$6:$C$35,Aportes!$B$6:$B$35,$A13)+SUMIFS(Aportes!$C$41:$C$48,Aportes!$A$41:$A$48,$A13)) -> 0 | F13: =IFERROR($E13/$E$20,0) -> 0 | G13: =$C13-$F13 -> 0.5
B14: Investidor | D14: 0 | E14: =IF($A14="",0,SUMIFS(Aportes!$C$6:$C$35,Aportes!$B$6:$B$35,$A14)+SUMIFS(Aportes!$C$41:$C$48,Aportes!$A$41:$A$48,$A14)) -> 0 | F14: =IFERROR($E14/$E$20,0) -> 0 | G14: =$C14-$F14 -> 0
B15: Investidor | C15: 0 | D15: 0 | E15: =IF($A15="",0,SUMIFS(Aportes!$C$6:$C$35,Aportes!$B$6:$B$35,$A15)+SUMIFS(Aportes!$C$41:$C$48,Aportes!$A$41:$A$48,$A15)) -> 0 | F15: =IFERROR($E15/$E$20,0) -> 0 | G15: =$C15-$F15 -> 0
B16: Investidor | C16: 0 | D16: 0 | E16: =IF($A16="",0,SUMIFS(Aportes!$C$6:$C$35,Aportes!$B$6:$B$35,$A16)+SUMIFS(Aportes!$C$41:$C$48,Aportes!$A$41:$A$48,$A16)) -> 0 | F16: =IFERROR($E16/$E$20,0) -> 0 | G16: =$C16-$F16 -> 0
B17: Investidor | C17: 0 | D17: 0 | E17: =IF($A17="",0,SUMIFS(Aportes!$C$6:$C$35,Aportes!$B$6:$B$35,$A17)+SUMIFS(Aportes!$C$41:$C$48,Aportes!$A$41:$A$48,$A17)) -> 0 | F17: =IFERROR($E17/$E$20,0) -> 0 | G17: =$C17-$F17 -> 0
B18: Investidor | C18: 0 | D18: 0 | E18: =IF($A18="",0,SUMIFS(Aportes!$C$6:$C$35,Aportes!$B$6:$B$35,$A18)+SUMIFS(Aportes!$C$41:$C$48,Aportes!$A$41:$A$48,$A18)) -> 0 | F18: =IFERROR($E18/$E$20,0) -> 0 | G18: =$C18-$F18 -> 0
B19: Investidor | C19: 0 | D19: 0 | E19: =IF($A19="",0,SUMIFS(Aportes!$C$6:$C$35,Aportes!$B$6:$B$35,$A19)+SUMIFS(Aportes!$C$41:$C$48,Aportes!$A$41:$A$48,$A19)) -> 0 | F19: =IFERROR($E19/$E$20,0) -> 0 | G19: =$C19-$F19 -> 0
A20: TOTAL | C20: =SUM(C7:C19) -> 1 | D20: =SUM(D7:D19) -> 1 | E20: =SUM(E7:E19) -> 77000 | F20: =SUM(F7:F19) -> 1
A21: Verificação — a participação soma 100%? | C21: =IF(ROUND(C20,6)=1,"✔ SIM","⚠ NÃO — ajuste") -> ✔ SIM
A23: 2. POLÍTICA DE DISTRIBUIÇÃO
A24: Meses de custo operacional a manter em caixa | B24: 6
A25: % do lucro disponível distribuído no ano | B25: 0 | C25: 0 | D25: 0.3 | E25: 0.4 | F25: 0.5 | I25: Zero nos primeiros anos: o caixa é para financiar o crescimento. A partir de 2028 distribui parte, e retém o resto.
A27: 3. APURAÇÃO — CENÁRIO ATIVO
B28: 2026 | C28: 2027 | D28: 2028 | E28: 2029 | F28: 2030 | G28: TOTAL
A29: Lucro líquido do exercício | B29: ='DRE Projetada'!B65 -> -38819.218 | C29: ='DRE Projetada'!C65 -> -71699.197 | D29: ='DRE Projetada'!D65 -> 1220220.7 | E29: ='DRE Projetada'!E65 -> 2107371.4 | F29: ='DRE Projetada'!F65 -> 4495092.4 | G29: =SUM(B29:F29) -> 7712166 | I29: Vem da DRE anual. É lucro contábil, não dinheiro em caixa.
A30: Lucro acumulado (compensa prejuízo dos anos anteriores) | B30: =B29 -> -38819.218 | C30: =B30+C29 -> -110518.42 | D30: =C30+D29 -> 1109702.2 | E30: =D30+E29 -> 3217073.6 | F30: =E30+F29 -> 7712166 | I30: Prejuízo de um ano abate o lucro do seguinte antes de qualquer distribuição.
A31: Distribuições já feitas em anos anteriores | B31: =0 -> 0 | C31: =B40 -> 0 | D31: =C40 -> 0 | E31: =D40 -> 0 | F31: =E40 -> 0 | I31: O que já foi distribuído em anos anteriores não pode ser distribuído de novo, nem continua em caixa.
A32: Lucro ainda não distribuído | B32: =MAX(0,B30-B31) -> 0 | C32: =MAX(0,C30-C31) -> 0 | D32: =MAX(0,D30-D31) -> 1109702.2 | E32: =MAX(0,E30-E31) -> 3217073.6 | F32: =MAX(0,F30-F31) -> 7712166
A33: Caixa em dezembro (antes de distribuir) | B33: ='Análise Fluxo'!M39 -> 44236.483 | C33: ='Análise Fluxo'!Y39 -> 164162.85 | D33: ='Análise Fluxo'!AK39 -> 1381709.1 | E33: ='Análise Fluxo'!AW39 -> 3480406 | F33: ='Análise Fluxo'!BI39 -> 7967323.9
A34: (−) Distribuições de anos anteriores | B34: =-B31 -> 0 | C34: =-C31 -> 0 | D34: =-D31 -> 0 | E34: =-E31 -> 0 | F34: =-F31 -> 0
A35: (−) Reserva de caixa | B35: =-$B$24*ABS(SUMIFS('Análise Fluxo'!$B$28:$BI$28,'Análise Fluxo'!$B$6:$BI$6,B$28))/12 -> -21913.348 | C35: =-$B$24*ABS(SUMIFS('Análise Fluxo'!$B$28:$BI$28,'Análise Fluxo'!$B$6:$BI$6,C$28))/12 -> -2164222.1 | D35: =-$B$24*ABS(SUMIFS('Análise Fluxo'!$B$28:$BI$28,'Análise Fluxo'!$B$6:$BI$6,D$28))/12 -> -5325248.1 | E35: =-$B$24*ABS(SUMIFS('Análise Fluxo'!$B$28:$BI$28,'Análise Fluxo'!$B$6:$BI$6,E$28))/12 -> -9555660.9 | F35: =-$B$24*ABS(SUMIFS('Análise Fluxo'!$B$28:$BI$28,'Análise Fluxo'!$B$6:$BI$6,F$28))/12 -> -15461490 | I35: Meses de custo operacional médio do ano, conforme a política acima.
A36: Caixa livre | B36: =MAX(0,B33+B34+B35) -> 22323.135 | C36: =MAX(0,C33+C34+C35) -> 0 | D36: =MAX(0,D33+D34+D35) -> 0 | E36: =MAX(0,E33+E34+E35) -> 0 | F36: =MAX(0,F33+F34+F35) -> 0
A37: LUCRO DISTRIBUÍVEL (o menor entre lucro e caixa livre) | B37: =MIN(B32,B36) -> 0 | C37: =MIN(C32,C36) -> 0 | D37: =MIN(D32,D36) -> 0 | E37: =MIN(E32,E36) -> 0 | F37: =MIN(F32,F36) -> 0 | I37: Só se distribui o que é lucro E está em caixa. Um dos dois limita.
A38: % aplicado | B38: =B25 -> 0 | C38: =C25 -> 0 | D38: =D25 -> 0.3 | E38: =E25 -> 0.4 | F38: =F25 -> 0.5
A39: DISTRIBUÍDO NO ANO | B39: =B37*B38 -> 0 | C39: =C37*C38 -> 0 | D39: =D37*D38 -> 0 | E39: =E37*E38 -> 0 | F39: =F37*F38 -> 0 | G39: =SUM(B39:F39) -> 0
A40: Distribuições acumuladas | B40: =B39 -> 0 | C40: =B40+C39 -> 0 | D40: =C40+D39 -> 0 | E40: =D40+E39 -> 0 | F40: =E40+F39 -> 0
A41: Pró-labore pago aos sócios no ano | B41: =SUMIFS(Pessoas!$B$44:$BI$44,Pessoas!$B$38:$BI$38,B$28) -> 0 | C41: =SUMIFS(Pessoas!$B$44:$BI$44,Pessoas!$B$38:$BI$38,C$28) -> 180000 | D41: =SUMIFS(Pessoas!$B$44:$BI$44,Pessoas!$B$38:$BI$38,D$28) -> 180000 | E41: =SUMIFS(Pessoas!$B$44:$BI$44,Pessoas!$B$38:$BI$38,E$28) -> 384000 | F41: =SUMIFS(Pessoas!$B$44:$BI$44,Pessoas!$B$38:$BI$38,F$28) -> 384000 | G41: =SUM(B41:F41) -> 1128000 | I41: Já está na DRE como despesa — é dinheiro que os sócios recebem trabalhando, separado da distribuição de lucros.
A42: Lucro retido na empresa | B42: =B30-B40 -> -38819.218 | C42: =C30-C40 -> -110518.42 | D42: =D30-D40 -> 1109702.2 | E42: =E30-E40 -> 3217073.6 | F42: =F30-F40 -> 7712166 | I42: Fica na empresa para financiar crescimento — e continua sendo dos sócios.
A44: 4. QUANTO CABE A CADA SÓCIO
A45: Distribuição de lucros por sócio | B45: 2026 | C45: 2027 | D45: 2028 | E45: 2029 | F45: 2030 | G45: TOTAL 5 ANOS
A46: =IF($A7="","",$A7) -> Paulo Kapp | B46: =$C7*B$39 -> 0 | C46: =$C7*C$39 -> 0 | D46: =$C7*D$39 -> 0 | E46: =$C7*E$39 -> 0 | F46: =$C7*F$39 -> 0 | G46: =SUM(B46:F46) -> 0
A47: =IF($A8="","",$A8) -> Lucas Medina | B47: =$C8*B$39 -> 0 | C47: =$C8*C$39 -> 0 | D47: =$C8*D$39 -> 0 | E47: =$C8*E$39 -> 0 | F47: =$C8*F$39 -> 0 | G47: =SUM(B47:F47) -> 0
A48: =IF($A9="","",$A9) -> Felipe Toescher | B48: =$C9*B$39 -> 0 | C48: =$C9*C$39 -> 0 | D48: =$C9*D$39 -> 0 | E48: =$C9*E$39 -> 0 | F48: =$C9*F$39 -> 0 | G48: =SUM(B48:F48) -> 0
A49: =IF($A10="","",$A10) -> Lucas Iung | B49: =$C10*B$39 -> 0 | C49: =$C10*C$39 -> 0 | D49: =$C10*D$39 -> 0 | E49: =$C10*E$39 -> 0 | F49: =$C10*F$39 -> 0 | G49: =SUM(B49:F49) -> 0
A50: =IF($A11="","",$A11) -> Felipe Martinelli | B50: =$C11*B$39 -> 0 | C50: =$C11*C$39 -> 0 | D50: =$C11*D$39 -> 0 | E50: =$C11*E$39 -> 0 | F50: =$C11*F$39 -> 0 | G50: =SUM(B50:F50) -> 0
A51: =IF($A12="","",$A12) -> CioT | B51: =$C12*B$39 -> 0 | C51: =$C12*C$39 -> 0 | D51: =$C12*D$39 -> 0 | E51: =$C12*E$39 -> 0 | F51: =$C12*F$39 -> 0 | G51: =SUM(B51:F51) -> 0
A52: =IF($A13="","",$A13) -> Tesouraria | B52: =$C13*B$39 -> 0 | C52: =$C13*C$39 -> 0 | D52: =$C13*D$39 -> 0 | E52: =$C13*E$39 -> 0 | F52: =$C13*F$39 -> 0 | G52: =SUM(B52:F52) -> 0
A53: =IF($A14="","",$A14) | B53: =$C14*B$39 -> 0 | C53: =$C14*C$39 -> 0 | D53: =$C14*D$39 -> 0 | E53: =$C14*E$39 -> 0 | F53: =$C14*F$39 -> 0 | G53: =SUM(B53:F53) -> 0
A54: =IF($A15="","",$A15) | B54: =$C15*B$39 -> 0 | C54: =$C15*C$39 -> 0 | D54: =$C15*D$39 -> 0 | E54: =$C15*E$39 -> 0 | F54: =$C15*F$39 -> 0 | G54: =SUM(B54:F54) -> 0
A55: =IF($A16="","",$A16) | B55: =$C16*B$39 -> 0 | C55: =$C16*C$39 -> 0 | D55: =$C16*D$39 -> 0 | E55: =$C16*E$39 -> 0 | F55: =$C16*F$39 -> 0 | G55: =SUM(B55:F55) -> 0
A56: =IF($A17="","",$A17) | B56: =$C17*B$39 -> 0 | C56: =$C17*C$39 -> 0 | D56: =$C17*D$39 -> 0 | E56: =$C17*E$39 -> 0 | F56: =$C17*F$39 -> 0 | G56: =SUM(B56:F56) -> 0
A57: =IF($A18="","",$A18) | B57: =$C18*B$39 -> 0 | C57: =$C18*C$39 -> 0 | D57: =$C18*D$39 -> 0 | E57: =$C18*E$39 -> 0 | F57: =$C18*F$39 -> 0 | G57: =SUM(B57:F57) -> 0
A58: =IF($A19="","",$A19) | B58: =$C19*B$39 -> 0 | C58: =$C19*C$39 -> 0 | D58: =$C19*D$39 -> 0 | E58: =$C19*E$39 -> 0 | F58: =$C19*F$39 -> 0 | G58: =SUM(B58:F58) -> 0
A59: TOTAL DISTRIBUÍDO | B59: =SUM(B46:B58) -> 0 | C59: =SUM(C46:C58) -> 0 | D59: =SUM(D46:D58) -> 0 | E59: =SUM(E46:E58) -> 0 | F59: =SUM(F46:F58) -> 0 | G59: =SUM(G46:G58) -> 0
A61: Total recebido por sócio nos 5 anos | B61: Distribuição de lucros | C61: Pró-labore | D61: TOTAL RECEBIDO | E61: Por 1% de participação
A62: =IF($A7="","",$A7) -> Paulo Kapp | B62: =$G46 -> 0 | C62: =$D7*$G$41 -> 282000 | D62: =$B62+$C62 -> 282000 | E62: =IFERROR($B62/$C7/100,0) -> 0
A63: =IF($A8="","",$A8) -> Lucas Medina | B63: =$G47 -> 0 | C63: =$D8*$G$41 -> 282000 | D63: =$B63+$C63 -> 282000 | E63: =IFERROR($B63/$C8/100,0) -> 0
A64: =IF($A9="","",$A9) -> Felipe Toescher | B64: =$G48 -> 0 | C64: =$D9*$G$41 -> 282000 | D64: =$B64+$C64 -> 282000 | E64: =IFERROR($B64/$C9/100,0) -> 0
A65: =IF($A10="","",$A10) -> Lucas Iung | B65: =$G49 -> 0 | C65: =$D10*$G$41 -> 282000 | D65: =$B65+$C65 -> 282000 | E65: =IFERROR($B65/$C10/100,0) -> 0
A66: =IF($A11="","",$A11) -> Felipe Martinelli | B66: =$G50 -> 0 | C66: =$D11*$G$41 -> 0 | D66: =$B66+$C66 -> 0 | E66: =IFERROR($B66/$C11/100,0) -> 0
A67: =IF($A12="","",$A12) -> CioT | B67: =$G51 -> 0 | C67: =$D12*$G$41 -> 0 | D67: =$B67+$C67 -> 0 | E67: =IFERROR($B67/$C12/100,0) -> 0
A68: =IF($A13="","",$A13) -> Tesouraria | B68: =$G52 -> 0 | C68: =$D13*$G$41 -> 0 | D68: =$B68+$C68 -> 0 | E68: =IFERROR($B68/$C13/100,0) -> 0
A69: =IF($A14="","",$A14) | B69: =$G53 -> 0 | C69: =$D14*$G$41 -> 0 | D69: =$B69+$C69 -> 0 | E69: =IFERROR($B69/$C14/100,0) -> 0
A70: =IF($A15="","",$A15) | B70: =$G54 -> 0 | C70: =$D15*$G$41 -> 0 | D70: =$B70+$C70 -> 0 | E70: =IFERROR($B70/$C15/100,0) -> 0
A71: =IF($A16="","",$A16) | B71: =$G55 -> 0 | C71: =$D16*$G$41 -> 0 | D71: =$B71+$C71 -> 0 | E71: =IFERROR($B71/$C16/100,0) -> 0
A72: =IF($A17="","",$A17) | B72: =$G56 -> 0 | C72: =$D17*$G$41 -> 0 | D72: =$B72+$C72 -> 0 | E72: =IFERROR($B72/$C17/100,0) -> 0
A73: =IF($A18="","",$A18) | B73: =$G57 -> 0 | C73: =$D18*$G$41 -> 0 | D73: =$B73+$C73 -> 0 | E73: =IFERROR($B73/$C18/100,0) -> 0
A74: =IF($A19="","",$A19) | B74: =$G58 -> 0 | C74: =$D19*$G$41 -> 0 | D74: =$B74+$C74 -> 0 | E74: =IFERROR($B74/$C19/100,0) -> 0

Sheet Faturamento
A1: FATURAMENTO PROJETADO
A2: =" Cenário ativo: "&Premissas!B7 -> Cenário ativo: PROVÁVEL
A4: Linha do tempo | B4: 46023 | C4: 46054 | D4: 46082 | E4: 46113 | F4: 46143 | G4: 46174 | H4: 46204 | I4: 46235 | J4: 46266 | K4: 46296 | L4: 46327 | M4: 46357 | N4: 46388 | O4: 46419 | P4: 46447 | Q4: 46478 | R4: 46508 | S4: 46539 | T4: 46569 | U4: 46600 | V4: 46631 | W4: 46661 | X4: 46692 | Y4: 46722 | Z4: 46753 | AA4: 46784 | AB4: 46813 | AC4: 46844 | AD4: 46874 | AE4: 46905 | AF4: 46935 | AG4: 46966 | AH4: 46997 | AI4: 47027 | AJ4: 47058 | AK4: 47088 | AL4: 47119 | AM4: 47150 | AN4: 47178 | AO4: 47209 | AP4: 47239 | AQ4: 47270 | AR4: 47300 | AS4: 47331 | AT4: 47362 | AU4: 47392 | AV4: 47423 | AW4: 47453 | AX4: 47484 | AY4: 47515 | AZ4: 47543 | BA4: 47574 | BB4: 47604 | BC4: 47635 | BD4: 47665 | BE4: 47696 | BF4: 47727 | BG4: 47757 | BH4: 47788 | BI4: 47818 | BJ4: TOTAL | BK4: % / Nota
A5: Mês nº | B5: 1 | C5: 2 | D5: 3 | E5: 4 | F5: 5 | G5: 6 | H5: 7 | I5: 8 | J5: 9 | K5: 10 | L5: 11 | M5: 12 | N5: 13 | O5: 14 | P5: 15 | Q5: 16 | R5: 17 | S5: 18 | T5: 19 | U5: 20 | V5: 21 | W5: 22 | X5: 23 | Y5: 24 | Z5: 25 | AA5: 26 | AB5: 27 | AC5: 28 | AD5: 29 | AE5: 30 | AF5: 31 | AG5: 32 | AH5: 33 | AI5: 34 | AJ5: 35 | AK5: 36 | AL5: 37 | AM5: 38 | AN5: 39 | AO5: 40 | AP5: 41 | AQ5: 42 | AR5: 43 | AS5: 44 | AT5: 45 | AU5: 46 | AV5: 47 | AW5: 48 | AX5: 49 | AY5: 50 | AZ5: 51 | BA5: 52 | BB5: 53 | BC5: 54 | BD5: 55 | BE5: 56 | BF5: 57 | BG5: 58 | BH5: 59 | BI5: 60
A6: Ano | B6: =YEAR(B4) -> 2026 | C6: =YEAR(C4) -> 2026 | D6: =YEAR(D4) -> 2026 | E6: =YEAR(E4) -> 2026 | F6: =YEAR(F4) -> 2026 | G6: =YEAR(G4) -> 2026 | H6: =YEAR(H4) -> 2026 | I6: =YEAR(I4) -> 2026 | ... BI6: =YEAR(BI4) -> 2030
A7: Índice do ano (auxiliar) | B7: =MATCH(B6,Premissas!$C$5:$G$5,0) -> 1 | C7: =MATCH(C6,Premissas!$C$5:$G$5,0) -> 1 | D7: =MATCH(D6,Premissas!$C$5:$G$5,0) -> 1 | E7: =MATCH(E6,Premissas!$C$5:$G$5,0) -> 1 | F7: =MATCH(F6,Premissas!$C$5:$G$5,0) -> 1 | G7: =MATCH(G6,Premissas!$C$5:$G$5,0) -> 1 | H7: =MATCH(H6,Premissas!$C$5:$G$5,0) -> 1 | I7: =MATCH(I6,Premissas!$C$5:$G$5,0) -> 1 | ... BI7: =MATCH(BI6,Premissas!$C$5:$G$5,0) -> 5
A8: RECEITA BRUTA
A9: Assinaturas — Plano Essencial | B9: =CHOOSE(Premissas!$B$6,Cenários!B20,Cenários!B66,Cenários!B112) -> 0 | C9: =CHOOSE(Premissas!$B$6,Cenários!C20,Cenários!C66,Cenários!C112) -> 0 | D9: =CHOOSE(Premissas!$B$6,Cenários!D20,Cenários!D66,Cenários!D112) -> 0 | E9: =CHOOSE(Premissas!$B$6,Cenários!E20,Cenários!E66,Cenários!E112) -> 0 | F9: =CHOOSE(Premissas!$B$6,Cenários!F20,Cenários!F66,Cenários!F112) -> 0 | G9: =CHOOSE(Premissas!$B$6,Cenários!G20,Cenários!G66,Cenários!G112) -> 0 | H9: =CHOOSE(Premissas!$B$6,Cenários!H20,Cenários!H66,Cenários!H112) -> 0 | I9: =CHOOSE(Premissas!$B$6,Cenários!I20,Cenários!I66,Cenários!I112) -> 0 | ... BI9: =CHOOSE(Premissas!$B$6,Cenários!BI20,Cenários!BI66,Cenários!BI112) -> 1806139.5 | BJ9: =SUM(B9:BI9) -> 41960684 | BK9: =IFERROR(BJ9/BJ$16,0) -> 0.57613356
A10: Assinaturas — Plano Premium | B10: =CHOOSE(Premissas!$B$6,Cenários!B21,Cenários!B67,Cenários!B113) -> 0 | C10: =CHOOSE(Premissas!$B$6,Cenários!C21,Cenários!C67,Cenários!C113) -> 0 | D10: =CHOOSE(Premissas!$B$6,Cenários!D21,Cenários!D67,Cenários!D113) -> 0 | E10: =CHOOSE(Premissas!$B$6,Cenários!E21,Cenários!E67,Cenários!E113) -> 0 | F10: =CHOOSE(Premissas!$B$6,Cenários!F21,Cenários!F67,Cenários!F113) -> 0 | G10: =CHOOSE(Premissas!$B$6,Cenários!G21,Cenários!G67,Cenários!G113) -> 0 | H10: =CHOOSE(Premissas!$B$6,Cenários!H21,Cenários!H67,Cenários!H113) -> 0 | I10: =CHOOSE(Premissas!$B$6,Cenários!I21,Cenários!I67,Cenários!I113) -> 0 | ... BI10: =CHOOSE(Premissas!$B$6,Cenários!BI21,Cenários!BI67,Cenários!BI113) -> 948355.1 | BJ10: =SUM(B10:BI10) -> 18131032 | BK10: =IFERROR(BJ10/BJ$16,0) -> 0.24894485
A11: Assinaturas — Plano Família | B11: =CHOOSE(Premissas!$B$6,Cenários!B22,Cenários!B68,Cenários!B114) -> 0 | C11: =CHOOSE(Premissas!$B$6,Cenários!C22,Cenários!C68,Cenários!C114) -> 0 | D11: =CHOOSE(Premissas!$B$6,Cenários!D22,Cenários!D68,Cenários!D114) -> 0 | E11: =CHOOSE(Premissas!$B$6,Cenários!E22,Cenários!E68,Cenários!E114) -> 0 | F11: =CHOOSE(Premissas!$B$6,Cenários!F22,Cenários!F68,Cenários!F114) -> 0 | G11: =CHOOSE(Premissas!$B$6,Cenários!G22,Cenários!G68,Cenários!G114) -> 0 | H11: =CHOOSE(Premissas!$B$6,Cenários!H22,Cenários!H68,Cenários!H114) -> 0 | I11: =CHOOSE(Premissas!$B$6,Cenários!I22,Cenários!I68,Cenários!I114) -> 0 | ... BI11: =CHOOSE(Premissas!$B$6,Cenários!BI22,Cenários!BI68,Cenários!BI114) -> 492789 | BJ11: =SUM(B11:BI11) -> 8792594 | BK11: =IFERROR(BJ11/BJ$16,0) -> 0.12072512
A12: Marketplace — comissões sobre dispositivos | B12: =CHOOSE(Premissas!$B$6,Cenários!B24,Cenários!B70,Cenários!B116) -> 0 | C12: =CHOOSE(Premissas!$B$6,Cenários!C24,Cenários!C70,Cenários!C116) -> 0 | D12: =CHOOSE(Premissas!$B$6,Cenários!D24,Cenários!D70,Cenários!D116) -> 0 | E12: =CHOOSE(Premissas!$B$6,Cenários!E24,Cenários!E70,Cenários!E116) -> 0 | F12: =CHOOSE(Premissas!$B$6,Cenários!F24,Cenários!F70,Cenários!F116) -> 0 | G12: =CHOOSE(Premissas!$B$6,Cenários!G24,Cenários!G70,Cenários!G116) -> 0 | H12: =CHOOSE(Premissas!$B$6,Cenários!H24,Cenários!H70,Cenários!H116) -> 0 | I12: =CHOOSE(Premissas!$B$6,Cenários!I24,Cenários!I70,Cenários!I116) -> 0 | ... BI12: =CHOOSE(Premissas!$B$6,Cenários!BI24,Cenários!BI70,Cenários!BI116) -> 195265.12 | BJ12: =SUM(B12:BI12) -> 3470461.5 | BK12: =IFERROR(BJ12/BJ$16,0) -> 0.047650542
A13: B2B — parcerias estratégicas | B13: =CHOOSE(Premissas!$B$6,Cenários!B25,Cenários!B71,Cenários!B117) -> 0 | C13: =CHOOSE(Premissas!$B$6,Cenários!C25,Cenários!C71,Cenários!C117) -> 0 | D13: =CHOOSE(Premissas!$B$6,Cenários!D25,Cenários!D71,Cenários!D117) -> 0 | E13: =CHOOSE(Premissas!$B$6,Cenários!E25,Cenários!E71,Cenários!E117) -> 0 | F13: =CHOOSE(Premissas!$B$6,Cenários!F25,Cenários!F71,Cenários!F117) -> 0 | G13: =CHOOSE(Premissas!$B$6,Cenários!G25,Cenários!G71,Cenários!G117) -> 0 | H13: =CHOOSE(Premissas!$B$6,Cenários!H25,Cenários!H71,Cenários!H117) -> 0 | I13: =CHOOSE(Premissas!$B$6,Cenários!I25,Cenários!I71,Cenários!I117) -> 0 | ... BI13: =CHOOSE(Premissas!$B$6,Cenários!BI25,Cenários!BI71,Cenários!BI117) -> 5000 | BJ13: =SUM(B13:BI13) -> 230000 | BK13: =IFERROR(BJ13/BJ$16,0) -> 0.0031579733
A14: B2B — venda de dados | B14: =CHOOSE(Premissas!$B$6,Cenários!B26,Cenários!B72,Cenários!B118) -> 0 | C14: =CHOOSE(Premissas!$B$6,Cenários!C26,Cenários!C72,Cenários!C118) -> 0 | D14: =CHOOSE(Premissas!$B$6,Cenários!D26,Cenários!D72,Cenários!D118) -> 0 | E14: =CHOOSE(Premissas!$B$6,Cenários!E26,Cenários!E72,Cenários!E118) -> 0 | F14: =CHOOSE(Premissas!$B$6,Cenários!F26,Cenários!F72,Cenários!F118) -> 0 | G14: =CHOOSE(Premissas!$B$6,Cenários!G26,Cenários!G72,Cenários!G118) -> 0 | H14: =CHOOSE(Premissas!$B$6,Cenários!H26,Cenários!H72,Cenários!H118) -> 0 | I14: =CHOOSE(Premissas!$B$6,Cenários!I26,Cenários!I72,Cenários!I118) -> 0 | ... BI14: =CHOOSE(Premissas!$B$6,Cenários!BI26,Cenários!BI72,Cenários!BI118) -> 5750 | BJ14: =SUM(B14:BI14) -> 246750 | BK14: =IFERROR(BJ14/BJ$16,0) -> 0.0033879562
A15: B2B — outras iniciativas | B15: =CHOOSE(Premissas!$B$6,Cenários!B27,Cenários!B73,Cenários!B119) -> 0 | C15: =CHOOSE(Premissas!$B$6,Cenários!C27,Cenários!C73,Cenários!C119) -> 0 | D15: =CHOOSE(Premissas!$B$6,Cenários!D27,Cenários!D73,Cenários!D119) -> 0 | E15: =CHOOSE(Premissas!$B$6,Cenários!E27,Cenários!E73,Cenários!E119) -> 0 | F15: =CHOOSE(Premissas!$B$6,Cenários!F27,Cenários!F73,Cenários!F119) -> 0 | G15: =CHOOSE(Premissas!$B$6,Cenários!G27,Cenários!G73,Cenários!G119) -> 0 | H15: =CHOOSE(Premissas!$B$6,Cenários!H27,Cenários!H73,Cenários!H119) -> 0 | I15: =CHOOSE(Premissas!$B$6,Cenários!I27,Cenários!I73,Cenários!I119) -> 0 | ... BI15: =CHOOSE(Premissas!$B$6,Cenários!BI27,Cenários!BI73,Cenários!BI119) -> 0 | BJ15: =SUM(B15:BI15) -> 0 | BK15: =IFERROR(BJ15/BJ$16,0) -> 0
A16: RECEITA BRUTA TOTAL | B16: =SUM(B9:B15) -> 0 | C16: =SUM(C9:C15) -> 0 | D16: =SUM(D9:D15) -> 0 | E16: =SUM(E9:E15) -> 0 | F16: =SUM(F9:F15) -> 0 | G16: =SUM(G9:G15) -> 0 | H16: =SUM(H9:H15) -> 0 | I16: =SUM(I9:I15) -> 0 | ... BI16: =SUM(BI9:BI15) -> 3453298.7 | BJ16: =SUM(B16:BI16) -> 72831521
A18: DEDUÇÕES DA RECEITA
A19: (−) Impostos sobre a receita | B19: =CHOOSE(Premissas!$B$6,Cenários!B31,Cenários!B77,Cenários!B123) -> 0 | C19: =CHOOSE(Premissas!$B$6,Cenários!C31,Cenários!C77,Cenários!C123) -> 0 | D19: =CHOOSE(Premissas!$B$6,Cenários!D31,Cenários!D77,Cenários!D123) -> 0 | E19: =CHOOSE(Premissas!$B$6,Cenários!E31,Cenários!E77,Cenários!E123) -> 0 | F19: =CHOOSE(Premissas!$B$6,Cenários!F31,Cenários!F77,Cenários!F123) -> 0 | G19: =CHOOSE(Premissas!$B$6,Cenários!G31,Cenários!G77,Cenários!G123) -> 0 | H19: =CHOOSE(Premissas!$B$6,Cenários!H31,Cenários!H77,Cenários!H123) -> 0 | I19: =CHOOSE(Premissas!$B$6,Cenários!I31,Cenários!I77,Cenários!I123) -> 0 | ... BI19: =CHOOSE(Premissas!$B$6,Cenários!BI31,Cenários!BI77,Cenários!BI123) -> -563923.68 | BJ19: =SUM(B19:BI19) -> -12004991 | BK19: =IFERROR(BJ19/BJ$16,0) -> -0.16483236
A20: (−) Comissão das lojas de aplicativos | B20: =CHOOSE(Premissas!$B$6,Cenários!B32,Cenários!B78,Cenários!B124) -> 0 | C20: =CHOOSE(Premissas!$B$6,Cenários!C32,Cenários!C78,Cenários!C124) -> 0 | D20: =CHOOSE(Premissas!$B$6,Cenários!D32,Cenários!D78,Cenários!D124) -> 0 | E20: =CHOOSE(Premissas!$B$6,Cenários!E32,Cenários!E78,Cenários!E124) -> 0 | F20: =CHOOSE(Premissas!$B$6,Cenários!F32,Cenários!F78,Cenários!F124) -> 0 | G20: =CHOOSE(Premissas!$B$6,Cenários!G32,Cenários!G78,Cenários!G124) -> 0 | H20: =CHOOSE(Premissas!$B$6,Cenários!H32,Cenários!H78,Cenários!H124) -> 0 | I20: =CHOOSE(Premissas!$B$6,Cenários!I32,Cenários!I78,Cenários!I124) -> 0 | ... BI20: =CHOOSE(Premissas!$B$6,Cenários!BI32,Cenários!BI78,Cenários!BI124) -> -340964.78 | BJ20: =SUM(B20:BI20) -> -7439957.6 | BK20: =IFERROR(BJ20/BJ$16,0) -> -0.10215299
A21: (−) Taxas de meios de pagamento | B21: =CHOOSE(Premissas!$B$6,Cenários!B33,Cenários!B79,Cenários!B125) -> 0 | C21: =CHOOSE(Premissas!$B$6,Cenários!C33,Cenários!C79,Cenários!C125) -> 0 | D21: =CHOOSE(Premissas!$B$6,Cenários!D33,Cenários!D79,Cenários!D125) -> 0 | E21: =CHOOSE(Premissas!$B$6,Cenários!E33,Cenários!E79,Cenários!E125) -> 0 | F21: =CHOOSE(Premissas!$B$6,Cenários!F33,Cenários!F79,Cenários!F125) -> 0 | G21: =CHOOSE(Premissas!$B$6,Cenários!G33,Cenários!G79,Cenários!G125) -> 0 | H21: =CHOOSE(Premissas!$B$6,Cenários!H33,Cenários!H79,Cenários!H125) -> 0 | I21: =CHOOSE(Premissas!$B$6,Cenários!I33,Cenários!I79,Cenários!I125) -> 0 | ... BI21: =CHOOSE(Premissas!$B$6,Cenários!BI33,Cenários!BI79,Cenários!BI125) -> -52625.259 | BJ21: =SUM(B21:BI21) -> -1023977.4 | BK21: =IFERROR(BJ21/BJ$16,0) -> -0.014059536
A22: RECEITA LÍQUIDA | B22: =B16+SUM(B19:B21) -> 0 | C22: =C16+SUM(C19:C21) -> 0 | D22: =D16+SUM(D19:D21) -> 0 | E22: =E16+SUM(E19:E21) -> 0 | F22: =F16+SUM(F19:F21) -> 0 | G22: =G16+SUM(G19:G21) -> 0 | H22: =H16+SUM(H19:H21) -> 0 | I22: =I16+SUM(I19:I21) -> 0 | ... BI22: =BI16+SUM(BI19:BI21) -> 2495785 | BJ22: =SUM(B22:BI22) -> 52362595 | BK22: =IFERROR(BJ22/BJ$16,0) -> 0.71895512
A23: Alíquota efetiva de impostos | B23: =CHOOSE(Premissas!$B$6,Cenários!B30,Cenários!B76,Cenários!B122) -> 0.155 | C23: =CHOOSE(Premissas!$B$6,Cenários!C30,Cenários!C76,Cenários!C122) -> 0.155 | D23: =CHOOSE(Premissas!$B$6,Cenários!D30,Cenários!D76,Cenários!D122) -> 0.155 | E23: =CHOOSE(Premissas!$B$6,Cenários!E30,Cenários!E76,Cenários!E122) -> 0.155 | F23: =CHOOSE(Premissas!$B$6,Cenários!F30,Cenários!F76,Cenários!F122) -> 0.155 | G23: =CHOOSE(Premissas!$B$6,Cenários!G30,Cenários!G76,Cenários!G122) -> 0.155 | H23: =CHOOSE(Premissas!$B$6,Cenários!H30,Cenários!H76,Cenários!H122) -> 0.155 | I23: =CHOOSE(Premissas!$B$6,Cenários!I30,Cenários!I76,Cenários!I122) -> 0.155 | ... BI23: =CHOOSE(Premissas!$B$6,Cenários!BI30,Cenários!BI76,Cenários!BI122) -> 0.1633 | BK23: Simples Nacional progressivo; migra para Lucro Presumido acima de R$ 4,8 mi.
A25: RESUMO ANUAL
A26: Ano | B26: 2026 | C26: 2027 | D26: 2028 | E26: 2029 | F26: 2030 | G26: TOTAL
A27: Receita bruta | B27: =SUMIFS($B$16:$BI$16,$B$6:$BI$6,B$26) -> 7191 | C27: =SUMIFS($B$16:$BI$16,$B$6:$BI$6,C$26) -> 4266370.6 | D27: =SUMIFS($B$16:$BI$16,$B$6:$BI$6,D$26) -> 11883042 | E27: =SUMIFS($B$16:$BI$16,$B$6:$BI$6,E$26) -> 21235019 | F27: =SUMIFS($B$16:$BI$16,$B$6:$BI$6,F$26) -> 35439898 | G27: =SUM(B27:F27) -> 72831521
A28: Receita líquida | B28: =SUMIFS($B$22:$BI$22,$B$6:$BI$6,B$26) -> 5111.0032 | C28: =SUMIFS($B$22:$BI$22,$B$6:$BI$6,C$26) -> 2937755.6 | D28: =SUMIFS($B$22:$BI$22,$B$6:$BI$6,D$26) -> 8506358.2 | E28: =SUMIFS($B$22:$BI$22,$B$6:$BI$6,E$26) -> 15297939 | F28: =SUMIFS($B$22:$BI$22,$B$6:$BI$6,F$26) -> 25615431 | G28: =SUM(B28:F28) -> 52362595
A29: Impostos sobre receita | B29: =SUMIFS($B$19:$BI$19,$B$6:$BI$6,B$26) -> -1114.605 | C29: =SUMIFS($B$19:$BI$19,$B$6:$BI$6,C$26) -> -797617.1 | D29: =SUMIFS($B$19:$BI$19,$B$6:$BI$6,D$26) -> -1951245.6 | E29: =SUMIFS($B$19:$BI$19,$B$6:$BI$6,E$26) -> -3467678.6 | F29: =SUMIFS($B$19:$BI$19,$B$6:$BI$6,F$26) -> -5787335.4 | G29: =SUM(B29:F29) -> -12004991
A30: Comissão de lojas | B30: =SUMIFS($B$20:$BI$20,$B$6:$BI$6,B$26) -> -916.8525 | C30: =SUMIFS($B$20:$BI$20,$B$6:$BI$6,C$26) -> -490071.44 | D30: =SUMIFS($B$20:$BI$20,$B$6:$BI$6,D$26) -> -1280724 | E30: =SUMIFS($B$20:$BI$20,$B$6:$BI$6,E$26) -> -2170901.1 | F30: =SUMIFS($B$20:$BI$20,$B$6:$BI$6,F$26) -> -3497344.2 | G30: =SUM(B30:F30) -> -7439957.6

Sheet Usuários
A1: USUÁRIOS E INDICADORES DE UNIDADE
A2: =" Cenário ativo: "&Premissas!B7&" · todas as linhas recalculam ao trocar o cenário." -> Cenário ativo: PROVÁVEL · todas as linhas recalculam ao trocar o cenário.
A4: Linha do tempo | B4: 46023 | C4: 46054 | D4: 46082 | E4: 46113 | F4: 46143 | G4: 46174 | H4: 46204 | I4: 46235 | J4: 46266 | K4: 46296 | L4: 46327 | M4: 46357 | N4: 46388 | O4: 46419 | P4: 46447 | Q4: 46478 | R4: 46508 | S4: 46539 | T4: 46569 | U4: 46600 | V4: 46631 | W4: 46661 | X4: 46692 | Y4: 46722 | Z4: 46753 | AA4: 46784 | AB4: 46813 | AC4: 46844 | AD4: 46874 | AE4: 46905 | AF4: 46935 | AG4: 46966 | AH4: 46997 | AI4: 47027 | AJ4: 47058 | AK4: 47088 | AL4: 47119 | AM4: 47150 | AN4: 47178 | AO4: 47209 | AP4: 47239 | AQ4: 47270 | AR4: 47300 | AS4: 47331 | AT4: 47362 | AU4: 47392 | AV4: 47423 | AW4: 47453 | AX4: 47484 | AY4: 47515 | AZ4: 47543 | BA4: 47574 | BB4: 47604 | BC4: 47635 | BD4: 47665 | BE4: 47696 | BF4: 47727 | BG4: 47757 | BH4: 47788 | BI4: 47818 | BJ4: TOTAL | BK4: % / Nota
A5: Mês nº | B5: 1 | C5: 2 | D5: 3 | E5: 4 | F5: 5 | G5: 6 | H5: 7 | I5: 8 | J5: 9 | K5: 10 | L5: 11 | M5: 12 | N5: 13 | O5: 14 | P5: 15 | Q5: 16 | R5: 17 | S5: 18 | T5: 19 | U5: 20 | V5: 21 | W5: 22 | X5: 23 | Y5: 24 | Z5: 25 | AA5: 26 | AB5: 27 | AC5: 28 | AD5: 29 | AE5: 30 | AF5: 31 | AG5: 32 | AH5: 33 | AI5: 34 | AJ5: 35 | AK5: 36 | AL5: 37 | AM5: 38 | AN5: 39 | AO5: 40 | AP5: 41 | AQ5: 42 | AR5: 43 | AS5: 44 | AT5: 45 | AU5: 46 | AV5: 47 | AW5: 48 | AX5: 49 | AY5: 50 | AZ5: 51 | BA5: 52 | BB5: 53 | BC5: 54 | BD5: 55 | BE5: 56 | BF5: 57 | BG5: 58 | BH5: 59 | BI5: 60
A6: Ano | B6: =YEAR(B4) -> 2026 | C6: =YEAR(C4) -> 2026 | D6: =YEAR(D4) -> 2026 | E6: =YEAR(E4) -> 2026 | F6: =YEAR(F4) -> 2026 | G6: =YEAR(G4) -> 2026 | H6: =YEAR(H4) -> 2026 | I6: =YEAR(I4) -> 2026 | ... BI6: =YEAR(BI4) -> 2030
A7: Índice do ano (auxiliar) | B7: =MATCH(B6,Premissas!$C$5:$G$5,0) -> 1 | C7: =MATCH(C6,Premissas!$C$5:$G$5,0) -> 1 | D7: =MATCH(D6,Premissas!$C$5:$G$5,0) -> 1 | E7: =MATCH(E6,Premissas!$C$5:$G$5,0) -> 1 | F7: =MATCH(F6,Premissas!$C$5:$G$5,0) -> 1 | G7: =MATCH(G6,Premissas!$C$5:$G$5,0) -> 1 | H7: =MATCH(H6,Premissas!$C$5:$G$5,0) -> 1 | I7: =MATCH(I6,Premissas!$C$5:$G$5,0) -> 1 | ... BI7: =MATCH(BI6,Premissas!$C$5:$G$5,0) -> 5
A8: FUNIL DE USUÁRIOS
A9: Novos usuários captados | B9: =CHOOSE(Premissas!$B$6,Cenários!B10,Cenários!B56,Cenários!B102) -> 0 | C9: =CHOOSE(Premissas!$B$6,Cenários!C10,Cenários!C56,Cenários!C102) -> 0 | D9: =CHOOSE(Premissas!$B$6,Cenários!D10,Cenários!D56,Cenários!D102) -> 0 | E9: =CHOOSE(Premissas!$B$6,Cenários!E10,Cenários!E56,Cenários!E102) -> 0 | F9: =CHOOSE(Premissas!$B$6,Cenários!F10,Cenários!F56,Cenários!F102) -> 0 | G9: =CHOOSE(Premissas!$B$6,Cenários!G10,Cenários!G56,Cenários!G102) -> 0 | H9: =CHOOSE(Premissas!$B$6,Cenários!H10,Cenários!H56,Cenários!H102) -> 0 | I9: =CHOOSE(Premissas!$B$6,Cenários!I10,Cenários!I56,Cenários!I102) -> 0 | ... BI9: =CHOOSE(Premissas!$B$6,Cenários!BI10,Cenários!BI56,Cenários!BI102) -> 91631.25 | BJ9: =SUM(B9:BI9) -> 2665225
A10: Base de usuários — início do mês | B10: =CHOOSE(Premissas!$B$6,Cenários!B11,Cenários!B57,Cenários!B103) -> 0 | C10: =CHOOSE(Premissas!$B$6,Cenários!C11,Cenários!C57,Cenários!C103) -> 0 | D10: =CHOOSE(Premissas!$B$6,Cenários!D11,Cenários!D57,Cenários!D103) -> 0 | E10: =CHOOSE(Premissas!$B$6,Cenários!E11,Cenários!E57,Cenários!E103) -> 0 | F10: =CHOOSE(Premissas!$B$6,Cenários!F11,Cenários!F57,Cenários!F103) -> 0 | G10: =CHOOSE(Premissas!$B$6,Cenários!G11,Cenários!G57,Cenários!G103) -> 0 | H10: =CHOOSE(Premissas!$B$6,Cenários!H11,Cenários!H57,Cenários!H103) -> 0 | I10: =CHOOSE(Premissas!$B$6,Cenários!I11,Cenários!I57,Cenários!I103) -> 0 | ... BI10: =CHOOSE(Premissas!$B$6,Cenários!BI11,Cenários!BI57,Cenários!BI103) -> 1092400.7 | BJ10: =BI10 -> 1092400.7 | BK10: Saldo em dez/2030.
A11: (−) Usuários perdidos (churn) | B11: =CHOOSE(Premissas!$B$6,Cenários!B12,Cenários!B58,Cenários!B104) -> 0 | C11: =CHOOSE(Premissas!$B$6,Cenários!C12,Cenários!C58,Cenários!C104) -> 0 | D11: =CHOOSE(Premissas!$B$6,Cenários!D12,Cenários!D58,Cenários!D104) -> 0 | E11: =CHOOSE(Premissas!$B$6,Cenários!E12,Cenários!E58,Cenários!E104) -> 0 | F11: =CHOOSE(Premissas!$B$6,Cenários!F12,Cenários!F58,Cenários!F104) -> 0 | G11: =CHOOSE(Premissas!$B$6,Cenários!G12,Cenários!G58,Cenários!G104) -> 0 | H11: =CHOOSE(Premissas!$B$6,Cenários!H12,Cenários!H58,Cenários!H104) -> 0 | I11: =CHOOSE(Premissas!$B$6,Cenários!I12,Cenários!I58,Cenários!I104) -> 0 | ... BI11: =CHOOSE(Premissas!$B$6,Cenários!BI12,Cenários!BI58,Cenários!BI104) -> -68231.255 | BJ11: =SUM(B11:BI11) -> -1549424.3
A12: Base de usuários — fim do mês | B12: =CHOOSE(Premissas!$B$6,Cenários!B13,Cenários!B59,Cenários!B105) -> 0 | C12: =CHOOSE(Premissas!$B$6,Cenários!C13,Cenários!C59,Cenários!C105) -> 0 | D12: =CHOOSE(Premissas!$B$6,Cenários!D13,Cenários!D59,Cenários!D105) -> 0 | E12: =CHOOSE(Premissas!$B$6,Cenários!E13,Cenários!E59,Cenários!E105) -> 0 | F12: =CHOOSE(Premissas!$B$6,Cenários!F13,Cenários!F59,Cenários!F105) -> 0 | G12: =CHOOSE(Premissas!$B$6,Cenários!G13,Cenários!G59,Cenários!G105) -> 0 | H12: =CHOOSE(Premissas!$B$6,Cenários!H13,Cenários!H59,Cenários!H105) -> 0 | I12: =CHOOSE(Premissas!$B$6,Cenários!I13,Cenários!I59,Cenários!I105) -> 0 | ... BI12: =CHOOSE(Premissas!$B$6,Cenários!BI13,Cenários!BI59,Cenários!BI105) -> 1115800.7 | BJ12: =BI12 -> 1115800.7 | BK12: Saldo em dez/2030.
A13: Taxa de conversão | B13: =CHOOSE(Premissas!$B$6,Cenários!B14,Cenários!B60,Cenários!B106) -> 0 | C13: =CHOOSE(Premissas!$B$6,Cenários!C14,Cenários!C60,Cenários!C106) -> 0 | D13: =CHOOSE(Premissas!$B$6,Cenários!D14,Cenários!D60,Cenários!D106) -> 0 | E13: =CHOOSE(Premissas!$B$6,Cenários!E14,Cenários!E60,Cenários!E106) -> 0 | F13: =CHOOSE(Premissas!$B$6,Cenários!F14,Cenários!F60,Cenários!F106) -> 0 | G13: =CHOOSE(Premissas!$B$6,Cenários!G14,Cenários!G60,Cenários!G106) -> 0 | H13: =CHOOSE(Premissas!$B$6,Cenários!H14,Cenários!H60,Cenários!H106) -> 0 | I13: =CHOOSE(Premissas!$B$6,Cenários!I14,Cenários!I60,Cenários!I106) -> 0 | ... BI13: =CHOOSE(Premissas!$B$6,Cenários!BI14,Cenários!BI60,Cenários!BI106) -> 0.033765264 | BJ13: =BI13 -> 0.033765264 | BK13: Saldo em dez/2030.
A14: Usuários pagantes | B14: =CHOOSE(Premissas!$B$6,Cenários!B15,Cenários!B61,Cenários!B107) -> 0 | C14: =CHOOSE(Premissas!$B$6,Cenários!C15,Cenários!C61,Cenários!C107) -> 0 | D14: =CHOOSE(Premissas!$B$6,Cenários!D15,Cenários!D61,Cenários!D107) -> 0 | E14: =CHOOSE(Premissas!$B$6,Cenários!E15,Cenários!E61,Cenários!E107) -> 0 | F14: =CHOOSE(Premissas!$B$6,Cenários!F15,Cenários!F61,Cenários!F107) -> 0 | G14: =CHOOSE(Premissas!$B$6,Cenários!G15,Cenários!G61,Cenários!G107) -> 0 | H14: =CHOOSE(Premissas!$B$6,Cenários!H15,Cenários!H61,Cenários!H107) -> 0 | I14: =CHOOSE(Premissas!$B$6,Cenários!I15,Cenários!I61,Cenários!I107) -> 0 | ... BI14: =CHOOSE(Premissas!$B$6,Cenários!BI15,Cenários!BI61,Cenários!BI107) -> 37675 | BJ14: =BI14 -> 37675 | BK14: Saldo em dez/2030.
A15: Pagantes — Plano Essencial | B15: =CHOOSE(Premissas!$B$6,Cenários!B16,Cenários!B62,Cenários!B108) -> 0 | C15: =CHOOSE(Premissas!$B$6,Cenários!C16,Cenários!C62,Cenários!C108) -> 0 | D15: =CHOOSE(Premissas!$B$6,Cenários!D16,Cenários!D62,Cenários!D108) -> 0 | E15: =CHOOSE(Premissas!$B$6,Cenários!E16,Cenários!E62,Cenários!E108) -> 0 | F15: =CHOOSE(Premissas!$B$6,Cenários!F16,Cenários!F62,Cenários!F108) -> 0 | G15: =CHOOSE(Premissas!$B$6,Cenários!G16,Cenários!G62,Cenários!G108) -> 0 | H15: =CHOOSE(Premissas!$B$6,Cenários!H16,Cenários!H62,Cenários!H108) -> 0 | I15: =CHOOSE(Premissas!$B$6,Cenários!I16,Cenários!I62,Cenários!I108) -> 0 | ... BI15: =CHOOSE(Premissas!$B$6,Cenários!BI16,Cenários!BI62,Cenários!BI108) -> 22605 | BJ15: =BI15 -> 22605 | BK15: Saldo em dez/2030.
A16: Pagantes — Plano Premium | B16: =CHOOSE(Premissas!$B$6,Cenários!B17,Cenários!B63,Cenários!B109) -> 0 | C16: =CHOOSE(Premissas!$B$6,Cenários!C17,Cenários!C63,Cenários!C109) -> 0 | D16: =CHOOSE(Premissas!$B$6,Cenários!D17,Cenários!D63,Cenários!D109) -> 0 | E16: =CHOOSE(Premissas!$B$6,Cenários!E17,Cenários!E63,Cenários!E109) -> 0 | F16: =CHOOSE(Premissas!$B$6,Cenários!F17,Cenários!F63,Cenários!F109) -> 0 | G16: =CHOOSE(Premissas!$B$6,Cenários!G17,Cenários!G63,Cenários!G109) -> 0 | H16: =CHOOSE(Premissas!$B$6,Cenários!H17,Cenários!H63,Cenários!H109) -> 0 | I16: =CHOOSE(Premissas!$B$6,Cenários!I17,Cenários!I63,Cenários!I109) -> 0 | ... BI16: =CHOOSE(Premissas!$B$6,Cenários!BI17,Cenários!BI63,Cenários!BI109) -> 10549 | BJ16: =BI16 -> 10549 | BK16: Saldo em dez/2030.
A17: Pagantes — Plano Família | B17: =CHOOSE(Premissas!$B$6,Cenários!B18,Cenários!B64,Cenários!B110) -> 0 | C17: =CHOOSE(Premissas!$B$6,Cenários!C18,Cenários!C64,Cenários!C110) -> 0 | D17: =CHOOSE(Premissas!$B$6,Cenários!D18,Cenários!D64,Cenários!D110) -> 0 | E17: =CHOOSE(Premissas!$B$6,Cenários!E18,Cenários!E64,Cenários!E110) -> 0 | F17: =CHOOSE(Premissas!$B$6,Cenários!F18,Cenários!F64,Cenários!F110) -> 0 | G17: =CHOOSE(Premissas!$B$6,Cenários!G18,Cenários!G64,Cenários!G110) -> 0 | H17: =CHOOSE(Premissas!$B$6,Cenários!H18,Cenários!H64,Cenários!H110) -> 0 | I17: =CHOOSE(Premissas!$B$6,Cenários!I18,Cenários!I64,Cenários!I110) -> 0 | ... BI17: =CHOOSE(Premissas!$B$6,Cenários!BI18,Cenários!BI64,Cenários!BI110) -> 4521 | BJ17: =BI17 -> 4521 | BK17: Saldo em dez/2030.
A18: Usuários no painel de dados (com consentimento) | B18: =CHOOSE(Premissas!$B$6,Cenários!B19,Cenários!B65,Cenários!B111) -> 0 | C18: =CHOOSE(Premissas!$B$6,Cenários!C19,Cenários!C65,Cenários!C111) -> 0 | D18: =CHOOSE(Premissas!$B$6,Cenários!D19,Cenários!D65,Cenários!D111) -> 0 | E18: =CHOOSE(Premissas!$B$6,Cenários!E19,Cenários!E65,Cenários!E111) -> 0 | F18: =CHOOSE(Premissas!$B$6,Cenários!F19,Cenários!F65,Cenários!F111) -> 0 | G18: =CHOOSE(Premissas!$B$6,Cenários!G19,Cenários!G65,Cenários!G111) -> 0 | H18: =CHOOSE(Premissas!$B$6,Cenários!H19,Cenários!H65,Cenários!H111) -> 0 | I18: =CHOOSE(Premissas!$B$6,Cenários!I19,Cenários!I65,Cenários!I111) -> 0 | ... BI18: =CHOOSE(Premissas!$B$6,Cenários!BI19,Cenários!BI65,Cenários!BI111) -> 1115801 | BK18: Zero enquanto a base consentida não atinge o mínimo comercial definido em Premissas.
A19: Pessoas na operação (headcount) | B19: =Pessoas!B41 -> 0 | C19: =Pessoas!C41 -> 0 | D19: =Pessoas!D41 -> 0 | E19: =Pessoas!E41 -> 0 | F19: =Pessoas!F41 -> 0 | G19: =Pessoas!G41 -> 0 | H19: =Pessoas!H41 -> 0 | I19: =Pessoas!I41 -> 0 | ... BI19: =Pessoas!BI41 -> 50
A20: Usuários gratuitos | B20: =B12-B14 -> 0 | C20: =C12-C14 -> 0 | D20: =D12-D14 -> 0 | E20: =E12-E14 -> 0 | F20: =F12-F14 -> 0 | G20: =G12-G14 -> 0 | H20: =H12-H14 -> 0 | I20: =I12-I14 -> 0 | ... BI20: =BI12-BI14 -> 1078125.7 | BJ20: =BI20 -> 1078125.7
A22: INDICADORES DE UNIDADE
A23: Investimento em mídia de aquisição | B23: {=B9*(1-INDEX(Premissas!$C$59:$G$59,B$7))*CHOOSE(Premissas!$B$6,INDEX(Premissas!$C$56:$G$56,B$7),INDEX(Premissas!$C$57:$G$57,B$7),INDEX(Premissas!$C$58:$G$58,B$7))} -> 0 | C23: {=C9*(1-INDEX(Premissas!$C$59:$G$59,C$7))*CHOOSE(Premissas!$B$6,INDEX(Premissas!$C$56:$G$56,C$7),INDEX(Premissas!$C$57:$G$57,C$7),INDEX(Premissas!$C$58:$G$58,C$7))} -> 0 | D23: {=D9*(1-INDEX(Premissas!$C$59:$G$59,D$7))*CHOOSE(Premissas!$B$6,INDEX(Premissas!$C$56:$G$56,D$7),INDEX(Premissas!$C$57:$G$57,D$7),INDEX(Premissas!$C$58:$G$58,D$7))} -> 0 | E23: {=E9*(1-INDEX(Premissas!$C$59:$G$59,E$7))*CHOOSE(Premissas!$B$6,INDEX(Premissas!$C$56:$G$56,E$7),INDEX(Premissas!$C$57:$G$57,E$7),INDEX(Premissas!$C$58:$G$58,E$7))} -> 0 | F23: {=F9*(1-INDEX(Premissas!$C$59:$G$59,F$7))*CHOOSE(Premissas!$B$6,INDEX(Premissas!$C$56:$G$56,F$7),INDEX(Premissas!$C$57:$G$57,F$7),INDEX(Premissas!$C$58:$G$58,F$7))} -> 0 | G23: {=G9*(1-INDEX(Premissas!$C$59:$G$59,G$7))*CHOOSE(Premissas!$B$6,INDEX(Premissas!$C$56:$G$56,G$7),INDEX(Premissas!$C$57:$G$57,G$7),INDEX(Premissas!$C$58:$G$58,G$7))} -> 0 | H23: {=H9*(1-INDEX(Premissas!$C$59:$G$59,H$7))*CHOOSE(Premissas!$B$6,INDEX(Premissas!$C$56:$G$56,H$7),INDEX(Premissas!$C$57:$G$57,H$7),INDEX(Premissas!$C$58:$G$58,H$7))} -> 0 | I23: {=I9*(1-INDEX(Premissas!$C$59:$G$59,I$7))*CHOOSE(Premissas!$B$6,INDEX(Premissas!$C$56:$G$56,I$7),INDEX(Premissas!$C$57:$G$57,I$7),INDEX(Premissas!$C$58:$G$58,I$7))} -> 0 | ... BI23: {=BI9*(1-INDEX(Premissas!$C$59:$G$59,BI$7))*CHOOSE(Premissas!$B$6,INDEX(Premissas!$C$56:$G$56,BI$7),INDEX(Premissas!$C$57:$G$57,BI$7),INDEX(Premissas!$C$58:$G$58,BI$7))} -> 240395.44 | BJ23: =SUM(B23:BI23) -> 6331666.2
A24: CAC — custo por usuário adquirido | B24: =IFERROR(B23/B9,0) -> 0 | C24: =IFERROR(C23/C9,0) -> 0 | D24: =IFERROR(D23/D9,0) -> 0 | E24: =IFERROR(E23/E9,0) -> 0 | F24: =IFERROR(F23/F9,0) -> 0 | G24: =IFERROR(G23/G9,0) -> 0 | H24: =IFERROR(H23/H9,0) -> 0 | I24: =IFERROR(I23/I9,0) -> 0 | ... BJ24: =IFERROR(BJ23/BJ9,0) -> 2.3756592 | BK24: Média do período.
A25: CAC por usuário PAGANTE conquistado | B25: =IFERROR(B23/(B9*B13),0) -> 0 | C25: =IFERROR(C23/(C9*C13),0) -> 0 | D25: =IFERROR(D23/(D9*D13),0) -> 0 | E25: =IFERROR(E23/(E9*E13),0) -> 0 | F25: =IFERROR(F23/(F9*F13),0) -> 0 | G25: =IFERROR(G23/(G9*G13),0) -> 0 | H25: =IFERROR(H23/(H9*H13),0) -> 0 | I25: =IFERROR(I23/(I9*I13),0) -> 0 | ... BI25: =IFERROR(BI23/(BI9*BI13),0) -> 77.69847 | BK25: É este o CAC que a receita de assinatura precisa pagar.
A26: ARPPU — receita média por assinante pagante | B26: =IFERROR(CHOOSE(Premissas!$B$6,Cenários!B23,Cenários!B69,Cenários!B115)/B14,0) -> 0 | C26: =IFERROR(CHOOSE(Premissas!$B$6,Cenários!C23,Cenários!C69,Cenários!C115)/C14,0) -> 0 | D26: =IFERROR(CHOOSE(Premissas!$B$6,Cenários!D23,Cenários!D69,Cenários!D115)/D14,0) -> 0 | E26: =IFERROR(CHOOSE(Premissas!$B$6,Cenários!E23,Cenários!E69,Cenários!E115)/E14,0) -> 0 | F26: =IFERROR(CHOOSE(Premissas!$B$6,Cenários!F23,Cenários!F69,Cenários!F115)/F14,0) -> 0 | G26: =IFERROR(CHOOSE(Premissas!$B$6,Cenários!G23,Cenários!G69,Cenários!G115)/G14,0) -> 0 | H26: =IFERROR(CHOOSE(Premissas!$B$6,Cenários!H23,Cenários!H69,Cenários!H115)/H14,0) -> 0 | I26: =IFERROR(CHOOSE(Premissas!$B$6,Cenários!I23,Cenários!I69,Cenários!I115)/I14,0) -> 0 | ... BI26: =IFERROR(CHOOSE(Premissas!$B$6,Cenários!BI23,Cenários!BI69,Cenários!BI115)/BI14,0) -> 86.192
A27: ARPU — receita média por usuário da base | B27: =IFERROR(CHOOSE(Premissas!$B$6,Cenários!B28,Cenários!B74,Cenários!B120)/B12,0) -> 0 | C27: =IFERROR(CHOOSE(Premissas!$B$6,Cenários!C28,Cenários!C74,Cenários!C120)/C12,0) -> 0 | D27: =IFERROR(CHOOSE(Premissas!$B$6,Cenários!D28,Cenários!D74,Cenários!D120)/D12,0) -> 0 | E27: =IFERROR(CHOOSE(Premissas!$B$6,Cenários!E28,Cenários!E74,Cenários!E120)/E12,0) -> 0 | F27: =IFERROR(CHOOSE(Premissas!$B$6,Cenários!F28,Cenários!F74,Cenários!F120)/F12,0) -> 0 | G27: =IFERROR(CHOOSE(Premissas!$B$6,Cenários!G28,Cenários!G74,Cenários!G120)/G12,0) -> 0 | H27: =IFERROR(CHOOSE(Premissas!$B$6,Cenários!H28,Cenários!H74,Cenários!H120)/H12,0) -> 0 | I27: =IFERROR(CHOOSE(Premissas!$B$6,Cenários!I28,Cenários!I74,Cenários!I120)/I12,0) -> 0 | ... BI27: =IFERROR(CHOOSE(Premissas!$B$6,Cenários!BI28,Cenários!BI74,Cenários!BI120)/BI12,0) -> 3.0949065
A28: Margem de contribuição por pagante (R$/mês) | B28: =IFERROR((CHOOSE(Premissas!$B$6,Cenários!B34,Cenários!B80,Cenários!B126)+CHOOSE(Premissas!$B$6,Cenários!B35,Cenários!B81,Cenários!B127)+CHOOSE(Premissas!$B$6,Cenários!B36,Cenários!B82,Cenários!B128))/B14,0) -> 0 | C28: =IFERROR((CHOOSE(Premissas!$B$6,Cenários!C34,Cenários!C80,Cenários!C126)+CHOOSE(Premissas!$B$6,Cenários!C35,Cenários!C81,Cenários!C127)+CHOOSE(Premissas!$B$6,Cenários!C36,Cenários!C82,Cenários!C128))/C14,0) -> 0 | D28: =IFERROR((CHOOSE(Premissas!$B$6,Cenários!D34,Cenários!D80,Cenários!D126)+CHOOSE(Premissas!$B$6,Cenários!D35,Cenários!D81,Cenários!D127)+CHOOSE(Premissas!$B$6,Cenários!D36,Cenários!D82,Cenários!D128))/D14,0) -> 0 | E28: =IFERROR((CHOOSE(Premissas!$B$6,Cenários!E34,Cenários!E80,Cenários!E126)+CHOOSE(Premissas!$B$6,Cenários!E35,Cenários!E81,Cenários!E127)+CHOOSE(Premissas!$B$6,Cenários!E36,Cenários!E82,Cenários!E128))/E14,0) -> 0 | F28: =IFERROR((CHOOSE(Premissas!$B$6,Cenários!F34,Cenários!F80,Cenários!F126)+CHOOSE(Premissas!$B$6,Cenários!F35,Cenários!F81,Cenários!F127)+CHOOSE(Premissas!$B$6,Cenários!F36,Cenários!F82,Cenários!F128))/F14,0) -> 0 | G28: =IFERROR((CHOOSE(Premissas!$B$6,Cenários!G34,Cenários!G80,Cenários!G126)+CHOOSE(Premissas!$B$6,Cenários!G35,Cenários!G81,Cenários!G127)+CHOOSE(Premissas!$B$6,Cenários!G36,Cenários!G82,Cenários!G128))/G14,0) -> 0 | H28: =IFERROR((CHOOSE(Premissas!$B$6,Cenários!H34,Cenários!H80,Cenários!H126)+CHOOSE(Premissas!$B$6,Cenários!H35,Cenários!H81,Cenários!H127)+CHOOSE(Premissas!$B$6,Cenários!H36,Cenários!H82,Cenários!H128))/H14,0) -> 0 | I28: =IFERROR((CHOOSE(Premissas!$B$6,Cenários!I34,Cenários!I80,Cenários!I126)+CHOOSE(Premissas!$B$6,Cenários!I35,Cenários!I81,Cenários!I127)+CHOOSE(Premissas!$B$6,Cenários!I36,Cenários!I82,Cenários!I128))/I14,0) -> 0 | ... BI28: =IFERROR((CHOOSE(Premissas!$B$6,Cenários!BI34,Cenários!BI80,Cenários!BI126)+CHOOSE(Premissas!$B$6,Cenários!BI35,Cenários!BI81,Cenários!BI127)+CHOOSE(Premissas!$B$6,Cenários!BI36,Cenários!BI82,Cenários!BI128))/BI14,0) -> 31.388767 | BK28: Receita líquida menos nuvem e suporte, por assinante.
