Workbook

Sheet Como usar
A1: COMO USAR ESTA PLANILHA
A2: Leia uma vez. Depois é só mexer nas células azuis e ver tudo recalcular.
B5: EM 30 SEGUNDOS
B6: Só existem dois lugares onde você digita: a aba PREMISSAS (todos os números do negócio) e a aba PESSOAS (o quadro de pessoal). Todo o resto da planilha é calculado a partir dessas duas. Comece olhando o RESUMO, volte, ajuste, olhe de novo.
B7: 1. Abra o Resumo | C7: Painel executivo com os três cenários lado a lado e o diagnóstico Go / No-Go. É a foto do modelo.
B8: 2. Mude o cenário | C8: Premissas, controle 1.1: digite 1 (Conservador), 2 (Provável) ou 3 (Agressivo). As abas de detalhe passam todas a mostrar o cenário escolhido. O Resumo mostra os três sempre.
B9: 3. Ajuste o que quiser | C9: Qualquer célula azul. O modelo inteiro recalcula na hora — não há nada para rodar ou atualizar.
B10: 4. Confira | C10: Na Análise Fluxo há uma linha de verificação que compara o detalhamento com o motor de cenários. Ela tem que ficar zerada. Se aparecer um número diferente de zero, alguma fórmula foi sobrescrita por engano.
B12: AS CORES DIZEM O QUE É CADA CÉLULA
B13: Azul | C13: Você digita. É uma premissa sua.
B14: Fundo amarelo | C14: Premissa-chave: mexer nela desloca bastante o resultado. Comece por essas.
B15: Preto | C15: Fórmula calculada dentro da própria aba. Não mexa.
B16: Verde | C16: Valor que vem de outra aba. Não mexa — mude na origem.
B17: Marca vermelha no canto | C17: Passe o mouse: há um comentário com a fonte ou a justificativa do número.
B19: AS PERGUNTAS MAIS COMUNS E ONDE MEXER
B20: “E se lançarmos mais tarde?” | C20: Premissas → Ano de lançamento e Mês de lançamento. São dois campos separados; a data e o mês nº da linha do tempo se ajustam sozinhos, e com eles receita, marketing e conversão.
B21: “Achamos que 5% de pagantes é otimista.” | C21: Premissas → seção 4 → Taxa de conversão. Digite o patamar de 2026 na coluna C e a evolução anual na coluna B. Lembre que este é o patamar DE REGIME: nos primeiros meses a conversão sobe pela rampa, então 2026 sai naturalmente mais tímido.
B22: “Quanto tempo até converter no patamar cheio?” | C22: Premissas → Rampa de maturação da conversão (meses). Com 6, o app leva 6 meses após o lançamento para atingir o patamar do ano. Coloque 1 se quiser conversão cheia desde o primeiro mês.
B23: “Vamos contratar mais gente / menos gente.” | C23: Aba PESSOAS. Uma linha por papel: quantidade, custo por pessoa, mês de início e mês de fim. Adicione linhas nos espaços em branco no fim da tabela. O custo total do mês é calculado sozinho e desce para a DRE e para o fluxo de caixa.
B24: “Quero ver o modelo só com o que já está contratado.” | C24: Premissas → controle “Considerar o plano de contratações?” → digite 0. Some do modelo tudo que está marcado como Plano na aba Pessoas, sobrando apenas a equipe do MVP.
B25: “E se os aportes atrasarem?” | C25: Aba APORTES: mude a data de qualquer linha. Veja o efeito na linha Caixa Acumulado da Análise Fluxo e no indicador “Caixa mínimo” do Resumo.
B26: “Quero incluir um investidor novo.” | C26: Aba APORTES. Se ele só coloca dinheiro, preencha uma linha em branco da tabela 1: data, nome, valor, status e tipo. Se ele também traz receita — uma parceria como a da Boston Scientific — use a tabela 2, que tem campos para o aporte e para a receita mensal recorrente, com início e fim. Não é preciso mexer em nenhuma fórmula.
B27: “E se a Boston fechar?” | C27: Aba Aportes, tabela 2: mude o status da linha da Boston para Confirmado, ou ligue o interruptor “Considerar acordos em negociação” na seção 7 de Premissas para ver todos os acordos em negociação de uma vez.
B28: “Quanto cada sócio tem do capital?” | C28: Aba Aportes, seção 5. É a proporção do dinheiro aportado — ponto de partida da conversa societária, não percentual de equity, que depende do valuation de cada rodada. Ao incluir um investidor novo, lembre de acrescentar o nome dele também nesta tabela: a linha “Capital não atribuído” avisa se você esquecer.
B29: “Queremos incluir uma nova frente de receita B2B.” | C29: Premissas, seção 5, tabela “Iniciativas de receita B2B”. Uma linha por frente: nome, categoria (Dados ou Outras), status, modelo de cobrança (valor fixo mensal ou por usuário do painel), valor e período. As duas primeiras linhas são a venda de dados, já planejada; as demais estão em branco para vocês preencherem.
B30: “Por que a receita de dados só aparece em 2028?” | C30: Porque o painel precisa de escala. O modelo zera essa receita enquanto a base que consentiu compartilhar dados não passa do mínimo definido em Premissas — mesmo que a data do contrato já tenha chegado. Mexa na taxa de consentimento e no mínimo do painel para ver o efeito.
B31: “Vamos mudar os preços dos planos.” | C31: Premissas → seção 3. Preços e mix por plano. A ARPPU implícita aparece logo abaixo do mix, para você conferir o efeito antes de olhar o resultado.
... B37: “O número de um mês específico é diferente do número do ano.” | C37: Aba AJUSTE MENSAL. Digite o valor naquele mês e ele passa a valer só ali. Em branco, o modelo usa a premissa anual. Serve também para fechar o passado: conforme os meses acontecem, digite o realizado e o modelo projeta só o que falta.
B39: AS ABAS, UMA A UMA
B40: Como usar | C40: Este guia.
B41: Resumo | C41: Painel executivo. Três cenários lado a lado, teste Go/No-Go em quatro perguntas objetivas, métricas de unidade e a lista de pontos de atenção que apareceram na modelagem. É a aba para mostrar a um investidor.
B42: Necessidade de Capital | C42: Quanto a empresa precisa de investimento e de quem. Mês a mês, com um bloco por cenário: o que a operação queima, o capital já na mesa por status, a reserva mínima desejada e a lacuna que sobra. Fecha com a resposta por cenário e o rateio entre os sócios. Há duas respostas para 'quanto falta captar' — uma ignorando as datas de entrada do capital e outra respeitando. A segunda é a que manda.
B43: Preço Mínimo | C43: A conta de trás pra frente: do custo para o preço. Quanto sobra de cada real cobrado depois de imposto, loja e meio de pagamento; o custo variável por assinante; e os pisos de preço de cada plano, mês a mês. A seção 6 responde se a assinatura cobre os primeiros meses do lançamento. Esta aba não altera a projeção — é régua, não motor.
B44: Premissas | C44: Todos os números do negócio, em oito seções: controles, tributação, preços e mix, drivers por cenário, monetização, custos operacionais, Boston Scientific e notas metodológicas. É aqui que você passa a maior parte do tempo.
B45: Ajuste Mensal | C45: Sobrepõe a premissa anual em um mês específico: captação, churn, conversão, CAC, nuvem fixa, marketing recorrente e administrativas. Em branco, nada muda. A coluna TOTAL conta quantos meses estão sobrepostos, e o bloco final avisa se alguma célula caiu fora da janela do driver e vai ser ignorada.
B46: Pessoas | C46: O quadro de pessoal, linha a linha. Separa o que está contratado do que é plano, calcula o headcount mês a mês e o Fator R — o índice que decide se a empresa fica no Anexo III ou no Anexo V do Simples.
B47: Sócios | C47: O lucro distribuível e o rateio por participação. Os percentuais estão provisórios — fundadores majoritários, investidores com cotas menores — porque os valores definitivos dependem do valuation de cada rodada. Troque os percentuais e o rateio responde.
B48: DRE Projetada | C48: A demonstração de resultado em regime de competência, mês a mês e consolidada por ano. Receita bruta → deduções → receita líquida → lucro bruto → EBITDA → lucro líquido, com as margens em cada etapa.
B49: Análise Fluxo | C49: O fluxo de caixa, na mesma estrutura da sua planilha de Análise de Investimento: Projeto (investimentos) → Operacionais → Fluxo de Caixa Livre → VPL, TIR e Payback. Traz também a linha de verificação e o caixa acumulado.
B50: Faturamento | C50: A receita aberta por linha de negócio — cada plano, marketplace, B2B — com as deduções e um resumo anual.
B51: Usuários | C51: O funil de usuários e as métricas de unidade: CAC, LTV, LTV/CAC, ARPPU, payback do CAC, queima de caixa e runway. Traz também o painel de dados — quantos usuários consentiram compartilhar dados, que é o que a receita B2B de dados monetiza.
... B55: Tributos | C55: Tabelas dos Anexos III e V do Simples Nacional, a tabela ativa conforme o regime escolhido, a explicação do Fator R e quanto custa por ano cair no anexo errado.
B57: O QUE NÃO MEXER
B58: Nada quebra de forma irreversível, mas três coisas causam confusão:
B59: A aba Cenários | C59: É o motor. Se você mudar uma fórmula lá, as outras abas passam a mostrar números que não batem entre si. A linha de verificação da Análise Fluxo vai acusar.
B60: As linhas de total | C60: Em negrito e com fundo azul-claro. São somas — mude as parcelas, não o total.
B61: A coluna TOTAL (última à direita) | C61: Em linhas de saldo — base de usuários, caixa acumulado, pagantes — ela mostra o valor do último mês, não uma soma. Está anotado ao lado de cada uma.
B63: SE ALGUM NÚMERO PARECER ERRADO
B64: Confira a linha de verificação | C64: Análise Fluxo, logo abaixo do Caixa Acumulado. Tem que estar zerada em todos os meses.
B65: Confira o mix de planos | C65: Premissas, seção 3: a linha de verificação do mix precisa somar 100% em todos os anos.
B66: Recalcule | C66: No Excel, F9 força o recálculo. Se você abriu o arquivo e os números parecem antigos, confira se o cálculo automático está ligado em Fórmulas → Opções de Cálculo.
B67: Cuidado ao sobrescrever fórmulas | C67: Nas seções com evolução anual (drivers por cenário), as colunas de 2027 a 2030 são calculadas. Digitar por cima é permitido e às vezes desejável — mas aquele ano deixa de seguir a taxa de evolução, e os anos seguintes passam a contar a partir do que você digitou.
B69: As premissas mais sensíveis do modelo, em ordem: taxa de conversão, churn, CAC e quadro de pessoal. Se for calibrar alguma coisa com os sócios, comece por essas quatro.

Sheet Resumo
A1: OPPA — VIABILIDADE FINANCEIRA · PAINEL EXECUTIVO
A2: Projeção de 60 meses (jan/2026 – dez/2030). Os três cenários são calculados simultaneamente. Todos os números vêm de fórmulas — nada está digitado à mão.
B4: INDICADOR | C4: CONSERVADOR | D4: PROVÁVEL | E4: AGRESSIVO
B5: Cenário em uso nas abas de detalhe | C5: =IF(Premissas!$B$6=1,"◀ ATIVO","") | D5: =IF(Premissas!$B$6=2,"◀ ATIVO","") -> ◀ ATIVO | E5: =IF(Premissas!$B$6=3,"◀ ATIVO","")
A7: TRAÇÃO — USUÁRIOS E RECEITA
B8: Usuários na base em dez/2026 | C8: =Cenários!$M$13 -> 29430.6 | D8: =Cenários!$M$59 -> 50071.84 | E8: =Cenários!$M$105 -> 71550.024 | G8: Meta do brief: 50 mil usuários ao final de 2026.
B9: Usuários na base em dez/2030 | C9: =Cenários!$BI$13 -> 422036.02 | D9: =Cenários!$BI$59 -> 1116849.8 | E9: =Cenários!$BI$105 -> 2424300.5
B10: Assinantes pagantes em dez/2026 | C10: =Cenários!$M$15 -> 441 | D10: =Cenários!$M$61 -> 1252 | E10: =Cenários!$M$107 -> 2504 | G10: Meta do brief: 5% da base pagante.
B11: Assinantes pagantes em dez/2030 | C11: =Cenários!$BI$15 -> 17225 | D11: =Cenários!$BI$61 -> 75973 | E11: =Cenários!$BI$107 -> 248459
B12: Receita bruta de 2026 | C12: =SUMIFS(Cenários!$B$28:$BI$28,Cenários!$B$6:$BI$6,2026) -> 13949.9 | D12: =SUMIFS(Cenários!$B$74:$BI$74,Cenários!$B$6:$BI$6,2026) -> 39441.8 | E12: =SUMIFS(Cenários!$B$120:$BI$120,Cenários!$B$6:$BI$6,2026) -> 78545.3
B13: Receita bruta de 2030 | C13: =SUMIFS(Cenários!$B$28:$BI$28,Cenários!$B$6:$BI$6,2030) -> 8750338.7 | D13: =SUMIFS(Cenários!$B$74:$BI$74,Cenários!$B$6:$BI$6,2030) -> 33253920 | E13: =SUMIFS(Cenários!$B$120:$BI$120,Cenários!$B$6:$BI$6,2030) -> 1.0144467e+08
B14: Receita bruta acumulada em 5 anos | C14: =SUM(Cenários!$B$28:$BI$28) -> 17316442 | D14: =SUM(Cenários!$B$74:$BI$74) -> 62932363 | E14: =SUM(Cenários!$B$120:$BI$120) -> 1.7927006e+08
A16: RESULTADO OPERACIONAL
B17: EBITDA de 2026 | C17: =SUMIFS(Cenários!$B$40:$BI$40,Cenários!$B$6:$BI$6,2026) -> -136110.43 | D17: =SUMIFS(Cenários!$B$86:$BI$86,Cenários!$B$6:$BI$6,2026) -> -124977.28 | E17: =SUMIFS(Cenários!$B$132:$BI$132,Cenários!$B$6:$BI$6,2026) -> -86438.931
B18: EBITDA de 2030 | C18: =SUMIFS(Cenários!$B$40:$BI$40,Cenários!$B$6:$BI$6,2030) -> -5412426.2 | D18: =SUMIFS(Cenários!$B$86:$BI$86,Cenários!$B$6:$BI$6,2030) -> 10815995 | E18: =SUMIFS(Cenários!$B$132:$BI$132,Cenários!$B$6:$BI$6,2030) -> 57369637
B19: EBITDA acumulado em 5 anos | C19: =SUM(Cenários!$B$40:$BI$40) -> -11914397 | D19: =SUM(Cenários!$B$86:$BI$86) -> 18055035 | E19: =SUM(Cenários!$B$132:$BI$132) -> 96972482
B20: Margem EBITDA em 2030 (% da receita bruta) | C20: =IFERROR(C18/C13,0) -> -0.61853905 | D20: =IFERROR(D18/D13,0) -> 0.32525473 | E20: =IFERROR(E18/E13,0) -> 0.56552635
B21: Break-even do EBITDA | C21: =IF(SUM(Cenários!$B$46:$BI$46)=0,"não atinge",CHOOSE(MOD(60-SUM(Cenários!$B$46:$BI$46),12)+1,"jan","fev","mar","abr","mai","jun","jul","ago","set","out","nov","dez")&"/"&(2026+INT((60-SUM(Cenários!$B$46:$BI$46))/12))) -> não atinge | D21: =IF(SUM(Cenários!$B$92:$BI$92)=0,"não atinge",CHOOSE(MOD(60-SUM(Cenários!$B$92:$BI$92),12)+1,"jan","fev","mar","abr","mai","jun","jul","ago","set","out","nov","dez")&"/"&(2026+INT((60-SUM(Cenários!$B$92:$BI$92))/12))) -> abr/2027 | E21: =IF(SUM(Cenários!$B$138:$BI$138)=0,"não atinge",CHOOSE(MOD(60-SUM(Cenários!$B$138:$BI$138),12)+1,"jan","fev","mar","abr","mai","jun","jul","ago","set","out","nov","dez")&"/"&(2026+INT((60-SUM(Cenários!$B$138:$BI$138))/12))) -> fev/2027 | G21: Primeiro mês com EBITDA positivo — quando a operação passa a se pagar.
A23: CAPITAL E CAIXA
B24: Investimento total (CAPEX) | C24: =-SUM(Cenários!$B$41:$BI$41) -> 149127.82 | D24: =-SUM(Cenários!$B$87:$BI$87) -> 149127.82 | E24: =-SUM(Cenários!$B$133:$BI$133) -> 149127.82
B25: Capital requerido (pico de caixa negativo do FCL) | C25: =-MIN(Cenários!$B$45:$BI$45) -> 12063525 | D25: =-MIN(Cenários!$B$91:$BI$91) -> 350781.55 | E25: =-MIN(Cenários!$B$137:$BI$137) -> 160419.32 | G25: Quanto a operação precisa de capital antes de se sustentar sozinha.
B26: Capital total considerado | C26: =SUM(Aportes!$B$98:$BI$98) -> 200000 | D26: =SUM(Aportes!$B$98:$BI$98) -> 200000 | E26: =SUM(Aportes!$B$98:$BI$98) -> 200000
B27: Caixa mínimo ao longo do período | C27: =MIN(Cenários!$B$49:$BI$49) -> -11863525 | D27: =MIN(Cenários!$B$95:$BI$95) -> -180781.55 | E27: =MIN(Cenários!$B$141:$BI$141) -> -4627.82 | G27: Se ficar negativo, o capital planejado não é suficiente — falta captar a diferença.
B28: Mês do caixa mínimo | C28: =CHOOSE(MOD(MATCH(MIN(Cenários!$B$49:$BI$49),Cenários!$B$49:$BI$49,0)-1,12)+1,"jan","fev","mar","abr","mai","jun","jul","ago","set","out","nov","dez")&"/"&(2026+INT((MATCH(MIN(Cenários!$B$49:$BI$49),Cenários!$B$49:$BI$49,0)-1)/12)) -> dez/2030 | D28: =CHOOSE(MOD(MATCH(MIN(Cenários!$B$95:$BI$95),Cenários!$B$95:$BI$95,0)-1,12)+1,"jan","fev","mar","abr","mai","jun","jul","ago","set","out","nov","dez")&"/"&(2026+INT((MATCH(MIN(Cenários!$B$95:$BI$95),Cenários!$B$95:$BI$95,0)-1)/12)) -> mar/2027 | E28: =CHOOSE(MOD(MATCH(MIN(Cenários!$B$141:$BI$141),Cenários!$B$141:$BI$141,0)-1,12)+1,"jan","fev","mar","abr","mai","jun","jul","ago","set","out","nov","dez")&"/"&(2026+INT((MATCH(MIN(Cenários!$B$141:$BI$141),Cenários!$B$141:$BI$141,0)-1)/12)) -> set/2026 | G28: Quando o caixa chega no fundo do poço — é o mês para o qual o aporte precisa chegar antes.
B29: Caixa em dez/2030 | C29: =Cenários!$BI$49 -> -11863525 | D29: =Cenários!$BI$95 -> 18105908 | E29: =Cenários!$BI$141 -> 97023354
B30: FALTA CAPTAR — respeitando as datas de entrada | C30: ='Necessidade de Capital'!B71 -> 14243306 | D30: ='Necessidade de Capital'!C71 -> 423788.68 | E30: ='Necessidade de Capital'!D71 -> 253883.27 | G30: Inclui a reserva mínima de caixa. Detalhe mês a mês na aba Necessidade de Capital.
B31: Primeiro mês com caixa negativo | C31: ='Necessidade de Capital'!B75 -> jun/2026 | D31: ='Necessidade de Capital'!C75 -> jun/2026 | E31: ='Necessidade de Capital'!D75 -> jun/2026 | G31: O prazo da captação. Pode ser bem antes do mês do fundo do poço.
B32: Por fundador, se os quatro cobrissem a lacuna | C32: ='Necessidade de Capital'!B82 -> 3560826.5 | D32: ='Necessidade de Capital'!C82 -> 105947.17 | E32: ='Necessidade de Capital'!D82 -> 63470.818 | G32: Além dos R$ 20 mil já comprometidos por cada um.
A34: PREÇO vs CUSTO — A CONTA DE TRÁS PRA FRENTE
B35: Primeiro mês em que a assinatura cobre o custo | C35: ='Preço Mínimo'!B86 -> não atinge | D35: ='Preço Mínimo'!C86 -> abr/2027 | E35: ='Preço Mínimo'!D86 -> fev/2027 | G35: Ao preço de tabela. É o mesmo mês do break-even acima — as duas contas são a mesma, lidas de lados opostos.
B36: EBITDA acumulado até o fim da janela de cobertura | C36: ='Preço Mínimo'!B85 -> -419187.63 | D36: ='Preço Mínimo'!C85 -> -302653.73 | E36: ='Preço Mínimo'!D85 -> -49907.888 | G36: Negativo significa que os primeiros meses não se pagam: a diferença vem de capital.
B37: Preço do Essencial que zeraria a janela inicial (cenário ativo) | C37: ='Preço Mínimo'!$B$68 -> 48.689548 | G37: Um preço único, cobrado em todos os meses da janela definida em Premissas.
B38: Quantas vezes o preço de hoje (cenário ativo) | C38: ='Preço Mínimo'!$B$72 -> 2.4467109 | G38: Acima de ~1,5x o preço deixa de ser vendável: o problema passa a ser de escala, não de preço.
B39: Assinantes necessários na janela, ao preço de hoje (cenário ativo) | C39: ='Preço Mínimo'!$B$73 -> 6178.6813 | G39: Contra a média projetada na mesma janela.
B40: Veredicto da janela inicial (cenário ativo) | C40: ='Preço Mínimo'!$B$77 -> Nenhum preço de mercado cobre: a janela é financiada por capital
A42: INDICADORES DE VIABILIDADE (sobre o Fluxo de Caixa Livre)
B43: VPL — Valor Presente Líquido | C43: =NPV(Premissas!$B$19,Cenários!$B$42:$BI$42) -> -5535282.7 | D43: =NPV(Premissas!$B$19,Cenários!$B$88:$BI$88) -> 7237765.1 | E43: =NPV(Premissas!$B$19,Cenários!$B$134:$BI$134) -> 40123778 | G43: Descontado à TMA definida em Premissas. Positivo = o projeto cria valor.
B44: TIR mensal | C44: =IFERROR(IRR(Cenários!$B$42:$BI$42),"n/d") -> n/d | D44: =IFERROR(IRR(Cenários!$B$88:$BI$88),"n/d") -> 0.1468989 | E44: =IFERROR(IRR(Cenários!$B$134:$BI$134),"n/d") -> 0.34011628
B45: TIR anual | C45: =IFERROR((1+C44)^12-1,"n/d") -> n/d | D45: =IFERROR((1+D44)^12-1,"n/d") -> 4.1796645 | E45: =IFERROR((1+E44)^12-1,"n/d") -> 32.551336 | G45: Compare com a TMA. Atenção: quando o investimento inicial é pequeno diante do caixa gerado, a TIR fica muito alta e perde poder de comparação — olhe o VPL junto.
B46: Payback simples (meses) | C46: =IF(Cenários!$BI$45<0,"> 60",MAX(Cenários!$B$50:$BI$50)+1) -> > 60 | D46: =IF(Cenários!$BI$91<0,"> 60",MAX(Cenários!$B$96:$BI$96)+1) -> 23 | E46: =IF(Cenários!$BI$137<0,"> 60",MAX(Cenários!$B$142:$BI$142)+1) -> 16 | G46: Mês em que o FCL acumulado passa a positivo e não volta mais.
B47: Payback descontado (meses) | C47: =IF(Cenários!$BI$44<0,"> 60",MAX(Cenários!$B$51:$BI$51)+1) -> > 60 | D47: =IF(Cenários!$BI$90<0,"> 60",MAX(Cenários!$B$97:$BI$97)+1) -> 24 | E47: =IF(Cenários!$BI$136<0,"> 60",MAX(Cenários!$B$143:$BI$143)+1) -> 16 | G47: Critério de decisão: payback desejado definido em Premissas.
B48: FCL acumulado em 5 anos | C48: =SUM(Cenários!$B$42:$BI$42) -> -12063525 | D48: =SUM(Cenários!$B$88:$BI$88) -> 17905908 | E48: =SUM(Cenários!$B$134:$BI$134) -> 96823354
B49: Retorno sobre o capital requerido (múltiplo) | C49: =IFERROR(C48/C25,0) -> -1 | D49: =IFERROR(D48/D25,0) -> 51.045751 | E49: =IFERROR(E48/E25,0) -> 603.56418 | G49: Múltiplo, não percentual: 3,0x significa devolver três vezes o capital que o projeto precisou. Negativo significa que o capital não volta.
A51: TESTE DE DECISÃO — GO / NO-GO
B52: O caixa nunca fica negativo? | C52: =IF(C27>=0,"SIM","NÃO") -> NÃO | D52: =IF(D27>=0,"SIM","NÃO") -> NÃO | E52: =IF(E27>=0,"SIM","NÃO") -> NÃO
B53: O VPL é positivo? | C53: =IF(C43>0,"SIM","NÃO") -> NÃO | D53: =IF(D43>0,"SIM","NÃO") -> SIM | E53: =IF(E43>0,"SIM","NÃO") -> SIM
B54: A TIR anual supera a TMA? | C54: =IF(N(C45)>Premissas!$B$18,"SIM","NÃO") -> NÃO | D54: =IF(N(D45)>Premissas!$B$18,"SIM","NÃO") -> SIM | E54: =IF(N(E45)>Premissas!$B$18,"SIM","NÃO") -> SIM
B55: O payback descontado cabe no prazo desejado? | C55: =IF(AND(ISNUMBER(C47),N(C47)<=Premissas!$B$20),"SIM","NÃO") -> NÃO | D55: =IF(AND(ISNUMBER(D47),N(D47)<=Premissas!$B$20),"SIM","NÃO") -> SIM | E55: =IF(AND(ISNUMBER(E47),N(E47)<=Premissas!$B$20),"SIM","NÃO") -> SIM
B56: DIAGNÓSTICO | C56: =IF(COUNTIF(C52:C55,"SIM")=4,"GO — VIÁVEL",IF(COUNTIF(C52:C55,"SIM")>=2,"GO COM RESSALVAS","NO GO — INVIÁVEL")) -> NO GO — INVIÁVEL | D56: =IF(COUNTIF(D52:D55,"SIM")=4,"GO — VIÁVEL",IF(COUNTIF(D52:D55,"SIM")>=2,"GO COM RESSALVAS","NO GO — INVIÁVEL")) -> GO COM RESSALVAS | E56: =IF(COUNTIF(E52:E55,"SIM")=4,"GO — VIÁVEL",IF(COUNTIF(E52:E55,"SIM")>=2,"GO COM RESSALVAS","NO GO — INVIÁVEL")) -> GO COM RESSALVAS | G56: Critério herdado da planilha de viabilidade da EMS (Go / No-Go).
A58: MÉTRICAS DE UNIDADE — CENÁRIO ATIVO (dez/2030)
B59: LTV — valor do assinante | C59: =Usuários!$BI$29 -> 461.20034
B60: CAC por assinante pagante | C60: =Usuários!$BI$25 -> 38.567154
B61: LTV ÷ CAC | C61: =Usuários!$BI$30 -> 11.958371 | G61: Referência: ≥ 3,0x é saudável. Abaixo de 1,0x destrói valor.
B62: Payback do CAC (meses) | C62: =Usuários!$BI$31 -> 1.3388335 | G62: Ideal abaixo de 12 meses.
B63: ARPPU — receita por assinante | C63: =Usuários!$BI$26 -> 38.995446
B64: Runway em dez/2026 (meses de caixa) | C64: =Usuários!$M$36 -> 0.21611027
B65: Pessoas na operação em dez/2030 | C65: =Usuários!$BI$19 -> 50 | G65: Quadro de pessoal projetado. Edite linha a linha na aba Pessoas.
A67: PONTOS DE ATENÇÃO IDENTIFICADOS NA MODELAGEM
B68: ▸ Fator R: o modelo está no Anexo V, e é isso mesmo
B69: A aba Pessoas calcula o Fator R do quadro projetado: fica entre 1% e 6%, muito abaixo dos 28% exigidos para o Anexo III. Como pagamento a PJ não conta como folha, o Anexo III simplesmente não está disponível com a estrutura atual — por isso o regime padrão do modelo é o Anexo V. Migrar parte do time para CLT ou elevar o pró-labore pode reverter isso e economizar até R$ 135 mil por ano; compare na aba Tributos antes de decidir.
B70: ▸ Dependência dos aportes não assinados
B71: Dos R$ 200 mil do caso-base, R$ 120 mil vêm de C-ioT, Felipe Martinelli e Shaiane — ainda não formalizados. Sem eles, o capital cai para R$ 80 mil e o lançamento com aquisição paga não se sustenta. Este é o maior risco de curto prazo do plano.
B72: ▸ Comissão das lojas de aplicativos
B73: Apple e Google retêm 15% da assinatura (Google desde o primeiro dia; Apple pelo Small Business Program, válido enquanto a receita anual for inferior a US$ 1 milhão). Acima disso a Apple volta a 30%. É a maior dedução isolada da receita e não estava no brief.
B74: ▸ Conversão de 5% é premissa de quartil superior
B75: Benchmarks de freemium apontam mediana de 2,2% a 2,6% e faixa típica de 2% a 5%. Os 5% do brief são defensáveis para saúde com feature paga clara (histórico de dados), mas são a premissa mais sensível do modelo — teste o cenário Conservador (3%).
B76: ▸ Teto do Simples Nacional
B77: O modelo troca automaticamente para o Lucro Presumido quando o RBT12 ultrapassa R$ 4,8 milhões. No cenário Provável isso acontece dentro do horizonte e eleva a carga tributária — planeje a transição societária e contábil com antecedência.
B78: ▸ Só a equipe do MVP está de fato contratada
B79: Hoje não há time. O único custo de pessoal comprometido são os R$ 21 mil da equipe PJ de set–out/2026 para entregar o app. Todo o quadro projetado a partir de 2027 é plano, não compromisso: está na aba Pessoas, linha a linha, e pode ser desligado inteiro pelo controle de Premissas. É a premissa de custo que mais desloca o resultado.
... B99: Na aba Necessidade de Capital, 'falta captar ignorando datas' e 'falta captar respeitando as datas' dão números diferentes. A segunda é maior porque parte do capital previsto chega depois do mês em que o caixa aperta. Antecipar aporte já previsto resolve parte da lacuna sem captar um real a mais.

Sheet Necessidade de Capital
A1: NECESSIDADE DE CAPITAL — QUANTO A EMPRESA PRECISA E DE QUEM
A2: Mês a mês, porque no começo é o mês que decide. O ano fecha positivo e a empresa quebra em março: é isso que a visão anual esconde.
A4: Linha do tempo | B4: 46023 | C4: 46054 | D4: 46082 | E4: 46113 | F4: 46143 | G4: 46174 | H4: 46204 | I4: 46235 | J4: 46266 | K4: 46296 | L4: 46327 | M4: 46357 | N4: 46388 | O4: 46419 | P4: 46447 | Q4: 46478 | R4: 46508 | S4: 46539 | T4: 46569 | U4: 46600 | V4: 46631 | W4: 46661 | X4: 46692 | Y4: 46722 | Z4: 46753 | AA4: 46784 | AB4: 46813 | AC4: 46844 | AD4: 46874 | AE4: 46905 | AF4: 46935 | AG4: 46966 | AH4: 46997 | AI4: 47027 | AJ4: 47058 | AK4: 47088 | AL4: 47119 | AM4: 47150 | AN4: 47178 | AO4: 47209 | AP4: 47239 | AQ4: 47270 | AR4: 47300 | AS4: 47331 | AT4: 47362 | AU4: 47392 | AV4: 47423 | AW4: 47453 | AX4: 47484 | AY4: 47515 | AZ4: 47543 | BA4: 47574 | BB4: 47604 | BC4: 47635 | BD4: 47665 | BE4: 47696 | BF4: 47727 | BG4: 47757 | BH4: 47788 | BI4: 47818 | BJ4: TOTAL | BK4: % / Nota
A5: Mês nº | B5: 1 | C5: 2 | D5: 3 | E5: 4 | F5: 5 | G5: 6 | H5: 7 | I5: 8 | J5: 9 | K5: 10 | L5: 11 | M5: 12 | N5: 13 | O5: 14 | P5: 15 | Q5: 16 | R5: 17 | S5: 18 | T5: 19 | U5: 20 | V5: 21 | W5: 22 | X5: 23 | Y5: 24 | Z5: 25 | AA5: 26 | AB5: 27 | AC5: 28 | AD5: 29 | AE5: 30 | AF5: 31 | AG5: 32 | AH5: 33 | AI5: 34 | AJ5: 35 | AK5: 36 | AL5: 37 | AM5: 38 | AN5: 39 | AO5: 40 | AP5: 41 | AQ5: 42 | AR5: 43 | AS5: 44 | AT5: 45 | AU5: 46 | AV5: 47 | AW5: 48 | AX5: 49 | AY5: 50 | AZ5: 51 | BA5: 52 | BB5: 53 | BC5: 54 | BD5: 55 | BE5: 56 | BF5: 57 | BG5: 58 | BH5: 59 | BI5: 60
A6: Ano | B6: =YEAR(B4) -> 2026 | C6: =YEAR(C4) -> 2026 | D6: =YEAR(D4) -> 2026 | E6: =YEAR(E4) -> 2026 | F6: =YEAR(F4) -> 2026 | G6: =YEAR(G4) -> 2026 | H6: =YEAR(H4) -> 2026 | I6: =YEAR(I4) -> 2026 | ... BI6: =YEAR(BI4) -> 2030
A7: Índice do ano (auxiliar) | B7: =MATCH(B6,Premissas!$C$5:$G$5,0) -> 1 | C7: =MATCH(C6,Premissas!$C$5:$G$5,0) -> 1 | D7: =MATCH(D6,Premissas!$C$5:$G$5,0) -> 1 | E7: =MATCH(E6,Premissas!$C$5:$G$5,0) -> 1 | F7: =MATCH(F6,Premissas!$C$5:$G$5,0) -> 1 | G7: =MATCH(G6,Premissas!$C$5:$G$5,0) -> 1 | H7: =MATCH(H6,Premissas!$C$5:$G$5,0) -> 1 | I7: =MATCH(I6,Premissas!$C$5:$G$5,0) -> 1 | ... BI7: =MATCH(BI6,Premissas!$C$5:$G$5,0) -> 5
A8: 1. O CAPITAL QUE JÁ ESTÁ NA MESA, POR STATUS — vale para os três cenários
A9: Realizado | B9: =SUMPRODUCT((Aportes!$D$6:$D$37="Realizado")*(Aportes!$A$6:$A$37>=B$4)*(Aportes!$A$6:$A$37<=EOMONTH(B$4,0))*Aportes!$C$6:$C$37) -> 0 | C9: =SUMPRODUCT((Aportes!$D$6:$D$37="Realizado")*(Aportes!$A$6:$A$37>=C$4)*(Aportes!$A$6:$A$37<=EOMONTH(C$4,0))*Aportes!$C$6:$C$37) -> 0 | D9: =SUMPRODUCT((Aportes!$D$6:$D$37="Realizado")*(Aportes!$A$6:$A$37>=D$4)*(Aportes!$A$6:$A$37<=EOMONTH(D$4,0))*Aportes!$C$6:$C$37) -> 0 | E9: =SUMPRODUCT((Aportes!$D$6:$D$37="Realizado")*(Aportes!$A$6:$A$37>=E$4)*(Aportes!$A$6:$A$37<=EOMONTH(E$4,0))*Aportes!$C$6:$C$37) -> 10000 | F9: =SUMPRODUCT((Aportes!$D$6:$D$37="Realizado")*(Aportes!$A$6:$A$37>=F$4)*(Aportes!$A$6:$A$37<=EOMONTH(F$4,0))*Aportes!$C$6:$C$37) -> 0 | G9: =SUMPRODUCT((Aportes!$D$6:$D$37="Realizado")*(Aportes!$A$6:$A$37>=G$4)*(Aportes!$A$6:$A$37<=EOMONTH(G$4,0))*Aportes!$C$6:$C$37) -> 0 | H9: =SUMPRODUCT((Aportes!$D$6:$D$37="Realizado")*(Aportes!$A$6:$A$37>=H$4)*(Aportes!$A$6:$A$37<=EOMONTH(H$4,0))*Aportes!$C$6:$C$37) -> 5000 | I9: =SUMPRODUCT((Aportes!$D$6:$D$37="Realizado")*(Aportes!$A$6:$A$37>=I$4)*(Aportes!$A$6:$A$37<=EOMONTH(I$4,0))*Aportes!$C$6:$C$37) -> 18000 | ... BI9: =SUMPRODUCT((Aportes!$D$6:$D$37="Realizado")*(Aportes!$A$6:$A$37>=BI$4)*(Aportes!$A$6:$A$37<=EOMONTH(BI$4,0))*Aportes!$C$6:$C$37) -> 0 | BJ9: =SUM(B9:BI9) -> 33000 | BK9: Dinheiro que já entrou na conta da empresa.
A10: Compromisso | B10: =SUMPRODUCT((Aportes!$D$6:$D$37="Compromisso")*(Aportes!$A$6:$A$37>=B$4)*(Aportes!$A$6:$A$37<=EOMONTH(B$4,0))*Aportes!$C$6:$C$37) -> 0 | C10: =SUMPRODUCT((Aportes!$D$6:$D$37="Compromisso")*(Aportes!$A$6:$A$37>=C$4)*(Aportes!$A$6:$A$37<=EOMONTH(C$4,0))*Aportes!$C$6:$C$37) -> 0 | D10: =SUMPRODUCT((Aportes!$D$6:$D$37="Compromisso")*(Aportes!$A$6:$A$37>=D$4)*(Aportes!$A$6:$A$37<=EOMONTH(D$4,0))*Aportes!$C$6:$C$37) -> 0 | E10: =SUMPRODUCT((Aportes!$D$6:$D$37="Compromisso")*(Aportes!$A$6:$A$37>=E$4)*(Aportes!$A$6:$A$37<=EOMONTH(E$4,0))*Aportes!$C$6:$C$37) -> 0 | F10: =SUMPRODUCT((Aportes!$D$6:$D$37="Compromisso")*(Aportes!$A$6:$A$37>=F$4)*(Aportes!$A$6:$A$37<=EOMONTH(F$4,0))*Aportes!$C$6:$C$37) -> 0 | G10: =SUMPRODUCT((Aportes!$D$6:$D$37="Compromisso")*(Aportes!$A$6:$A$37>=G$4)*(Aportes!$A$6:$A$37<=EOMONTH(G$4,0))*Aportes!$C$6:$C$37) -> 0 | H10: =SUMPRODUCT((Aportes!$D$6:$D$37="Compromisso")*(Aportes!$A$6:$A$37>=H$4)*(Aportes!$A$6:$A$37<=EOMONTH(H$4,0))*Aportes!$C$6:$C$37) -> 0 | I10: =SUMPRODUCT((Aportes!$D$6:$D$37="Compromisso")*(Aportes!$A$6:$A$37>=I$4)*(Aportes!$A$6:$A$37<=EOMONTH(I$4,0))*Aportes!$C$6:$C$37) -> 0 | ... BI10: =SUMPRODUCT((Aportes!$D$6:$D$37="Compromisso")*(Aportes!$A$6:$A$37>=BI$4)*(Aportes!$A$6:$A$37<=EOMONTH(BI$4,0))*Aportes!$C$6:$C$37) -> 0 | BJ10: =SUM(B10:BI10) -> 47000 | BK10: Fundadores já se comprometeram; ainda não integralizaram.
A11: Previsto | B11: =SUMPRODUCT((Aportes!$D$6:$D$37="Previsto")*(Aportes!$A$6:$A$37>=B$4)*(Aportes!$A$6:$A$37<=EOMONTH(B$4,0))*Aportes!$C$6:$C$37) -> 0 | C11: =SUMPRODUCT((Aportes!$D$6:$D$37="Previsto")*(Aportes!$A$6:$A$37>=C$4)*(Aportes!$A$6:$A$37<=EOMONTH(C$4,0))*Aportes!$C$6:$C$37) -> 0 | D11: =SUMPRODUCT((Aportes!$D$6:$D$37="Previsto")*(Aportes!$A$6:$A$37>=D$4)*(Aportes!$A$6:$A$37<=EOMONTH(D$4,0))*Aportes!$C$6:$C$37) -> 0 | E11: =SUMPRODUCT((Aportes!$D$6:$D$37="Previsto")*(Aportes!$A$6:$A$37>=E$4)*(Aportes!$A$6:$A$37<=EOMONTH(E$4,0))*Aportes!$C$6:$C$37) -> 0 | F11: =SUMPRODUCT((Aportes!$D$6:$D$37="Previsto")*(Aportes!$A$6:$A$37>=F$4)*(Aportes!$A$6:$A$37<=EOMONTH(F$4,0))*Aportes!$C$6:$C$37) -> 0 | G11: =SUMPRODUCT((Aportes!$D$6:$D$37="Previsto")*(Aportes!$A$6:$A$37>=G$4)*(Aportes!$A$6:$A$37<=EOMONTH(G$4,0))*Aportes!$C$6:$C$37) -> 0 | H11: =SUMPRODUCT((Aportes!$D$6:$D$37="Previsto")*(Aportes!$A$6:$A$37>=H$4)*(Aportes!$A$6:$A$37<=EOMONTH(H$4,0))*Aportes!$C$6:$C$37) -> 0 | I11: =SUMPRODUCT((Aportes!$D$6:$D$37="Previsto")*(Aportes!$A$6:$A$37>=I$4)*(Aportes!$A$6:$A$37<=EOMONTH(I$4,0))*Aportes!$C$6:$C$37) -> 0 | ... BI11: =SUMPRODUCT((Aportes!$D$6:$D$37="Previsto")*(Aportes!$A$6:$A$37>=BI$4)*(Aportes!$A$6:$A$37<=EOMONTH(BI$4,0))*Aportes!$C$6:$C$37) -> 0 | BJ11: =SUM(B11:BI11) -> 120000 | BK11: Negociação em curso, sem assinatura. Ligado/desligado em Premissas.
A12: Em negociação | B12: =SUMPRODUCT((Aportes!$D$6:$D$37="Em negociação")*(Aportes!$A$6:$A$37>=B$4)*(Aportes!$A$6:$A$37<=EOMONTH(B$4,0))*Aportes!$C$6:$C$37) -> 0 | C12: =SUMPRODUCT((Aportes!$D$6:$D$37="Em negociação")*(Aportes!$A$6:$A$37>=C$4)*(Aportes!$A$6:$A$37<=EOMONTH(C$4,0))*Aportes!$C$6:$C$37) -> 0 | D12: =SUMPRODUCT((Aportes!$D$6:$D$37="Em negociação")*(Aportes!$A$6:$A$37>=D$4)*(Aportes!$A$6:$A$37<=EOMONTH(D$4,0))*Aportes!$C$6:$C$37) -> 0 | E12: =SUMPRODUCT((Aportes!$D$6:$D$37="Em negociação")*(Aportes!$A$6:$A$37>=E$4)*(Aportes!$A$6:$A$37<=EOMONTH(E$4,0))*Aportes!$C$6:$C$37) -> 0 | F12: =SUMPRODUCT((Aportes!$D$6:$D$37="Em negociação")*(Aportes!$A$6:$A$37>=F$4)*(Aportes!$A$6:$A$37<=EOMONTH(F$4,0))*Aportes!$C$6:$C$37) -> 0 | G12: =SUMPRODUCT((Aportes!$D$6:$D$37="Em negociação")*(Aportes!$A$6:$A$37>=G$4)*(Aportes!$A$6:$A$37<=EOMONTH(G$4,0))*Aportes!$C$6:$C$37) -> 0 | H12: =SUMPRODUCT((Aportes!$D$6:$D$37="Em negociação")*(Aportes!$A$6:$A$37>=H$4)*(Aportes!$A$6:$A$37<=EOMONTH(H$4,0))*Aportes!$C$6:$C$37) -> 0 | I12: =SUMPRODUCT((Aportes!$D$6:$D$37="Em negociação")*(Aportes!$A$6:$A$37>=I$4)*(Aportes!$A$6:$A$37<=EOMONTH(I$4,0))*Aportes!$C$6:$C$37) -> 0 | ... BI12: =SUMPRODUCT((Aportes!$D$6:$D$37="Em negociação")*(Aportes!$A$6:$A$37>=BI$4)*(Aportes!$A$6:$A$37<=EOMONTH(BI$4,0))*Aportes!$C$6:$C$37) -> 0 | BJ12: =SUM(B12:BI12) -> 0 | BK12: Sem compromisso nenhum. Desligado por padrão.
A13: Investidores estratégicos (tabela 2 da aba Aportes) | B13: =SUMPRODUCT((Aportes!$D$43:$D$50>=B$4)*(Aportes!$D$43:$D$50<=EOMONTH(B$4,0))*Aportes!$C$43:$C$50) -> 0 | C13: =SUMPRODUCT((Aportes!$D$43:$D$50>=C$4)*(Aportes!$D$43:$D$50<=EOMONTH(C$4,0))*Aportes!$C$43:$C$50) -> 0 | D13: =SUMPRODUCT((Aportes!$D$43:$D$50>=D$4)*(Aportes!$D$43:$D$50<=EOMONTH(D$4,0))*Aportes!$C$43:$C$50) -> 0 | E13: =SUMPRODUCT((Aportes!$D$43:$D$50>=E$4)*(Aportes!$D$43:$D$50<=EOMONTH(E$4,0))*Aportes!$C$43:$C$50) -> 0 | F13: =SUMPRODUCT((Aportes!$D$43:$D$50>=F$4)*(Aportes!$D$43:$D$50<=EOMONTH(F$4,0))*Aportes!$C$43:$C$50) -> 0 | G13: =SUMPRODUCT((Aportes!$D$43:$D$50>=G$4)*(Aportes!$D$43:$D$50<=EOMONTH(G$4,0))*Aportes!$C$43:$C$50) -> 0 | H13: =SUMPRODUCT((Aportes!$D$43:$D$50>=H$4)*(Aportes!$D$43:$D$50<=EOMONTH(H$4,0))*Aportes!$C$43:$C$50) -> 0 | I13: =SUMPRODUCT((Aportes!$D$43:$D$50>=I$4)*(Aportes!$D$43:$D$50<=EOMONTH(I$4,0))*Aportes!$C$43:$C$50) -> 0 | ... BI13: =SUMPRODUCT((Aportes!$D$43:$D$50>=BI$4)*(Aportes!$D$43:$D$50<=EOMONTH(BI$4,0))*Aportes!$C$43:$C$50) -> 0 | BJ13: =SUM(B13:BI13) -> 500000
A14: Capital de todos os status, somado | B14: =SUM(B9:B13) -> 0 | C14: =SUM(C9:C13) -> 0 | D14: =SUM(D9:D13) -> 0 | E14: =SUM(E9:E13) -> 10000 | F14: =SUM(F9:F13) -> 0 | G14: =SUM(G9:G13) -> 0 | H14: =SUM(H9:H13) -> 5000 | I14: =SUM(I9:I13) -> 18000 | ... BI14: =SUM(BI9:BI13) -> 0 | BJ14: =SUM(B14:BI14) -> 700000
A15: Capital que o modelo considera (depois dos interruptores) | B15: =Aportes!B98 -> 0 | C15: =Aportes!C98 -> 0 | D15: =Aportes!D98 -> 0 | E15: =Aportes!E98 -> 10000 | F15: =Aportes!F98 -> 0 | G15: =Aportes!G98 -> 0 | H15: =Aportes!H98 -> 5000 | I15: =Aportes!I98 -> 18000 | ... BI15: =Aportes!BI98 -> 0 | BJ15: =SUM(B15:BI15) -> 200000 | BK15: É este que entra no caixa. A diferença para a linha acima é o que está desligado.
A16: Capital considerado — acumulado | B16: =Aportes!B99 -> 0 | C16: =Aportes!C99 -> 0 | D16: =Aportes!D99 -> 0 | E16: =Aportes!E99 -> 10000 | F16: =Aportes!F99 -> 10000 | G16: =Aportes!G99 -> 10000 | H16: =Aportes!H99 -> 15000 | I16: =Aportes!I99 -> 33000 | ... BI16: =Aportes!BI99 -> 200000
A19: CENÁRIO 1 — CONSERVADOR
A20: Fluxo de caixa livre do mês (FCL) | B20: =Cenários!B42 -> 0 | C20: =Cenários!C42 -> 0 | D20: =Cenários!D42 -> 0 | E20: =Cenários!E42 -> -1500 | F20: =Cenários!F42 -> -8100 | G20: =Cenários!G42 -> -2100 | H20: =Cenários!H42 -> -2100 | I20: =Cenários!I42 -> -11227.82 | ... BI20: =Cenários!BI42 -> -392239.05 | BJ20: =SUM(B20:BI20) -> -12063525 | BK20: Não inclui aporte: aporte é financiamento, não geração de caixa.
A21: Buraco do mês (quanto a operação queimou) | B21: =IF(B20<0,-B20,0) -> 0 | C21: =IF(C20<0,-C20,0) -> 0 | D21: =IF(D20<0,-D20,0) -> 0 | E21: =IF(E20<0,-E20,0) -> 1500 | F21: =IF(F20<0,-F20,0) -> 8100 | G21: =IF(G20<0,-G20,0) -> 2100 | H21: =IF(H20<0,-H20,0) -> 2100 | I21: =IF(I20<0,-I20,0) -> 11227.82 | ... BI21: =IF(BI20<0,-BI20,0) -> 392239.05 | BJ21: =SUM(B21:BI21) -> 12063525
A22: Buraco acumulado | B22: =B21 -> 0 | C22: =B22+C21 -> 0 | D22: =C22+D21 -> 0 | E22: =D22+E21 -> 1500 | F22: =E22+F21 -> 9600 | G22: =F22+G21 -> 11700 | H22: =G22+H21 -> 13800 | I22: =H22+I21 -> 25027.82 | J22: =I22+J21 -> 37627.82 | ... BI22: =BH22+BI21 -> 12063525 | BK22: Soma de todos os meses negativos, sem compensar com os positivos.
A23: FCL acumulado (os positivos já abatendo os negativos) | B23: =Cenários!B45 -> 0 | C23: =Cenários!C45 -> 0 | D23: =Cenários!D45 -> 0 | E23: =Cenários!E45 -> -1500 | F23: =Cenários!F45 -> -9600 | G23: =Cenários!G45 -> -11700 | H23: =Cenários!H45 -> -13800 | I23: =Cenários!I45 -> -25027.82 | ... BI23: =Cenários!BI45 -> -12063525 | BK23: O fundo do poço desta linha é o capital requerido pela operação.
A24: Custo fixo do mês (nuvem, pessoas, marketing recorrente, administrativas) | B24: =-(Cenários!B35+'Análise Fluxo'!B18+'Análise Fluxo'!B19+'Análise Fluxo'!B20+'Análise Fluxo'!B22+'Análise Fluxo'!B27) -> 0 | C24: =-(Cenários!C35+'Análise Fluxo'!C18+'Análise Fluxo'!C19+'Análise Fluxo'!C20+'Análise Fluxo'!C22+'Análise Fluxo'!C27) -> 0 | D24: =-(Cenários!D35+'Análise Fluxo'!D18+'Análise Fluxo'!D19+'Análise Fluxo'!D20+'Análise Fluxo'!D22+'Análise Fluxo'!D27) -> 0 | E24: =-(Cenários!E35+'Análise Fluxo'!E18+'Análise Fluxo'!E19+'Análise Fluxo'!E20+'Análise Fluxo'!E22+'Análise Fluxo'!E27) -> 1500 | F24: =-(Cenários!F35+'Análise Fluxo'!F18+'Análise Fluxo'!F19+'Análise Fluxo'!F20+'Análise Fluxo'!F22+'Análise Fluxo'!F27) -> 2100 | G24: =-(Cenários!G35+'Análise Fluxo'!G18+'Análise Fluxo'!G19+'Análise Fluxo'!G20+'Análise Fluxo'!G22+'Análise Fluxo'!G27) -> 2100 | H24: =-(Cenários!H35+'Análise Fluxo'!H18+'Análise Fluxo'!H19+'Análise Fluxo'!H20+'Análise Fluxo'!H22+'Análise Fluxo'!H27) -> 2100 | I24: =-(Cenários!I35+'Análise Fluxo'!I18+'Análise Fluxo'!I19+'Análise Fluxo'!I20+'Análise Fluxo'!I22+'Análise Fluxo'!I27) -> 2100 | ... BI24: =-(Cenários!BI35+'Análise Fluxo'!BI18+'Análise Fluxo'!BI19+'Análise Fluxo'!BI20+'Análise Fluxo'!BI22+'Análise Fluxo'!BI27) -> 793260.32 | BJ24: =SUM(B24:BI24) -> 18862462 | BK24: Sem aquisição paga, imposto, loja e meio de pagamento: esses variam com a operação, não com a existência dela.
A25: Reserva mínima desejada | B25: =MAX(SUMPRODUCT((B$5:BI$5>B$5)*(B$5:BI$5<=B$5+Premissas!$B$118)*B$24:BI$24),Premissas!$B$118*B24) -> 1500 | C25: =MAX(SUMPRODUCT((B$5:BI$5>C$5)*(B$5:BI$5<=C$5+Premissas!$B$118)*B$24:BI$24),Premissas!$B$118*C24) -> 3600 | D25: =MAX(SUMPRODUCT((B$5:BI$5>D$5)*(B$5:BI$5<=D$5+Premissas!$B$118)*B$24:BI$24),Premissas!$B$118*D24) -> 5700 | E25: =MAX(SUMPRODUCT((B$5:BI$5>E$5)*(B$5:BI$5<=E$5+Premissas!$B$118)*B$24:BI$24),Premissas!$B$118*E24) -> 6300 | F25: =MAX(SUMPRODUCT((B$5:BI$5>F$5)*(B$5:BI$5<=F$5+Premissas!$B$118)*B$24:BI$24),Premissas!$B$118*F24) -> 6300 | G25: =MAX(SUMPRODUCT((B$5:BI$5>G$5)*(B$5:BI$5<=G$5+Premissas!$B$118)*B$24:BI$24),Premissas!$B$118*G24) -> 6300 | H25: =MAX(SUMPRODUCT((B$5:BI$5>H$5)*(B$5:BI$5<=H$5+Premissas!$B$118)*B$24:BI$24),Premissas!$B$118*H24) -> 9597.12 | I25: =MAX(SUMPRODUCT((B$5:BI$5>I$5)*(B$5:BI$5<=I$5+Premissas!$B$118)*B$24:BI$24),Premissas!$B$118*I24) -> 13314.68 | J25: =MAX(SUMPRODUCT((B$5:BI$5>J$5)*(B$5:BI$5<=J$5+Premissas!$B$118)*B$24:BI$24),Premissas!$B$118*J24) -> 17555.972 | K25: =MAX(SUMPRODUCT((B$5:BI$5>K$5)*(B$5:BI$5<=K$5+Premissas!$B$118)*B$24:BI$24),Premissas!$B$118*K24) -> 80196.027 | L25: =MAX(SUMPRODUCT((B$5:BI$5>L$5)*(B$5:BI$5<=L$5+Premissas!$B$118)*B$24:BI$24),Premissas!$B$118*L24) -> 143341.69 | M25: =MAX(SUMPRODUCT((B$5:BI$5>M$5)*(B$5:BI$5<=M$5+Premissas!$B$118)*B$24:BI$24),Premissas!$B$118*M24) -> 206982.56 | N25: =MAX(SUMPRODUCT((B$5:BI$5>N$5)*(B$5:BI$5<=N$5+Premissas!$B$118)*B$24:BI$24),Premissas!$B$118*N24) -> 209504.12 | O25: =MAX(SUMPRODUCT((B$5:BI$5>O$5)*(B$5:BI$5<=O$5+Premissas!$B$118)*B$24:BI$24),Premissas!$B$118*O24) -> 211621.42 | P25: =MAX(SUMPRODUCT((B$5:BI$5>P$5)*(B$5:BI$5<=P$5+Premissas!$B$118)*B$24:BI$24),Premissas!$B$118*P24) -> 213191.11 | Q25: =MAX(SUMPRODUCT((B$5:BI$5>Q$5)*(B$5:BI$5<=Q$5+Premissas!$B$118)*B$24:BI$24),Premissas!$B$118*Q24) -> 214610.6 | R25: =MAX(SUMPRODUCT((B$5:BI$5>R$5)*(B$5:BI$5<=R$5+Premissas!$B$118)*B$24:BI$24),Premissas!$B$118*R24) -> 215893.81 | S25: =MAX(SUMPRODUCT((B$5:BI$5>S$5)*(B$5:BI$5<=S$5+Premissas!$B$118)*B$24:BI$24),Premissas!$B$118*S24) -> 217054.17 | T25: =MAX(SUMPRODUCT((B$5:BI$5>T$5)*(B$5:BI$5<=T$5+Premissas!$B$118)*B$24:BI$24),Premissas!$B$118*T24) -> 218103.43 | U25: =MAX(SUMPRODUCT((B$5:BI$5>U$5)*(B$5:BI$5<=U$5+Premissas!$B$118)*B$24:BI$24),Premissas!$B$118*U24) -> 219051.62 | V25: =MAX(SUMPRODUCT((B$5:BI$5>V$5)*(B$5:BI$5<=V$5+Premissas!$B$118)*B$24:BI$24),Premissas!$B$118*V24) -> 219908.45 | W25: =MAX(SUMPRODUCT((B$5:BI$5>W$5)*(B$5:BI$5<=W$5+Premissas!$B$118)*B$24:BI$24),Premissas!$B$118*W24) -> 364881.88 | X25: =MAX(SUMPRODUCT((B$5:BI$5>X$5)*(B$5:BI$5<=X$5+Premissas!$B$118)*B$24:BI$24),Premissas!$B$118*X24) -> 510105.96 | Y25: =MAX(SUMPRODUCT((B$5:BI$5>Y$5)*(B$5:BI$5<=Y$5+Premissas!$B$118)*B$24:BI$24),Premissas!$B$118*Y24) -> 655558.59 | Z25: =MAX(SUMPRODUCT((B$5:BI$5>Z$5)*(B$5:BI$5<=Z$5+Premissas!$B$118)*B$24:BI$24),Premissas!$B$118*Z24) -> 657020.49 | AA25: =MAX(SUMPRODUCT((B$5:BI$5>AA$5)*(B$5:BI$5<=AA$5+Premissas!$B$118)*B$24:BI$24),Premissas!$B$118*AA24) -> 658347.48 | AB25: =MAX(SUMPRODUCT((B$5:BI$5>AB$5)*(B$5:BI$5<=AB$5+Premissas!$B$118)*B$24:BI$24),Premissas!$B$118*AB24) -> 659551.36 | AC25: =MAX(SUMPRODUCT((B$5:BI$5>AC$5)*(B$5:BI$5<=AC$5+Premissas!$B$118)*B$24:BI$24),Premissas!$B$118*AC24) -> 660644.71 | AD25: =MAX(SUMPRODUCT((B$5:BI$5>AD$5)*(B$5:BI$5<=AD$5+Premissas!$B$118)*B$24:BI$24),Premissas!$B$118*AD24) -> 661637.52 | AE25: =MAX(SUMPRODUCT((B$5:BI$5>AE$5)*(B$5:BI$5<=AE$5+Premissas!$B$118)*B$24:BI$24),Premissas!$B$118*AE24) -> 662539.47 | AF25: =MAX(SUMPRODUCT((B$5:BI$5>AF$5)*(B$5:BI$5<=AF$5+Premissas!$B$118)*B$24:BI$24),Premissas!$B$118*AF24) -> 663357.74 | AG25: =MAX(SUMPRODUCT((B$5:BI$5>AG$5)*(B$5:BI$5<=AG$5+Premissas!$B$118)*B$24:BI$24),Premissas!$B$118*AG24) -> 664100.38 | AH25: =MAX(SUMPRODUCT((B$5:BI$5>AH$5)*(B$5:BI$5<=AH$5+Premissas!$B$118)*B$24:BI$24),Premissas!$B$118*AH24) -> 664775.21 | AI25: =MAX(SUMPRODUCT((B$5:BI$5>AI$5)*(B$5:BI$5<=AI$5+Premissas!$B$118)*B$24:BI$24),Premissas!$B$118*AI24) -> 925595.8 | AJ25: =MAX(SUMPRODUCT((B$5:BI$5>AJ$5)*(B$5:BI$5<=AJ$5+Premissas!$B$118)*B$24:BI$24),Premissas!$B$118*AJ24) -> 1186785.1 | AK25: =MAX(SUMPRODUCT((B$5:BI$5>AK$5)*(B$5:BI$5<=AK$5+Premissas!$B$118)*B$24:BI$24),Premissas!$B$118*AK24) -> 1448309.7 | AL25: =MAX(SUMPRODUCT((B$5:BI$5>AL$5)*(B$5:BI$5<=AL$5+Premissas!$B$118)*B$24:BI$24),Premissas!$B$118*AL24) -> 1453770.3 | AM25: =MAX(SUMPRODUCT((B$5:BI$5>AM$5)*(B$5:BI$5<=AM$5+Premissas!$B$118)*B$24:BI$24),Premissas!$B$118*AM24) -> 1459223.6 | AN25: =MAX(SUMPRODUCT((B$5:BI$5>AN$5)*(B$5:BI$5<=AN$5+Premissas!$B$118)*B$24:BI$24),Premissas!$B$118*AN24) -> 1464672 | AO25: =MAX(SUMPRODUCT((B$5:BI$5>AO$5)*(B$5:BI$5<=AO$5+Premissas!$B$118)*B$24:BI$24),Premissas!$B$118*AO24) -> 1466278.9 | AP25: =MAX(SUMPRODUCT((B$5:BI$5>AP$5)*(B$5:BI$5<=AP$5+Premissas!$B$118)*B$24:BI$24),Premissas!$B$118*AP24) -> 1467744.5 | AQ25: =MAX(SUMPRODUCT((B$5:BI$5>AQ$5)*(B$5:BI$5<=AQ$5+Premissas!$B$118)*B$24:BI$24),Premissas!$B$118*AQ24) -> 1469080.2 | AR25: =MAX(SUMPRODUCT((B$5:BI$5>AR$5)*(B$5:BI$5<=AR$5+Premissas!$B$118)*B$24:BI$24),Premissas!$B$118*AR24) -> 1470297.2 | AS25: =MAX(SUMPRODUCT((B$5:BI$5>AS$5)*(B$5:BI$5<=AS$5+Premissas!$B$118)*B$24:BI$24),Premissas!$B$118*AS24) -> 1471406.1 | AT25: =MAX(SUMPRODUCT((B$5:BI$5>AT$5)*(B$5:BI$5<=AT$5+Premissas!$B$118)*B$24:BI$24),Premissas!$B$118*AT24) -> 1472417.3 | AU25: =MAX(SUMPRODUCT((B$5:BI$5>AU$5)*(B$5:BI$5<=AU$5+Premissas!$B$118)*B$24:BI$24),Premissas!$B$118*AU24) -> 1767344.7 | AV25: =MAX(SUMPRODUCT((B$5:BI$5>AV$5)*(B$5:BI$5<=AV$5+Premissas!$B$118)*B$24:BI$24),Premissas!$B$118*AV24) -> 2063006.6 | AW25: =MAX(SUMPRODUCT((B$5:BI$5>AW$5)*(B$5:BI$5<=AW$5+Premissas!$B$118)*B$24:BI$24),Premissas!$B$118*AW24) -> 2359340.7 | AX25: =MAX(SUMPRODUCT((B$5:BI$5>AX$5)*(B$5:BI$5<=AX$5+Premissas!$B$118)*B$24:BI$24),Premissas!$B$118*AX24) -> 2362286.3 | AY25: =MAX(SUMPRODUCT((B$5:BI$5>AY$5)*(B$5:BI$5<=AY$5+Premissas!$B$118)*B$24:BI$24),Premissas!$B$118*AY24) -> 2364981.4 | AZ25: =MAX(SUMPRODUCT((B$5:BI$5>AZ$5)*(B$5:BI$5<=AZ$5+Premissas!$B$118)*B$24:BI$24),Premissas!$B$118*AZ24) -> 2367447.8 | BA25: =MAX(SUMPRODUCT((B$5:BI$5>BA$5)*(B$5:BI$5<=BA$5+Premissas!$B$118)*B$24:BI$24),Premissas!$B$118*BA24) -> 2369704.4 | BB25: =MAX(SUMPRODUCT((B$5:BI$5>BB$5)*(B$5:BI$5<=BB$5+Premissas!$B$118)*B$24:BI$24),Premissas!$B$118*BB24) -> 2371769.3 | BC25: =MAX(SUMPRODUCT((B$5:BI$5>BC$5)*(B$5:BI$5<=BC$5+Premissas!$B$118)*B$24:BI$24),Premissas!$B$118*BC24) -> 2373659.1 | BD25: =MAX(SUMPRODUCT((B$5:BI$5>BD$5)*(B$5:BI$5<=BD$5+Premissas!$B$118)*B$24:BI$24),Premissas!$B$118*BD24) -> 2375388.7 | BE25: =MAX(SUMPRODUCT((B$5:BI$5>BE$5)*(B$5:BI$5<=BE$5+Premissas!$B$118)*B$24:BI$24),Premissas!$B$118*BE24) -> 2376971 | BF25: =MAX(SUMPRODUCT((B$5:BI$5>BF$5)*(B$5:BI$5<=BF$5+Premissas!$B$118)*B$24:BI$24),Premissas!$B$118*BF24) -> 2378418.8 | BG25: =MAX(SUMPRODUCT((B$5:BI$5>BG$5)*(B$5:BI$5<=BG$5+Premissas!$B$118)*B$24:BI$24),Premissas!$B$118*BG24) -> 2377016 | BH25: =MAX(SUMPRODUCT((B$5:BI$5>BH$5)*(B$5:BI$5<=BH$5+Premissas!$B$118)*B$24:BI$24),Premissas!$B$118*BH24) -> 2378459.4 | BI25: =MAX(SUMPRODUCT((B$5:BI$5>BI$5)*(B$5:BI$5<=BI$5+Premissas!$B$118)*B$24:BI$24),Premissas!$B$118*BI24) -> 2379780.9 | BK25: Custo fixo dos próximos meses. Nos últimos meses do horizonte não há 'próximos', então cai para o custo fixo do mês vezes o número de meses — senão a reserva sumiria justamente onde a empresa é maior.
A26: Caixa projetado no fim do mês | B26: =Cenários!B49 -> 0 | C26: =Cenários!C49 -> 0 | D26: =Cenários!D49 -> 0 | E26: =Cenários!E49 -> 8500 | F26: =Cenários!F49 -> 400 | G26: =Cenários!G49 -> -1700 | H26: =Cenários!H49 -> 1200 | I26: =Cenários!I49 -> 7972.18 | ... BI26: =Cenários!BI49 -> -11863525
A27: Caixa acima (ou abaixo) da reserva | B27: =B26-B25 -> -1500 | C27: =C26-C25 -> -3600 | D27: =D26-D25 -> -5700 | E27: =E26-E25 -> 2200 | F27: =F26-F25 -> -5900 | G27: =G26-G25 -> -8000 | H27: =H26-H25 -> -8397.12 | I27: =I26-I25 -> -5342.5 | ... BI27: =BI26-BI25 -> -14243306 | BK27: Negativo aqui já é sinal amarelo, mesmo com o caixa no positivo.
A28: FALTA CAPTAR neste mês | B28: =MAX(0,B25-B26) -> 1500 | C28: =MAX(0,C25-C26) -> 3600 | D28: =MAX(0,D25-D26) -> 5700 | E28: =MAX(0,E25-E26) -> 0 | F28: =MAX(0,F25-F26) -> 5900 | G28: =MAX(0,G25-G26) -> 8000 | H28: =MAX(0,H25-H26) -> 8397.12 | I28: =MAX(0,I25-I26) -> 5342.5 | ... BI28: =MAX(0,BI25-BI26) -> 14243306 | BK28: Quanto teria de estar em caixa neste mês e não está.
A29: FALTA CAPTAR — pior caso até aqui (cronograma de captação) | B29: =MAX($B28:B28) -> 1500 | C29: =MAX($B28:C28) -> 3600 | D29: =MAX($B28:D28) -> 5700 | E29: =MAX($B28:E28) -> 5700 | F29: =MAX($B28:F28) -> 5900 | G29: =MAX($B28:G28) -> 8000 | H29: =MAX($B28:H28) -> 8397.12 | I29: =MAX($B28:I28) -> 8397.12 | ... BI29: =MAX($B28:BI28) -> 14243306 | BK29: Só sobe. É a meta de captação que precisa estar fechada até este mês.
A30: Marcador — mês com caixa negativo | B30: =IF(B26<0,B$5,9999) -> 9999 | C30: =IF(C26<0,C$5,9999) -> 9999 | D30: =IF(D26<0,D$5,9999) -> 9999 | E30: =IF(E26<0,E$5,9999) -> 9999 | F30: =IF(F26<0,F$5,9999) -> 9999 | G30: =IF(G26<0,G$5,9999) -> 6 | H30: =IF(H26<0,H$5,9999) -> 9999 | I30: =IF(I26<0,I$5,9999) -> 9999 | ... BI30: =IF(BI26<0,BI$5,9999) -> 60 | BK30: Auxiliar: guarda o nº do mês quando o caixa fica negativo. O menor valor é o primeiro mês sem fundo.
A31: Meses de caixa restantes (runway) | B31: =IFERROR(IF(B24<=0,"",MAX(0,B26)/B24),"") | C31: =IFERROR(IF(C24<=0,"",MAX(0,C26)/C24),"") | D31: =IFERROR(IF(D24<=0,"",MAX(0,D26)/D24),"") | E31: =IFERROR(IF(E24<=0,"",MAX(0,E26)/E24),"") -> 5.6666667 | F31: =IFERROR(IF(F24<=0,"",MAX(0,F26)/F24),"") -> 0.19047619 | G31: =IFERROR(IF(G24<=0,"",MAX(0,G26)/G24),"") -> 0 | H31: =IFERROR(IF(H24<=0,"",MAX(0,H26)/H24),"") -> 0.57142857 | I31: =IFERROR(IF(I24<=0,"",MAX(0,I26)/I24),"") -> 3.7962762 | ... BI31: =IFERROR(IF(BI24<=0,"",MAX(0,BI26)/BI24),"") -> 0 | BK31: Caixa dividido pelo custo fixo do mês. Abaixo de 3 é zona de risco.
A33: CENÁRIO 2 — PROVÁVEL
A34: Fluxo de caixa livre do mês (FCL) | B34: =Cenários!B88 -> 0 | C34: =Cenários!C88 -> 0 | D34: =Cenários!D88 -> 0 | E34: =Cenários!E88 -> -1500 | F34: =Cenários!F88 -> -8100 | G34: =Cenários!G88 -> -2100 | H34: =Cenários!H88 -> -2100 | I34: =Cenários!I88 -> -11227.82 | ... BI34: =Cenários!BI88 -> 1213823.4 | BJ34: =SUM(B34:BI34) -> 17905908 | BK34: Não inclui aporte: aporte é financiamento, não geração de caixa.
A35: Buraco do mês (quanto a operação queimou) | B35: =IF(B34<0,-B34,0) -> 0 | C35: =IF(C34<0,-C34,0) -> 0 | D35: =IF(D34<0,-D34,0) -> 0 | E35: =IF(E34<0,-E34,0) -> 1500 | F35: =IF(F34<0,-F34,0) -> 8100 | G35: =IF(G34<0,-G34,0) -> 2100 | H35: =IF(H34<0,-H34,0) -> 2100 | I35: =IF(I34<0,-I34,0) -> 11227.82 | ... BI35: =IF(BI34<0,-BI34,0) -> 0 | BJ35: =SUM(B35:BI35) -> 350781.55
A36: Buraco acumulado | B36: =B35 -> 0 | C36: =B36+C35 -> 0 | D36: =C36+D35 -> 0 | E36: =D36+E35 -> 1500 | F36: =E36+F35 -> 9600 | G36: =F36+G35 -> 11700 | H36: =G36+H35 -> 13800 | I36: =H36+I35 -> 25027.82 | J36: =I36+J35 -> 37627.82 | ... BI36: =BH36+BI35 -> 350781.55 | BK36: Soma de todos os meses negativos, sem compensar com os positivos.
A37: FCL acumulado (os positivos já abatendo os negativos) | B37: =Cenários!B91 -> 0 | C37: =Cenários!C91 -> 0 | D37: =Cenários!D91 -> 0 | E37: =Cenários!E91 -> -1500 | F37: =Cenários!F91 -> -9600 | G37: =Cenários!G91 -> -11700 | H37: =Cenários!H91 -> -13800 | I37: =Cenários!I91 -> -25027.82 | ... BI37: =Cenários!BI91 -> 17905908 | BK37: O fundo do poço desta linha é o capital requerido pela operação.
A38: Custo fixo do mês (nuvem, pessoas, marketing recorrente, administrativas) | B38: =-(Cenários!B81+'Análise Fluxo'!B18+'Análise Fluxo'!B19+'Análise Fluxo'!B20+'Análise Fluxo'!B22+'Análise Fluxo'!B27) -> 0 | C38: =-(Cenários!C81+'Análise Fluxo'!C18+'Análise Fluxo'!C19+'Análise Fluxo'!C20+'Análise Fluxo'!C22+'Análise Fluxo'!C27) -> 0 | D38: =-(Cenários!D81+'Análise Fluxo'!D18+'Análise Fluxo'!D19+'Análise Fluxo'!D20+'Análise Fluxo'!D22+'Análise Fluxo'!D27) -> 0 | E38: =-(Cenários!E81+'Análise Fluxo'!E18+'Análise Fluxo'!E19+'Análise Fluxo'!E20+'Análise Fluxo'!E22+'Análise Fluxo'!E27) -> 1500 | F38: =-(Cenários!F81+'Análise Fluxo'!F18+'Análise Fluxo'!F19+'Análise Fluxo'!F20+'Análise Fluxo'!F22+'Análise Fluxo'!F27) -> 2100 | G38: =-(Cenários!G81+'Análise Fluxo'!G18+'Análise Fluxo'!G19+'Análise Fluxo'!G20+'Análise Fluxo'!G22+'Análise Fluxo'!G27) -> 2100 | H38: =-(Cenários!H81+'Análise Fluxo'!H18+'Análise Fluxo'!H19+'Análise Fluxo'!H20+'Análise Fluxo'!H22+'Análise Fluxo'!H27) -> 2100 | I38: =-(Cenários!I81+'Análise Fluxo'!I18+'Análise Fluxo'!I19+'Análise Fluxo'!I20+'Análise Fluxo'!I22+'Análise Fluxo'!I27) -> 2100 | ... BI38: =-(Cenários!BI81+'Análise Fluxo'!BI18+'Análise Fluxo'!BI19+'Análise Fluxo'!BI20+'Análise Fluxo'!BI22+'Análise Fluxo'!BI27) -> 867833.7 | BJ38: =SUM(B38:BI38) -> 20521157 | BK38: Sem aquisição paga, imposto, loja e meio de pagamento: esses variam com a operação, não com a existência dela.
A39: Reserva mínima desejada | B39: =MAX(SUMPRODUCT((B$5:BI$5>B$5)*(B$5:BI$5<=B$5+Premissas!$B$118)*B$38:BI$38),Premissas!$B$118*B38) -> 1500 | C39: =MAX(SUMPRODUCT((B$5:BI$5>C$5)*(B$5:BI$5<=C$5+Premissas!$B$118)*B$38:BI$38),Premissas!$B$118*C38) -> 3600 | D39: =MAX(SUMPRODUCT((B$5:BI$5>D$5)*(B$5:BI$5<=D$5+Premissas!$B$118)*B$38:BI$38),Premissas!$B$118*D38) -> 5700 | E39: =MAX(SUMPRODUCT((B$5:BI$5>E$5)*(B$5:BI$5<=E$5+Premissas!$B$118)*B$38:BI$38),Premissas!$B$118*E38) -> 6300 | F39: =MAX(SUMPRODUCT((B$5:BI$5>F$5)*(B$5:BI$5<=F$5+Premissas!$B$118)*B$38:BI$38),Premissas!$B$118*F38) -> 6300 | G39: =MAX(SUMPRODUCT((B$5:BI$5>G$5)*(B$5:BI$5<=G$5+Premissas!$B$118)*B$38:BI$38),Premissas!$B$118*G38) -> 6300 | H39: =MAX(SUMPRODUCT((B$5:BI$5>H$5)*(B$5:BI$5<=H$5+Premissas!$B$118)*B$38:BI$38),Premissas!$B$118*H38) -> 9885.48 | I39: =MAX(SUMPRODUCT((B$5:BI$5>I$5)*(B$5:BI$5<=I$5+Premissas!$B$118)*B$38:BI$38),Premissas!$B$118*I38) -> 14437.44 | J39: =MAX(SUMPRODUCT((B$5:BI$5>J$5)*(B$5:BI$5<=J$5+Premissas!$B$118)*B$38:BI$38),Premissas!$B$118*J38) -> 20291.837 | K39: =MAX(SUMPRODUCT((B$5:BI$5>K$5)*(B$5:BI$5<=K$5+Premissas!$B$118)*B$38:BI$38),Premissas!$B$118*K38) -> 85592.006 | L39: =MAX(SUMPRODUCT((B$5:BI$5>L$5)*(B$5:BI$5<=L$5+Premissas!$B$118)*B$38:BI$38),Premissas!$B$118*L38) -> 152532.77 | M39: =MAX(SUMPRODUCT((B$5:BI$5>M$5)*(B$5:BI$5<=M$5+Premissas!$B$118)*B$38:BI$38),Premissas!$B$118*M38) -> 221144.64 | N39: =MAX(SUMPRODUCT((B$5:BI$5>N$5)*(B$5:BI$5<=N$5+Premissas!$B$118)*B$38:BI$38),Premissas!$B$118*N38) -> 228423.84 | O39: =MAX(SUMPRODUCT((B$5:BI$5>O$5)*(B$5:BI$5<=O$5+Premissas!$B$118)*B$38:BI$38),Premissas!$B$118*O38) -> 234666.99 | P39: =MAX(SUMPRODUCT((B$5:BI$5>P$5)*(B$5:BI$5<=P$5+Premissas!$B$118)*B$38:BI$38),Premissas!$B$118*P38) -> 239388.79 | Q39: =MAX(SUMPRODUCT((B$5:BI$5>Q$5)*(B$5:BI$5<=Q$5+Premissas!$B$118)*B$38:BI$38),Premissas!$B$118*Q38) -> 243755.28 | R39: =MAX(SUMPRODUCT((B$5:BI$5>R$5)*(B$5:BI$5<=R$5+Premissas!$B$118)*B$38:BI$38),Premissas!$B$118*R38) -> 247793.56 | S39: =MAX(SUMPRODUCT((B$5:BI$5>S$5)*(B$5:BI$5<=S$5+Premissas!$B$118)*B$38:BI$38),Premissas!$B$118*S38) -> 251527.64 | T39: =MAX(SUMPRODUCT((B$5:BI$5>T$5)*(B$5:BI$5<=T$5+Premissas!$B$118)*B$38:BI$38),Premissas!$B$118*T38) -> 254981.09 | U39: =MAX(SUMPRODUCT((B$5:BI$5>U$5)*(B$5:BI$5<=U$5+Premissas!$B$118)*B$38:BI$38),Premissas!$B$118*U38) -> 258174.49 | V39: =MAX(SUMPRODUCT((B$5:BI$5>V$5)*(B$5:BI$5<=V$5+Premissas!$B$118)*B$38:BI$38),Premissas!$B$118*V38) -> 261128.04 | W39: =MAX(SUMPRODUCT((B$5:BI$5>W$5)*(B$5:BI$5<=W$5+Premissas!$B$118)*B$38:BI$38),Premissas!$B$118*W38) -> 411599.86 | X39: =MAX(SUMPRODUCT((B$5:BI$5>X$5)*(B$5:BI$5<=X$5+Premissas!$B$118)*B$38:BI$38),Premissas!$B$118*X38) -> 563279.28 | Y39: =MAX(SUMPRODUCT((B$5:BI$5>Y$5)*(B$5:BI$5<=Y$5+Premissas!$B$118)*B$38:BI$38),Premissas!$B$118*Y38) -> 716086.31 | Z39: =MAX(SUMPRODUCT((B$5:BI$5>Z$5)*(B$5:BI$5<=Z$5+Premissas!$B$118)*B$38:BI$38),Premissas!$B$118*Z38) -> 722203.99 | AA39: =MAX(SUMPRODUCT((B$5:BI$5>AA$5)*(B$5:BI$5<=AA$5+Premissas!$B$118)*B$38:BI$38),Premissas!$B$118*AA38) -> 727889.96 | AB39: =MAX(SUMPRODUCT((B$5:BI$5>AB$5)*(B$5:BI$5<=AB$5+Premissas!$B$118)*B$38:BI$38),Premissas!$B$118*AB38) -> 733173.73 | AC39: =MAX(SUMPRODUCT((B$5:BI$5>AC$5)*(B$5:BI$5<=AC$5+Premissas!$B$118)*B$38:BI$38),Premissas!$B$118*AC38) -> 738083.97 | AD39: =MAX(SUMPRODUCT((B$5:BI$5>AD$5)*(B$5:BI$5<=AD$5+Premissas!$B$118)*B$38:BI$38),Premissas!$B$118*AD38) -> 742646.49 | AE39: =MAX(SUMPRODUCT((B$5:BI$5>AE$5)*(B$5:BI$5<=AE$5+Premissas!$B$118)*B$38:BI$38),Premissas!$B$118*AE38) -> 746887.53 | AF39: =MAX(SUMPRODUCT((B$5:BI$5>AF$5)*(B$5:BI$5<=AF$5+Premissas!$B$118)*B$38:BI$38),Premissas!$B$118*AF38) -> 750829.45 | AG39: =MAX(SUMPRODUCT((B$5:BI$5>AG$5)*(B$5:BI$5<=AG$5+Premissas!$B$118)*B$38:BI$38),Premissas!$B$118*AG38) -> 754492.87 | AH39: =MAX(SUMPRODUCT((B$5:BI$5>AH$5)*(B$5:BI$5<=AH$5+Premissas!$B$118)*B$38:BI$38),Premissas!$B$118*AH38) -> 757895.71 | AI39: =MAX(SUMPRODUCT((B$5:BI$5>AI$5)*(B$5:BI$5<=AI$5+Premissas!$B$118)*B$38:BI$38),Premissas!$B$118*AI38) -> 1021257.7 | AJ39: =MAX(SUMPRODUCT((B$5:BI$5>AJ$5)*(B$5:BI$5<=AJ$5+Premissas!$B$118)*B$38:BI$38),Premissas!$B$118*AJ38) -> 1286274.5 | AK39: =MAX(SUMPRODUCT((B$5:BI$5>AK$5)*(B$5:BI$5<=AK$5+Premissas!$B$118)*B$38:BI$38),Premissas!$B$118*AK38) -> 1552841.5 | AL39: =MAX(SUMPRODUCT((B$5:BI$5>AL$5)*(B$5:BI$5<=AL$5+Premissas!$B$118)*B$38:BI$38),Premissas!$B$118*AL38) -> 1560660.2 | AM39: =MAX(SUMPRODUCT((B$5:BI$5>AM$5)*(B$5:BI$5<=AM$5+Premissas!$B$118)*B$38:BI$38),Premissas!$B$118*AM38) -> 1567959.1 | AN39: =MAX(SUMPRODUCT((B$5:BI$5>AN$5)*(B$5:BI$5<=AN$5+Premissas!$B$118)*B$38:BI$38),Premissas!$B$118*AN38) -> 1574773.3 | AO39: =MAX(SUMPRODUCT((B$5:BI$5>AO$5)*(B$5:BI$5<=AO$5+Premissas!$B$118)*B$38:BI$38),Premissas!$B$118*AO38) -> 1581134.2 | AP39: =MAX(SUMPRODUCT((B$5:BI$5>AP$5)*(B$5:BI$5<=AP$5+Premissas!$B$118)*B$38:BI$38),Premissas!$B$118*AP38) -> 1587072.6 | AQ39: =MAX(SUMPRODUCT((B$5:BI$5>AQ$5)*(B$5:BI$5<=AQ$5+Premissas!$B$118)*B$38:BI$38),Premissas!$B$118*AQ38) -> 1592616.5 | AR39: =MAX(SUMPRODUCT((B$5:BI$5>AR$5)*(B$5:BI$5<=AR$5+Premissas!$B$118)*B$38:BI$38),Premissas!$B$118*AR38) -> 1597792.4 | AS39: =MAX(SUMPRODUCT((B$5:BI$5>AS$5)*(B$5:BI$5<=AS$5+Premissas!$B$118)*B$38:BI$38),Premissas!$B$118*AS38) -> 1602624.2 | AT39: =MAX(SUMPRODUCT((B$5:BI$5>AT$5)*(B$5:BI$5<=AT$5+Premissas!$B$118)*B$38:BI$38),Premissas!$B$118*AT38) -> 1607135.4 | AU39: =MAX(SUMPRODUCT((B$5:BI$5>AU$5)*(B$5:BI$5<=AU$5+Premissas!$B$118)*B$38:BI$38),Premissas!$B$118*AU38) -> 1907194.4 | AV39: =MAX(SUMPRODUCT((B$5:BI$5>AV$5)*(B$5:BI$5<=AV$5+Premissas!$B$118)*B$38:BI$38),Premissas!$B$118*AV38) -> 2209874.6 | AW39: =MAX(SUMPRODUCT((B$5:BI$5>AW$5)*(B$5:BI$5<=AW$5+Premissas!$B$118)*B$38:BI$38),Premissas!$B$118*AW38) -> 2515017.8 | AX39: =MAX(SUMPRODUCT((B$5:BI$5>AX$5)*(B$5:BI$5<=AX$5+Premissas!$B$118)*B$38:BI$38),Premissas!$B$118*AX38) -> 2526627.3 | AY39: =MAX(SUMPRODUCT((B$5:BI$5>AY$5)*(B$5:BI$5<=AY$5+Premissas!$B$118)*B$38:BI$38),Premissas!$B$118*AY38) -> 2537511.7 | AZ39: =MAX(SUMPRODUCT((B$5:BI$5>AZ$5)*(B$5:BI$5<=AZ$5+Premissas!$B$118)*B$38:BI$38),Premissas!$B$118*AZ38) -> 2547716.2 | BA39: =MAX(SUMPRODUCT((B$5:BI$5>BA$5)*(B$5:BI$5<=BA$5+Premissas!$B$118)*B$38:BI$38),Premissas!$B$118*BA38) -> 2557284 | BB39: =MAX(SUMPRODUCT((B$5:BI$5>BB$5)*(B$5:BI$5<=BB$5+Premissas!$B$118)*B$38:BI$38),Premissas!$B$118*BB38) -> 2566253.7 | BC39: =MAX(SUMPRODUCT((B$5:BI$5>BC$5)*(B$5:BI$5<=BC$5+Premissas!$B$118)*B$38:BI$38),Premissas!$B$118*BC38) -> 2574663.4 | BD39: =MAX(SUMPRODUCT((B$5:BI$5>BD$5)*(B$5:BI$5<=BD$5+Premissas!$B$118)*B$38:BI$38),Premissas!$B$118*BD38) -> 2582547.2 | BE39: =MAX(SUMPRODUCT((B$5:BI$5>BE$5)*(B$5:BI$5<=BE$5+Premissas!$B$118)*B$38:BI$38),Premissas!$B$118*BE38) -> 2589938.9 | BF39: =MAX(SUMPRODUCT((B$5:BI$5>BF$5)*(B$5:BI$5<=BF$5+Premissas!$B$118)*B$38:BI$38),Premissas!$B$118*BF38) -> 2596868.6 | BG39: =MAX(SUMPRODUCT((B$5:BI$5>BG$5)*(B$5:BI$5<=BG$5+Premissas!$B$118)*B$38:BI$38),Premissas!$B$118*BG38) -> 2590091.8 | BH39: =MAX(SUMPRODUCT((B$5:BI$5>BH$5)*(B$5:BI$5<=BH$5+Premissas!$B$118)*B$38:BI$38),Premissas!$B$118*BH38) -> 2597013 | BI39: =MAX(SUMPRODUCT((B$5:BI$5>BI$5)*(B$5:BI$5<=BI$5+Premissas!$B$118)*B$38:BI$38),Premissas!$B$118*BI38) -> 2603501.1 | BK39: Custo fixo dos próximos meses. Nos últimos meses do horizonte não há 'próximos', então cai para o custo fixo do mês vezes o número de meses — senão a reserva sumiria justamente onde a empresa é maior.
A40: Caixa projetado no fim do mês | B40: =Cenários!B95 -> 0 | C40: =Cenários!C95 -> 0 | D40: =Cenários!D95 -> 0 | E40: =Cenários!E95 -> 8500 | F40: =Cenários!F95 -> 400 | G40: =Cenários!G95 -> -1700 | H40: =Cenários!H95 -> 1200 | I40: =Cenários!I95 -> 7972.18 | ... BI40: =Cenários!BI95 -> 18105908
A41: Caixa acima (ou abaixo) da reserva | B41: =B40-B39 -> -1500 | C41: =C40-C39 -> -3600 | D41: =D40-D39 -> -5700 | E41: =E40-E39 -> 2200 | F41: =F40-F39 -> -5900 | G41: =G40-G39 -> -8000 | H41: =H40-H39 -> -8685.48 | I41: =I40-I39 -> -6465.26 | ... BI41: =BI40-BI39 -> 15502406 | BK41: Negativo aqui já é sinal amarelo, mesmo com o caixa no positivo.
A42: FALTA CAPTAR neste mês | B42: =MAX(0,B39-B40) -> 1500 | C42: =MAX(0,C39-C40) -> 3600 | D42: =MAX(0,D39-D40) -> 5700 | E42: =MAX(0,E39-E40) -> 0 | F42: =MAX(0,F39-F40) -> 5900 | G42: =MAX(0,G39-G40) -> 8000 | H42: =MAX(0,H39-H40) -> 8685.48 | I42: =MAX(0,I39-I40) -> 6465.26 | ... BI42: =MAX(0,BI39-BI40) -> 0 | BK42: Quanto teria de estar em caixa neste mês e não está.
A43: FALTA CAPTAR — pior caso até aqui (cronograma de captação) | B43: =MAX($B42:B42) -> 1500 | C43: =MAX($B42:C42) -> 3600 | D43: =MAX($B42:D42) -> 5700 | E43: =MAX($B42:E42) -> 5700 | F43: =MAX($B42:F42) -> 5900 | G43: =MAX($B42:G42) -> 8000 | H43: =MAX($B42:H42) -> 8685.48 | I43: =MAX($B42:I42) -> 8685.48 | ... BI43: =MAX($B42:BI42) -> 423788.68 | BK43: Só sobe. É a meta de captação que precisa estar fechada até este mês.
A44: Marcador — mês com caixa negativo | B44: =IF(B40<0,B$5,9999) -> 9999 | C44: =IF(C40<0,C$5,9999) -> 9999 | D44: =IF(D40<0,D$5,9999) -> 9999 | E44: =IF(E40<0,E$5,9999) -> 9999 | F44: =IF(F40<0,F$5,9999) -> 9999 | G44: =IF(G40<0,G$5,9999) -> 6 | H44: =IF(H40<0,H$5,9999) -> 9999 | I44: =IF(I40<0,I$5,9999) -> 9999 | ... BI44: =IF(BI40<0,BI$5,9999) -> 9999 | BK44: Auxiliar: guarda o nº do mês quando o caixa fica negativo. O menor valor é o primeiro mês sem fundo.
A45: Meses de caixa restantes (runway) | B45: =IFERROR(IF(B38<=0,"",MAX(0,B40)/B38),"") | C45: =IFERROR(IF(C38<=0,"",MAX(0,C40)/C38),"") | D45: =IFERROR(IF(D38<=0,"",MAX(0,D40)/D38),"") | E45: =IFERROR(IF(E38<=0,"",MAX(0,E40)/E38),"") -> 5.6666667 | F45: =IFERROR(IF(F38<=0,"",MAX(0,F40)/F38),"") -> 0.19047619 | G45: =IFERROR(IF(G38<=0,"",MAX(0,G40)/G38),"") -> 0 | H45: =IFERROR(IF(H38<=0,"",MAX(0,H40)/H38),"") -> 0.57142857 | I45: =IFERROR(IF(I38<=0,"",MAX(0,I40)/I38),"") -> 3.7962762 | ... BI45: =IFERROR(IF(BI38<=0,"",MAX(0,BI40)/BI38),"") -> 20.863338 | BK45: Caixa dividido pelo custo fixo do mês. Abaixo de 3 é zona de risco.
A47: CENÁRIO 3 — AGRESSIVO
A48: Fluxo de caixa livre do mês (FCL) | B48: =Cenários!B134 -> 0 | C48: =Cenários!C134 -> 0 | D48: =Cenários!D134 -> 0 | E48: =Cenários!E134 -> -1500 | F48: =Cenários!F134 -> -8100 | G48: =Cenários!G134 -> -2100 | H48: =Cenários!H134 -> -2100 | I48: =Cenários!I134 -> -11227.82 | ... BI48: =Cenários!BI134 -> 5966412.8 | BJ48: =SUM(B48:BI48) -> 96823354 | BK48: Não inclui aporte: aporte é financiamento, não geração de caixa.
A49: Buraco do mês (quanto a operação queimou) | B49: =IF(B48<0,-B48,0) -> 0 | C49: =IF(C48<0,-C48,0) -> 0 | D49: =IF(D48<0,-D48,0) -> 0 | E49: =IF(E48<0,-E48,0) -> 1500 | F49: =IF(F48<0,-F48,0) -> 8100 | G49: =IF(G48<0,-G48,0) -> 2100 | H49: =IF(H48<0,-H48,0) -> 2100 | I49: =IF(I48<0,-I48,0) -> 11227.82 | ... BI49: =IF(BI48<0,-BI48,0) -> 0 | BJ49: =SUM(B49:BI49) -> 160419.32
A50: Buraco acumulado | B50: =B49 -> 0 | C50: =B50+C49 -> 0 | D50: =C50+D49 -> 0 | E50: =D50+E49 -> 1500 | F50: =E50+F49 -> 9600 | G50: =F50+G49 -> 11700 | H50: =G50+H49 -> 13800 | I50: =H50+I49 -> 25027.82 | J50: =I50+J49 -> 37627.82 | ... BI50: =BH50+BI49 -> 160419.32 | BK50: Soma de todos os meses negativos, sem compensar com os positivos.
A51: FCL acumulado (os positivos já abatendo os negativos) | B51: =Cenários!B137 -> 0 | C51: =Cenários!C137 -> 0 | D51: =Cenários!D137 -> 0 | E51: =Cenários!E137 -> -1500 | F51: =Cenários!F137 -> -9600 | G51: =Cenários!G137 -> -11700 | H51: =Cenários!H137 -> -13800 | I51: =Cenários!I137 -> -25027.82 | ... BI51: =Cenários!BI137 -> 96823354 | BK51: O fundo do poço desta linha é o capital requerido pela operação.
A52: Custo fixo do mês (nuvem, pessoas, marketing recorrente, administrativas) | B52: =-(Cenários!B127+'Análise Fluxo'!B18+'Análise Fluxo'!B19+'Análise Fluxo'!B20+'Análise Fluxo'!B22+'Análise Fluxo'!B27) -> 0 | C52: =-(Cenários!C127+'Análise Fluxo'!C18+'Análise Fluxo'!C19+'Análise Fluxo'!C20+'Análise Fluxo'!C22+'Análise Fluxo'!C27) -> 0 | D52: =-(Cenários!D127+'Análise Fluxo'!D18+'Análise Fluxo'!D19+'Análise Fluxo'!D20+'Análise Fluxo'!D22+'Análise Fluxo'!D27) -> 0 | E52: =-(Cenários!E127+'Análise Fluxo'!E18+'Análise Fluxo'!E19+'Análise Fluxo'!E20+'Análise Fluxo'!E22+'Análise Fluxo'!E27) -> 1500 | F52: =-(Cenários!F127+'Análise Fluxo'!F18+'Análise Fluxo'!F19+'Análise Fluxo'!F20+'Análise Fluxo'!F22+'Análise Fluxo'!F27) -> 2100 | G52: =-(Cenários!G127+'Análise Fluxo'!G18+'Análise Fluxo'!G19+'Análise Fluxo'!G20+'Análise Fluxo'!G22+'Análise Fluxo'!G27) -> 2100 | H52: =-(Cenários!H127+'Análise Fluxo'!H18+'Análise Fluxo'!H19+'Análise Fluxo'!H20+'Análise Fluxo'!H22+'Análise Fluxo'!H27) -> 2100 | I52: =-(Cenários!I127+'Análise Fluxo'!I18+'Análise Fluxo'!I19+'Análise Fluxo'!I20+'Análise Fluxo'!I22+'Análise Fluxo'!I27) -> 2100 | ... BI52: =-(Cenários!BI127+'Análise Fluxo'!BI18+'Análise Fluxo'!BI19+'Análise Fluxo'!BI20+'Análise Fluxo'!BI22+'Análise Fluxo'!BI27) -> 1062976 | BJ52: =SUM(B52:BI52) -> 24285475 | BK52: Sem aquisição paga, imposto, loja e meio de pagamento: esses variam com a operação, não com a existência dela.
A53: Reserva mínima desejada | B53: =MAX(SUMPRODUCT((B$5:BI$5>B$5)*(B$5:BI$5<=B$5+Premissas!$B$118)*B$52:BI$52),Premissas!$B$118*B52) -> 1500 | C53: =MAX(SUMPRODUCT((B$5:BI$5>C$5)*(B$5:BI$5<=C$5+Premissas!$B$118)*B$52:BI$52),Premissas!$B$118*C52) -> 3600 | D53: =MAX(SUMPRODUCT((B$5:BI$5>D$5)*(B$5:BI$5<=D$5+Premissas!$B$118)*B$52:BI$52),Premissas!$B$118*D52) -> 5700 | E53: =MAX(SUMPRODUCT((B$5:BI$5>E$5)*(B$5:BI$5<=E$5+Premissas!$B$118)*B$52:BI$52),Premissas!$B$118*E52) -> 6300 | F53: =MAX(SUMPRODUCT((B$5:BI$5>F$5)*(B$5:BI$5<=F$5+Premissas!$B$118)*B$52:BI$52),Premissas!$B$118*F52) -> 6300 | G53: =MAX(SUMPRODUCT((B$5:BI$5>G$5)*(B$5:BI$5<=G$5+Premissas!$B$118)*B$52:BI$52),Premissas!$B$118*G52) -> 6300 | H53: =MAX(SUMPRODUCT((B$5:BI$5>H$5)*(B$5:BI$5<=H$5+Premissas!$B$118)*B$52:BI$52),Premissas!$B$118*H52) -> 10244.88 | I53: =MAX(SUMPRODUCT((B$5:BI$5>I$5)*(B$5:BI$5<=I$5+Premissas!$B$118)*B$52:BI$52),Premissas!$B$118*I52) -> 15925.632 | J53: =MAX(SUMPRODUCT((B$5:BI$5>J$5)*(B$5:BI$5<=J$5+Premissas!$B$118)*B$52:BI$52),Premissas!$B$118*J52) -> 24062.552 | K53: =MAX(SUMPRODUCT((B$5:BI$5>K$5)*(B$5:BI$5<=K$5+Premissas!$B$118)*B$52:BI$52),Premissas!$B$118*K52) -> 93563.392 | L53: =MAX(SUMPRODUCT((B$5:BI$5>L$5)*(B$5:BI$5<=L$5+Premissas!$B$118)*B$52:BI$52),Premissas!$B$118*L52) -> 166817.16 | M53: =MAX(SUMPRODUCT((B$5:BI$5>M$5)*(B$5:BI$5<=M$5+Premissas!$B$118)*B$52:BI$52),Premissas!$B$118*M52) -> 244049.58 | N53: =MAX(SUMPRODUCT((B$5:BI$5>N$5)*(B$5:BI$5<=N$5+Premissas!$B$118)*B$52:BI$52),Premissas!$B$118*N52) -> 259750.55 | O53: =MAX(SUMPRODUCT((B$5:BI$5>O$5)*(B$5:BI$5<=O$5+Premissas!$B$118)*B$52:BI$52),Premissas!$B$118*O52) -> 273531.74 | P53: =MAX(SUMPRODUCT((B$5:BI$5>P$5)*(B$5:BI$5<=P$5+Premissas!$B$118)*B$52:BI$52),Premissas!$B$118*P52) -> 284251.36 | Q53: =MAX(SUMPRODUCT((B$5:BI$5>Q$5)*(B$5:BI$5<=Q$5+Premissas!$B$118)*B$52:BI$52),Premissas!$B$118*Q52) -> 298425.34 | R53: =MAX(SUMPRODUCT((B$5:BI$5>R$5)*(B$5:BI$5<=R$5+Premissas!$B$118)*B$52:BI$52),Premissas!$B$118*R52) -> 312384.12 | S53: =MAX(SUMPRODUCT((B$5:BI$5>S$5)*(B$5:BI$5<=S$5+Premissas!$B$118)*B$52:BI$52),Premissas!$B$118*S52) -> 326138.96 | T53: =MAX(SUMPRODUCT((B$5:BI$5>T$5)*(B$5:BI$5<=T$5+Premissas!$B$118)*B$52:BI$52),Premissas!$B$118*T52) -> 335657.52 | U53: =MAX(SUMPRODUCT((B$5:BI$5>U$5)*(B$5:BI$5<=U$5+Premissas!$B$118)*B$52:BI$52),Premissas!$B$118*U52) -> 344651.41 | V53: =MAX(SUMPRODUCT((B$5:BI$5>V$5)*(B$5:BI$5<=V$5+Premissas!$B$118)*B$52:BI$52),Premissas!$B$118*V52) -> 353149.23 | W53: =MAX(SUMPRODUCT((B$5:BI$5>W$5)*(B$5:BI$5<=W$5+Premissas!$B$118)*B$52:BI$52),Premissas!$B$118*W52) -> 505895.01 | X53: =MAX(SUMPRODUCT((B$5:BI$5>X$5)*(B$5:BI$5<=X$5+Premissas!$B$118)*B$52:BI$52),Premissas!$B$118*X52) -> 661268.1 | Y53: =MAX(SUMPRODUCT((B$5:BI$5>Y$5)*(B$5:BI$5<=Y$5+Premissas!$B$118)*B$52:BI$52),Premissas!$B$118*Y52) -> 819146.34 | Z53: =MAX(SUMPRODUCT((B$5:BI$5>Z$5)*(B$5:BI$5<=Z$5+Premissas!$B$118)*B$52:BI$52),Premissas!$B$118*Z52) -> 834697.51 | AA53: =MAX(SUMPRODUCT((B$5:BI$5>AA$5)*(B$5:BI$5<=AA$5+Premissas!$B$118)*B$52:BI$52),Premissas!$B$118*AA52) -> 849458.97 | AB53: =MAX(SUMPRODUCT((B$5:BI$5>AB$5)*(B$5:BI$5<=AB$5+Premissas!$B$118)*B$52:BI$52),Premissas!$B$118*AB52) -> 863472.67 | AC53: =MAX(SUMPRODUCT((B$5:BI$5>AC$5)*(B$5:BI$5<=AC$5+Premissas!$B$118)*B$52:BI$52),Premissas!$B$118*AC52) -> 876774.34 | AD53: =MAX(SUMPRODUCT((B$5:BI$5>AD$5)*(B$5:BI$5<=AD$5+Premissas!$B$118)*B$52:BI$52),Premissas!$B$118*AD52) -> 889400.47 | AE53: =MAX(SUMPRODUCT((B$5:BI$5>AE$5)*(B$5:BI$5<=AE$5+Premissas!$B$118)*B$52:BI$52),Premissas!$B$118*AE52) -> 901384.7 | AF53: =MAX(SUMPRODUCT((B$5:BI$5>AF$5)*(B$5:BI$5<=AF$5+Premissas!$B$118)*B$52:BI$52),Premissas!$B$118*AF52) -> 912760.32 | AG53: =MAX(SUMPRODUCT((B$5:BI$5>AG$5)*(B$5:BI$5<=AG$5+Premissas!$B$118)*B$52:BI$52),Premissas!$B$118*AG52) -> 923557.85 | AH53: =MAX(SUMPRODUCT((B$5:BI$5>AH$5)*(B$5:BI$5<=AH$5+Premissas!$B$118)*B$52:BI$52),Premissas!$B$118*AH52) -> 933807.47 | AI53: =MAX(SUMPRODUCT((B$5:BI$5>AI$5)*(B$5:BI$5<=AI$5+Premissas!$B$118)*B$52:BI$52),Premissas!$B$118*AI52) -> 1204439.8 | AJ53: =MAX(SUMPRODUCT((B$5:BI$5>AJ$5)*(B$5:BI$5<=AJ$5+Premissas!$B$118)*B$52:BI$52),Premissas!$B$118*AJ52) -> 1479391.4 | AK53: =MAX(SUMPRODUCT((B$5:BI$5>AK$5)*(B$5:BI$5<=AK$5+Premissas!$B$118)*B$52:BI$52),Premissas!$B$118*AK52) -> 1758473.4 | AL53: =MAX(SUMPRODUCT((B$5:BI$5>AL$5)*(B$5:BI$5<=AL$5+Premissas!$B$118)*B$52:BI$52),Premissas!$B$118*AL52) -> 1780603.3 | AM53: =MAX(SUMPRODUCT((B$5:BI$5>AM$5)*(B$5:BI$5<=AM$5+Premissas!$B$118)*B$52:BI$52),Premissas!$B$118*AM52) -> 1801698.8 | AN53: =MAX(SUMPRODUCT((B$5:BI$5>AN$5)*(B$5:BI$5<=AN$5+Premissas!$B$118)*B$52:BI$52),Premissas!$B$118*AN52) -> 1821808.7 | AO53: =MAX(SUMPRODUCT((B$5:BI$5>AO$5)*(B$5:BI$5<=AO$5+Premissas!$B$118)*B$52:BI$52),Premissas!$B$118*AO52) -> 1840980 | AP53: =MAX(SUMPRODUCT((B$5:BI$5>AP$5)*(B$5:BI$5<=AP$5+Premissas!$B$118)*B$52:BI$52),Premissas!$B$118*AP52) -> 1859255.4 | AQ53: =MAX(SUMPRODUCT((B$5:BI$5>AQ$5)*(B$5:BI$5<=AQ$5+Premissas!$B$118)*B$52:BI$52),Premissas!$B$118*AQ52) -> 1876676.9 | AR53: =MAX(SUMPRODUCT((B$5:BI$5>AR$5)*(B$5:BI$5<=AR$5+Premissas!$B$118)*B$52:BI$52),Premissas!$B$118*AR52) -> 1893283.1 | AS53: =MAX(SUMPRODUCT((B$5:BI$5>AS$5)*(B$5:BI$5<=AS$5+Premissas!$B$118)*B$52:BI$52),Premissas!$B$118*AS52) -> 1909114.3 | AT53: =MAX(SUMPRODUCT((B$5:BI$5>AT$5)*(B$5:BI$5<=AT$5+Premissas!$B$118)*B$52:BI$52),Premissas!$B$118*AT52) -> 1924206.2 | AU53: =MAX(SUMPRODUCT((B$5:BI$5>AU$5)*(B$5:BI$5<=AU$5+Premissas!$B$118)*B$52:BI$52),Premissas!$B$118*AU52) -> 2240548 | AV53: =MAX(SUMPRODUCT((B$5:BI$5>AV$5)*(B$5:BI$5<=AV$5+Premissas!$B$118)*B$52:BI$52),Premissas!$B$118*AV52) -> 2564220.6 | AW53: =MAX(SUMPRODUCT((B$5:BI$5>AW$5)*(B$5:BI$5<=AW$5+Premissas!$B$118)*B$52:BI$52),Premissas!$B$118*AW52) -> 2894927.1 | AX53: =MAX(SUMPRODUCT((B$5:BI$5>AX$5)*(B$5:BI$5<=AX$5+Premissas!$B$118)*B$52:BI$52),Premissas!$B$118*AX52) -> 2930429.1 | AY53: =MAX(SUMPRODUCT((B$5:BI$5>AY$5)*(B$5:BI$5<=AY$5+Premissas!$B$118)*B$52:BI$52),Premissas!$B$118*AY52) -> 2964405.5 | AZ53: =MAX(SUMPRODUCT((B$5:BI$5>AZ$5)*(B$5:BI$5<=AZ$5+Premissas!$B$118)*B$52:BI$52),Premissas!$B$118*AZ52) -> 2996921.4 | BA53: =MAX(SUMPRODUCT((B$5:BI$5>BA$5)*(B$5:BI$5<=BA$5+Premissas!$B$118)*B$52:BI$52),Premissas!$B$118*BA52) -> 3028039.3 | BB53: =MAX(SUMPRODUCT((B$5:BI$5>BB$5)*(B$5:BI$5<=BB$5+Premissas!$B$118)*B$52:BI$52),Premissas!$B$118*BB52) -> 3057819.4 | BC53: =MAX(SUMPRODUCT((B$5:BI$5>BC$5)*(B$5:BI$5<=BC$5+Premissas!$B$118)*B$52:BI$52),Premissas!$B$118*BC52) -> 3086319.2 | BD53: =MAX(SUMPRODUCT((B$5:BI$5>BD$5)*(B$5:BI$5<=BD$5+Premissas!$B$118)*B$52:BI$52),Premissas!$B$118*BD52) -> 3113595 | BE53: =MAX(SUMPRODUCT((B$5:BI$5>BE$5)*(B$5:BI$5<=BE$5+Premissas!$B$118)*B$52:BI$52),Premissas!$B$118*BE52) -> 3139697.8 | BF53: =MAX(SUMPRODUCT((B$5:BI$5>BF$5)*(B$5:BI$5<=BF$5+Premissas!$B$118)*B$52:BI$52),Premissas!$B$118*BF52) -> 3164678.8 | BG53: =MAX(SUMPRODUCT((B$5:BI$5>BG$5)*(B$5:BI$5<=BG$5+Premissas!$B$118)*B$52:BI$52),Premissas!$B$118*BG52) -> 3140072.5 | BH53: =MAX(SUMPRODUCT((B$5:BI$5>BH$5)*(B$5:BI$5<=BH$5+Premissas!$B$118)*B$52:BI$52),Premissas!$B$118*BH52) -> 3165036.1 | BI53: =MAX(SUMPRODUCT((B$5:BI$5>BI$5)*(B$5:BI$5<=BI$5+Premissas!$B$118)*B$52:BI$52),Premissas!$B$118*BI52) -> 3188927.9 | BK53: Custo fixo dos próximos meses. Nos últimos meses do horizonte não há 'próximos', então cai para o custo fixo do mês vezes o número de meses — senão a reserva sumiria justamente onde a empresa é maior.
A54: Caixa projetado no fim do mês | B54: =Cenários!B141 -> 0 | C54: =Cenários!C141 -> 0 | D54: =Cenários!D141 -> 0 | E54: =Cenários!E141 -> 8500 | F54: =Cenários!F141 -> 400 | G54: =Cenários!G141 -> -1700 | H54: =Cenários!H141 -> 1200 | I54: =Cenários!I141 -> 7972.18 | ... BI54: =Cenários!BI141 -> 97023354
A55: Caixa acima (ou abaixo) da reserva | B55: =B54-B53 -> -1500 | C55: =C54-C53 -> -3600 | D55: =D54-D53 -> -5700 | E55: =E54-E53 -> 2200 | F55: =F54-F53 -> -5900 | G55: =G54-G53 -> -8000 | H55: =H54-H53 -> -9044.88 | I55: =I54-I53 -> -7953.452 | ... BI55: =BI54-BI53 -> 93834426 | BK55: Negativo aqui já é sinal amarelo, mesmo com o caixa no positivo.
A56: FALTA CAPTAR neste mês | B56: =MAX(0,B53-B54) -> 1500 | C56: =MAX(0,C53-C54) -> 3600 | D56: =MAX(0,D53-D54) -> 5700 | E56: =MAX(0,E53-E54) -> 0 | F56: =MAX(0,F53-F54) -> 5900 | G56: =MAX(0,G53-G54) -> 8000 | H56: =MAX(0,H53-H54) -> 9044.88 | I56: =MAX(0,I53-I54) -> 7953.452 | ... BI56: =MAX(0,BI53-BI54) -> 0 | BK56: Quanto teria de estar em caixa neste mês e não está.
A57: FALTA CAPTAR — pior caso até aqui (cronograma de captação) | B57: =MAX($B56:B56) -> 1500 | C57: =MAX($B56:C56) -> 3600 | D57: =MAX($B56:D56) -> 5700 | E57: =MAX($B56:E56) -> 5700 | F57: =MAX($B56:F56) -> 5900 | G57: =MAX($B56:G56) -> 8000 | H57: =MAX($B56:H56) -> 9044.88 | I57: =MAX($B56:I56) -> 9044.88 | ... BI57: =MAX($B56:BI56) -> 253883.27 | BK57: Só sobe. É a meta de captação que precisa estar fechada até este mês.
A58: Marcador — mês com caixa negativo | B58: =IF(B54<0,B$5,9999) -> 9999 | C58: =IF(C54<0,C$5,9999) -> 9999 | D58: =IF(D54<0,D$5,9999) -> 9999 | E58: =IF(E54<0,E$5,9999) -> 9999 | F58: =IF(F54<0,F$5,9999) -> 9999 | G58: =IF(G54<0,G$5,9999) -> 6 | H58: =IF(H54<0,H$5,9999) -> 9999 | I58: =IF(I54<0,I$5,9999) -> 9999 | ... BI58: =IF(BI54<0,BI$5,9999) -> 9999 | BK58: Auxiliar: guarda o nº do mês quando o caixa fica negativo. O menor valor é o primeiro mês sem fundo.
A59: Meses de caixa restantes (runway) | B59: =IFERROR(IF(B52<=0,"",MAX(0,B54)/B52),"") | C59: =IFERROR(IF(C52<=0,"",MAX(0,C54)/C52),"") | D59: =IFERROR(IF(D52<=0,"",MAX(0,D54)/D52),"") | E59: =IFERROR(IF(E52<=0,"",MAX(0,E54)/E52),"") -> 5.6666667 | F59: =IFERROR(IF(F52<=0,"",MAX(0,F54)/F52),"") -> 0.19047619 | G59: =IFERROR(IF(G52<=0,"",MAX(0,G54)/G52),"") -> 0 | H59: =IFERROR(IF(H52<=0,"",MAX(0,H54)/H52),"") -> 0.57142857 | I59: =IFERROR(IF(I52<=0,"",MAX(0,I54)/I52),"") -> 3.7962762 | ... BI59: =IFERROR(IF(BI52<=0,"",MAX(0,BI54)/BI52),"") -> 91.275209 | BK59: Caixa dividido pelo custo fixo do mês. Abaixo de 3 é zona de risco.
A62: RESPOSTA POR CENÁRIO
A63: QUANTO A EMPRESA PRECISA | B63: CONSERVADOR | C63: PROVÁVEL | D63: AGRESSIVO
A64: Capital requerido pela operação (pico do FCL acumulado negativo) | B64: =-MIN(0,MIN($B$23:$BI$23)) -> 12063525 | C64: =-MIN(0,MIN($B$37:$BI$37)) -> 350781.55 | D64: =-MIN(0,MIN($B$51:$BI$51)) -> 160419.32 | F64: Quanto a operação consome antes de virar. Ignora a data em que o dinheiro chega.
A65: (+) Reserva mínima no mês mais apertado | B65: =INDEX($B$25:$BI$25,MATCH(MIN($B$26:$BI$26),$B$26:$BI$26,0)) -> 2379780.9 | C65: =INDEX($B$39:$BI$39,MATCH(MIN($B$40:$BI$40),$B$40:$BI$40,0)) -> 239388.79 | D65: =INDEX($B$53:$BI$53,MATCH(MIN($B$54:$BI$54),$B$54:$BI$54,0)) -> 24062.552
A66: (=) NECESSIDADE TOTAL DE CAPITAL | B66: =B64+B65 -> 14443306 | C66: =C64+C65 -> 590170.34 | D66: =D64+D65 -> 184481.87
A67: (−) Já realizado | B67: =-Aportes!$C$54 -> -33000 | C67: =-Aportes!$C$54 -> -33000 | D67: =-Aportes!$C$54 -> -33000
A68: (−) Compromisso dos fundadores a integralizar | B68: =-Aportes!$C$55 -> -47000 | C68: =-Aportes!$C$55 -> -47000 | D68: =-Aportes!$C$55 -> -47000
A69: (−) Previsto (negociação em curso) | B69: =-Aportes!$C$56 -> -120000 | C69: =-Aportes!$C$56 -> -120000 | D69: =-Aportes!$C$56 -> -120000 | F69: Entra como zero se o interruptor de aportes previstos estiver desligado em Premissas.
A70: (=) FALTA CAPTAR — ignorando as datas de entrada | B70: =MAX(0,B66+B67+B68+B69) -> 14243306 | C70: =MAX(0,C66+C67+C68+C69) -> 390170.34 | D70: =MAX(0,D66+D67+D68+D69) -> 0 | F70: Serve para a conversa de rodada: o tamanho do cheque, supondo o dinheiro disponível desde o primeiro mês.
A71: (=) FALTA CAPTAR — respeitando as datas de entrada | B71: =MAX($B$28:$BI$28) -> 14243306 | C71: =MAX($B$42:$BI$42) -> 423788.68 | D71: =MAX($B$56:$BI$56) -> 253883.27 | F71: Esta é a que manda: a pior lacuna de qualquer mês, com cada aporte entrando na data prevista e a reserva mínima respeitada.
A72: Mês em que essa lacuna aparece | B72: =CHOOSE(MOD(MATCH(MAX($B$28:$BI$28),$B$28:$BI$28,0)-1,12)+1,"jan","fev","mar","abr","mai","jun","jul","ago","set","out","nov","dez")&"/"&(2026+INT((MATCH(MAX($B$28:$BI$28),$B$28:$BI$28,0)-1)/12)) -> dez/2030 | C72: =CHOOSE(MOD(MATCH(MAX($B$42:$BI$42),$B$42:$BI$42,0)-1,12)+1,"jan","fev","mar","abr","mai","jun","jul","ago","set","out","nov","dez")&"/"&(2026+INT((MATCH(MAX($B$42:$BI$42),$B$42:$BI$42,0)-1)/12)) -> abr/2027 | D72: =CHOOSE(MOD(MATCH(MAX($B$56:$BI$56),$B$56:$BI$56,0)-1,12)+1,"jan","fev","mar","abr","mai","jun","jul","ago","set","out","nov","dez")&"/"&(2026+INT((MATCH(MAX($B$56:$BI$56),$B$56:$BI$56,0)-1)/12)) -> fev/2027
A73: Caixa mínimo projetado | B73: =MIN($B$26:$BI$26) -> -11863525 | C73: =MIN($B$40:$BI$40) -> -180781.55 | D73: =MIN($B$54:$BI$54) -> -4627.82 | F73: Negativo significa conta sem fundo naquele mês — não é um aviso, é a operação parando.
A74: Mês do caixa mínimo | B74: =CHOOSE(MOD(MATCH(MIN($B$26:$BI$26),$B$26:$BI$26,0)-1,12)+1,"jan","fev","mar","abr","mai","jun","jul","ago","set","out","nov","dez")&"/"&(2026+INT((MATCH(MIN($B$26:$BI$26),$B$26:$BI$26,0)-1)/12)) -> dez/2030 | C74: =CHOOSE(MOD(MATCH(MIN($B$40:$BI$40),$B$40:$BI$40,0)-1,12)+1,"jan","fev","mar","abr","mai","jun","jul","ago","set","out","nov","dez")&"/"&(2026+INT((MATCH(MIN($B$40:$BI$40),$B$40:$BI$40,0)-1)/12)) -> mar/2027 | D74: =CHOOSE(MOD(MATCH(MIN($B$54:$BI$54),$B$54:$BI$54,0)-1,12)+1,"jan","fev","mar","abr","mai","jun","jul","ago","set","out","nov","dez")&"/"&(2026+INT((MATCH(MIN($B$54:$BI$54),$B$54:$BI$54,0)-1)/12)) -> set/2026 | F74: Prazo real da captação: o dinheiro precisa estar na conta ANTES deste mês.
A75: Primeiro mês em que o caixa fica NEGATIVO | B75: =IF(MIN($B$30:$BI$30)=9999,"nunca",CHOOSE(MOD(MIN($B$30:$BI$30)-1,12)+1,"jan","fev","mar","abr","mai","jun","jul","ago","set","out","nov","dez")&"/"&(2026+INT((MIN($B$30:$BI$30)-1)/12))) -> jun/2026 | C75: =IF(MIN($B$44:$BI$44)=9999,"nunca",CHOOSE(MOD(MIN($B$44:$BI$44)-1,12)+1,"jan","fev","mar","abr","mai","jun","jul","ago","set","out","nov","dez")&"/"&(2026+INT((MIN($B$44:$BI$44)-1)/12))) -> jun/2026 | D75: =IF(MIN($B$58:$BI$58)=9999,"nunca",CHOOSE(MOD(MIN($B$58:$BI$58)-1,12)+1,"jan","fev","mar","abr","mai","jun","jul","ago","set","out","nov","dez")&"/"&(2026+INT((MIN($B$58:$BI$58)-1)/12))) -> jun/2026 | F75: O prazo que não se negocia. Antes deste mês o dinheiro tem de estar na conta — pode ser bem antes do mês do fundo do poço.
A77: QUANTO SAI DE CADA SÓCIO
A78: Fundadores no quadro | B78: =COUNTIF(Aportes!$A$64:$A$67,"?*") -> 4 | C78: =COUNTIF(Aportes!$A$64:$A$67,"?*") -> 4 | D78: =COUNTIF(Aportes!$A$64:$A$67,"?*") -> 4 | F78: Lido da tabela de compromisso dos fundadores, na aba Aportes.
A79: Compromisso total dos fundadores | B79: =SUM(Aportes!$B$64:$B$67) -> 80000 | C79: =SUM(Aportes!$B$64:$B$67) -> 80000 | D79: =SUM(Aportes!$B$64:$B$67) -> 80000 | F79: R$ 20 mil cada, conforme o acordo em curso.
A80: Já integralizado pelos fundadores | B80: =SUMIFS(Aportes!$C$6:$C$37,Aportes!$E$6:$E$37,"Fundador",Aportes!$D$6:$D$37,"Realizado") -> 33000 | C80: =SUMIFS(Aportes!$C$6:$C$37,Aportes!$E$6:$E$37,"Fundador",Aportes!$D$6:$D$37,"Realizado") -> 33000 | D80: =SUMIFS(Aportes!$C$6:$C$37,Aportes!$E$6:$E$37,"Fundador",Aportes!$D$6:$D$37,"Realizado") -> 33000
A81: Ainda por integralizar do compromisso atual | B81: =SUMIFS(Aportes!$C$6:$C$37,Aportes!$E$6:$E$37,"Fundador",Aportes!$D$6:$D$37,"Compromisso") -> 47000 | C81: =SUMIFS(Aportes!$C$6:$C$37,Aportes!$E$6:$E$37,"Fundador",Aportes!$D$6:$D$37,"Compromisso") -> 47000 | D81: =SUMIFS(Aportes!$C$6:$C$37,Aportes!$E$6:$E$37,"Fundador",Aportes!$D$6:$D$37,"Compromisso") -> 47000 | F81: Já está dentro do capital que o modelo considera. Não é captação nova.
A82: Se os fundadores cobrissem TODA a lacuna, quanto sai de cada um | B82: =IFERROR(B71/B78,0) -> 3560826.5 | C82: =IFERROR(C71/C78,0) -> 105947.17 | D82: =IFERROR(D71/D78,0) -> 63470.818 | F82: Além do compromisso que já existe. É a conta de quanto cada um teria de pôr para não precisar de dinheiro de fora e não diluir ninguém.
A83: Quantas vezes o que cada fundador já integralizou | B83: =IFERROR(B82/(B80/B78),0) -> 431.61533 | C83: =IFERROR(C82/(C80/C78),0) -> 12.842081 | D83: =IFERROR(D82/(D80/D78),0) -> 7.6934325 | F83: Régua de realismo: serve para saber se a conta cabe no bolso dos quatro ou se a captação externa é inevitável.
A84: Capital externo necessário, se os fundadores só honrarem o compromisso | B84: =B71 -> 14243306 | C84: =C71 -> 423788.68 | D84: =D71 -> 253883.27 | F84: O compromisso dos fundadores já está contado no caixa projetado, então a lacuna que sobra é exatamente o que precisa vir de fora.
A85: Diluição implícita desse capital externo | B85: =IFERROR(B84/(Aportes!$C$59+B84),0) -> 0.98615275 | C85: =IFERROR(C84/(Aportes!$C$59+C84),0) -> 0.6793786 | D85: =IFERROR(D84/(Aportes!$C$59+D84),0) -> 0.55935807 | F85: Participação que o dinheiro novo compraria se o preço fosse o capital aportado — é piso, não preço: valuation de verdade se negocia, não se calcula aqui. Com um valuation pré-dinheiro maior, a diluição cai na mesma proporção.
A88: Por que as duas respostas de 'falta captar' diferem: a primeira soma o buraco total e desconta todo o capital previsto, como se o dinheiro estivesse disponível desde janeiro. A segunda percorre os 60 meses e pergunta, em cada um, se o saldo cobre a reserva. Quando a segunda é maior, o problema não é o tamanho do capital — é a data.
A89: A reserva mínima é o que separa as duas. Zere a célula em Premissas e a necessidade cai para o mínimo matemático: o capital que apenas evita o saldo negativo, sem nenhuma folga. É um número para medir o piso, não para operar.

Sheet Preço Mínimo
A1: PREÇO MÍNIMO — DO CUSTO PARA O PREÇO
A2: =" Cenário ativo: "&Premissas!B7 -> Cenário ativo: PROVÁVEL
A4: Linha do tempo | B4: 46023 | C4: 46054 | D4: 46082 | E4: 46113 | F4: 46143 | G4: 46174 | H4: 46204 | I4: 46235 | J4: 46266 | K4: 46296 | L4: 46327 | M4: 46357 | N4: 46388 | O4: 46419 | P4: 46447 | Q4: 46478 | R4: 46508 | S4: 46539 | T4: 46569 | U4: 46600 | V4: 46631 | W4: 46661 | X4: 46692 | Y4: 46722 | Z4: 46753 | AA4: 46784 | AB4: 46813 | AC4: 46844 | AD4: 46874 | AE4: 46905 | AF4: 46935 | AG4: 46966 | AH4: 46997 | AI4: 47027 | AJ4: 47058 | AK4: 47088 | AL4: 47119 | AM4: 47150 | AN4: 47178 | AO4: 47209 | AP4: 47239 | AQ4: 47270 | AR4: 47300 | AS4: 47331 | AT4: 47362 | AU4: 47392 | AV4: 47423 | AW4: 47453 | AX4: 47484 | AY4: 47515 | AZ4: 47543 | BA4: 47574 | BB4: 47604 | BC4: 47635 | BD4: 47665 | BE4: 47696 | BF4: 47727 | BG4: 47757 | BH4: 47788 | BI4: 47818 | BJ4: TOTAL | BK4: % / Nota
A5: Mês nº | B5: 1 | C5: 2 | D5: 3 | E5: 4 | F5: 5 | G5: 6 | H5: 7 | I5: 8 | J5: 9 | K5: 10 | L5: 11 | M5: 12 | N5: 13 | O5: 14 | P5: 15 | Q5: 16 | R5: 17 | S5: 18 | T5: 19 | U5: 20 | V5: 21 | W5: 22 | X5: 23 | Y5: 24 | Z5: 25 | AA5: 26 | AB5: 27 | AC5: 28 | AD5: 29 | AE5: 30 | AF5: 31 | AG5: 32 | AH5: 33 | AI5: 34 | AJ5: 35 | AK5: 36 | AL5: 37 | AM5: 38 | AN5: 39 | AO5: 40 | AP5: 41 | AQ5: 42 | AR5: 43 | AS5: 44 | AT5: 45 | AU5: 46 | AV5: 47 | AW5: 48 | AX5: 49 | AY5: 50 | AZ5: 51 | BA5: 52 | BB5: 53 | BC5: 54 | BD5: 55 | BE5: 56 | BF5: 57 | BG5: 58 | BH5: 59 | BI5: 60
A6: Ano | B6: =YEAR(B4) -> 2026 | C6: =YEAR(C4) -> 2026 | D6: =YEAR(D4) -> 2026 | E6: =YEAR(E4) -> 2026 | F6: =YEAR(F4) -> 2026 | G6: =YEAR(G4) -> 2026 | H6: =YEAR(H4) -> 2026 | I6: =YEAR(I4) -> 2026 | ... BI6: =YEAR(BI4) -> 2030
A7: Índice do ano (auxiliar) | B7: =MATCH(B6,Premissas!$C$5:$G$5,0) -> 1 | C7: =MATCH(C6,Premissas!$C$5:$G$5,0) -> 1 | D7: =MATCH(D6,Premissas!$C$5:$G$5,0) -> 1 | E7: =MATCH(E6,Premissas!$C$5:$G$5,0) -> 1 | F7: =MATCH(F6,Premissas!$C$5:$G$5,0) -> 1 | G7: =MATCH(G6,Premissas!$C$5:$G$5,0) -> 1 | H7: =MATCH(H6,Premissas!$C$5:$G$5,0) -> 1 | I7: =MATCH(I6,Premissas!$C$5:$G$5,0) -> 1 | ... BI7: =MATCH(BI6,Premissas!$C$5:$G$5,0) -> 5
A8: 1. QUEM PAGA, E QUANTO PAGA HOJE
A9: Assinantes pagantes | B9: =CHOOSE(Premissas!$B$6,Cenários!B15,Cenários!B61,Cenários!B107) -> 0 | C9: =CHOOSE(Premissas!$B$6,Cenários!C15,Cenários!C61,Cenários!C107) -> 0 | D9: =CHOOSE(Premissas!$B$6,Cenários!D15,Cenários!D61,Cenários!D107) -> 0 | E9: =CHOOSE(Premissas!$B$6,Cenários!E15,Cenários!E61,Cenários!E107) -> 0 | F9: =CHOOSE(Premissas!$B$6,Cenários!F15,Cenários!F61,Cenários!F107) -> 0 | G9: =CHOOSE(Premissas!$B$6,Cenários!G15,Cenários!G61,Cenários!G107) -> 0 | H9: =CHOOSE(Premissas!$B$6,Cenários!H15,Cenários!H61,Cenários!H107) -> 0 | I9: =CHOOSE(Premissas!$B$6,Cenários!I15,Cenários!I61,Cenários!I107) -> 0 | ... BI9: =CHOOSE(Premissas!$B$6,Cenários!BI15,Cenários!BI61,Cenários!BI107) -> 75973
A10: Pagantes — Essencial | B10: =CHOOSE(Premissas!$B$6,Cenários!B16,Cenários!B62,Cenários!B108) -> 0 | C10: =CHOOSE(Premissas!$B$6,Cenários!C16,Cenários!C62,Cenários!C108) -> 0 | D10: =CHOOSE(Premissas!$B$6,Cenários!D16,Cenários!D62,Cenários!D108) -> 0 | E10: =CHOOSE(Premissas!$B$6,Cenários!E16,Cenários!E62,Cenários!E108) -> 0 | F10: =CHOOSE(Premissas!$B$6,Cenários!F16,Cenários!F62,Cenários!F108) -> 0 | G10: =CHOOSE(Premissas!$B$6,Cenários!G16,Cenários!G62,Cenários!G108) -> 0 | H10: =CHOOSE(Premissas!$B$6,Cenários!H16,Cenários!H62,Cenários!H108) -> 0 | I10: =CHOOSE(Premissas!$B$6,Cenários!I16,Cenários!I62,Cenários!I108) -> 0 | ... BI10: =CHOOSE(Premissas!$B$6,Cenários!BI16,Cenários!BI62,Cenários!BI108) -> 45584
A11: Pagantes — Premium | B11: =CHOOSE(Premissas!$B$6,Cenários!B17,Cenários!B63,Cenários!B109) -> 0 | C11: =CHOOSE(Premissas!$B$6,Cenários!C17,Cenários!C63,Cenários!C109) -> 0 | D11: =CHOOSE(Premissas!$B$6,Cenários!D17,Cenários!D63,Cenários!D109) -> 0 | E11: =CHOOSE(Premissas!$B$6,Cenários!E17,Cenários!E63,Cenários!E109) -> 0 | F11: =CHOOSE(Premissas!$B$6,Cenários!F17,Cenários!F63,Cenários!F109) -> 0 | G11: =CHOOSE(Premissas!$B$6,Cenários!G17,Cenários!G63,Cenários!G109) -> 0 | H11: =CHOOSE(Premissas!$B$6,Cenários!H17,Cenários!H63,Cenários!H109) -> 0 | I11: =CHOOSE(Premissas!$B$6,Cenários!I17,Cenários!I63,Cenários!I109) -> 0 | ... BI11: =CHOOSE(Premissas!$B$6,Cenários!BI17,Cenários!BI63,Cenários!BI109) -> 21272 | BK11: Zero até o mês de entrada do plano, definido em Premissas.
A12: Pagantes — Família | B12: =CHOOSE(Premissas!$B$6,Cenários!B18,Cenários!B64,Cenários!B110) -> 0 | C12: =CHOOSE(Premissas!$B$6,Cenários!C18,Cenários!C64,Cenários!C110) -> 0 | D12: =CHOOSE(Premissas!$B$6,Cenários!D18,Cenários!D64,Cenários!D110) -> 0 | E12: =CHOOSE(Premissas!$B$6,Cenários!E18,Cenários!E64,Cenários!E110) -> 0 | F12: =CHOOSE(Premissas!$B$6,Cenários!F18,Cenários!F64,Cenários!F110) -> 0 | G12: =CHOOSE(Premissas!$B$6,Cenários!G18,Cenários!G64,Cenários!G110) -> 0 | H12: =CHOOSE(Premissas!$B$6,Cenários!H18,Cenários!H64,Cenários!H110) -> 0 | I12: =CHOOSE(Premissas!$B$6,Cenários!I18,Cenários!I64,Cenários!I110) -> 0 | ... BI12: =CHOOSE(Premissas!$B$6,Cenários!BI18,Cenários!BI64,Cenários!BI110) -> 9117
A13: Preço do Essencial vigente no mês | B13: =Premissas!$B$29*(1+Premissas!$B$32)^(B$6-2026) -> 19.9 | C13: =Premissas!$B$29*(1+Premissas!$B$32)^(C$6-2026) -> 19.9 | D13: =Premissas!$B$29*(1+Premissas!$B$32)^(D$6-2026) -> 19.9 | E13: =Premissas!$B$29*(1+Premissas!$B$32)^(E$6-2026) -> 19.9 | F13: =Premissas!$B$29*(1+Premissas!$B$32)^(F$6-2026) -> 19.9 | G13: =Premissas!$B$29*(1+Premissas!$B$32)^(G$6-2026) -> 19.9 | H13: =Premissas!$B$29*(1+Premissas!$B$32)^(H$6-2026) -> 19.9 | I13: =Premissas!$B$29*(1+Premissas!$B$32)^(I$6-2026) -> 19.9 | ... BI13: =Premissas!$B$29*(1+Premissas!$B$32)^(BI$6-2026) -> 23.73112
A14: Premium ÷ Essencial | B14: =IFERROR(Premissas!$B$30/Premissas!$B$29,0) -> 2.0050251 | C14: =IFERROR(Premissas!$B$30/Premissas!$B$29,0) -> 2.0050251 | D14: =IFERROR(Premissas!$B$30/Premissas!$B$29,0) -> 2.0050251 | E14: =IFERROR(Premissas!$B$30/Premissas!$B$29,0) -> 2.0050251 | F14: =IFERROR(Premissas!$B$30/Premissas!$B$29,0) -> 2.0050251 | G14: =IFERROR(Premissas!$B$30/Premissas!$B$29,0) -> 2.0050251 | H14: =IFERROR(Premissas!$B$30/Premissas!$B$29,0) -> 2.0050251 | I14: =IFERROR(Premissas!$B$30/Premissas!$B$29,0) -> 2.0050251 | ... BI14: =IFERROR(Premissas!$B$30/Premissas!$B$29,0) -> 2.0050251 | BK14: A razão entre os preços. É o que permite traduzir todo mundo em Essencial.
A15: Família ÷ Essencial | B15: =IFERROR(Premissas!$B$31/Premissas!$B$29,0) -> 4.0150754 | C15: =IFERROR(Premissas!$B$31/Premissas!$B$29,0) -> 4.0150754 | D15: =IFERROR(Premissas!$B$31/Premissas!$B$29,0) -> 4.0150754 | E15: =IFERROR(Premissas!$B$31/Premissas!$B$29,0) -> 4.0150754 | F15: =IFERROR(Premissas!$B$31/Premissas!$B$29,0) -> 4.0150754 | G15: =IFERROR(Premissas!$B$31/Premissas!$B$29,0) -> 4.0150754 | H15: =IFERROR(Premissas!$B$31/Premissas!$B$29,0) -> 4.0150754 | I15: =IFERROR(Premissas!$B$31/Premissas!$B$29,0) -> 4.0150754 | ... BI15: =IFERROR(Premissas!$B$31/Premissas!$B$29,0) -> 4.0150754
A16: Assinantes equivalentes a Essencial (unidades equivalentes) | B16: =B10+B11*B14+B12*B15 -> 0 | C16: =C10+C11*C14+C12*C15 -> 0 | D16: =D10+D11*D14+D12*D15 -> 0 | E16: =E10+E11*E14+E12*E15 -> 0 | F16: =F10+F11*F14+F12*F15 -> 0 | G16: =G10+G11*G14+G12*G15 -> 0 | H16: =H10+H11*H14+H12*H15 -> 0 | I16: =I10+I11*I14+I12*I15 -> 0 | ... BI16: =BI10+BI11*BI14+BI12*BI15 -> 124840.34 | BK16: Receita de assinatura = preço do Essencial × esta linha. É a unidade da conta.
A17: Receita de assinaturas (conferência: deve bater com o motor) | B17: =B13*B16-CHOOSE(Premissas!$B$6,Cenários!B23,Cenários!B69,Cenários!B115) -> 0 | C17: =C13*C16-CHOOSE(Premissas!$B$6,Cenários!C23,Cenários!C69,Cenários!C115) -> 0 | D17: =D13*D16-CHOOSE(Premissas!$B$6,Cenários!D23,Cenários!D69,Cenários!D115) -> 0 | E17: =E13*E16-CHOOSE(Premissas!$B$6,Cenários!E23,Cenários!E69,Cenários!E115) -> 0 | F17: =F13*F16-CHOOSE(Premissas!$B$6,Cenários!F23,Cenários!F69,Cenários!F115) -> 0 | G17: =G13*G16-CHOOSE(Premissas!$B$6,Cenários!G23,Cenários!G69,Cenários!G115) -> 0 | H17: =H13*H16-CHOOSE(Premissas!$B$6,Cenários!H23,Cenários!H69,Cenários!H115) -> 0 | I17: =I13*I16-CHOOSE(Premissas!$B$6,Cenários!I23,Cenários!I69,Cenários!I115) -> 0 | ... BI17: =BI13*BI16-CHOOSE(Premissas!$B$6,Cenários!BI23,Cenários!BI69,Cenários!BI115) -> 0 | BJ17: =SUM(B17:BI17) -> 0 | BK17: Deve ser zero em todos os meses.
A18: ARPPU real do mês (receita de assinatura ÷ pagantes) | B18: =IFERROR(CHOOSE(Premissas!$B$6,Cenários!B23,Cenários!B69,Cenários!B115)/B9,0) -> 0 | C18: =IFERROR(CHOOSE(Premissas!$B$6,Cenários!C23,Cenários!C69,Cenários!C115)/C9,0) -> 0 | D18: =IFERROR(CHOOSE(Premissas!$B$6,Cenários!D23,Cenários!D69,Cenários!D115)/D9,0) -> 0 | E18: =IFERROR(CHOOSE(Premissas!$B$6,Cenários!E23,Cenários!E69,Cenários!E115)/E9,0) -> 0 | F18: =IFERROR(CHOOSE(Premissas!$B$6,Cenários!F23,Cenários!F69,Cenários!F115)/F9,0) -> 0 | G18: =IFERROR(CHOOSE(Premissas!$B$6,Cenários!G23,Cenários!G69,Cenários!G115)/G9,0) -> 0 | H18: =IFERROR(CHOOSE(Premissas!$B$6,Cenários!H23,Cenários!H69,Cenários!H115)/H9,0) -> 0 | I18: =IFERROR(CHOOSE(Premissas!$B$6,Cenários!I23,Cenários!I69,Cenários!I115)/I9,0) -> 0 | ... BI18: =IFERROR(CHOOSE(Premissas!$B$6,Cenários!BI23,Cenários!BI69,Cenários!BI115)/BI9,0) -> 38.995446 | BK18: Durante a fase só-Essencial, igual ao preço do Essencial.
A20: 2. QUANTO SOBRA DE CADA REAL COBRADO
A21: (−) Imposto sobre a receita (alíquota efetiva) | B21: =CHOOSE(Premissas!$B$6,Cenários!B30,Cenários!B76,Cenários!B122) -> 0.155 | C21: =CHOOSE(Premissas!$B$6,Cenários!C30,Cenários!C76,Cenários!C122) -> 0.155 | D21: =CHOOSE(Premissas!$B$6,Cenários!D30,Cenários!D76,Cenários!D122) -> 0.155 | E21: =CHOOSE(Premissas!$B$6,Cenários!E30,Cenários!E76,Cenários!E122) -> 0.155 | F21: =CHOOSE(Premissas!$B$6,Cenários!F30,Cenários!F76,Cenários!F122) -> 0.155 | G21: =CHOOSE(Premissas!$B$6,Cenários!G30,Cenários!G76,Cenários!G122) -> 0.155 | H21: =CHOOSE(Premissas!$B$6,Cenários!H30,Cenários!H76,Cenários!H122) -> 0.155 | I21: =CHOOSE(Premissas!$B$6,Cenários!I30,Cenários!I76,Cenários!I122) -> 0.155 | ... BI21: =CHOOSE(Premissas!$B$6,Cenários!BI30,Cenários!BI76,Cenários!BI122) -> 0.1633
A22: (−) Comissão das lojas, efetiva | B22: =Premissas!$B$73*INDEX(Premissas!$C$74:$G$74,B$7) -> 0.1275 | C22: =Premissas!$B$73*INDEX(Premissas!$C$74:$G$74,C$7) -> 0.1275 | D22: =Premissas!$B$73*INDEX(Premissas!$C$74:$G$74,D$7) -> 0.1275 | E22: =Premissas!$B$73*INDEX(Premissas!$C$74:$G$74,E$7) -> 0.1275 | F22: =Premissas!$B$73*INDEX(Premissas!$C$74:$G$74,F$7) -> 0.1275 | G22: =Premissas!$B$73*INDEX(Premissas!$C$74:$G$74,G$7) -> 0.1275 | H22: =Premissas!$B$73*INDEX(Premissas!$C$74:$G$74,H$7) -> 0.1275 | I22: =Premissas!$B$73*INDEX(Premissas!$C$74:$G$74,I$7) -> 0.1275 | ... BI22: =Premissas!$B$73*INDEX(Premissas!$C$74:$G$74,BI$7) -> 0.105 | BK22: 15% só sobre a parte cobrada dentro do app. Fora dela não há comissão.
A23: (−) Meio de pagamento, efetivo | B23: =Premissas!$B$75*(1-INDEX(Premissas!$C$74:$G$74,B$7)) -> 0.00675 | C23: =Premissas!$B$75*(1-INDEX(Premissas!$C$74:$G$74,C$7)) -> 0.00675 | D23: =Premissas!$B$75*(1-INDEX(Premissas!$C$74:$G$74,D$7)) -> 0.00675 | E23: =Premissas!$B$75*(1-INDEX(Premissas!$C$74:$G$74,E$7)) -> 0.00675 | F23: =Premissas!$B$75*(1-INDEX(Premissas!$C$74:$G$74,F$7)) -> 0.00675 | G23: =Premissas!$B$75*(1-INDEX(Premissas!$C$74:$G$74,G$7)) -> 0.00675 | H23: =Premissas!$B$75*(1-INDEX(Premissas!$C$74:$G$74,H$7)) -> 0.00675 | I23: =Premissas!$B$75*(1-INDEX(Premissas!$C$74:$G$74,I$7)) -> 0.00675 | ... BI23: =Premissas!$B$75*(1-INDEX(Premissas!$C$74:$G$74,BI$7)) -> 0.0135
A24: (=) Fica para a empresa, de cada real de assinatura | B24: =1-B21-B22-B23 -> 0.71075 | C24: =1-C21-C22-C23 -> 0.71075 | D24: =1-D21-D22-D23 -> 0.71075 | E24: =1-E21-E22-E23 -> 0.71075 | F24: =1-F21-F22-F23 -> 0.71075 | G24: =1-G21-G22-G23 -> 0.71075 | H24: =1-H21-H22-H23 -> 0.71075 | I24: =1-I21-I22-I23 -> 0.71075 | ... BI24: =1-BI21-BI22-BI23 -> 0.7182 | BK24: É o divisor de toda a aba: cobrar R$ 1 não é receber R$ 1.
A26: 3. O CUSTO A COBRIR
A27: Nuvem por assinante pagante | B27: =INDEX(Premissas!$C$104:$G$104,B$7) -> 1.5 | C27: =INDEX(Premissas!$C$104:$G$104,C$7) -> 1.5 | D27: =INDEX(Premissas!$C$104:$G$104,D$7) -> 1.5 | E27: =INDEX(Premissas!$C$104:$G$104,E$7) -> 1.5 | F27: =INDEX(Premissas!$C$104:$G$104,F$7) -> 1.5 | G27: =INDEX(Premissas!$C$104:$G$104,G$7) -> 1.5 | H27: =INDEX(Premissas!$C$104:$G$104,H$7) -> 1.5 | I27: =INDEX(Premissas!$C$104:$G$104,I$7) -> 1.5 | ... BI27: =INDEX(Premissas!$C$104:$G$104,BI$7) -> 0.9
A28: Suporte por assinante pagante | B28: =INDEX(Premissas!$C$106:$G$106,B$7) -> 0.35 | C28: =INDEX(Premissas!$C$106:$G$106,C$7) -> 0.35 | D28: =INDEX(Premissas!$C$106:$G$106,D$7) -> 0.35 | E28: =INDEX(Premissas!$C$106:$G$106,E$7) -> 0.35 | F28: =INDEX(Premissas!$C$106:$G$106,F$7) -> 0.35 | G28: =INDEX(Premissas!$C$106:$G$106,G$7) -> 0.35 | H28: =INDEX(Premissas!$C$106:$G$106,H$7) -> 0.35 | I28: =INDEX(Premissas!$C$106:$G$106,I$7) -> 0.35 | ... BI28: =INDEX(Premissas!$C$106:$G$106,BI$7) -> 0.25
A29: Nuvem dos usuários gratuitos, rateada por pagante | B29: =IFERROR((CHOOSE(Premissas!$B$6,Cenários!B13,Cenários!B59,Cenários!B105)-CHOOSE(Premissas!$B$6,Cenários!B15,Cenários!B61,Cenários!B107))*INDEX(Premissas!$C$105:$G$105,B$7)/B9,0) -> 0 | C29: =IFERROR((CHOOSE(Premissas!$B$6,Cenários!C13,Cenários!C59,Cenários!C105)-CHOOSE(Premissas!$B$6,Cenários!C15,Cenários!C61,Cenários!C107))*INDEX(Premissas!$C$105:$G$105,C$7)/C9,0) -> 0 | D29: =IFERROR((CHOOSE(Premissas!$B$6,Cenários!D13,Cenários!D59,Cenários!D105)-CHOOSE(Premissas!$B$6,Cenários!D15,Cenários!D61,Cenários!D107))*INDEX(Premissas!$C$105:$G$105,D$7)/D9,0) -> 0 | E29: =IFERROR((CHOOSE(Premissas!$B$6,Cenários!E13,Cenários!E59,Cenários!E105)-CHOOSE(Premissas!$B$6,Cenários!E15,Cenários!E61,Cenários!E107))*INDEX(Premissas!$C$105:$G$105,E$7)/E9,0) -> 0 | F29: =IFERROR((CHOOSE(Premissas!$B$6,Cenários!F13,Cenários!F59,Cenários!F105)-CHOOSE(Premissas!$B$6,Cenários!F15,Cenários!F61,Cenários!F107))*INDEX(Premissas!$C$105:$G$105,F$7)/F9,0) -> 0 | G29: =IFERROR((CHOOSE(Premissas!$B$6,Cenários!G13,Cenários!G59,Cenários!G105)-CHOOSE(Premissas!$B$6,Cenários!G15,Cenários!G61,Cenários!G107))*INDEX(Premissas!$C$105:$G$105,G$7)/G9,0) -> 0 | H29: =IFERROR((CHOOSE(Premissas!$B$6,Cenários!H13,Cenários!H59,Cenários!H105)-CHOOSE(Premissas!$B$6,Cenários!H15,Cenários!H61,Cenários!H107))*INDEX(Premissas!$C$105:$G$105,H$7)/H9,0) -> 0 | I29: =IFERROR((CHOOSE(Premissas!$B$6,Cenários!I13,Cenários!I59,Cenários!I105)-CHOOSE(Premissas!$B$6,Cenários!I15,Cenários!I61,Cenários!I107))*INDEX(Premissas!$C$105:$G$105,I$7)/I9,0) -> 0 | ... BI29: =IFERROR((CHOOSE(Premissas!$B$6,Cenários!BI13,Cenários!BI59,Cenários!BI105)-CHOOSE(Premissas!$B$6,Cenários!BI15,Cenários!BI61,Cenários!BI107))*INDEX(Premissas!$C$105:$G$105,BI$7)/BI9,0) -> 0.20550922 | BK29: O plano gratuito não paga, mas consome. Quem paga sustenta quem não paga.
A30: Painel de dados, rateado por pagante | B30: =IFERROR(CHOOSE(Premissas!$B$6,Cenários!B19,Cenários!B65,Cenários!B111)*Premissas!$B$80/B9,0) -> 0 | C30: =IFERROR(CHOOSE(Premissas!$B$6,Cenários!C19,Cenários!C65,Cenários!C111)*Premissas!$B$80/C9,0) -> 0 | D30: =IFERROR(CHOOSE(Premissas!$B$6,Cenários!D19,Cenários!D65,Cenários!D111)*Premissas!$B$80/D9,0) -> 0 | E30: =IFERROR(CHOOSE(Premissas!$B$6,Cenários!E19,Cenários!E65,Cenários!E111)*Premissas!$B$80/E9,0) -> 0 | F30: =IFERROR(CHOOSE(Premissas!$B$6,Cenários!F19,Cenários!F65,Cenários!F111)*Premissas!$B$80/F9,0) -> 0 | G30: =IFERROR(CHOOSE(Premissas!$B$6,Cenários!G19,Cenários!G65,Cenários!G111)*Premissas!$B$80/G9,0) -> 0 | H30: =IFERROR(CHOOSE(Premissas!$B$6,Cenários!H19,Cenários!H65,Cenários!H111)*Premissas!$B$80/H9,0) -> 0 | I30: =IFERROR(CHOOSE(Premissas!$B$6,Cenários!I19,Cenários!I65,Cenários!I111)*Premissas!$B$80/I9,0) -> 0 | ... BI30: =IFERROR(CHOOSE(Premissas!$B$6,Cenários!BI19,Cenários!BI65,Cenários!BI111)*Premissas!$B$80/BI9,0) -> 0.25726047
A31: (=) Custo variável por pagante | B31: =SUM(B27:B30) -> 1.85 | C31: =SUM(C27:C30) -> 1.85 | D31: =SUM(D27:D30) -> 1.85 | E31: =SUM(E27:E30) -> 1.85 | F31: =SUM(F27:F30) -> 1.85 | G31: =SUM(G27:G30) -> 1.85 | H31: =SUM(H27:H30) -> 1.85 | I31: =SUM(I27:I30) -> 1.85 | ... BI31: =SUM(BI27:BI30) -> 1.6127697
A32: CAC por assinante conquistado | B32: =IFERROR((1-INDEX(Premissas!$C$70:$G$70,B$7))*CHOOSE(Premissas!$B$6,IF('Ajuste Mensal'!B$16="",INDEX(Premissas!$C$67:$G$67,B$7),'Ajuste Mensal'!B$16),IF('Ajuste Mensal'!B$22="",INDEX(Premissas!$C$68:$G$68,B$7),'Ajuste Mensal'!B$22),IF('Ajuste Mensal'!B$28="",INDEX(Premissas!$C$69:$G$69,B$7),'Ajuste Mensal'!B$28))/CHOOSE(Premissas!$B$6,Cenários!B14,Cenários!B60,Cenários!B106),0) -> 0 | C32: =IFERROR((1-INDEX(Premissas!$C$70:$G$70,C$7))*CHOOSE(Premissas!$B$6,IF('Ajuste Mensal'!C$16="",INDEX(Premissas!$C$67:$G$67,C$7),'Ajuste Mensal'!C$16),IF('Ajuste Mensal'!C$22="",INDEX(Premissas!$C$68:$G$68,C$7),'Ajuste Mensal'!C$22),IF('Ajuste Mensal'!C$28="",INDEX(Premissas!$C$69:$G$69,C$7),'Ajuste Mensal'!C$28))/CHOOSE(Premissas!$B$6,Cenários!C14,Cenários!C60,Cenários!C106),0) -> 0 | D32: =IFERROR((1-INDEX(Premissas!$C$70:$G$70,D$7))*CHOOSE(Premissas!$B$6,IF('Ajuste Mensal'!D$16="",INDEX(Premissas!$C$67:$G$67,D$7),'Ajuste Mensal'!D$16),IF('Ajuste Mensal'!D$22="",INDEX(Premissas!$C$68:$G$68,D$7),'Ajuste Mensal'!D$22),IF('Ajuste Mensal'!D$28="",INDEX(Premissas!$C$69:$G$69,D$7),'Ajuste Mensal'!D$28))/CHOOSE(Premissas!$B$6,Cenários!D14,Cenários!D60,Cenários!D106),0) -> 0 | E32: =IFERROR((1-INDEX(Premissas!$C$70:$G$70,E$7))*CHOOSE(Premissas!$B$6,IF('Ajuste Mensal'!E$16="",INDEX(Premissas!$C$67:$G$67,E$7),'Ajuste Mensal'!E$16),IF('Ajuste Mensal'!E$22="",INDEX(Premissas!$C$68:$G$68,E$7),'Ajuste Mensal'!E$22),IF('Ajuste Mensal'!E$28="",INDEX(Premissas!$C$69:$G$69,E$7),'Ajuste Mensal'!E$28))/CHOOSE(Premissas!$B$6,Cenários!E14,Cenários!E60,Cenários!E106),0) -> 0 | F32: =IFERROR((1-INDEX(Premissas!$C$70:$G$70,F$7))*CHOOSE(Premissas!$B$6,IF('Ajuste Mensal'!F$16="",INDEX(Premissas!$C$67:$G$67,F$7),'Ajuste Mensal'!F$16),IF('Ajuste Mensal'!F$22="",INDEX(Premissas!$C$68:$G$68,F$7),'Ajuste Mensal'!F$22),IF('Ajuste Mensal'!F$28="",INDEX(Premissas!$C$69:$G$69,F$7),'Ajuste Mensal'!F$28))/CHOOSE(Premissas!$B$6,Cenários!F14,Cenários!F60,Cenários!F106),0) -> 0 | G32: =IFERROR((1-INDEX(Premissas!$C$70:$G$70,G$7))*CHOOSE(Premissas!$B$6,IF('Ajuste Mensal'!G$16="",INDEX(Premissas!$C$67:$G$67,G$7),'Ajuste Mensal'!G$16),IF('Ajuste Mensal'!G$22="",INDEX(Premissas!$C$68:$G$68,G$7),'Ajuste Mensal'!G$22),IF('Ajuste Mensal'!G$28="",INDEX(Premissas!$C$69:$G$69,G$7),'Ajuste Mensal'!G$28))/CHOOSE(Premissas!$B$6,Cenários!G14,Cenários!G60,Cenários!G106),0) -> 0 | H32: =IFERROR((1-INDEX(Premissas!$C$70:$G$70,H$7))*CHOOSE(Premissas!$B$6,IF('Ajuste Mensal'!H$16="",INDEX(Premissas!$C$67:$G$67,H$7),'Ajuste Mensal'!H$16),IF('Ajuste Mensal'!H$22="",INDEX(Premissas!$C$68:$G$68,H$7),'Ajuste Mensal'!H$22),IF('Ajuste Mensal'!H$28="",INDEX(Premissas!$C$69:$G$69,H$7),'Ajuste Mensal'!H$28))/CHOOSE(Premissas!$B$6,Cenários!H14,Cenários!H60,Cenários!H106),0) -> 0 | I32: =IFERROR((1-INDEX(Premissas!$C$70:$G$70,I$7))*CHOOSE(Premissas!$B$6,IF('Ajuste Mensal'!I$16="",INDEX(Premissas!$C$67:$G$67,I$7),'Ajuste Mensal'!I$16),IF('Ajuste Mensal'!I$22="",INDEX(Premissas!$C$68:$G$68,I$7),'Ajuste Mensal'!I$22),IF('Ajuste Mensal'!I$28="",INDEX(Premissas!$C$69:$G$69,I$7),'Ajuste Mensal'!I$28))/CHOOSE(Premissas!$B$6,Cenários!I14,Cenários!I60,Cenários!I106),0) -> 0 | ... BI32: =IFERROR((1-INDEX(Premissas!$C$70:$G$70,BI$7))*CHOOSE(Premissas!$B$6,IF('Ajuste Mensal'!BI$16="",INDEX(Premissas!$C$67:$G$67,BI$7),'Ajuste Mensal'!BI$16),IF('Ajuste Mensal'!BI$22="",INDEX(Premissas!$C$68:$G$68,BI$7),'Ajuste Mensal'!BI$22),IF('Ajuste Mensal'!BI$28="",INDEX(Premissas!$C$69:$G$69,BI$7),'Ajuste Mensal'!BI$28))/CHOOSE(Premissas!$B$6,Cenários!BI14,Cenários!BI60,Cenários!BI106),0) -> 38.567154 | BK32: CAC por usuário captado, dividido pela conversão: o custo de conquistar um PAGANTE.
A33: CAC diluído por mês de vida do assinante | B33: =B32*CHOOSE(Premissas!$B$6,IF('Ajuste Mensal'!B$14="",INDEX(Premissas!$C$59:$G$59,B$7),'Ajuste Mensal'!B$14),IF('Ajuste Mensal'!B$20="",INDEX(Premissas!$C$60:$G$60,B$7),'Ajuste Mensal'!B$20),IF('Ajuste Mensal'!B$26="",INDEX(Premissas!$C$61:$G$61,B$7),'Ajuste Mensal'!B$26)) -> 0 | C33: =C32*CHOOSE(Premissas!$B$6,IF('Ajuste Mensal'!C$14="",INDEX(Premissas!$C$59:$G$59,C$7),'Ajuste Mensal'!C$14),IF('Ajuste Mensal'!C$20="",INDEX(Premissas!$C$60:$G$60,C$7),'Ajuste Mensal'!C$20),IF('Ajuste Mensal'!C$26="",INDEX(Premissas!$C$61:$G$61,C$7),'Ajuste Mensal'!C$26)) -> 0 | D33: =D32*CHOOSE(Premissas!$B$6,IF('Ajuste Mensal'!D$14="",INDEX(Premissas!$C$59:$G$59,D$7),'Ajuste Mensal'!D$14),IF('Ajuste Mensal'!D$20="",INDEX(Premissas!$C$60:$G$60,D$7),'Ajuste Mensal'!D$20),IF('Ajuste Mensal'!D$26="",INDEX(Premissas!$C$61:$G$61,D$7),'Ajuste Mensal'!D$26)) -> 0 | E33: =E32*CHOOSE(Premissas!$B$6,IF('Ajuste Mensal'!E$14="",INDEX(Premissas!$C$59:$G$59,E$7),'Ajuste Mensal'!E$14),IF('Ajuste Mensal'!E$20="",INDEX(Premissas!$C$60:$G$60,E$7),'Ajuste Mensal'!E$20),IF('Ajuste Mensal'!E$26="",INDEX(Premissas!$C$61:$G$61,E$7),'Ajuste Mensal'!E$26)) -> 0 | F33: =F32*CHOOSE(Premissas!$B$6,IF('Ajuste Mensal'!F$14="",INDEX(Premissas!$C$59:$G$59,F$7),'Ajuste Mensal'!F$14),IF('Ajuste Mensal'!F$20="",INDEX(Premissas!$C$60:$G$60,F$7),'Ajuste Mensal'!F$20),IF('Ajuste Mensal'!F$26="",INDEX(Premissas!$C$61:$G$61,F$7),'Ajuste Mensal'!F$26)) -> 0 | G33: =G32*CHOOSE(Premissas!$B$6,IF('Ajuste Mensal'!G$14="",INDEX(Premissas!$C$59:$G$59,G$7),'Ajuste Mensal'!G$14),IF('Ajuste Mensal'!G$20="",INDEX(Premissas!$C$60:$G$60,G$7),'Ajuste Mensal'!G$20),IF('Ajuste Mensal'!G$26="",INDEX(Premissas!$C$61:$G$61,G$7),'Ajuste Mensal'!G$26)) -> 0 | H33: =H32*CHOOSE(Premissas!$B$6,IF('Ajuste Mensal'!H$14="",INDEX(Premissas!$C$59:$G$59,H$7),'Ajuste Mensal'!H$14),IF('Ajuste Mensal'!H$20="",INDEX(Premissas!$C$60:$G$60,H$7),'Ajuste Mensal'!H$20),IF('Ajuste Mensal'!H$26="",INDEX(Premissas!$C$61:$G$61,H$7),'Ajuste Mensal'!H$26)) -> 0 | I33: =I32*CHOOSE(Premissas!$B$6,IF('Ajuste Mensal'!I$14="",INDEX(Premissas!$C$59:$G$59,I$7),'Ajuste Mensal'!I$14),IF('Ajuste Mensal'!I$20="",INDEX(Premissas!$C$60:$G$60,I$7),'Ajuste Mensal'!I$20),IF('Ajuste Mensal'!I$26="",INDEX(Premissas!$C$61:$G$61,I$7),'Ajuste Mensal'!I$26)) -> 0 | ... BI33: =BI32*CHOOSE(Premissas!$B$6,IF('Ajuste Mensal'!BI$14="",INDEX(Premissas!$C$59:$G$59,BI$7),'Ajuste Mensal'!BI$14),IF('Ajuste Mensal'!BI$20="",INDEX(Premissas!$C$60:$G$60,BI$7),'Ajuste Mensal'!BI$20),IF('Ajuste Mensal'!BI$26="",INDEX(Premissas!$C$61:$G$61,BI$7),'Ajuste Mensal'!BI$26)) -> 2.4089012 | BK33: Vida esperada = 1 ÷ churn. Multiplicar por churn é diluir o CAC nessa vida.
A35: Custo operacional total do mês | B35: =-('Análise Fluxo'!B16+'Análise Fluxo'!B17+'Análise Fluxo'!B18+'Análise Fluxo'!B19+'Análise Fluxo'!B20+'Análise Fluxo'!B21+'Análise Fluxo'!B22+'Análise Fluxo'!B23+'Análise Fluxo'!B27) -> 0 | C35: =-('Análise Fluxo'!C16+'Análise Fluxo'!C17+'Análise Fluxo'!C18+'Análise Fluxo'!C19+'Análise Fluxo'!C20+'Análise Fluxo'!C21+'Análise Fluxo'!C22+'Análise Fluxo'!C23+'Análise Fluxo'!C27) -> 0 | D35: =-('Análise Fluxo'!D16+'Análise Fluxo'!D17+'Análise Fluxo'!D18+'Análise Fluxo'!D19+'Análise Fluxo'!D20+'Análise Fluxo'!D21+'Análise Fluxo'!D22+'Análise Fluxo'!D23+'Análise Fluxo'!D27) -> 0 | E35: =-('Análise Fluxo'!E16+'Análise Fluxo'!E17+'Análise Fluxo'!E18+'Análise Fluxo'!E19+'Análise Fluxo'!E20+'Análise Fluxo'!E21+'Análise Fluxo'!E22+'Análise Fluxo'!E23+'Análise Fluxo'!E27) -> 1500 | F35: =-('Análise Fluxo'!F16+'Análise Fluxo'!F17+'Análise Fluxo'!F18+'Análise Fluxo'!F19+'Análise Fluxo'!F20+'Análise Fluxo'!F21+'Análise Fluxo'!F22+'Análise Fluxo'!F23+'Análise Fluxo'!F27) -> 2100 | G35: =-('Análise Fluxo'!G16+'Análise Fluxo'!G17+'Análise Fluxo'!G18+'Análise Fluxo'!G19+'Análise Fluxo'!G20+'Análise Fluxo'!G21+'Análise Fluxo'!G22+'Análise Fluxo'!G23+'Análise Fluxo'!G27) -> 2100 | H35: =-('Análise Fluxo'!H16+'Análise Fluxo'!H17+'Análise Fluxo'!H18+'Análise Fluxo'!H19+'Análise Fluxo'!H20+'Análise Fluxo'!H21+'Análise Fluxo'!H22+'Análise Fluxo'!H23+'Análise Fluxo'!H27) -> 2100 | I35: =-('Análise Fluxo'!I16+'Análise Fluxo'!I17+'Análise Fluxo'!I18+'Análise Fluxo'!I19+'Análise Fluxo'!I20+'Análise Fluxo'!I21+'Análise Fluxo'!I22+'Análise Fluxo'!I23+'Análise Fluxo'!I27) -> 2100 | ... BI35: =-('Análise Fluxo'!BI16+'Análise Fluxo'!BI17+'Análise Fluxo'!BI18+'Análise Fluxo'!BI19+'Análise Fluxo'!BI20+'Análise Fluxo'!BI21+'Análise Fluxo'!BI22+'Análise Fluxo'!BI23+'Análise Fluxo'!BI27) -> 1127222.4 | BJ35: =SUM(B35:BI35) -> 27376909 | BK35: Nuvem, suporte, pessoas, marketing e administrativas. Sem imposto, loja e meio de pagamento: esses já estão descontados no fator acima.
A36: Outras receitas, líquidas (marketplace e B2B) | B36: =(CHOOSE(Premissas!$B$6,Cenários!B24,Cenários!B70,Cenários!B116))*(1-B21-Premissas!$B$75)+(CHOOSE(Premissas!$B$6,Cenários!B25,Cenários!B71,Cenários!B117)+CHOOSE(Premissas!$B$6,Cenários!B26,Cenários!B72,Cenários!B118)+CHOOSE(Premissas!$B$6,Cenários!B27,Cenários!B73,Cenários!B119))*(1-B21) -> 0 | C36: =(CHOOSE(Premissas!$B$6,Cenários!C24,Cenários!C70,Cenários!C116))*(1-C21-Premissas!$B$75)+(CHOOSE(Premissas!$B$6,Cenários!C25,Cenários!C71,Cenários!C117)+CHOOSE(Premissas!$B$6,Cenários!C26,Cenários!C72,Cenários!C118)+CHOOSE(Premissas!$B$6,Cenários!C27,Cenários!C73,Cenários!C119))*(1-C21) -> 0 | D36: =(CHOOSE(Premissas!$B$6,Cenários!D24,Cenários!D70,Cenários!D116))*(1-D21-Premissas!$B$75)+(CHOOSE(Premissas!$B$6,Cenários!D25,Cenários!D71,Cenários!D117)+CHOOSE(Premissas!$B$6,Cenários!D26,Cenários!D72,Cenários!D118)+CHOOSE(Premissas!$B$6,Cenários!D27,Cenários!D73,Cenários!D119))*(1-D21) -> 0 | E36: =(CHOOSE(Premissas!$B$6,Cenários!E24,Cenários!E70,Cenários!E116))*(1-E21-Premissas!$B$75)+(CHOOSE(Premissas!$B$6,Cenários!E25,Cenários!E71,Cenários!E117)+CHOOSE(Premissas!$B$6,Cenários!E26,Cenários!E72,Cenários!E118)+CHOOSE(Premissas!$B$6,Cenários!E27,Cenários!E73,Cenários!E119))*(1-E21) -> 0 | F36: =(CHOOSE(Premissas!$B$6,Cenários!F24,Cenários!F70,Cenários!F116))*(1-F21-Premissas!$B$75)+(CHOOSE(Premissas!$B$6,Cenários!F25,Cenários!F71,Cenários!F117)+CHOOSE(Premissas!$B$6,Cenários!F26,Cenários!F72,Cenários!F118)+CHOOSE(Premissas!$B$6,Cenários!F27,Cenários!F73,Cenários!F119))*(1-F21) -> 0 | G36: =(CHOOSE(Premissas!$B$6,Cenários!G24,Cenários!G70,Cenários!G116))*(1-G21-Premissas!$B$75)+(CHOOSE(Premissas!$B$6,Cenários!G25,Cenários!G71,Cenários!G117)+CHOOSE(Premissas!$B$6,Cenários!G26,Cenários!G72,Cenários!G118)+CHOOSE(Premissas!$B$6,Cenários!G27,Cenários!G73,Cenários!G119))*(1-G21) -> 0 | H36: =(CHOOSE(Premissas!$B$6,Cenários!H24,Cenários!H70,Cenários!H116))*(1-H21-Premissas!$B$75)+(CHOOSE(Premissas!$B$6,Cenários!H25,Cenários!H71,Cenários!H117)+CHOOSE(Premissas!$B$6,Cenários!H26,Cenários!H72,Cenários!H118)+CHOOSE(Premissas!$B$6,Cenários!H27,Cenários!H73,Cenários!H119))*(1-H21) -> 0 | I36: =(CHOOSE(Premissas!$B$6,Cenários!I24,Cenários!I70,Cenários!I116))*(1-I21-Premissas!$B$75)+(CHOOSE(Premissas!$B$6,Cenários!I25,Cenários!I71,Cenários!I117)+CHOOSE(Premissas!$B$6,Cenários!I26,Cenários!I72,Cenários!I118)+CHOOSE(Premissas!$B$6,Cenários!I27,Cenários!I73,Cenários!I119))*(1-I21) -> 0 | ... BI36: =(CHOOSE(Premissas!$B$6,Cenários!BI24,Cenários!BI70,Cenários!BI116))*(1-BI21-Premissas!$B$75)+(CHOOSE(Premissas!$B$6,Cenários!BI25,Cenários!BI71,Cenários!BI117)+CHOOSE(Premissas!$B$6,Cenários!BI26,Cenários!BI72,Cenários!BI118)+CHOOSE(Premissas!$B$6,Cenários!BI27,Cenários!BI73,Cenários!BI119))*(1-BI21) -> 213305.75 | BJ36: =SUM(B36:BI36) -> 4396988.7 | BK36: Entram como abatimento: o que o marketplace e o B2B pagam, a assinatura não precisa pagar. Venda de dados não passa por loja nem por adquirente.
A37: (=) Custo que a assinatura tem de cobrir | B37: =B35-B36 -> 0 | C37: =C35-C36 -> 0 | D37: =D35-D36 -> 0 | E37: =E35-E36 -> 1500 | F37: =F35-F36 -> 2100 | G37: =G35-G36 -> 2100 | H37: =H35-H36 -> 2100 | I37: =I35-I36 -> 2100 | ... BI37: =BI35-BI36 -> 913916.65 | BJ37: =SUM(B37:BI37) -> 22979920
A38: Investimento do mês (CAPEX) — fora da conta de preço | B38: =-'Análise Fluxo'!B13 -> 0 | C38: =-'Análise Fluxo'!C13 -> 0 | D38: =-'Análise Fluxo'!D13 -> 0 | E38: =-'Análise Fluxo'!E13 -> 0 | F38: =-'Análise Fluxo'!F13 -> 6000 | G38: =-'Análise Fluxo'!G13 -> 0 | H38: =-'Análise Fluxo'!H13 -> 0 | I38: =-'Análise Fluxo'!I13 -> 9127.82 | ... BI38: =-'Análise Fluxo'!BI13 -> 0 | BJ38: =SUM(B38:BI38) -> 149127.82 | BK38: Equipamento e certificação são investimento, pagos por capital, não por assinatura. Ficam de fora de propósito — aparecem aqui só para você ver o tamanho.
A40: 4. OS PISOS DE PREÇO DO ESSENCIAL, MÊS A MÊS
A41: Piso 1 — cobre só o custo variável (margem de contribuição zero) | B41: =IFERROR(B31/B24,0) -> 2.6028843 | C41: =IFERROR(C31/C24,0) -> 2.6028843 | D41: =IFERROR(D31/D24,0) -> 2.6028843 | E41: =IFERROR(E31/E24,0) -> 2.6028843 | F41: =IFERROR(F31/F24,0) -> 2.6028843 | G41: =IFERROR(G31/G24,0) -> 2.6028843 | H41: =IFERROR(H31/H24,0) -> 2.6028843 | I41: =IFERROR(I31/I24,0) -> 2.6028843 | ... BI41: =IFERROR(BI31/BI24,0) -> 2.2455718 | BK41: Abaixo disto, cada assinante novo dá prejuízo. É o piso absoluto.
A42: Piso 2 — cobre o variável e o CAC diluído | B42: =IFERROR((B31+B33)/B24,0) -> 2.6028843 | C42: =IFERROR((C31+C33)/C24,0) -> 2.6028843 | D42: =IFERROR((D31+D33)/D24,0) -> 2.6028843 | E42: =IFERROR((E31+E33)/E24,0) -> 2.6028843 | F42: =IFERROR((F31+F33)/F24,0) -> 2.6028843 | G42: =IFERROR((G31+G33)/G24,0) -> 2.6028843 | H42: =IFERROR((H31+H33)/H24,0) -> 2.6028843 | I42: =IFERROR((I31+I33)/I24,0) -> 2.6028843 | ... BI42: =IFERROR((BI31+BI33)/BI24,0) -> 5.5996532 | BK42: Abaixo disto, crescer destrói valor: o assinante não devolve o que custou conquistar.
A43: Piso 3 — EQUILIBRA O MÊS (EBITDA zero) | B43: =IFERROR(B37/(B16*B24),0) -> 0 | C43: =IFERROR(C37/(C16*C24),0) -> 0 | D43: =IFERROR(D37/(D16*D24),0) -> 0 | E43: =IFERROR(E37/(E16*E24),0) -> 0 | F43: =IFERROR(F37/(F16*F24),0) -> 0 | G43: =IFERROR(G37/(G16*G24),0) -> 0 | H43: =IFERROR(H37/(H16*H24),0) -> 0 | I43: =IFERROR(I37/(I16*I24),0) -> 0 | ... BI43: =IFERROR(BI37/(BI16*BI24),0) -> 10.193099 | BK43: Com a base daquele mês. Nos primeiros meses fica absurdo — e é esse o ponto: não é o preço que está errado, é a base que ainda é pequena.
A44: Preço-alvo — entrega a margem EBITDA desejada | B44: =IFERROR((B35/(1-Premissas!$B$49)-B36)/(B16*B24),0) -> 0 | C44: =IFERROR((C35/(1-Premissas!$B$49)-C36)/(C16*C24),0) -> 0 | D44: =IFERROR((D35/(1-Premissas!$B$49)-D36)/(D16*D24),0) -> 0 | E44: =IFERROR((E35/(1-Premissas!$B$49)-E36)/(E16*E24),0) -> 0 | F44: =IFERROR((F35/(1-Premissas!$B$49)-F36)/(F16*F24),0) -> 0 | G44: =IFERROR((G35/(1-Premissas!$B$49)-G36)/(G16*G24),0) -> 0 | H44: =IFERROR((H35/(1-Premissas!$B$49)-H36)/(H16*H24),0) -> 0 | I44: =IFERROR((I35/(1-Premissas!$B$49)-I36)/(I16*I24),0) -> 0 | ... BI44: =IFERROR((BI35/(1-Premissas!$B$49)-BI36)/(BI16*BI24),0) -> 13.336135
A46: Os mesmos pisos, traduzidos para os outros dois planos
A47: Premium — piso de equilíbrio do mês | B47: =B43*B14 -> 0 | C47: =C43*C14 -> 0 | D47: =D43*D14 -> 0 | E47: =E43*E14 -> 0 | F47: =F43*F14 -> 0 | G47: =G43*G14 -> 0 | H47: =H43*H14 -> 0 | I47: =I43*I14 -> 0 | ... BI47: =BI43*BI14 -> 20.43742 | BK47: Mantém a razão de preço atual entre os planos. Mude os preços em Premissas e a razão muda com eles.
A48: Família — piso de equilíbrio do mês | B48: =B43*B15 -> 0 | C48: =C43*C15 -> 0 | D48: =D43*D15 -> 0 | E48: =E43*E15 -> 0 | F48: =F43*F15 -> 0 | G48: =G43*G15 -> 0 | H48: =H43*H15 -> 0 | I48: =I43*I15 -> 0 | ... BI48: =BI43*BI15 -> 40.926062
A49: Premium — preço-alvo | B49: =B44*B14 -> 0 | C49: =C44*C14 -> 0 | D49: =D44*D14 -> 0 | E49: =E44*E14 -> 0 | F49: =F44*F14 -> 0 | G49: =G44*G14 -> 0 | H49: =H44*H14 -> 0 | I49: =I44*I14 -> 0 | ... BI49: =BI44*BI14 -> 26.739285
A50: Família — preço-alvo | B50: =B44*B15 -> 0 | C50: =C44*C15 -> 0 | D50: =D44*D15 -> 0 | E50: =E44*E15 -> 0 | F50: =F44*F15 -> 0 | G50: =G44*G15 -> 0 | H50: =H44*H15 -> 0 | I50: =I44*I15 -> 0 | ... BI50: =BI44*BI15 -> 53.545587
A52: 5. O OUTRO LADO DA MESMA CONTA: QUANTOS ASSINANTES
A53: Assinantes equivalentes necessários para equilibrar o mês | B53: =IFERROR(B37/(B13*B24),0) -> 0 | C53: =IFERROR(C37/(C13*C24),0) -> 0 | D53: =IFERROR(D37/(D13*D24),0) -> 0 | E53: =IFERROR(E37/(E13*E24),0) -> 106.0526 | F53: =IFERROR(F37/(F13*F24),0) -> 148.47364 | G53: =IFERROR(G37/(G13*G24),0) -> 148.47364 | H53: =IFERROR(H37/(H13*H24),0) -> 148.47364 | I53: =IFERROR(I37/(I13*I24),0) -> 148.47364 | ... BI53: =IFERROR(BI37/(BI13*BI24),0) -> 53621.993 | BK53: Ao preço de tabela. É o piso 3 lido pelo outro lado.
A54: Assinantes equivalentes projetados | B54: =B16 -> 0 | C54: =C16 -> 0 | D54: =D16 -> 0 | E54: =E16 -> 0 | F54: =F16 -> 0 | G54: =G16 -> 0 | H54: =H16 -> 0 | I54: =I16 -> 0 | ... BI54: =BI16 -> 124840.34
A55: Faltam (ou sobram) | B55: =B54-B53 -> 0 | C55: =C54-C53 -> 0 | D55: =D54-D53 -> 0 | E55: =E54-E53 -> -106.0526 | F55: =F54-F53 -> -148.47364 | G55: =G54-G53 -> -148.47364 | H55: =H54-H53 -> -148.47364 | I55: =I54-I53 -> -148.47364 | ... BI55: =BI54-BI53 -> 71218.344 | BK55: Positivo = o mês se paga no preço atual.
A56: Marcador — mês em que a projeção cobre o custo | B56: =IF(AND(B54>0,B54>=B53),B$5,9999) -> 9999 | C56: =IF(AND(C54>0,C54>=C53),C$5,9999) -> 9999 | D56: =IF(AND(D54>0,D54>=D53),D$5,9999) -> 9999 | E56: =IF(AND(E54>0,E54>=E53),E$5,9999) -> 9999 | F56: =IF(AND(F54>0,F54>=F53),F$5,9999) -> 9999 | G56: =IF(AND(G54>0,G54>=G53),G$5,9999) -> 9999 | H56: =IF(AND(H54>0,H54>=H53),H$5,9999) -> 9999 | I56: =IF(AND(I54>0,I54>=I53),I$5,9999) -> 9999 | ... BI56: =IF(AND(BI54>0,BI54>=BI53),BI$5,9999) -> 60
A57: ✔ Reconciliação com o motor (deve ser zero em todos os meses) | B57: =B13*B16*B24+B36-B35-CHOOSE(Premissas!$B$6,Cenários!B40,Cenários!B86,Cenários!B132) -> 0 | C57: =C13*C16*C24+C36-C35-CHOOSE(Premissas!$B$6,Cenários!C40,Cenários!C86,Cenários!C132) -> 0 | D57: =D13*D16*D24+D36-D35-CHOOSE(Premissas!$B$6,Cenários!D40,Cenários!D86,Cenários!D132) -> 0 | E57: =E13*E16*E24+E36-E35-CHOOSE(Premissas!$B$6,Cenários!E40,Cenários!E86,Cenários!E132) -> 0 | F57: =F13*F16*F24+F36-F35-CHOOSE(Premissas!$B$6,Cenários!F40,Cenários!F86,Cenários!F132) -> 0 | G57: =G13*G16*G24+G36-G35-CHOOSE(Premissas!$B$6,Cenários!G40,Cenários!G86,Cenários!G132) -> 0 | H57: =H13*H16*H24+H36-H35-CHOOSE(Premissas!$B$6,Cenários!H40,Cenários!H86,Cenários!H132) -> 0 | I57: =I13*I16*I24+I36-I35-CHOOSE(Premissas!$B$6,Cenários!I40,Cenários!I86,Cenários!I132) -> 0 | ... BI57: =BI13*BI16*BI24+BI36-BI35-CHOOSE(Premissas!$B$6,Cenários!BI40,Cenários!BI86,Cenários!BI132) -> 0 | BJ57: =SUM(B57:BI57) -> 5.4569682e-12 | BK57: Prova a identidade da aba contra o EBITDA do motor. Se der diferente de zero, a decomposição de custo ou o fator de retenção estão errados.
A60: 6. A PERGUNTA DO LANÇAMENTO: O ESSENCIAL COBRE OS PRIMEIROS MESES?
A61: Primeiro mês da janela | B61: =Premissas!$B$13 -> 46296
A62: Último mês da janela | B62: =EDATE(Premissas!$B$13,Premissas!$B$47-1) -> 46447 | D62: O número de meses está em Premissas, seção 3.
A63: Custo operacional dentro da janela | B63: =SUMPRODUCT(($B$5:$BI$5>=Premissas!$B$14)*($B$5:$BI$5<=Premissas!$B$14+Premissas!$B$47-1)*$B$35:$BI$35) -> 525987.87
A64: Custo operacional anterior ao lançamento | B64: =SUMPRODUCT(($B$5:$BI$5<Premissas!$B$14)*$B$35:$BI$35)*Premissas!$B$48 -> 12000 | D64: Nuvem desde maio, administrativas desde abril, a equipe PJ de setembro e outubro e a propaganda de lançamento. Entra ou não conforme o interruptor em Premissas.
A65: (−) Outras receitas líquidas na janela | B65: =-SUMPRODUCT(($B$5:$BI$5>=Premissas!$B$14)*($B$5:$BI$5<=Premissas!$B$14+Premissas!$B$47-1)*$B$36:$BI$36) -> -11902.463
A66: (=) Total que a assinatura precisa cobrir | B66: =B63+B64+B65 -> 526085.41
A67: Assinantes equivalentes × fator de retenção, somados na janela | B67: =SUMPRODUCT(($B$5:$BI$5>=Premissas!$B$14)*($B$5:$BI$5<=Premissas!$B$14+Premissas!$B$47-1)*$B$16:$BI$16*$B$24:$BI$24) -> 10804.894
A68: PREÇO ÚNICO DO ESSENCIAL QUE ZERA A JANELA | B68: =IFERROR(B66/B67,0) -> 48.689548 | D68: Um só preço, cobrado em todos os meses da janela, que faz a conta fechar no fim dela.
A69: Premium equivalente | B69: =B68*IFERROR(Premissas!$B$30/Premissas!$B$29,0) -> 97.623766
A70: Família equivalente | B70: =B68*IFERROR(Premissas!$B$31/Premissas!$B$29,0) -> 195.4922
A71: Preço do Essencial hoje | B71: =Premissas!$B$29 -> 19.9
A72: Quantas vezes o preço de hoje | B72: =IFERROR(B68/B71,0) -> 2.4467109 | D72: Acima de ~1,5x o preço perde o mercado: é sinal de que a resposta não é preço.
A73: Assinantes necessários na janela, mantendo o preço de hoje | B73: =IFERROR(B66/(B71*SUMPRODUCT(($B$5:$BI$5>=Premissas!$B$14)*($B$5:$BI$5<=Premissas!$B$14+Premissas!$B$47-1)*$B$24:$BI$24)),0) -> 6178.6813 | D73: Média de assinantes equivalentes ao longo da janela, não no último mês.
A74: Assinantes equivalentes projetados no último mês da janela | B74: =IFERROR(INDEX($B$16:$BI$16,Premissas!$B$14+Premissas!$B$47-1),0) -> 6214
A75: Média de assinantes equivalentes projetada na janela | B75: =IFERROR(SUMPRODUCT(($B$5:$BI$5>=Premissas!$B$14)*($B$5:$BI$5<=Premissas!$B$14+Premissas!$B$47-1)*$B$16:$BI$16)/Premissas!$B$47,0) -> 2519.8333
A76: Quanto falta de base para o preço de hoje bastar | B76: =IFERROR(B73/B75,0) -> 2.4520198 | D76: Quantas vezes a base projetada teria de ser maior. É a mesma pergunta do preço, do lado do volume.
A77: VEREDICTO | B77: =IF(B75<=0,"Sem base na janela — nenhum preço cobre",IF(B72<=1,"O preço de hoje cobre a janela",IF(B72<=1.5,"Dá para fechar com reajuste: "&TEXT(B68,"R$ 0.00"),"Nenhum preço de mercado cobre: a janela é financiada por capital"))) -> Nenhum preço de mercado cobre: a janela é financiada por capital
A79: A leitura honesta: assinatura de ticket baixo não paga custo fixo com base pequena. O preço cobre o custo variável desde o primeiro assinante — é o piso 1 e ele é baixo. O custo fixo dos primeiros meses é pago por capital, e é exatamente isso que a aba NECESSIDADE DE CAPITAL dimensiona. Preço alto demais no lançamento não resolve o caixa: reduz a conversão e piora o caixa.
A81: 7. RESUMO POR CENÁRIO
A82: INDICADOR | B82: CONSERVADOR | C82: PROVÁVEL | D82: AGRESSIVO
A83: Assinantes equivalentes no último mês da janela | B83: =IFERROR(INDEX(Cenários!$B$16:$BI$16,Premissas!$B$14+Premissas!$B$47-1)+INDEX(Cenários!$B$17:$BI$17,Premissas!$B$14+Premissas!$B$47-1)*Premissas!$B$30/Premissas!$B$29+INDEX(Cenários!$B$18:$BI$18,Premissas!$B$14+Premissas!$B$47-1)*Premissas!$B$31/Premissas!$B$29,0) -> 2045 | C83: =IFERROR(INDEX(Cenários!$B$62:$BI$62,Premissas!$B$14+Premissas!$B$47-1)+INDEX(Cenários!$B$63:$BI$63,Premissas!$B$14+Premissas!$B$47-1)*Premissas!$B$30/Premissas!$B$29+INDEX(Cenários!$B$64:$BI$64,Premissas!$B$14+Premissas!$B$47-1)*Premissas!$B$31/Premissas!$B$29,0) -> 6214 | D83: =IFERROR(INDEX(Cenários!$B$108:$BI$108,Premissas!$B$14+Premissas!$B$47-1)+INDEX(Cenários!$B$109:$BI$109,Premissas!$B$14+Premissas!$B$47-1)*Premissas!$B$30/Premissas!$B$29+INDEX(Cenários!$B$110:$BI$110,Premissas!$B$14+Premissas!$B$47-1)*Premissas!$B$31/Premissas!$B$29,0) -> 13505
A84: EBITDA acumulado na janela | B84: =SUMPRODUCT(($B$5:$BI$5>=Premissas!$B$14)*($B$5:$BI$5<=Premissas!$B$14+Premissas!$B$47-1)*Cenários!$B$40:$BI$40) -> -407187.63 | C84: =SUMPRODUCT(($B$5:$BI$5>=Premissas!$B$14)*($B$5:$BI$5<=Premissas!$B$14+Premissas!$B$47-1)*Cenários!$B$86:$BI$86) -> -290653.73 | D84: =SUMPRODUCT(($B$5:$BI$5>=Premissas!$B$14)*($B$5:$BI$5<=Premissas!$B$14+Premissas!$B$47-1)*Cenários!$B$132:$BI$132) -> -37907.888 | F84: Negativo significa que a janela não se paga: a diferença vem de capital.
A85: EBITDA acumulado até o fim da janela, somando o que veio antes | B85: =SUMPRODUCT(($B$5:$BI$5<=Premissas!$B$14+Premissas!$B$47-1)*Cenários!$B$40:$BI$40) -> -419187.63 | C85: =SUMPRODUCT(($B$5:$BI$5<=Premissas!$B$14+Premissas!$B$47-1)*Cenários!$B$86:$BI$86) -> -302653.73 | D85: =SUMPRODUCT(($B$5:$BI$5<=Premissas!$B$14+Premissas!$B$47-1)*Cenários!$B$132:$BI$132) -> -49907.888
A86: Primeiro mês em que o EBITDA cobre o custo | B86: =IF(MAX(Cenários!$B$46:$BI$46)=0,"não atinge",CHOOSE(MOD(60-SUM(Cenários!$B$46:$BI$46),12)+1,"jan","fev","mar","abr","mai","jun","jul","ago","set","out","nov","dez")&"/"&(2026+INT((60-SUM(Cenários!$B$46:$BI$46))/12))) -> não atinge | C86: =IF(MAX(Cenários!$B$92:$BI$92)=0,"não atinge",CHOOSE(MOD(60-SUM(Cenários!$B$92:$BI$92),12)+1,"jan","fev","mar","abr","mai","jun","jul","ago","set","out","nov","dez")&"/"&(2026+INT((60-SUM(Cenários!$B$92:$BI$92))/12))) -> abr/2027 | D86: =IF(MAX(Cenários!$B$138:$BI$138)=0,"não atinge",CHOOSE(MOD(60-SUM(Cenários!$B$138:$BI$138),12)+1,"jan","fev","mar","abr","mai","jun","jul","ago","set","out","nov","dez")&"/"&(2026+INT((60-SUM(Cenários!$B$138:$BI$138))/12))) -> fev/2027 | F86: Mesmo mês do break-even no Resumo. Se divergir, há inconsistência entre as abas.

Sheet Premissas
A1: OPPA — PREMISSAS DO MODELO
A2: AZUL = você digita · fundo AMARELO = premissa-chave · PRETO = calculado pelo modelo. Células com marca vermelha no canto têm a fonte do número em comentário. O quadro de pessoas fica na aba Pessoas.
A4: 1. CONTROLES DO MODELO
A5: Ano → | B5: Evolução a.a. | C5: 2026 | D5: 2027 | E5: 2028 | F5: 2029 | G5: 2030
A6: Cenário ativo (1 = Conservador · 2 = Provável · 3 = Agressivo) | B6: 2 | D6: Troque este número e a planilha inteira recalcula no cenário escolhido.
A7: Cenário ativo — nome | B7: =CHOOSE($B$6,"CONSERVADOR","PROVÁVEL","AGRESSIVO") -> PROVÁVEL
A8: Considerar o plano de contratações? (1 = Sim · 0 = Não) | B8: 1 | D8: Com 0, o modelo considera só quem já está contratado (equipe do MVP).
A10: LANÇAMENTO DO APP
A11: Ano de lançamento | B11: 2026
A12: Mês de lançamento (1 = janeiro … 12 = dezembro) | B12: 10 | D12: Brief: app majoritariamente pronto em outubro.
A13: Data de lançamento (calculada) | B13: =DATE($B$11,$B$12,1) -> 46296
A14: Mês nº do lançamento na linha do tempo | B14: =($B$11-2026)*12+$B$12 -> 10
A15: Rampa de maturação da conversão (meses) | B15: 6 | D15: É isto que torna 2026 mais tímido. Coloque 1 para converter no patamar cheio desde o primeiro mês.
A17: PARÂMETROS FINANCEIROS
A18: TMA — taxa mínima de atratividade (a.a.) | B18: 0.25 | D18: Original usava 16% a.a.; 25% reflete risco de startup pré-receita.
A19: TMA equivalente mensal | B19: =(1+$B$18)^(1/12)-1 -> 0.018769265
A20: Payback desejado (meses) — critério de decisão | B20: 36 | D20: Critério Go/No-Go, herdado da planilha de viabilidade da EMS.
A22: 2. TRIBUTAÇÃO
A23: Regime (1 = Simples Anexo III · 2 = Simples Anexo V · 3 = Lucro Presumido) | B23: 2 | D23: ⚠ Padrão = 2 (Anexo V). O Fator R do quadro atual fica muito abaixo de 28%, então o Anexo III não está disponível. Veja a conferência na aba Pessoas.
A24: Alíquota Lucro Presumido / acima do teto do Simples | B24: 0.1633 | D24: PIS 0,65 + COFINS 3,00 + ISS 5,00 + IRPJ 4,80 + CSLL 2,88 = 16,33%
A25: Teto do Simples Nacional (RBT12) | B25: 4800000 | D25: LC 123/2006. Acima disso o modelo passa sozinho ao Lucro Presumido.
A27: 3. PREÇOS E MIX DE PLANOS
A28: • São quatro planos, conforme o backlog do produto: Free (gratuito, entra na base de usuários mas não gera receita de assinatura), Essencial, Premium e Família. Os três pagos estão abaixo; o Free é a diferença entre a base ativa e os pagantes, na aba Usuários.
A29: Plano Essencial (R$/mês) · 1 familiar, até 3 cuidadores | B29: 19.9
A30: Plano Premium (R$/mês) · 1 familiar, cuidadores ilimitados | B30: 39.9
A31: Plano Família (R$/mês) · até 4 familiares, cuidadores ilimitados | B31: 79.9
A32: Reajuste anual de preços (a.a.) | B32: 0.045 | D32: Aplicado a partir de 2027 (IPCA projetado ~4,5%).
A33: Mix de pagantes por plano (% dos assinantes)
A34: Plano Essencial | C34: 0.75 | D34: 0.72 | E34: 0.68 | F34: 0.64 | G34: 0.6 | I34: Efeito compromisso (Simonson & Tversky, 1992) + padrão de assinatura B2C de ticket baixo.
A35: Plano Premium | C35: 0.2 | D35: 0.22 | E35: 0.24 | F35: 0.26 | G35: 0.28 | I35: Plano-ponte: cresce conforme o Premium ganha valor percebido.
A36: Plano Família | C36: 0.05 | D36: 0.06 | E36: 0.08 | F36: 0.1 | G36: 0.12 | I36: Fatia menor mas crescente — ancoragem de preço que sustenta o Intermediário.
A37: Verificação do mix (deve somar 100%) | C37: =SUM(C34:C36) -> 1 | D37: =SUM(D34:D36) -> 1 | E37: =SUM(E34:E36) -> 1 | F37: =SUM(F34:F36) -> 1 | G37: =SUM(G34:G36) -> 1
A38: ARPPU implícita (receita média por assinante pagante) | C38: =(C34*$B$29+C35*$B$30+C36*$B$31)*(1+$B$32)^(C$5-2026) -> 26.9 | D38: =(D34*$B$29+D35*$B$30+D36*$B$31)*(1+$B$32)^(D$5-2026) -> 29.1555 | E38: =(E34*$B$29+E35*$B$30+E36*$B$31)*(1+$B$32)^(E$5-2026) -> 32.214737 | F38: =(F34*$B$29+F35*$B$30+F36*$B$31)*(1+$B$32)^(F$5-2026) -> 35.490266 | G38: =(G34*$B$29+G35*$B$30+G36*$B$31)*(1+$B$32)^(G$5-2026) -> 38.995358 | I38: Ignora a entrada faseada: é a ARPPU com os três planos no ar. A ARPPU real, mês a mês, está na aba Preço Mínimo.
A40: Entrada dos planos — o que está no ar em cada mês
A41: • No lançamento só existe o Essencial. Premium e Família entram quando o produto tiver recurso que os justifique. Antes da data de entrada, quem assina vai todo para o Essencial — o mix dos outros dois é ignorado, não redistribuído. Para vender só o Essencial nos cinco anos, jogue as duas datas para depois de dez/2030.
A42: Mês de entrada do plano Premium | B42: 46478 | D42: Padrão: 6 meses após o lançamento. Antes disso, todo pagante é Essencial.
A43: Mês de entrada do plano Família | B43: 46661 | D43: Padrão: 12 meses após o lançamento.
A45: Política de preço — parâmetros da conta de trás pra frente
A46: • A aba PREÇO MÍNIMO parte do custo e devolve o preço. Estes três campos definem a régua. Nada aqui altera a projeção: o preço que o modelo cobra é o digitado acima. Fechar o laço criaria circularidade — preço muda receita, receita muda a faixa do Simples, a faixa muda o preço mínimo.
A47: Meses iniciais que a assinatura precisa cobrir | B47: 6 | D47: Contados do mês de lançamento. É a janela da pergunta “o Essencial cobre os primeiros seis meses?”
A48: Incluir na conta os custos anteriores ao lançamento? (1 = Sim · 0 = Não) | B48: 1 | D48: Com 1, a janela paga também o que foi gasto antes do lançamento.
A49: Margem EBITDA desejada no preço-alvo | B49: 0.2 | D49: Usada só na linha de preço-alvo. Não entra na projeção.
A51: 4. DRIVERS POR CENÁRIO
A52: • Cada driver tem 3 linhas — Conservador, Provável e Agressivo. O modelo usa a do cenário ativo.
A53: • Digite o patamar de 2026 na coluna C e a taxa de evolução anual na coluna B: 2027 a 2030 são calculados sozinhos. Quer um ano específico fora da curva? Digite por cima — a célula vira entrada manual e os anos seguintes continuam a partir dela.
A54: Novos usuários captados por mês (média do ano)
A55: Conservador | B55: 0.4 | C55: 10860 | D55: =C55*(1+$B55) -> 15204 | E55: =D55*(1+$B55) -> 21285.6 | F55: =E55*(1+$B55) -> 29799.84 | G55: =F55*(1+$B55) -> 41719.776
A56: Provável | B56: 0.5 | C56: 18100 | D56: =C56*(1+$B56) -> 27150 | E56: =D56*(1+$B56) -> 40725 | F56: =E56*(1+$B56) -> 61087.5 | G56: =F56*(1+$B56) -> 91631.25 | I56: Calibrado para a meta de ~50.000 usuários em dez/2026.
A57: Agressivo | B57: 0.6 | C57: 25340 | D57: =C57*(1+$B57) -> 40544 | E57: =D57*(1+$B57) -> 64870.4 | F57: =E57*(1+$B57) -> 103792.64 | G57: =F57*(1+$B57) -> 166068.22
A58: Churn mensal da base de usuários
A59: Conservador | B59: -0.04 | C59: 0.1 | D59: =C59*(1+$B59) -> 0.096 | E59: =D59*(1+$B59) -> 0.09216 | F59: =E59*(1+$B59) -> 0.0884736 | G59: =F59*(1+$B59) -> 0.084934656
A60: Provável | B60: -0.06 | C60: 0.08 | D60: =C60*(1+$B60) -> 0.0752 | E60: =D60*(1+$B60) -> 0.070688 | F60: =E60*(1+$B60) -> 0.06644672 | G60: =F60*(1+$B60) -> 0.062459917 | I60: Saúde & Fitness: 7–10%/mês (mediana 9,2%). Evolução negativa = churn melhorando.
A61: Agressivo | B61: -0.08 | C61: 0.06 | D61: =C61*(1+$B61) -> 0.0552 | E61: =D61*(1+$B61) -> 0.050784 | F61: =E61*(1+$B61) -> 0.04672128 | G61: =F61*(1+$B61) -> 0.042983578
A62: Taxa de conversão (pagantes ÷ base ativa) — patamar de regime
A63: Conservador | B63: 0.08 | C63: 0.03 | D63: =MIN(0.25,C63*(1+$B63)) -> 0.0324 | E63: =MIN(0.25,D63*(1+$B63)) -> 0.034992 | F63: =MIN(0.25,E63*(1+$B63)) -> 0.03779136 | G63: =MIN(0.25,F63*(1+$B63)) -> 0.040814669
A64: Provável | B64: 0.08 | C64: 0.05 | D64: =MIN(0.25,C64*(1+$B64)) -> 0.054 | E64: =MIN(0.25,D64*(1+$B64)) -> 0.05832 | F64: =MIN(0.25,E64*(1+$B64)) -> 0.0629856 | G64: =MIN(0.25,F64*(1+$B64)) -> 0.068024448 | I64: Patamar de regime. A rampa (controle 1) segura a conversão nos primeiros meses.
A65: Agressivo | B65: 0.1 | C65: 0.07 | D65: =MIN(0.25,C65*(1+$B65)) -> 0.077 | E65: =MIN(0.25,D65*(1+$B65)) -> 0.0847 | F65: =MIN(0.25,E65*(1+$B65)) -> 0.09317 | G65: =MIN(0.25,F65*(1+$B65)) -> 0.102487
A66: CAC — custo de aquisição por novo usuário (R$)
A67: Conservador | B67: 0.18 | C67: 4 | D67: =C67*(1+$B67) -> 4.72 | E67: =D67*(1+$B67) -> 5.5696 | F67: =E67*(1+$B67) -> 6.572128 | G67: =F67*(1+$B67) -> 7.755111
A68: Provável | B68: 0.15 | C68: 2.5 | D68: =C68*(1+$B68) -> 2.875 | E68: =D68*(1+$B68) -> 3.30625 | F68: =E68*(1+$B68) -> 3.8021875 | G68: =F68*(1+$B68) -> 4.3725156 | I68: CPI Brasil saúde: R$ 1,50–4,00. Sobe com a escala.
A69: Agressivo | B69: 0.15 | C69: 1.5 | D69: =C69*(1+$B69) -> 1.725 | E69: =D69*(1+$B69) -> 1.98375 | F69: =E69*(1+$B69) -> 2.2813125 | G69: =F69*(1+$B69) -> 2.6235094
A70: Aquisição orgânica (% dos novos usuários, sem custo de mídia) | C70: 0.3 | D70: 0.32 | E70: 0.35 | F70: 0.38 | G70: 0.4 | I70: Boca a boca + conteúdo da agência da Shaiane. Reduz a fatia paga com mídia.
A72: 5. MONETIZAÇÃO — CANAIS, TAXAS E RECEITA B2B
A73: Taxa das lojas de aplicativos (App Store / Google Play) | B73: 0.15 | D73: Google Play 15% desde o 1º dia; Apple 15% no Small Business Program.
A74: % da receita de assinaturas cobrada pelas lojas | C74: 0.85 | D74: 0.8 | E74: 0.75 | F74: 0.72 | G74: 0.7 | I74: Migração gradual para checkout web/PIX próprio, que não paga comissão de loja.
A75: Taxa de meio de pagamento (venda direta web/PIX) | B75: 0.045 | D75: Média ponderada de cartão (~4,99%) e PIX (~1,0%).
A76: Receita B2B de dados — o painel
A77: • O dado só vale se houver escala e consentimento. Estas três premissas definem o tamanho do painel comercializável; a tabela logo abaixo define o que se cobra por ele. Enquanto o painel não atingir o mínimo, nenhum contrato de dados gera receita, por mais que a data de início já tenha passado.
A78: % da base que consente compartilhar dados | C78: 0.25 | D78: 0.28 | E78: 0.3 | F78: 0.32 | G78: 0.35 | I78: ⚠ Consentimento específico e destacado, separado dos termos do app. Revogável.
A79: Base mínima do painel para ter valor comercial (usuários) | B79: 75000 | D79: Abaixo deste número, a receita de dados é zero, mesmo com contrato na tabela.
A80: Custo de processamento do painel (R$/usuário/mês) | B80: 0.05 | D80: Anonimização, agregação e entrega dos dados. Entra na linha de nuvem.
A81: Considerar iniciativas B2B EM ESTUDO? (1 = Sim · 0 = Não) | B81: 0 | D81: ⚠ Desligado. Liga as linhas marcadas como 'Em estudo' na tabela abaixo.
A82: Iniciativas de receita B2B
A83: Uma linha por iniciativa. As duas primeiras são a venda de dados, já planejada. As demais estão em branco para vocês preencherem — recompra de medicamento de uso crônico, integrações com farmácia, o que vier. Categoria separa o que aparece como 'venda de dados' do que aparece como 'outras iniciativas' na DRE.
A84: Iniciativa | B84: Categoria | C84: Status | D84: Modelo | E84: Valor | F84: Início | G84: Fim
A85: Venda de dados à indústria farmacêutica | B85: Dados | C85: Planejado | D85: Fixo mensal | E85: 45000 | F85: 46935 | G85: 47818 | I85: Modelo 'Fixo mensal': o valor é R$/mês de contrato. 'Por usuário': o valor é R$ por usuário do painel por mês.
A86: Venda de dados a redes de farmácia | B86: Dados | C86: Planejado | D86: Fixo mensal | E86: 25000 | F86: 47119 | G86: 47818
A87: Recompra de medicamento de uso crônico | B87: Outras | C87: Em estudo | D87: Fixo mensal | E87: 0 | F87: 47119 | G87: 47818
B88: Outras | C88: Em estudo | D88: Fixo mensal | E88: 0 | F88: 47119 | G88: 47818
B89: Outras | C89: Em estudo | D89: Fixo mensal | E89: 0 | F89: 47119 | G89: 47818
B90: Outras | C90: Em estudo | D90: Fixo mensal | E90: 0 | F90: 47119 | G90: 47818
B91: Outras | C91: Em estudo | D91: Fixo mensal | E91: 0 | F91: 47119 | G91: 47818
B92: Outras | C92: Em estudo | D92: Fixo mensal | E92: 0 | F92: 47119 | G92: 47818
B93: Outras | C93: Em estudo | D93: Fixo mensal | E93: 0 | F93: 47119 | G93: 47818
A96: Marketplace de dispositivos
A97: Comissão média sobre GMV | B97: 0.1 | D97: Brief: faixa de 5% a 15%. Adotado o ponto médio.
A98: Ticket médio do dispositivo (R$) | B98: 350 | D98: Oxímetro ~R$150, smartwatch de saúde ~R$400, balança/pressão ~R$250.
A99: Taxa de compra mensal (% da base ativa que compra no mês) | C99: 0 | D99: 0.0015 | E99: 0.0025 | F99: 0.004 | G99: 0.005 | I99: Marketplace só entra no ar em 2027. Compra de device é evento raro e de alto ticket.
A101: 6. CUSTOS OPERACIONAIS (exceto pessoas — ver aba Pessoas)
A102: Início dos custos de nuvem | B102: 46143 | D102: Primeiro gasto real registrado: R$ 532,29 em 04/05/2026.
A103: Nuvem — custo fixo mensal (R$) | C103: 600 | D103: 2500 | E103: 8000 | F103: 18000 | G103: 30000 | I103: Base: gasto real de R$ 532,29 em 04/05/2026.
A104: Nuvem — custo variável por usuário PAGANTE (R$/mês) | C104: 1.5 | D104: 1.35 | E104: 1.15 | F104: 1 | G104: 0.9 | I104: Só o pagante gera histórico — premissa do brief.
A105: Nuvem — custo variável por usuário GRATUITO (R$/mês) | C105: 0.02 | D105: 0.02 | E105: 0.018 | F105: 0.015 | G105: 0.015 | I105: Não é zero: ingestão em tempo real e API consomem compute mesmo sem histórico.
A106: Suporte — ferramentas e custo variável por pagante (R$/mês) | C106: 0.35 | D106: 0.35 | E106: 0.3 | F106: 0.28 | G106: 0.25 | I106: Chatbot, help desk e base de conhecimento. As PESSOAS de suporte estão na aba Pessoas.
A107: Início das despesas administrativas | B107: 46113 | D107: A partir da constituição da empresa / primeiro aporte (16/04/2026).
A108: Administrativas (contabilidade, jurídico, ferramentas) — R$/mês | C108: 1500 | D108: 6000 | E108: 25000 | F108: 60000 | G108: 110000 | I108: Não inclui pessoas. Escalonado com o porte da operação.
A109: Marketing recorrente — mídia de conteúdo e ferramentas (R$/mês) | C109: 3000 | D109: 15000 | E109: 60000 | F109: 140000 | G109: 250000 | I109: Reduzido pela agência da Shaiane, mas não eliminado.
A110: Início do marketing recorrente | B110: 46296
A111: Propaganda de lançamento — valor único (R$) | B111: 25000
A112: Mês da propaganda de lançamento | B112: 46296
...

Sheet Ajuste Mensal
A1: AJUSTE MENSAL — SOBREPOR O DRIVER ANUAL EM UM MÊS ESPECÍFICO
A2: Tudo em branco: o modelo roda só com as premissas anuais. Digite em um mês e aquele mês passa a usar o que você digitou. A coluna TOTAL conta quantos meses estão sobrepostos — é o jeito rápido de ver se sobrou alguma célula esquecida.
A4: Linha do tempo | B4: 46023 | C4: 46054 | D4: 46082 | E4: 46113 | F4: 46143 | G4: 46174 | H4: 46204 | I4: 46235 | J4: 46266 | K4: 46296 | L4: 46327 | M4: 46357 | N4: 46388 | O4: 46419 | P4: 46447 | Q4: 46478 | R4: 46508 | S4: 46539 | T4: 46569 | U4: 46600 | V4: 46631 | W4: 46661 | X4: 46692 | Y4: 46722 | Z4: 46753 | AA4: 46784 | AB4: 46813 | AC4: 46844 | AD4: 46874 | AE4: 46905 | AF4: 46935 | AG4: 46966 | AH4: 46997 | AI4: 47027 | AJ4: 47058 | AK4: 47088 | AL4: 47119 | AM4: 47150 | AN4: 47178 | AO4: 47209 | AP4: 47239 | AQ4: 47270 | AR4: 47300 | AS4: 47331 | AT4: 47362 | AU4: 47392 | AV4: 47423 | AW4: 47453 | AX4: 47484 | AY4: 47515 | AZ4: 47543 | BA4: 47574 | BB4: 47604 | BC4: 47635 | BD4: 47665 | BE4: 47696 | BF4: 47727 | BG4: 47757 | BH4: 47788 | BI4: 47818 | BJ4: TOTAL | BK4: % / Nota
A5: Mês nº | B5: 1 | C5: 2 | D5: 3 | E5: 4 | F5: 5 | G5: 6 | H5: 7 | I5: 8 | J5: 9 | K5: 10 | L5: 11 | M5: 12 | N5: 13 | O5: 14 | P5: 15 | Q5: 16 | R5: 17 | S5: 18 | T5: 19 | U5: 20 | V5: 21 | W5: 22 | X5: 23 | Y5: 24 | Z5: 25 | AA5: 26 | AB5: 27 | AC5: 28 | AD5: 29 | AE5: 30 | AF5: 31 | AG5: 32 | AH5: 33 | AI5: 34 | AJ5: 35 | AK5: 36 | AL5: 37 | AM5: 38 | AN5: 39 | AO5: 40 | AP5: 41 | AQ5: 42 | AR5: 43 | AS5: 44 | AT5: 45 | AU5: 46 | AV5: 47 | AW5: 48 | AX5: 49 | AY5: 50 | AZ5: 51 | BA5: 52 | BB5: 53 | BC5: 54 | BD5: 55 | BE5: 56 | BF5: 57 | BG5: 58 | BH5: 59 | BI5: 60
A6: Ano | B6: =YEAR(B4) -> 2026 | C6: =YEAR(C4) -> 2026 | D6: =YEAR(D4) -> 2026 | E6: =YEAR(E4) -> 2026 | F6: =YEAR(F4) -> 2026 | G6: =YEAR(G4) -> 2026 | H6: =YEAR(H4) -> 2026 | I6: =YEAR(I4) -> 2026 | ... BI6: =YEAR(BI4) -> 2030
A7: Índice do ano (auxiliar) | B7: =MATCH(B6,Premissas!$C$5:$G$5,0) -> 1 | C7: =MATCH(C6,Premissas!$C$5:$G$5,0) -> 1 | D7: =MATCH(D6,Premissas!$C$5:$G$5,0) -> 1 | E7: =MATCH(E6,Premissas!$C$5:$G$5,0) -> 1 | F7: =MATCH(F6,Premissas!$C$5:$G$5,0) -> 1 | G7: =MATCH(G6,Premissas!$C$5:$G$5,0) -> 1 | H7: =MATCH(H6,Premissas!$C$5:$G$5,0) -> 1 | I7: =MATCH(I6,Premissas!$C$5:$G$5,0) -> 1 | ... BI7: =MATCH(BI6,Premissas!$C$5:$G$5,0) -> 5
A8: • Serve para os primeiros meses, quando o número do ano não descreve o mês: a captação do mês do lançamento, a conversão do primeiro mês de loja, o CAC de uma campanha pontual, o mês em que a nuvem muda de plano.
A9: • Também serve para fechar o passado: conforme os meses acontecem, digite o realizado e o modelo projeta só o que falta.
A10: • Zero é um valor, não um branco. Digitar 0 em 'novos usuários' força um mês sem captação; deixar vazio usa o driver do ano.
A12: CENÁRIO 1 — CONSERVADOR
A13: Novos usuários captados no mês | BJ13: =COUNT(B13:BI13) -> 0 | BK13: Meses sobrepostos (coluna TOTAL à esquerda).
A14: Churn mensal da base | BJ14: =COUNT(B14:BI14) -> 0 | BK14: Meses sobrepostos (coluna TOTAL à esquerda).
A15: Taxa de conversão — patamar, antes da rampa | BJ15: =COUNT(B15:BI15) -> 0 | BK15: Meses sobrepostos (coluna TOTAL à esquerda).
A16: CAC — custo por usuário captado | BJ16: =COUNT(B16:BI16) -> 0 | BK16: Meses sobrepostos (coluna TOTAL à esquerda).
A18: CENÁRIO 2 — PROVÁVEL
A19: Novos usuários captados no mês | BJ19: =COUNT(B19:BI19) -> 0 | BK19: Meses sobrepostos (coluna TOTAL à esquerda).
A20: Churn mensal da base | BJ20: =COUNT(B20:BI20) -> 0 | BK20: Meses sobrepostos (coluna TOTAL à esquerda).
A21: Taxa de conversão — patamar, antes da rampa | BJ21: =COUNT(B21:BI21) -> 0 | BK21: Meses sobrepostos (coluna TOTAL à esquerda).
A22: CAC — custo por usuário captado | BJ22: =COUNT(B22:BI22) -> 0 | BK22: Meses sobrepostos (coluna TOTAL à esquerda).
A24: CENÁRIO 3 — AGRESSIVO
A25: Novos usuários captados no mês | BJ25: =COUNT(B25:BI25) -> 0 | BK25: Meses sobrepostos (coluna TOTAL à esquerda).
A26: Churn mensal da base | BJ26: =COUNT(B26:BI26) -> 0 | BK26: Meses sobrepostos (coluna TOTAL à esquerda).
A27: Taxa de conversão — patamar, antes da rampa | BJ27: =COUNT(B27:BI27) -> 0 | BK27: Meses sobrepostos (coluna TOTAL à esquerda).
A28: CAC — custo por usuário captado | BJ28: =COUNT(B28:BI28) -> 0 | BK28: Meses sobrepostos (coluna TOTAL à esquerda).
A30: CUSTOS — VALEM PARA OS TRÊS CENÁRIOS
A31: Nuvem — custo fixo mensal | BJ31: =COUNT(B31:BI31) -> 0 | BK31: Continua respeitando a data de início dos custos de nuvem, em Premissas.
A32: Marketing recorrente | BJ32: =COUNT(B32:BI32) -> 0 | BK32: Continua respeitando a data de início do marketing recorrente.
A33: Despesas administrativas | BJ33: =COUNT(B33:BI33) -> 0 | BK33: Continua respeitando a data de início das despesas administrativas.
A36: CONFERÊNCIA — SOBREPOSIÇÕES QUE O MODELO VAI IGNORAR
A37: ⚠ Novos usuários digitados antes do lançamento | B37: =SUMPRODUCT((B13:BI13<>"")*(B$4:BI$4<Premissas!$B$13))+SUMPRODUCT((B19:BI19<>"")*(B$4:BI$4<Premissas!$B$13))+SUMPRODUCT((B25:BI25<>"")*(B$4:BI$4<Premissas!$B$13)) -> 0 | C37: =IF(B37=0,"✔ nada ignorado","⚠ "&B37&" célula(s) sem efeito — mude a data de início em Premissas ou apague o valor") -> ✔ nada ignorado
A38: ⚠ Conversão digitada antes do lançamento | B38: =SUMPRODUCT((B15:BI15<>"")*(B$4:BI$4<Premissas!$B$13))+SUMPRODUCT((B21:BI21<>"")*(B$4:BI$4<Premissas!$B$13))+SUMPRODUCT((B27:BI27<>"")*(B$4:BI$4<Premissas!$B$13)) -> 0 | C38: =IF(B38=0,"✔ nada ignorado","⚠ "&B38&" célula(s) sem efeito — mude a data de início em Premissas ou apague o valor") -> ✔ nada ignorado
A39: ⚠ Nuvem fixa digitada antes do início dos custos de nuvem | B39: =SUMPRODUCT((B31:BI31<>"")*(B$4:BI$4<Premissas!$B$102)) -> 0 | C39: =IF(B39=0,"✔ nada ignorado","⚠ "&B39&" célula(s) sem efeito — mude a data de início em Premissas ou apague o valor") -> ✔ nada ignorado
A40: ⚠ Marketing recorrente digitado antes do início previsto | B40: =SUMPRODUCT((B32:BI32<>"")*(B$4:BI$4<Premissas!$B$110)) -> 0 | C40: =IF(B40=0,"✔ nada ignorado","⚠ "&B40&" célula(s) sem efeito — mude a data de início em Premissas ou apague o valor") -> ✔ nada ignorado
A41: ⚠ Administrativas digitadas antes do início previsto | B41: =SUMPRODUCT((B33:BI33<>"")*(B$4:BI$4<Premissas!$B$107)) -> 0 | C41: =IF(B41=0,"✔ nada ignorado","⚠ "&B41&" célula(s) sem efeito — mude a data de início em Premissas ou apague o valor") -> ✔ nada ignorado
A43: O pessoal não está aqui de propósito: a aba PESSOAS já é linha a linha e mês a mês, com data de entrada e de saída de cada pessoa. É lá que se ajusta equipe.

Sheet Pessoas
A1: PESSOAS — QUADRO DE PESSOAL
A2: Uma linha por papel. Edite quantidade, custo, início e fim livremente. Status 'Contratado' entra sempre; 'Plano' só entra se o controle 1 de Premissas estiver em 1. Todo o custo de pessoal do modelo sai daqui.
A4: QUADRO — edite livremente, inclusive as linhas em branco no fim
A5: Função / papel | B5: Tipo | C5: Status | D5: Qtd | E5: Custo mensal por pessoa | F5: Encargos (% sobre CLT) | G5: Custo total mensal | H5: Início | I5: Fim | J5: Classificação
A6: Equipe PJ — desenvolvimento do MVP | B6: PJ | C6: Contratado | D6: 1 | E6: 10500 | F6: 0 | G6: =$D6*$E6*(1+$F6) -> 10500 | H6: 46266 | I6: 46296 | J6: Investimento
A7: Desenvolvimento — time base | B7: PJ | C7: Plano | D7: 2 | E7: 9000 | F7: 0 | G7: =$D7*$E7*(1+$F7) -> 18000 | H7: 46388 | I7: 47818 | J7: Despesa
A8: Desenvolvimento — ampliação 2028 (adicional) | B8: PJ | C8: Plano | D8: 3 | E8: 9500 | F8: 0 | G8: =$D8*$E8*(1+$F8) -> 28500 | H8: 46753 | I8: 47818 | J8: Despesa
A9: Desenvolvimento — ampliação 2029 (adicional) | B9: PJ | C9: Plano | D9: 5 | E9: 10000 | F9: 0 | G9: =$D9*$E9*(1+$F9) -> 50000 | H9: 47119 | I9: 47818 | J9: Despesa
A10: Desenvolvimento — ampliação 2030 (adicional) | B10: PJ | C10: Plano | D10: 6 | E10: 10500 | F10: 0 | G10: =$D10*$E10*(1+$F10) -> 63000 | H10: 47484 | I10: 47818 | J10: Despesa
A11: Suporte ao cliente — time base | B11: PJ | C11: Plano | D11: 1 | E11: 3500 | F11: 0 | G11: =$D11*$E11*(1+$F11) -> 3500 | H11: 46388 | I11: 47818 | J11: Despesa
A12: Suporte — ampliação 2028 (adicional) | B12: PJ | C12: Plano | D12: 3 | E12: 3500 | F12: 0 | G12: =$D12*$E12*(1+$F12) -> 10500 | H12: 46753 | I12: 47818 | J12: Despesa
A13: Suporte — ampliação 2029 (adicional) | B13: PJ | C13: Plano | D13: 6 | E13: 3800 | F13: 0 | G13: =$D13*$E13*(1+$F13) -> 22800 | H13: 47119 | I13: 47818 | J13: Despesa
A14: Suporte — ampliação 2030 (adicional) | B14: PJ | C14: Plano | D14: 8 | E14: 4000 | F14: 0 | G14: =$D14*$E14*(1+$F14) -> 32000 | H14: 47484 | I14: 47818 | J14: Despesa
A15: Growth e marketing | B15: PJ | C15: Plano | D15: 1 | E15: 6000 | F15: 0 | G15: =$D15*$E15*(1+$F15) -> 6000 | H15: 46388 | I15: 47818 | J15: Despesa
A16: Growth — ampliação 2028 (adicional) | B16: PJ | C16: Plano | D16: 2 | E16: 7000 | F16: 0 | G16: =$D16*$E16*(1+$F16) -> 14000 | H16: 46753 | I16: 47818 | J16: Despesa
A17: Growth — ampliação 2029 (adicional) | B17: PJ | C17: Plano | D17: 3 | E17: 8000 | F17: 0 | G17: =$D17*$E17*(1+$F17) -> 24000 | H17: 47119 | I17: 47818 | J17: Despesa
... A24: (exemplo) Contratação CLT | B24: CLT | C24: Plano | D24: 0 | E24: 8000 | F24: 0.7 | G24: =$D24*$E24*(1+$F24) -> 0 | H24: 46753 | I24: 47818 | J24: Despesa
B25: PJ | C25: Plano | D25: 0 | E25: 0 | F25: 0 | G25: =$D25*$E25*(1+$F25) -> 0 | H25: 46388 | I25: 47818 | J25: Despesa
B26: PJ | C26: Plano | D26: 0 | E26: 0 | F26: 0 | G26: =$D26*$E26*(1+$F26) -> 0 | H26: 46388 | I26: 47818 | J26: Despesa
B27: PJ | C27: Plano | D27: 0 | E27: 0 | F27: 0 | G27: =$D27*$E27*(1+$F27) -> 0 | H27: 46388 | I27: 47818 | J27: Despesa
B28: PJ | C28: Plano | D28: 0 | E28: 0 | F28: 0 | G28: =$D28*$E28*(1+$F28) -> 0 | H28: 46388 | I28: 47818 | J28: Despesa
B29: PJ | C29: Plano | D29: 0 | E29: 0 | F29: 0 | G29: =$D29*$E29*(1+$F29) -> 0 | H29: 46388 | I29: 47818 | J29: Despesa
B30: PJ | C30: Plano | D30: 0 | E30: 0 | F30: 0 | G30: =$D30*$E30*(1+$F30) -> 0 | H30: 46388 | I30: 47818 | J30: Despesa
B31: PJ | C31: Plano | D31: 0 | E31: 0 | F31: 0 | G31: =$D31*$E31*(1+$F31) -> 0 | H31: 46388 | I31: 47818 | J31: Despesa
B32: PJ | C32: Plano | D32: 0 | E32: 0 | F32: 0 | G32: =$D32*$E32*(1+$F32) -> 0 | H32: 46388 | I32: 47818 | J32: Despesa
A33: TOTAL DO QUADRO (custo mensal se todas as linhas estivessem ativas) | G33: =SUM(G6:G32) -> 399800
A34: Azul-escuro/verde = já contratado · azul-claro = plano sugerido, a validar. Coluna 'Custo total mensal' é calculada.
A36: Linha do tempo | B36: 46023 | C36: 46054 | D36: 46082 | E36: 46113 | F36: 46143 | G36: 46174 | H36: 46204 | I36: 46235 | J36: 46266 | K36: 46296 | L36: 46327 | M36: 46357 | N36: 46388 | O36: 46419 | P36: 46447 | Q36: 46478 | R36: 46508 | S36: 46539 | T36: 46569 | U36: 46600 | V36: 46631 | W36: 46661 | X36: 46692 | Y36: 46722 | Z36: 46753 | AA36: 46784 | AB36: 46813 | AC36: 46844 | AD36: 46874 | AE36: 46905 | AF36: 46935 | AG36: 46966 | AH36: 46997 | AI36: 47027 | AJ36: 47058 | AK36: 47088 | AL36: 47119 | AM36: 47150 | AN36: 47178 | AO36: 47209 | AP36: 47239 | AQ36: 47270 | AR36: 47300 | AS36: 47331 | AT36: 47362 | AU36: 47392 | AV36: 47423 | AW36: 47453 | AX36: 47484 | AY36: 47515 | AZ36: 47543 | BA36: 47574 | BB36: 47604 | BC36: 47635 | BD36: 47665 | BE36: 47696 | BF36: 47727 | BG36: 47757 | BH36: 47788 | BI36: 47818 | BJ36: TOTAL | BK36: % / Nota
A37: Mês nº | B37: 1 | C37: 2 | D37: 3 | E37: 4 | F37: 5 | G37: 6 | H37: 7 | I37: 8 | J37: 9 | K37: 10 | L37: 11 | M37: 12 | N37: 13 | O37: 14 | P37: 15 | Q37: 16 | R37: 17 | S37: 18 | T37: 19 | U37: 20 | V37: 21 | W37: 22 | X37: 23 | Y37: 24 | Z37: 25 | AA37: 26 | AB37: 27 | AC37: 28 | AD37: 29 | AE37: 30 | AF37: 31 | AG37: 32 | AH37: 33 | AI37: 34 | AJ37: 35 | AK37: 36 | AL37: 37 | AM37: 38 | AN37: 39 | AO37: 40 | AP37: 41 | AQ37: 42 | AR37: 43 | AS37: 44 | AT37: 45 | AU37: 46 | AV37: 47 | AW37: 48 | AX37: 49 | AY37: 50 | AZ37: 51 | BA37: 52 | BB37: 53 | BC37: 54 | BD37: 55 | BE37: 56 | BF37: 57 | BG37: 58 | BH37: 59 | BI37: 60
A38: Ano | B38: =YEAR(B36) -> 2026 | C38: =YEAR(C36) -> 2026 | D38: =YEAR(D36) -> 2026 | E38: =YEAR(E36) -> 2026 | F38: =YEAR(F36) -> 2026 | G38: =YEAR(G36) -> 2026 | H38: =YEAR(H36) -> 2026 | I38: =YEAR(I36) -> 2026 | ... BI38: =YEAR(BI36) -> 2030
A39: Índice do ano (auxiliar) | B39: =MATCH(B38,Premissas!$C$5:$G$5,0) -> 1 | C39: =MATCH(C38,Premissas!$C$5:$G$5,0) -> 1 | D39: =MATCH(D38,Premissas!$C$5:$G$5,0) -> 1 | E39: =MATCH(E38,Premissas!$C$5:$G$5,0) -> 1 | F39: =MATCH(F38,Premissas!$C$5:$G$5,0) -> 1 | G39: =MATCH(G38,Premissas!$C$5:$G$5,0) -> 1 | H39: =MATCH(H38,Premissas!$C$5:$G$5,0) -> 1 | I39: =MATCH(I38,Premissas!$C$5:$G$5,0) -> 1 | ... BI39: =MATCH(BI38,Premissas!$C$5:$G$5,0) -> 5
A40: CUSTO MENSAL DE PESSOAL
A41: Pessoas ativas no mês (headcount) | B41: =SUMPRODUCT(($H$6:$H$32<=B$36)*($I$6:$I$32>=B$36)*(($C$6:$C$32="Contratado")+($C$6:$C$32="Plano")*Premissas!$B$8)*$D$6:$D$32) -> 0 | C41: =SUMPRODUCT(($H$6:$H$32<=C$36)*($I$6:$I$32>=C$36)*(($C$6:$C$32="Contratado")+($C$6:$C$32="Plano")*Premissas!$B$8)*$D$6:$D$32) -> 0 | D41: =SUMPRODUCT(($H$6:$H$32<=D$36)*($I$6:$I$32>=D$36)*(($C$6:$C$32="Contratado")+($C$6:$C$32="Plano")*Premissas!$B$8)*$D$6:$D$32) -> 0 | E41: =SUMPRODUCT(($H$6:$H$32<=E$36)*($I$6:$I$32>=E$36)*(($C$6:$C$32="Contratado")+($C$6:$C$32="Plano")*Premissas!$B$8)*$D$6:$D$32) -> 0 | F41: =SUMPRODUCT(($H$6:$H$32<=F$36)*($I$6:$I$32>=F$36)*(($C$6:$C$32="Contratado")+($C$6:$C$32="Plano")*Premissas!$B$8)*$D$6:$D$32) -> 0 | G41: =SUMPRODUCT(($H$6:$H$32<=G$36)*($I$6:$I$32>=G$36)*(($C$6:$C$32="Contratado")+($C$6:$C$32="Plano")*Premissas!$B$8)*$D$6:$D$32) -> 0 | H41: =SUMPRODUCT(($H$6:$H$32<=H$36)*($I$6:$I$32>=H$36)*(($C$6:$C$32="Contratado")+($C$6:$C$32="Plano")*Premissas!$B$8)*$D$6:$D$32) -> 0 | I41: =SUMPRODUCT(($H$6:$H$32<=I$36)*($I$6:$I$32>=I$36)*(($C$6:$C$32="Contratado")+($C$6:$C$32="Plano")*Premissas!$B$8)*$D$6:$D$32) -> 0 | ... BI41: =SUMPRODUCT(($H$6:$H$32<=BI$36)*($I$6:$I$32>=BI$36)*(($C$6:$C$32="Contratado")+($C$6:$C$32="Plano")*Premissas!$B$8)*$D$6:$D$32) -> 50 | BJ41: =BI41 -> 50 | BK41: Quadro em dez/2030, não soma.
A42: Equipe PJ (despesa) | B42: =SUMPRODUCT(($B$6:$B$32="PJ")*($J$6:$J$32="Despesa")*($H$6:$H$32<=B$36)*($I$6:$I$32>=B$36)*(($C$6:$C$32="Contratado")+($C$6:$C$32="Plano")*Premissas!$B$8)*$G$6:$G$32) -> 0 | C42: =SUMPRODUCT(($B$6:$B$32="PJ")*($J$6:$J$32="Despesa")*($H$6:$H$32<=C$36)*($I$6:$I$32>=C$36)*(($C$6:$C$32="Contratado")+($C$6:$C$32="Plano")*Premissas!$B$8)*$G$6:$G$32) -> 0 | D42: =SUMPRODUCT(($B$6:$B$32="PJ")*($J$6:$J$32="Despesa")*($H$6:$H$32<=D$36)*($I$6:$I$32>=D$36)*(($C$6:$C$32="Contratado")+($C$6:$C$32="Plano")*Premissas!$B$8)*$G$6:$G$32) -> 0 | E42: =SUMPRODUCT(($B$6:$B$32="PJ")*($J$6:$J$32="Despesa")*($H$6:$H$32<=E$36)*($I$6:$I$32>=E$36)*(($C$6:$C$32="Contratado")+($C$6:$C$32="Plano")*Premissas!$B$8)*$G$6:$G$32) -> 0 | F42: =SUMPRODUCT(($B$6:$B$32="PJ")*($J$6:$J$32="Despesa")*($H$6:$H$32<=F$36)*($I$6:$I$32>=F$36)*(($C$6:$C$32="Contratado")+($C$6:$C$32="Plano")*Premissas!$B$8)*$G$6:$G$32) -> 0 | G42: =SUMPRODUCT(($B$6:$B$32="PJ")*($J$6:$J$32="Despesa")*($H$6:$H$32<=G$36)*($I$6:$I$32>=G$36)*(($C$6:$C$32="Contratado")+($C$6:$C$32="Plano")*Premissas!$B$8)*$G$6:$G$32) -> 0 | H42: =SUMPRODUCT(($B$6:$B$32="PJ")*($J$6:$J$32="Despesa")*($H$6:$H$32<=H$36)*($I$6:$I$32>=H$36)*(($C$6:$C$32="Contratado")+($C$6:$C$32="Plano")*Premissas!$B$8)*$G$6:$G$32) -> 0 | I42: =SUMPRODUCT(($B$6:$B$32="PJ")*($J$6:$J$32="Despesa")*($H$6:$H$32<=I$36)*($I$6:$I$32>=I$36)*(($C$6:$C$32="Contratado")+($C$6:$C$32="Plano")*Premissas!$B$8)*$G$6:$G$32) -> 0 | ... BI42: =SUMPRODUCT(($B$6:$B$32="PJ")*($J$6:$J$32="Despesa")*($H$6:$H$32<=BI$36)*($I$6:$I$32>=BI$36)*(($C$6:$C$32="Contratado")+($C$6:$C$32="Plano")*Premissas!$B$8)*$G$6:$G$32) -> 342300 | BJ42: =SUM(B42:BI42) -> 8323200
A43: Equipe CLT — salários e encargos (despesa) | B43: =SUMPRODUCT(($B$6:$B$32="CLT")*($J$6:$J$32="Despesa")*($H$6:$H$32<=B$36)*($I$6:$I$32>=B$36)*(($C$6:$C$32="Contratado")+($C$6:$C$32="Plano")*Premissas!$B$8)*$G$6:$G$32) -> 0 | C43: =SUMPRODUCT(($B$6:$B$32="CLT")*($J$6:$J$32="Despesa")*($H$6:$H$32<=C$36)*($I$6:$I$32>=C$36)*(($C$6:$C$32="Contratado")+($C$6:$C$32="Plano")*Premissas!$B$8)*$G$6:$G$32) -> 0 | D43: =SUMPRODUCT(($B$6:$B$32="CLT")*($J$6:$J$32="Despesa")*($H$6:$H$32<=D$36)*($I$6:$I$32>=D$36)*(($C$6:$C$32="Contratado")+($C$6:$C$32="Plano")*Premissas!$B$8)*$G$6:$G$32) -> 0 | E43: =SUMPRODUCT(($B$6:$B$32="CLT")*($J$6:$J$32="Despesa")*($H$6:$H$32<=E$36)*($I$6:$I$32>=E$36)*(($C$6:$C$32="Contratado")+($C$6:$C$32="Plano")*Premissas!$B$8)*$G$6:$G$32) -> 0 | F43: =SUMPRODUCT(($B$6:$B$32="CLT")*($J$6:$J$32="Despesa")*($H$6:$H$32<=F$36)*($I$6:$I$32>=F$36)*(($C$6:$C$32="Contratado")+($C$6:$C$32="Plano")*Premissas!$B$8)*$G$6:$G$32) -> 0 | G43: =SUMPRODUCT(($B$6:$B$32="CLT")*($J$6:$J$32="Despesa")*($H$6:$H$32<=G$36)*($I$6:$I$32>=G$36)*(($C$6:$C$32="Contratado")+($C$6:$C$32="Plano")*Premissas!$B$8)*$G$6:$G$32) -> 0 | H43: =SUMPRODUCT(($B$6:$B$32="CLT")*($J$6:$J$32="Despesa")*($H$6:$H$32<=H$36)*($I$6:$I$32>=H$36)*(($C$6:$C$32="Contratado")+($C$6:$C$32="Plano")*Premissas!$B$8)*$G$6:$G$32) -> 0 | I43: =SUMPRODUCT(($B$6:$B$32="CLT")*($J$6:$J$32="Despesa")*($H$6:$H$32<=I$36)*($I$6:$I$32>=I$36)*(($C$6:$C$32="Contratado")+($C$6:$C$32="Plano")*Premissas!$B$8)*$G$6:$G$32) -> 0 | ... BI43: =SUMPRODUCT(($B$6:$B$32="CLT")*($J$6:$J$32="Despesa")*($H$6:$H$32<=BI$36)*($I$6:$I$32>=BI$36)*(($C$6:$C$32="Contratado")+($C$6:$C$32="Plano")*Premissas!$B$8)*$G$6:$G$32) -> 0 | BJ43: =SUM(B43:BI43) -> 0
A44: Pró-labore dos sócios (despesa) | B44: =SUMPRODUCT(($B$6:$B$32="Sócio")*($J$6:$J$32="Despesa")*($H$6:$H$32<=B$36)*($I$6:$I$32>=B$36)*(($C$6:$C$32="Contratado")+($C$6:$C$32="Plano")*Premissas!$B$8)*$G$6:$G$32) -> 0 | C44: =SUMPRODUCT(($B$6:$B$32="Sócio")*($J$6:$J$32="Despesa")*($H$6:$H$32<=C$36)*($I$6:$I$32>=C$36)*(($C$6:$C$32="Contratado")+($C$6:$C$32="Plano")*Premissas!$B$8)*$G$6:$G$32) -> 0 | D44: =SUMPRODUCT(($B$6:$B$32="Sócio")*($J$6:$J$32="Despesa")*($H$6:$H$32<=D$36)*($I$6:$I$32>=D$36)*(($C$6:$C$32="Contratado")+($C$6:$C$32="Plano")*Premissas!$B$8)*$G$6:$G$32) -> 0 | E44: =SUMPRODUCT(($B$6:$B$32="Sócio")*($J$6:$J$32="Despesa")*($H$6:$H$32<=E$36)*($I$6:$I$32>=E$36)*(($C$6:$C$32="Contratado")+($C$6:$C$32="Plano")*Premissas!$B$8)*$G$6:$G$32) -> 0 | F44: =SUMPRODUCT(($B$6:$B$32="Sócio")*($J$6:$J$32="Despesa")*($H$6:$H$32<=F$36)*($I$6:$I$32>=F$36)*(($C$6:$C$32="Contratado")+($C$6:$C$32="Plano")*Premissas!$B$8)*$G$6:$G$32) -> 0 | G44: =SUMPRODUCT(($B$6:$B$32="Sócio")*($J$6:$J$32="Despesa")*($H$6:$H$32<=G$36)*($I$6:$I$32>=G$36)*(($C$6:$C$32="Contratado")+($C$6:$C$32="Plano")*Premissas!$B$8)*$G$6:$G$32) -> 0 | H44: =SUMPRODUCT(($B$6:$B$32="Sócio")*($J$6:$J$32="Despesa")*($H$6:$H$32<=H$36)*($I$6:$I$32>=H$36)*(($C$6:$C$32="Contratado")+($C$6:$C$32="Plano")*Premissas!$B$8)*$G$6:$G$32) -> 0 | I44: =SUMPRODUCT(($B$6:$B$32="Sócio")*($J$6:$J$32="Despesa")*($H$6:$H$32<=I$36)*($I$6:$I$32>=I$36)*(($C$6:$C$32="Contratado")+($C$6:$C$32="Plano")*Premissas!$B$8)*$G$6:$G$32) -> 0 | ... BI44: =SUMPRODUCT(($B$6:$B$32="Sócio")*($J$6:$J$32="Despesa")*($H$6:$H$32<=BI$36)*($I$6:$I$32>=BI$36)*(($C$6:$C$32="Contratado")+($C$6:$C$32="Plano")*Premissas!$B$8)*$G$6:$G$32) -> 32000 | BJ44: =SUM(B44:BI44) -> 1128000
A45: TOTAL DE PESSOAL — DESPESA | B45: =SUMPRODUCT(($J$6:$J$32="Despesa")*($H$6:$H$32<=B$36)*($I$6:$I$32>=B$36)*(($C$6:$C$32="Contratado")+($C$6:$C$32="Plano")*Premissas!$B$8)*$G$6:$G$32) -> 0 | C45: =SUMPRODUCT(($J$6:$J$32="Despesa")*($H$6:$H$32<=C$36)*($I$6:$I$32>=C$36)*(($C$6:$C$32="Contratado")+($C$6:$C$32="Plano")*Premissas!$B$8)*$G$6:$G$32) -> 0 | D45: =SUMPRODUCT(($J$6:$J$32="Despesa")*($H$6:$H$32<=D$36)*($I$6:$I$32>=D$36)*(($C$6:$C$32="Contratado")+($C$6:$C$32="Plano")*Premissas!$B$8)*$G$6:$G$32) -> 0 | E45: =SUMPRODUCT(($J$6:$J$32="Despesa")*($H$6:$H$32<=E$36)*($I$6:$I$32>=E$36)*(($C$6:$C$32="Contratado")+($C$6:$C$32="Plano")*Premissas!$B$8)*$G$6:$G$32) -> 0 | F45: =SUMPRODUCT(($J$6:$J$32="Despesa")*($H$6:$H$32<=F$36)*($I$6:$I$32>=F$36)*(($C$6:$C$32="Contratado")+($C$6:$C$32="Plano")*Premissas!$B$8)*$G$6:$G$32) -> 0 | G45: =SUMPRODUCT(($J$6:$J$32="Despesa")*($H$6:$H$32<=G$36)*($I$6:$I$32>=G$36)*(($C$6:$C$32="Contratado")+($C$6:$C$32="Plano")*Premissas!$B$8)*$G$6:$G$32) -> 0 | H45: =SUMPRODUCT(($J$6:$J$32="Despesa")*($H$6:$H$32<=H$36)*($I$6:$I$32>=H$36)*(($C$6:$C$32="Contratado")+($C$6:$C$32="Plano")*Premissas!$B$8)*$G$6:$G$32) -> 0 | I45: =SUMPRODUCT(($J$6:$J$32="Despesa")*($H$6:$H$32<=I$36)*($I$6:$I$32>=I$36)*(($C$6:$C$32="Contratado")+($C$6:$C$32="Plano")*Premissas!$B$8)*$G$6:$G$32) -> 0 | ... BI45: =SUMPRODUCT(($J$6:$J$32="Despesa")*($H$6:$H$32<=BI$36)*($I$6:$I$32>=BI$36)*(($C$6:$C$32="Contratado")+($C$6:$C$32="Plano")*Premissas!$B$8)*$G$6:$G$32) -> 374300 | BJ45: =SUM(B45:BI45) -> 9451200
A46: Pessoal capitalizado — INVESTIMENTO | B46: =SUMPRODUCT(($J$6:$J$32="Investimento")*($H$6:$H$32<=B$36)*($I$6:$I$32>=B$36)*(($C$6:$C$32="Contratado")+($C$6:$C$32="Plano")*Premissas!$B$8)*$G$6:$G$32) -> 0 | C46: =SUMPRODUCT(($J$6:$J$32="Investimento")*($H$6:$H$32<=C$36)*($I$6:$I$32>=C$36)*(($C$6:$C$32="Contratado")+($C$6:$C$32="Plano")*Premissas!$B$8)*$G$6:$G$32) -> 0 | D46: =SUMPRODUCT(($J$6:$J$32="Investimento")*($H$6:$H$32<=D$36)*($I$6:$I$32>=D$36)*(($C$6:$C$32="Contratado")+($C$6:$C$32="Plano")*Premissas!$B$8)*$G$6:$G$32) -> 0 | E46: =SUMPRODUCT(($J$6:$J$32="Investimento")*($H$6:$H$32<=E$36)*($I$6:$I$32>=E$36)*(($C$6:$C$32="Contratado")+($C$6:$C$32="Plano")*Premissas!$B$8)*$G$6:$G$32) -> 0 | F46: =SUMPRODUCT(($J$6:$J$32="Investimento")*($H$6:$H$32<=F$36)*($I$6:$I$32>=F$36)*(($C$6:$C$32="Contratado")+($C$6:$C$32="Plano")*Premissas!$B$8)*$G$6:$G$32) -> 0 | G46: =SUMPRODUCT(($J$6:$J$32="Investimento")*($H$6:$H$32<=G$36)*($I$6:$I$32>=G$36)*(($C$6:$C$32="Contratado")+($C$6:$C$32="Plano")*Premissas!$B$8)*$G$6:$G$32) -> 0 | H46: =SUMPRODUCT(($J$6:$J$32="Investimento")*($H$6:$H$32<=H$36)*($I$6:$I$32>=H$36)*(($C$6:$C$32="Contratado")+($C$6:$C$32="Plano")*Premissas!$B$8)*$G$6:$G$32) -> 0 | I46: =SUMPRODUCT(($J$6:$J$32="Investimento")*($H$6:$H$32<=I$36)*($I$6:$I$32>=I$36)*(($C$6:$C$32="Contratado")+($C$6:$C$32="Plano")*Premissas!$B$8)*$G$6:$G$32) -> 0 | ... BI46: =SUMPRODUCT(($J$6:$J$32="Investimento")*($H$6:$H$32<=BI$36)*($I$6:$I$32>=BI$36)*(($C$6:$C$32="Contratado")+($C$6:$C$32="Plano")*Premissas!$B$8)*$G$6:$G$32) -> 0 | BJ46: =SUM(B46:BI46) -> 21000 | BK46: Vai para a aba Investimentos e é amortizado em 60 meses.
A47: Folha que conta para o Fator R (CLT + pró-labore) | B47: =SUMPRODUCT((($B$6:$B$32="CLT")+($B$6:$B$32="Sócio"))*($H$6:$H$32<=B$36)*($I$6:$I$32>=B$36)*(($C$6:$C$32="Contratado")+($C$6:$C$32="Plano")*Premissas!$B$8)*$G$6:$G$32) -> 0 | C47: =SUMPRODUCT((($B$6:$B$32="CLT")+($B$6:$B$32="Sócio"))*($H$6:$H$32<=C$36)*($I$6:$I$32>=C$36)*(($C$6:$C$32="Contratado")+($C$6:$C$32="Plano")*Premissas!$B$8)*$G$6:$G$32) -> 0 | D47: =SUMPRODUCT((($B$6:$B$32="CLT")+($B$6:$B$32="Sócio"))*($H$6:$H$32<=D$36)*($I$6:$I$32>=D$36)*(($C$6:$C$32="Contratado")+($C$6:$C$32="Plano")*Premissas!$B$8)*$G$6:$G$32) -> 0 | E47: =SUMPRODUCT((($B$6:$B$32="CLT")+($B$6:$B$32="Sócio"))*($H$6:$H$32<=E$36)*($I$6:$I$32>=E$36)*(($C$6:$C$32="Contratado")+($C$6:$C$32="Plano")*Premissas!$B$8)*$G$6:$G$32) -> 0 | F47: =SUMPRODUCT((($B$6:$B$32="CLT")+($B$6:$B$32="Sócio"))*($H$6:$H$32<=F$36)*($I$6:$I$32>=F$36)*(($C$6:$C$32="Contratado")+($C$6:$C$32="Plano")*Premissas!$B$8)*$G$6:$G$32) -> 0 | G47: =SUMPRODUCT((($B$6:$B$32="CLT")+($B$6:$B$32="Sócio"))*($H$6:$H$32<=G$36)*($I$6:$I$32>=G$36)*(($C$6:$C$32="Contratado")+($C$6:$C$32="Plano")*Premissas!$B$8)*$G$6:$G$32) -> 0 | H47: =SUMPRODUCT((($B$6:$B$32="CLT")+($B$6:$B$32="Sócio"))*($H$6:$H$32<=H$36)*($I$6:$I$32>=H$36)*(($C$6:$C$32="Contratado")+($C$6:$C$32="Plano")*Premissas!$B$8)*$G$6:$G$32) -> 0 | I47: =SUMPRODUCT((($B$6:$B$32="CLT")+($B$6:$B$32="Sócio"))*($H$6:$H$32<=I$36)*($I$6:$I$32>=I$36)*(($C$6:$C$32="Contratado")+($C$6:$C$32="Plano")*Premissas!$B$8)*$G$6:$G$32) -> 0 | ... BI47: =SUMPRODUCT((($B$6:$B$32="CLT")+($B$6:$B$32="Sócio"))*($H$6:$H$32<=BI$36)*($I$6:$I$32>=BI$36)*(($C$6:$C$32="Contratado")+($C$6:$C$32="Plano")*Premissas!$B$8)*$G$6:$G$32) -> 32000 | BJ47: =SUM(B47:BI47) -> 1128000 | BK47: Pagamento a PJ não entra no Fator R.
A49: RESUMO ANUAL E FATOR R
B50: 2026 | C50: 2027 | D50: 2028 | E50: 2029 | F50: 2030
A51: Custo total de pessoal (despesa) | B51: =SUMIFS($B$45:$BI$45,$B$38:$BI$38,B$50) -> 0 | C51: =SUMIFS($B$45:$BI$45,$B$38:$BI$38,C$50) -> 510000 | D51: =SUMIFS($B$45:$BI$45,$B$38:$BI$38,D$50) -> 1410000 | E51: =SUMIFS($B$45:$BI$45,$B$38:$BI$38,E$50) -> 3039600 | F51: =SUMIFS($B$45:$BI$45,$B$38:$BI$38,F$50) -> 4491600
A52: Pessoal capitalizado (investimento) | B52: =SUMIFS($B$46:$BI$46,$B$38:$BI$38,B$50) -> 21000 | C52: =SUMIFS($B$46:$BI$46,$B$38:$BI$38,C$50) -> 0 | D52: =SUMIFS($B$46:$BI$46,$B$38:$BI$38,D$50) -> 0 | E52: =SUMIFS($B$46:$BI$46,$B$38:$BI$38,E$50) -> 0 | F52: =SUMIFS($B$46:$BI$46,$B$38:$BI$38,F$50) -> 0
A53: Folha do Fator R (CLT + pró-labore) | B53: =SUMIFS($B$47:$BI$47,$B$38:$BI$38,B$50) -> 0 | C53: =SUMIFS($B$47:$BI$47,$B$38:$BI$38,C$50) -> 180000 | D53: =SUMIFS($B$47:$BI$47,$B$38:$BI$38,D$50) -> 180000 | E53: =SUMIFS($B$47:$BI$47,$B$38:$BI$38,E$50) -> 384000 | F53: =SUMIFS($B$47:$BI$47,$B$38:$BI$38,F$50) -> 384000
A54: Pessoas ativas em dezembro | B54: =M41 -> 0 | C54: =Y41 -> 7 | D54: =AK41 -> 17 | E54: =AW41 -> 34 | F54: =BI41 -> 50
A55: Receita bruta do ano (cenário ativo) | B55: =SUMIFS(Faturamento!$B$16:$BI$16,Faturamento!$B$6:$BI$6,B$50) -> 39441.8 | C55: =SUMIFS(Faturamento!$B$16:$BI$16,Faturamento!$B$6:$BI$6,C$50) -> 2878342.4 | D55: =SUMIFS(Faturamento!$B$16:$BI$16,Faturamento!$B$6:$BI$6,D$50) -> 8769934.8 | E55: =SUMIFS(Faturamento!$B$16:$BI$16,Faturamento!$B$6:$BI$6,E$50) -> 17990723 | F55: =SUMIFS(Faturamento!$B$16:$BI$16,Faturamento!$B$6:$BI$6,F$50) -> 33253920
A56: FATOR R (folha ÷ receita bruta) | B56: =IFERROR(B53/B55,0) -> 0 | C56: =IFERROR(C53/C55,0) -> 0.062535992 | D56: =IFERROR(D53/D55,0) -> 0.020524668 | E56: =IFERROR(E53/E55,0) -> 0.021344333 | F56: =IFERROR(F53/F55,0) -> 0.011547511
A57: Anexo aplicável | B57: =IF(B56>=0.28,"Anexo III","Anexo V") -> Anexo V | C57: =IF(C56>=0.28,"Anexo III","Anexo V") -> Anexo V | D57: =IF(D56>=0.28,"Anexo III","Anexo V") -> Anexo V | E57: =IF(E56>=0.28,"Anexo III","Anexo V") -> Anexo V | F57: =IF(F56>=0.28,"Anexo III","Anexo V") -> Anexo V
A58: Regime escolhido em Premissas | B58: =CHOOSE(Premissas!$B$23,"Anexo III","Anexo V","Lucro Presumido") -> Anexo V | C58: =CHOOSE(Premissas!$B$23,"Anexo III","Anexo V","Lucro Presumido") -> Anexo V | D58: =CHOOSE(Premissas!$B$23,"Anexo III","Anexo V","Lucro Presumido") -> Anexo V | E58: =CHOOSE(Premissas!$B$23,"Anexo III","Anexo V","Lucro Presumido") -> Anexo V | F58: =CHOOSE(Premissas!$B$23,"Anexo III","Anexo V","Lucro Presumido") -> Anexo V
A59: Escolha compatível com o Fator R? | B59: =IF(Premissas!$B$23=3,"n/a",IF(B58=B57,"✔ SIM","⚠ NÃO")) -> ✔ SIM | C59: =IF(Premissas!$B$23=3,"n/a",IF(C58=C57,"✔ SIM","⚠ NÃO")) -> ✔ SIM | D59: =IF(Premissas!$B$23=3,"n/a",IF(D58=D57,"✔ SIM","⚠ NÃO")) -> ✔ SIM | E59: =IF(Premissas!$B$23=3,"n/a",IF(E58=E57,"✔ SIM","⚠ NÃO")) -> ✔ SIM | F59: =IF(Premissas!$B$23=3,"n/a",IF(F58=F57,"✔ SIM","⚠ NÃO")) -> ✔ SIM
A60: Custo de pessoal ÷ receita bruta | B60: =IFERROR(B51/B55,0) -> 0 | C60: =IFERROR(C51/C55,0) -> 0.17718531 | D60: =IFERROR(D51/D55,0) -> 0.16077656 | E60: =IFERROR(E51/E55,0) -> 0.16895374 | F60: =IFERROR(F51/F55,0) -> 0.13506979
A62: ▸ Como o Fator R funciona
A63: Fator R = (folha CLT + pró-labore dos últimos 12 meses) ÷ receita bruta dos últimos 12 meses. Igual ou acima de 28%, a empresa fica no Anexo III do Simples (alíquota efetiva a partir de 6%). Abaixo, cai no Anexo V (a partir de 15,5%). Pagamento a equipe PJ NÃO entra na conta.
A64: ▸ Por que isso importa para a Oppa
A65: Com o quadro atual — equipe PJ e pró-labore modesto — o Fator R fica bem abaixo de 28%, o que leva ao Anexo V. Migrar parte do time para CLT ou aumentar o pró-labore eleva o custo de folha, mas pode reduzir mais imposto do que custa. Use a linha de exemplo CLT e a aba Tributos para comparar os dois efeitos antes de decidir.
A66: ▸ O que está de fato contratado
A67: Só a equipe PJ do MVP, de setembro a outubro de 2026, R$ 21.000 no total. Todo o resto é plano — desligue no controle 1 de Premissas para ver o modelo sem nenhuma contratação futura.

Sheet Sócios
A1: SÓCIOS — QUANTO SOBRA PARA DIVIDIR
A2: Quanto o negócio gera de lucro, quanto disso pode virar dinheiro no bolso dos sócios, e quanto cabe a cada um. Os percentuais de participação são PLACEHOLDER — troque pelos reais quando o quadro societário estiver fechado.
A4: 1. QUADRO SOCIETÁRIO — preencha quando os percentuais estiverem fechados
A5: ⚠ Os percentuais abaixo são um PLACEHOLDER que apenas reflete o que você disse: fundadores majoritários (52% somados) e investidores com fatias menores. Não vieram de negociação nenhuma. Participação societária depende do valuation acordado em cada rodada, e é diferente da proporção do capital aportado — a coluna da direita mostra o tamanho dessa diferença.
A6: Sócio | B6: Tipo | C6: Participação societária | D6: Fatia do pró-labore | E6: Capital aportado | F6: Proporção do capital | G6: Prêmio sobre o capital
A7: Paulo Kapp | B7: Fundador | C7: 0.13 | D7: 0.25 | E7: =IF($A7="",0,SUMIFS(Aportes!$C$6:$C$37,Aportes!$B$6:$B$37,$A7)+SUMIFS(Aportes!$C$43:$C$50,Aportes!$A$43:$A$50,$A7)) -> 20000 | F7: =IFERROR($E7/$E$20,0) -> 0.1 | G7: =$C7-$F7 -> 0.03
A8: Lucas Medina | B8: Fundador | C8: 0.13 | D8: 0.25 | E8: =IF($A8="",0,SUMIFS(Aportes!$C$6:$C$37,Aportes!$B$6:$B$37,$A8)+SUMIFS(Aportes!$C$43:$C$50,Aportes!$A$43:$A$50,$A8)) -> 20000 | F8: =IFERROR($E8/$E$20,0) -> 0.1 | G8: =$C8-$F8 -> 0.03
A9: Felipe Toescher | B9: Fundador | C9: 0.13 | D9: 0.25 | E9: =IF($A9="",0,SUMIFS(Aportes!$C$6:$C$37,Aportes!$B$6:$B$37,$A9)+SUMIFS(Aportes!$C$43:$C$50,Aportes!$A$43:$A$50,$A9)) -> 20000 | F9: =IFERROR($E9/$E$20,0) -> 0.1 | G9: =$C9-$F9 -> 0.03
A10: Lucas Iung | B10: Fundador | C10: 0.13 | D10: 0.25 | E10: =IF($A10="",0,SUMIFS(Aportes!$C$6:$C$37,Aportes!$B$6:$B$37,$A10)+SUMIFS(Aportes!$C$43:$C$50,Aportes!$A$43:$A$50,$A10)) -> 20000 | F10: =IFERROR($E10/$E$20,0) -> 0.1 | G10: =$C10-$F10 -> 0.03
A11: C-ioT | B11: Investidor | C11: 0.16 | D11: 0 | E11: =IF($A11="",0,SUMIFS(Aportes!$C$6:$C$37,Aportes!$B$6:$B$37,$A11)+SUMIFS(Aportes!$C$43:$C$50,Aportes!$A$43:$A$50,$A11)) -> 40000 | F11: =IFERROR($E11/$E$20,0) -> 0.2 | G11: =$C11-$F11 -> -0.04
A12: Felipe Martinelli | B12: Investidor | C12: 0.16 | D12: 0 | E12: =IF($A12="",0,SUMIFS(Aportes!$C$6:$C$37,Aportes!$B$6:$B$37,$A12)+SUMIFS(Aportes!$C$43:$C$50,Aportes!$A$43:$A$50,$A12)) -> 40000 | F12: =IFERROR($E12/$E$20,0) -> 0.2 | G12: =$C12-$F12 -> -0.04
A13: Shaiane | B13: Investidor | C13: 0.16 | D13: 0 | E13: =IF($A13="",0,SUMIFS(Aportes!$C$6:$C$37,Aportes!$B$6:$B$37,$A13)+SUMIFS(Aportes!$C$43:$C$50,Aportes!$A$43:$A$50,$A13)) -> 40000 | F13: =IFERROR($E13/$E$20,0) -> 0.2 | G13: =$C13-$F13 -> -0.04
B14: Investidor | C14: 0 | D14: 0 | E14: =IF($A14="",0,SUMIFS(Aportes!$C$6:$C$37,Aportes!$B$6:$B$37,$A14)+SUMIFS(Aportes!$C$43:$C$50,Aportes!$A$43:$A$50,$A14)) -> 0 | F14: =IFERROR($E14/$E$20,0) -> 0 | G14: =$C14-$F14 -> 0
B15: Investidor | C15: 0 | D15: 0 | E15: =IF($A15="",0,SUMIFS(Aportes!$C$6:$C$37,Aportes!$B$6:$B$37,$A15)+SUMIFS(Aportes!$C$43:$C$50,Aportes!$A$43:$A$50,$A15)) -> 0 | F15: =IFERROR($E15/$E$20,0) -> 0 | G15: =$C15-$F15 -> 0
B16: Investidor | C16: 0 | D16: 0 | E16: =IF($A16="",0,SUMIFS(Aportes!$C$6:$C$37,Aportes!$B$6:$B$37,$A16)+SUMIFS(Aportes!$C$43:$C$50,Aportes!$A$43:$A$50,$A16)) -> 0 | F16: =IFERROR($E16/$E$20,0) -> 0 | G16: =$C16-$F16 -> 0
B17: Investidor | C17: 0 | D17: 0 | E17: =IF($A17="",0,SUMIFS(Aportes!$C$6:$C$37,Aportes!$B$6:$B$37,$A17)+SUMIFS(Aportes!$C$43:$C$50,Aportes!$A$43:$A$50,$A17)) -> 0 | F17: =IFERROR($E17/$E$20,0) -> 0 | G17: =$C17-$F17 -> 0
B18: Investidor | C18: 0 | D18: 0 | E18: =IF($A18="",0,SUMIFS(Aportes!$C$6:$C$37,Aportes!$B$6:$B$37,$A18)+SUMIFS(Aportes!$C$43:$C$50,Aportes!$A$43:$A$50,$A18)) -> 0 | F18: =IFERROR($E18/$E$20,0) -> 0 | G18: =$C18-$F18 -> 0
B19: Investidor | C19: 0 | D19: 0 | E19: =IF($A19="",0,SUMIFS(Aportes!$C$6:$C$37,Aportes!$B$6:$B$37,$A19)+SUMIFS(Aportes!$C$43:$C$50,Aportes!$A$43:$A$50,$A19)) -> 0 | F19: =IFERROR($E19/$E$20,0) -> 0 | G19: =$C19-$F19 -> 0
A20: TOTAL | C20: =SUM(C7:C19) -> 1 | D20: =SUM(D7:D19) -> 1 | E20: =SUM(E7:E19) -> 200000 | F20: =SUM(F7:F19) -> 1
A21: Verificação — a participação soma 100%? | C21: =IF(ROUND(C20,6)=1,"✔ SIM","⚠ NÃO — ajuste") -> ✔ SIM | I21: Os fundadores somam 52% neste placeholder. Se a participação seguisse o capital aportado, eles teriam 40% e seriam minoria.
A23: 2. POLÍTICA DE DISTRIBUIÇÃO
A24: Meses de custo operacional a manter em caixa | B24: 6
A25: % do lucro disponível distribuído no ano | B25: 0 | C25: 0 | D25: 0.3 | E25: 0.5 | F25: 0.5 | I25: Zero nos primeiros anos: o caixa é para financiar o crescimento. A partir de 2028 distribui parte, e retém o resto.
A27: 3. APURAÇÃO — CENÁRIO ATIVO
B28: 2026 | C28: 2027 | D28: 2028 | E28: 2029 | F28: 2030 | G28: TOTAL
A29: Lucro líquido do exercício | B29: ='DRE Projetada'!B65 -> -127160.8 | C29: ='DRE Projetada'!C65 -> 316660.5 | D29: ='DRE Projetada'!D65 -> 2140204.3 | E29: ='DRE Projetada'!E65 -> 4856792.8 | F29: ='DRE Projetada'!F65 -> 10789169 | G29: =SUM(B29:F29) -> 17975666 | I29: Vem da DRE anual. É lucro contábil, não dinheiro em caixa.
A30: Lucro acumulado (compensa prejuízo dos anos anteriores) | B30: =B29 -> -127160.8 | C30: =B30+C29 -> 189499.7 | D30: =C30+D29 -> 2329704 | E30: =D30+E29 -> 7186496.8 | F30: =E30+F29 -> 17975666 | I30: Prejuízo de um ano abate o lucro do seguinte antes de qualquer distribuição.
A31: Distribuições já feitas em anos anteriores | B31: =0 -> 0 | C31: =B40 -> 0 | D31: =C40 -> 0 | E31: =D40 -> 0 | F31: =E40 -> 381805 | I31: O que já foi distribuído em anos anteriores não pode ser distribuído de novo, nem continua em caixa.
A32: Lucro ainda não distribuído | B32: =MAX(0,B30-B31) -> 0 | C32: =MAX(0,C30-C31) -> 189499.7 | D32: =MAX(0,D30-D31) -> 2329704 | E32: =MAX(0,E30-E31) -> 7186496.8 | F32: =MAX(0,F30-F31) -> 17593861
A33: Caixa em dezembro (antes de distribuir) | B33: ='Análise Fluxo'!M39 -> 8894.9026 | C33: ='Análise Fluxo'!Y39 -> 324264.3 | D33: ='Análise Fluxo'!AK39 -> 2466794.1 | E33: ='Análise Fluxo'!AW39 -> 7319912.5 | F33: ='Análise Fluxo'!BI39 -> 18105908
A34: (−) Distribuições de anos anteriores | B34: =-B31 -> 0 | C34: =-C31 -> 0 | D34: =-D31 -> 0 | E34: =-E31 -> 0 | F34: =-F31 -> -381805
A35: (−) Reserva de caixa | B35: =-$B$24*ABS(SUMIFS('Análise Fluxo'!$B$28:$BI$28,'Análise Fluxo'!$B$6:$BI$6,B$28))/12 -> -82209.539 | C35: =-$B$24*ABS(SUMIFS('Análise Fluxo'!$B$28:$BI$28,'Análise Fluxo'!$B$6:$BI$6,C$28))/12 -> -1274986.5 | D35: =-$B$24*ABS(SUMIFS('Análise Fluxo'!$B$28:$BI$28,'Análise Fluxo'!$B$6:$BI$6,D$28))/12 -> -3306202.5 | E35: =-$B$24*ABS(SUMIFS('Análise Fluxo'!$B$28:$BI$28,'Análise Fluxo'!$B$6:$BI$6,E$28))/12 -> -6556302.5 | F35: =-$B$24*ABS(SUMIFS('Análise Fluxo'!$B$28:$BI$28,'Análise Fluxo'!$B$6:$BI$6,F$28))/12 -> -11218963 | I35: Meses de custo operacional médio do ano, conforme a política acima.
A36: Caixa livre | B36: =MAX(0,B33+B34+B35) -> 0 | C36: =MAX(0,C33+C34+C35) -> 0 | D36: =MAX(0,D33+D34+D35) -> 0 | E36: =MAX(0,E33+E34+E35) -> 763609.99 | F36: =MAX(0,F33+F34+F35) -> 6505139.8
A37: LUCRO DISTRIBUÍVEL (o menor entre lucro e caixa livre) | B37: =MIN(B32,B36) -> 0 | C37: =MIN(C32,C36) -> 0 | D37: =MIN(D32,D36) -> 0 | E37: =MIN(E32,E36) -> 763609.99 | F37: =MIN(F32,F36) -> 6505139.8 | I37: Só se distribui o que é lucro E está em caixa. Um dos dois limita.
A38: % aplicado | B38: =B25 -> 0 | C38: =C25 -> 0 | D38: =D25 -> 0.3 | E38: =E25 -> 0.5 | F38: =F25 -> 0.5
A39: DISTRIBUÍDO NO ANO | B39: =B37*B38 -> 0 | C39: =C37*C38 -> 0 | D39: =D37*D38 -> 0 | E39: =E37*E38 -> 381805 | F39: =F37*F38 -> 3252569.9 | G39: =SUM(B39:F39) -> 3634374.9
A40: Distribuições acumuladas | B40: =B39 -> 0 | C40: =B40+C39 -> 0 | D40: =C40+D39 -> 0 | E40: =D40+E39 -> 381805 | F40: =E40+F39 -> 3634374.9
A41: Pró-labore pago aos sócios no ano | B41: =SUMIFS(Pessoas!$B$44:$BI$44,Pessoas!$B$38:$BI$38,B$28) -> 0 | C41: =SUMIFS(Pessoas!$B$44:$BI$44,Pessoas!$B$38:$BI$38,C$28) -> 180000 | D41: =SUMIFS(Pessoas!$B$44:$BI$44,Pessoas!$B$38:$BI$38,D$28) -> 180000 | E41: =SUMIFS(Pessoas!$B$44:$BI$44,Pessoas!$B$38:$BI$38,E$28) -> 384000 | F41: =SUMIFS(Pessoas!$B$44:$BI$44,Pessoas!$B$38:$BI$38,F$28) -> 384000 | G41: =SUM(B41:F41) -> 1128000 | I41: Já está na DRE como despesa — é dinheiro que os sócios recebem trabalhando, separado da distribuição de lucros.
A42: Lucro retido na empresa | B42: =B30-B40 -> -127160.8 | C42: =C30-C40 -> 189499.7 | D42: =D30-D40 -> 2329704 | E42: =E30-E40 -> 6804691.8 | F42: =F30-F40 -> 14341291 | I42: Fica na empresa para financiar crescimento — e continua sendo dos sócios.
A44: 4. QUANTO CABE A CADA SÓCIO
A45: Distribuição de lucros por sócio | B45: 2026 | C45: 2027 | D45: 2028 | E45: 2029 | F45: 2030 | G45: TOTAL 5 ANOS
A46: =IF($A7="","",$A7) -> Paulo Kapp | B46: =$C7*B$39 -> 0 | C46: =$C7*C$39 -> 0 | D46: =$C7*D$39 -> 0 | E46: =$C7*E$39 -> 49634.65 | F46: =$C7*F$39 -> 422834.09 | G46: =SUM(B46:F46) -> 472468.74
A47: =IF($A8="","",$A8) -> Lucas Medina | B47: =$C8*B$39 -> 0 | C47: =$C8*C$39 -> 0 | D47: =$C8*D$39 -> 0 | E47: =$C8*E$39 -> 49634.65 | F47: =$C8*F$39 -> 422834.09 | G47: =SUM(B47:F47) -> 472468.74
A48: =IF($A9="","",$A9) -> Felipe Toescher | B48: =$C9*B$39 -> 0 | C48: =$C9*C$39 -> 0 | D48: =$C9*D$39 -> 0 | E48: =$C9*E$39 -> 49634.65 | F48: =$C9*F$39 -> 422834.09 | G48: =SUM(B48:F48) -> 472468.74
A49: =IF($A10="","",$A10) -> Lucas Iung | B49: =$C10*B$39 -> 0 | C49: =$C10*C$39 -> 0 | D49: =$C10*D$39 -> 0 | E49: =$C10*E$39 -> 49634.65 | F49: =$C10*F$39 -> 422834.09 | G49: =SUM(B49:F49) -> 472468.74
A50: =IF($A11="","",$A11) -> C-ioT | B50: =$C11*B$39 -> 0 | C50: =$C11*C$39 -> 0 | D50: =$C11*D$39 -> 0 | E50: =$C11*E$39 -> 61088.799 | F50: =$C11*F$39 -> 520411.19 | G50: =SUM(B50:F50) -> 581499.99
A51: =IF($A12="","",$A12) -> Felipe Martinelli | B51: =$C12*B$39 -> 0 | C51: =$C12*C$39 -> 0 | D51: =$C12*D$39 -> 0 | E51: =$C12*E$39 -> 61088.799 | F51: =$C12*F$39 -> 520411.19 | G51: =SUM(B51:F51) -> 581499.99
A52: =IF($A13="","",$A13) -> Shaiane | B52: =$C13*B$39 -> 0 | C52: =$C13*C$39 -> 0 | D52: =$C13*D$39 -> 0 | E52: =$C13*E$39 -> 61088.799 | F52: =$C13*F$39 -> 520411.19 | G52: =SUM(B52:F52) -> 581499.99
A53: =IF($A14="","",$A14) | B53: =$C14*B$39 -> 0 | C53: =$C14*C$39 -> 0 | D53: =$C14*D$39 -> 0 | E53: =$C14*E$39 -> 0 | F53: =$C14*F$39 -> 0 | G53: =SUM(B53:F53) -> 0
A54: =IF($A15="","",$A15) | B54: =$C15*B$39 -> 0 | C54: =$C15*C$39 -> 0 | D54: =$C15*D$39 -> 0 | E54: =$C15*E$39 -> 0 | F54: =$C15*F$39 -> 0 | G54: =SUM(B54:F54) -> 0
A55: =IF($A16="","",$A16) | B55: =$C16*B$39 -> 0 | C55: =$C16*C$39 -> 0 | D55: =$C16*D$39 -> 0 | E55: =$C16*E$39 -> 0 | F55: =$C16*F$39 -> 0 | G55: =SUM(B55:F55) -> 0
A56: =IF($A17="","",$A17) | B56: =$C17*B$39 -> 0 | C56: =$C17*C$39 -> 0 | D56: =$C17*D$39 -> 0 | E56: =$C17*E$39 -> 0 | F56: =$C17*F$39 -> 0 | G56: =SUM(B56:F56) -> 0
A57: =IF($A18="","",$A18) | B57: =$C18*B$39 -> 0 | C57: =$C18*C$39 -> 0 | D57: =$C18*D$39 -> 0 | E57: =$C18*E$39 -> 0 | F57: =$C18*F$39 -> 0 | G57: =SUM(B57:F57) -> 0
A58: =IF($A19="","",$A19) | B58: =$C19*B$39 -> 0 | C58: =$C19*C$39 -> 0 | D58: =$C19*D$39 -> 0 | E58: =$C19*E$39 -> 0 | F58: =$C19*F$39 -> 0 | G58: =SUM(B58:F58) -> 0
A59: TOTAL DISTRIBUÍDO | B59: =SUM(B46:B58) -> 0 | C59: =SUM(C46:C58) -> 0 | D59: =SUM(D46:D58) -> 0 | E59: =SUM(E46:E58) -> 381805 | F59: =SUM(F46:F58) -> 3252569.9 | G59: =SUM(G46:G58) -> 3634374.9
A61: Total recebido por sócio nos 5 anos | B61: Distribuição de lucros | C61: Pró-labore | D61: TOTAL RECEBIDO | E61: Por 1% de participação
A62: =IF($A7="","",$A7) -> Paulo Kapp | B62: =$G46 -> 472468.74 | C62: =$D7*$G$41 -> 282000 | D62: =$B62+$C62 -> 754468.74 | E62: =IFERROR($B62/$C7/100,0) -> 36343.749
A63: =IF($A8="","",$A8) -> Lucas Medina | B63: =$G47 -> 472468.74 | C63: =$D8*$G$41 -> 282000 | D63: =$B63+$C63 -> 754468.74 | E63: =IFERROR($B63/$C8/100,0) -> 36343.749
A64: =IF($A9="","",$A9) -> Felipe Toescher | B64: =$G48 -> 472468.74 | C64: =$D9*$G$41 -> 282000 | D64: =$B64+$C64 -> 754468.74 | E64: =IFERROR($B64/$C9/100,0) -> 36343.749
A65: =IF($A10="","",$A10) -> Lucas Iung | B65: =$G49 -> 472468.74 | C65: =$D10*$G$41 -> 282000 | D65: =$B65+$C65 -> 754468.74 | E65: =IFERROR($B65/$C10/100,0) -> 36343.749
A66: =IF($A11="","",$A11) -> C-ioT | B66: =$G50 -> 581499.99 | C66: =$D11*$G$41 -> 0 | D66: =$B66+$C66 -> 581499.99 | E66: =IFERROR($B66/$C11/100,0) -> 36343.749
A67: =IF($A12="","",$A12) -> Felipe Martinelli | B67: =$G51 -> 581499.99 | C67: =$D12*$G$41 -> 0 | D67: =$B67+$C67 -> 581499.99 | E67: =IFERROR($B67/$C12/100,0) -> 36343.749
A68: =IF($A13="","",$A13) -> Shaiane | B68: =$G52 -> 581499.99 | C68: =$D13*$G$41 -> 0 | D68: =$B68+$C68 -> 581499.99 | E68: =IFERROR($B68/$C13/100,0) -> 36343.749
A69: =IF($A14="","",$A14) | B69: =$G53 -> 0 | C69: =$D14*$G$41 -> 0 | D69: =$B69+$C69 -> 0 | E69: =IFERROR($B69/$C14/100,0) -> 0
A70: =IF($A15="","",$A15) | B70: =$G54 -> 0 | C70: =$D15*$G$41 -> 0 | D70: =$B70+$C70 -> 0 | E70: =IFERROR($B70/$C15/100,0) -> 0
A71: =IF($A16="","",$A16) | B71: =$G55 -> 0 | C71: =$D16*$G$41 -> 0 | D71: =$B71+$C71 -> 0 | E71: =IFERROR($B71/$C16/100,0) -> 0
A72: =IF($A17="","",$A17) | B72: =$G56 -> 0 | C72: =$D17*$G$41 -> 0 | D72: =$B72+$C72 -> 0 | E72: =IFERROR($B72/$C17/100,0) -> 0
A73: =IF($A18="","",$A18) | B73: =$G57 -> 0 | C73: =$D18*$G$41 -> 0 | D73: =$B73+$C73 -> 0 | E73: =IFERROR($B73/$C18/100,0) -> 0
A74: =IF($A19="","",$A19) | B74: =$G58 -> 0 | C74: =$D19*$G$41 -> 0 | D74: =$B74+$C74 -> 0 | E74: =IFERROR($B74/$C19/100,0) -> 0

Sheet DRE Projetada
A1: DRE PROJETADA MENSAL — DEMONSTRAÇÃO DO RESULTADO DO EXERCÍCIO
A2: =" Cenário ativo: "&Premissas!B7 -> Cenário ativo: PROVÁVEL
A4: Linha do tempo | B4: 46023 | C4: 46054 | D4: 46082 | E4: 46113 | F4: 46143 | G4: 46174 | H4: 46204 | I4: 46235 | J4: 46266 | K4: 46296 | L4: 46327 | M4: 46357 | N4: 46388 | O4: 46419 | P4: 46447 | Q4: 46478 | R4: 46508 | S4: 46539 | T4: 46569 | U4: 46600 | V4: 46631 | W4: 46661 | X4: 46692 | Y4: 46722 | Z4: 46753 | AA4: 46784 | AB4: 46813 | AC4: 46844 | AD4: 46874 | AE4: 46905 | AF4: 46935 | AG4: 46966 | AH4: 46997 | AI4: 47027 | AJ4: 47058 | AK4: 47088 | AL4: 47119 | AM4: 47150 | AN4: 47178 | AO4: 47209 | AP4: 47239 | AQ4: 47270 | AR4: 47300 | AS4: 47331 | AT4: 47362 | AU4: 47392 | AV4: 47423 | AW4: 47453 | AX4: 47484 | AY4: 47515 | AZ4: 47543 | BA4: 47574 | BB4: 47604 | BC4: 47635 | BD4: 47665 | BE4: 47696 | BF4: 47727 | BG4: 47757 | BH4: 47788 | BI4: 47818 | BJ4: TOTAL | BK4: % / Nota
A5: Mês nº | B5: 1 | C5: 2 | D5: 3 | E5: 4 | F5: 5 | G5: 6 | H5: 7 | I5: 8 | J5: 9 | K5: 10 | L5: 11 | M5: 12 | N5: 13 | O5: 14 | P5: 15 | Q5: 16 | R5: 17 | S5: 18 | T5: 19 | U5: 20 | V5: 21 | W5: 22 | X5: 23 | Y5: 24 | Z5: 25 | AA5: 26 | AB5: 27 | AC5: 28 | AD5: 29 | AE5: 30 | AF5: 31 | AG5: 32 | AH5: 33 | AI5: 34 | AJ5: 35 | AK5: 36 | AL5: 37 | AM5: 38 | AN5: 39 | AO5: 40 | AP5: 41 | AQ5: 42 | AR5: 43 | AS5: 44 | AT5: 45 | AU5: 46 | AV5: 47 | AW5: 48 | AX5: 49 | AY5: 50 | AZ5: 51 | BA5: 52 | BB5: 53 | BC5: 54 | BD5: 55 | BE5: 56 | BF5: 57 | BG5: 58 | BH5: 59 | BI5: 60
A6: Ano | B6: =YEAR(B4) -> 2026 | C6: =YEAR(C4) -> 2026 | D6: =YEAR(D4) -> 2026 | E6: =YEAR(E4) -> 2026 | F6: =YEAR(F4) -> 2026 | G6: =YEAR(G4) -> 2026 | H6: =YEAR(H4) -> 2026 | I6: =YEAR(I4) -> 2026 | ... BI6: =YEAR(BI4) -> 2030
A7: Índice do ano (auxiliar) | B7: =MATCH(B6,Premissas!$C$5:$G$5,0) -> 1 | C7: =MATCH(C6,Premissas!$C$5:$G$5,0) -> 1 | D7: =MATCH(D6,Premissas!$C$5:$G$5,0) -> 1 | E7: =MATCH(E6,Premissas!$C$5:$G$5,0) -> 1 | F7: =MATCH(F6,Premissas!$C$5:$G$5,0) -> 1 | G7: =MATCH(G6,Premissas!$C$5:$G$5,0) -> 1 | H7: =MATCH(H6,Premissas!$C$5:$G$5,0) -> 1 | I7: =MATCH(I6,Premissas!$C$5:$G$5,0) -> 1 | ... BI7: =MATCH(BI6,Premissas!$C$5:$G$5,0) -> 5
A8: RECEITA OPERACIONAL BRUTA
A9: Assinaturas — Plano Essencial | B9: =CHOOSE(Premissas!$B$6,Cenários!B20,Cenários!B66,Cenários!B112) -> 0 | C9: =CHOOSE(Premissas!$B$6,Cenários!C20,Cenários!C66,Cenários!C112) -> 0 | D9: =CHOOSE(Premissas!$B$6,Cenários!D20,Cenários!D66,Cenários!D112) -> 0 | E9: =CHOOSE(Premissas!$B$6,Cenários!E20,Cenários!E66,Cenários!E112) -> 0 | F9: =CHOOSE(Premissas!$B$6,Cenários!F20,Cenários!F66,Cenários!F112) -> 0 | G9: =CHOOSE(Premissas!$B$6,Cenários!G20,Cenários!G66,Cenários!G112) -> 0 | H9: =CHOOSE(Premissas!$B$6,Cenários!H20,Cenários!H66,Cenários!H112) -> 0 | I9: =CHOOSE(Premissas!$B$6,Cenários!I20,Cenários!I66,Cenários!I112) -> 0 | ... BI9: =CHOOSE(Premissas!$B$6,Cenários!BI20,Cenários!BI66,Cenários!BI112) -> 1081759.4 | BJ9: =SUM(B9:BI9) -> 23211987
A10: Assinaturas — Plano Premium | B10: =CHOOSE(Premissas!$B$6,Cenários!B21,Cenários!B67,Cenários!B113) -> 0 | C10: =CHOOSE(Premissas!$B$6,Cenários!C21,Cenários!C67,Cenários!C113) -> 0 | D10: =CHOOSE(Premissas!$B$6,Cenários!D21,Cenários!D67,Cenários!D113) -> 0 | E10: =CHOOSE(Premissas!$B$6,Cenários!E21,Cenários!E67,Cenários!E113) -> 0 | F10: =CHOOSE(Premissas!$B$6,Cenários!F21,Cenários!F67,Cenários!F113) -> 0 | G10: =CHOOSE(Premissas!$B$6,Cenários!G21,Cenários!G67,Cenários!G113) -> 0 | H10: =CHOOSE(Premissas!$B$6,Cenários!H21,Cenários!H67,Cenários!H113) -> 0 | I10: =CHOOSE(Premissas!$B$6,Cenários!I21,Cenários!I67,Cenários!I113) -> 0 | ... BI10: =CHOOSE(Premissas!$B$6,Cenários!BI21,Cenários!BI67,Cenários!BI113) -> 1012153.5 | BJ10: =SUM(B10:BI10) -> 19261644
A11: Assinaturas — Plano Família | B11: =CHOOSE(Premissas!$B$6,Cenários!B22,Cenários!B68,Cenários!B114) -> 0 | C11: =CHOOSE(Premissas!$B$6,Cenários!C22,Cenários!C68,Cenários!C114) -> 0 | D11: =CHOOSE(Premissas!$B$6,Cenários!D22,Cenários!D68,Cenários!D114) -> 0 | E11: =CHOOSE(Premissas!$B$6,Cenários!E22,Cenários!E68,Cenários!E114) -> 0 | F11: =CHOOSE(Premissas!$B$6,Cenários!F22,Cenários!F68,Cenários!F114) -> 0 | G11: =CHOOSE(Premissas!$B$6,Cenários!G22,Cenários!G68,Cenários!G114) -> 0 | H11: =CHOOSE(Premissas!$B$6,Cenários!H22,Cenários!H68,Cenários!H114) -> 0 | I11: =CHOOSE(Premissas!$B$6,Cenários!I22,Cenários!I68,Cenários!I114) -> 0 | ... BI11: =CHOOSE(Premissas!$B$6,Cenários!BI22,Cenários!BI68,Cenários!BI114) -> 868688.15 | BJ11: =SUM(B11:BI11) -> 15008328
A12: Marketplace — comissões | B12: =CHOOSE(Premissas!$B$6,Cenários!B24,Cenários!B70,Cenários!B116) -> 0 | C12: =CHOOSE(Premissas!$B$6,Cenários!C24,Cenários!C70,Cenários!C116) -> 0 | D12: =CHOOSE(Premissas!$B$6,Cenários!D24,Cenários!D70,Cenários!D116) -> 0 | E12: =CHOOSE(Premissas!$B$6,Cenários!E24,Cenários!E70,Cenários!E116) -> 0 | F12: =CHOOSE(Premissas!$B$6,Cenários!F24,Cenários!F70,Cenários!F116) -> 0 | G12: =CHOOSE(Premissas!$B$6,Cenários!G24,Cenários!G70,Cenários!G116) -> 0 | H12: =CHOOSE(Premissas!$B$6,Cenários!H24,Cenários!H70,Cenários!H116) -> 0 | I12: =CHOOSE(Premissas!$B$6,Cenários!I24,Cenários!I70,Cenários!I116) -> 0 | ... BI12: =CHOOSE(Premissas!$B$6,Cenários!BI24,Cenários!BI70,Cenários!BI116) -> 195448.71 | BJ12: =SUM(B12:BI12) -> 3500403.2
A13: B2B — parcerias estratégicas | B13: =CHOOSE(Premissas!$B$6,Cenários!B25,Cenários!B71,Cenários!B117) -> 0 | C13: =CHOOSE(Premissas!$B$6,Cenários!C25,Cenários!C71,Cenários!C117) -> 0 | D13: =CHOOSE(Premissas!$B$6,Cenários!D25,Cenários!D71,Cenários!D117) -> 0 | E13: =CHOOSE(Premissas!$B$6,Cenários!E25,Cenários!E71,Cenários!E117) -> 0 | F13: =CHOOSE(Premissas!$B$6,Cenários!F25,Cenários!F71,Cenários!F117) -> 0 | G13: =CHOOSE(Premissas!$B$6,Cenários!G25,Cenários!G71,Cenários!G117) -> 0 | H13: =CHOOSE(Premissas!$B$6,Cenários!H25,Cenários!H71,Cenários!H117) -> 0 | I13: =CHOOSE(Premissas!$B$6,Cenários!I25,Cenários!I71,Cenários!I117) -> 0 | ... BI13: =CHOOSE(Premissas!$B$6,Cenários!BI25,Cenários!BI71,Cenários!BI117) -> 0 | BJ13: =SUM(B13:BI13) -> 0
A14: B2B — venda de dados | B14: =CHOOSE(Premissas!$B$6,Cenários!B26,Cenários!B72,Cenários!B118) -> 0 | C14: =CHOOSE(Premissas!$B$6,Cenários!C26,Cenários!C72,Cenários!C118) -> 0 | D14: =CHOOSE(Premissas!$B$6,Cenários!D26,Cenários!D72,Cenários!D118) -> 0 | E14: =CHOOSE(Premissas!$B$6,Cenários!E26,Cenários!E72,Cenários!E118) -> 0 | F14: =CHOOSE(Premissas!$B$6,Cenários!F26,Cenários!F72,Cenários!F118) -> 0 | G14: =CHOOSE(Premissas!$B$6,Cenários!G26,Cenários!G72,Cenários!G118) -> 0 | H14: =CHOOSE(Premissas!$B$6,Cenários!H26,Cenários!H72,Cenários!H118) -> 0 | I14: =CHOOSE(Premissas!$B$6,Cenários!I26,Cenários!I72,Cenários!I118) -> 0 | ... BI14: =CHOOSE(Premissas!$B$6,Cenários!BI26,Cenários!BI72,Cenários!BI118) -> 70000 | BJ14: =SUM(B14:BI14) -> 1950000 | BK14: Contratos da tabela de iniciativas B2B em Premissas, categoria Dados.
A15: B2B — outras iniciativas | B15: =CHOOSE(Premissas!$B$6,Cenários!B27,Cenários!B73,Cenários!B119) -> 0 | C15: =CHOOSE(Premissas!$B$6,Cenários!C27,Cenários!C73,Cenários!C119) -> 0 | D15: =CHOOSE(Premissas!$B$6,Cenários!D27,Cenários!D73,Cenários!D119) -> 0 | E15: =CHOOSE(Premissas!$B$6,Cenários!E27,Cenários!E73,Cenários!E119) -> 0 | F15: =CHOOSE(Premissas!$B$6,Cenários!F27,Cenários!F73,Cenários!F119) -> 0 | G15: =CHOOSE(Premissas!$B$6,Cenários!G27,Cenários!G73,Cenários!G119) -> 0 | H15: =CHOOSE(Premissas!$B$6,Cenários!H27,Cenários!H73,Cenários!H119) -> 0 | I15: =CHOOSE(Premissas!$B$6,Cenários!I27,Cenários!I73,Cenários!I119) -> 0 | ... BI15: =CHOOSE(Premissas!$B$6,Cenários!BI27,Cenários!BI73,Cenários!BI119) -> 0 | BJ15: =SUM(B15:BI15) -> 0
A16: (=) RECEITA BRUTA | B16: =SUM(B9:B15) -> 0 | C16: =SUM(C9:C15) -> 0 | D16: =SUM(D9:D15) -> 0 | E16: =SUM(E9:E15) -> 0 | F16: =SUM(F9:F15) -> 0 | G16: =SUM(G9:G15) -> 0 | H16: =SUM(H9:H15) -> 0 | I16: =SUM(I9:I15) -> 0 | ... BI16: =SUM(BI9:BI15) -> 3228049.7 | BJ16: =SUM(B16:BI16) -> 62932363
A18: DEDUÇÕES DA RECEITA BRUTA
A19: (−) Impostos sobre a receita (Simples / Lucro Presumido) | B19: =CHOOSE(Premissas!$B$6,Cenários!B31,Cenários!B77,Cenários!B123) -> 0 | C19: =CHOOSE(Premissas!$B$6,Cenários!C31,Cenários!C77,Cenários!C123) -> 0 | D19: =CHOOSE(Premissas!$B$6,Cenários!D31,Cenários!D77,Cenários!D123) -> 0 | E19: =CHOOSE(Premissas!$B$6,Cenários!E31,Cenários!E77,Cenários!E123) -> 0 | F19: =CHOOSE(Premissas!$B$6,Cenários!F31,Cenários!F77,Cenários!F123) -> 0 | G19: =CHOOSE(Premissas!$B$6,Cenários!G31,Cenários!G77,Cenários!G123) -> 0 | H19: =CHOOSE(Premissas!$B$6,Cenários!H31,Cenários!H77,Cenários!H123) -> 0 | I19: =CHOOSE(Premissas!$B$6,Cenários!I31,Cenários!I77,Cenários!I123) -> 0 | ... BI19: =CHOOSE(Premissas!$B$6,Cenários!BI31,Cenários!BI77,Cenários!BI123) -> -527140.52 | BJ19: =SUM(B19:BI19) -> -10425017 | BK19: =IFERROR(BJ19/BJ$16,0) -> -0.16565431
A20: (−) Comissão das lojas de aplicativos | B20: =CHOOSE(Premissas!$B$6,Cenários!B32,Cenários!B78,Cenários!B124) -> 0 | C20: =CHOOSE(Premissas!$B$6,Cenários!C32,Cenários!C78,Cenários!C124) -> 0 | D20: =CHOOSE(Premissas!$B$6,Cenários!D32,Cenários!D78,Cenários!D124) -> 0 | E20: =CHOOSE(Premissas!$B$6,Cenários!E32,Cenários!E78,Cenários!E124) -> 0 | F20: =CHOOSE(Premissas!$B$6,Cenários!F32,Cenários!F78,Cenários!F124) -> 0 | G20: =CHOOSE(Premissas!$B$6,Cenários!G32,Cenários!G78,Cenários!G124) -> 0 | H20: =CHOOSE(Premissas!$B$6,Cenários!H32,Cenários!H78,Cenários!H124) -> 0 | I20: =CHOOSE(Premissas!$B$6,Cenários!I32,Cenários!I78,Cenários!I124) -> 0 | ... BI20: =CHOOSE(Premissas!$B$6,Cenários!BI32,Cenários!BI78,Cenários!BI124) -> -311073.11 | BJ20: =SUM(B20:BI20) -> -6187421.9 | BK20: Apple/Google. A maior dedução isolada da receita de assinatura.
A21: (−) Taxas de meios de pagamento | B21: =CHOOSE(Premissas!$B$6,Cenários!B33,Cenários!B79,Cenários!B125) -> 0 | C21: =CHOOSE(Premissas!$B$6,Cenários!C33,Cenários!C79,Cenários!C125) -> 0 | D21: =CHOOSE(Premissas!$B$6,Cenários!D33,Cenários!D79,Cenários!D125) -> 0 | E21: =CHOOSE(Premissas!$B$6,Cenários!E33,Cenários!E79,Cenários!E125) -> 0 | F21: =CHOOSE(Premissas!$B$6,Cenários!F33,Cenários!F79,Cenários!F125) -> 0 | G21: =CHOOSE(Premissas!$B$6,Cenários!G33,Cenários!G79,Cenários!G125) -> 0 | H21: =CHOOSE(Premissas!$B$6,Cenários!H33,Cenários!H79,Cenários!H125) -> 0 | I21: =CHOOSE(Premissas!$B$6,Cenários!I33,Cenários!I79,Cenários!I125) -> 0 | ... BI21: =CHOOSE(Premissas!$B$6,Cenários!BI33,Cenários!BI79,Cenários!BI125) -> -48790.306 | BJ21: =SUM(B21:BI21) -> -887979.78 | BK21: =IFERROR(BJ21/BJ$16,0) -> -0.014110066
A22: (=) RECEITA OPERACIONAL LÍQUIDA | B22: =B16+SUM(B19:B21) -> 0 | C22: =C16+SUM(C19:C21) -> 0 | D22: =D16+SUM(D19:D21) -> 0 | E22: =E16+SUM(E19:E21) -> 0 | F22: =F16+SUM(F19:F21) -> 0 | G22: =G16+SUM(G19:G21) -> 0 | H22: =H16+SUM(H19:H21) -> 0 | I22: =I16+SUM(I19:I21) -> 0 | ... BI22: =BI16+SUM(BI19:BI21) -> 2341045.8 | BJ22: =SUM(B22:BI22) -> 45431944 | BK22: =IFERROR(BJ22/BJ$16,0) -> 0.72191703
A24: CUSTO DOS SERVIÇOS PRESTADOS
A25: (−) Infraestrutura e nuvem | B25: =CHOOSE(Premissas!$B$6,Cenários!B35,Cenários!B81,Cenários!B127) -> 0 | C25: =CHOOSE(Premissas!$B$6,Cenários!C35,Cenários!C81,Cenários!C127) -> 0 | D25: =CHOOSE(Premissas!$B$6,Cenários!D35,Cenários!D81,Cenários!D127) -> 0 | E25: =CHOOSE(Premissas!$B$6,Cenários!E35,Cenários!E81,Cenários!E127) -> 0 | F25: =CHOOSE(Premissas!$B$6,Cenários!F35,Cenários!F81,Cenários!F127) -> -600 | G25: =CHOOSE(Premissas!$B$6,Cenários!G35,Cenários!G81,Cenários!G127) -> -600 | H25: =CHOOSE(Premissas!$B$6,Cenários!H35,Cenários!H81,Cenários!H127) -> -600 | I25: =CHOOSE(Premissas!$B$6,Cenários!I35,Cenários!I81,Cenários!I127) -> -600 | ... BI25: =CHOOSE(Premissas!$B$6,Cenários!BI35,Cenários!BI81,Cenários!BI127) -> -133533.7 | BJ25: =SUM(B25:BI25) -> -3055456.9 | BK25: =IFERROR(BJ25/BJ$16,0) -> -0.048551441
A26: (−) Suporte ao cliente | B26: =CHOOSE(Premissas!$B$6,Cenários!B36,Cenários!B82,Cenários!B128) -> 0 | C26: =CHOOSE(Premissas!$B$6,Cenários!C36,Cenários!C82,Cenários!C128) -> 0 | D26: =CHOOSE(Premissas!$B$6,Cenários!D36,Cenários!D82,Cenários!D128) -> 0 | E26: =CHOOSE(Premissas!$B$6,Cenários!E36,Cenários!E82,Cenários!E128) -> 0 | F26: =CHOOSE(Premissas!$B$6,Cenários!F36,Cenários!F82,Cenários!F128) -> 0 | G26: =CHOOSE(Premissas!$B$6,Cenários!G36,Cenários!G82,Cenários!G128) -> 0 | H26: =CHOOSE(Premissas!$B$6,Cenários!H36,Cenários!H82,Cenários!H128) -> 0 | I26: =CHOOSE(Premissas!$B$6,Cenários!I36,Cenários!I82,Cenários!I128) -> 0 | ... BI26: =CHOOSE(Premissas!$B$6,Cenários!BI36,Cenários!BI82,Cenários!BI128) -> -18993.25 | BJ26: =SUM(B26:BI26) -> -435736.02 | BK26: =IFERROR(BJ26/BJ$16,0) -> -0.0069238783
A27: (=) LUCRO BRUTO | B27: =B22+B25+B26 -> 0 | C27: =C22+C25+C26 -> 0 | D27: =D22+D25+D26 -> 0 | E27: =E22+E25+E26 -> 0 | F27: =F22+F25+F26 -> -600 | G27: =G22+G25+G26 -> -600 | H27: =H22+H25+H26 -> -600 | I27: =I22+I25+I26 -> -600 | ... BI27: =BI22+BI25+BI26 -> 2188518.9 | BJ27: =SUM(B27:BI27) -> 41940752
A28: Margem bruta (% da receita líquida) | B28: =IFERROR(B27/B22,0) -> 0 | C28: =IFERROR(C27/C22,0) -> 0 | D28: =IFERROR(D27/D22,0) -> 0 | E28: =IFERROR(E27/E22,0) -> 0 | F28: =IFERROR(F27/F22,0) -> 0 | G28: =IFERROR(G27/G22,0) -> 0 | H28: =IFERROR(H27/H22,0) -> 0 | I28: =IFERROR(I27/I22,0) -> 0 | ... BJ28: =IFERROR(BJ27/BJ22,0) -> 0.92315555
A30: DESPESAS OPERACIONAIS
A31: (−) Pessoal — equipe PJ, CLT e pró-labore | B31: ='Análise Fluxo'!B18+'Análise Fluxo'!B19+'Análise Fluxo'!B20 -> 0 | C31: ='Análise Fluxo'!C18+'Análise Fluxo'!C19+'Análise Fluxo'!C20 -> 0 | D31: ='Análise Fluxo'!D18+'Análise Fluxo'!D19+'Análise Fluxo'!D20 -> 0 | E31: ='Análise Fluxo'!E18+'Análise Fluxo'!E19+'Análise Fluxo'!E20 -> 0 | F31: ='Análise Fluxo'!F18+'Análise Fluxo'!F19+'Análise Fluxo'!F20 -> 0 | G31: ='Análise Fluxo'!G18+'Análise Fluxo'!G19+'Análise Fluxo'!G20 -> 0 | H31: ='Análise Fluxo'!H18+'Análise Fluxo'!H19+'Análise Fluxo'!H20 -> 0 | I31: ='Análise Fluxo'!I18+'Análise Fluxo'!I19+'Análise Fluxo'!I20 -> 0 | ... BI31: ='Análise Fluxo'!BI18+'Análise Fluxo'!BI19+'Análise Fluxo'!BI20 -> -374300 | BJ31: =SUM(B31:BI31) -> -9451200 | BK31: =IFERROR(BJ31/BJ$16,0) -> -0.15018028
A32: (−) Marketing e aquisição | B32: ='Análise Fluxo'!B21+'Análise Fluxo'!B22+'Análise Fluxo'!B23 -> 0 | C32: ='Análise Fluxo'!C21+'Análise Fluxo'!C22+'Análise Fluxo'!C23 -> 0 | D32: ='Análise Fluxo'!D21+'Análise Fluxo'!D22+'Análise Fluxo'!D23 -> 0 | E32: ='Análise Fluxo'!E21+'Análise Fluxo'!E22+'Análise Fluxo'!E23 -> 0 | F32: ='Análise Fluxo'!F21+'Análise Fluxo'!F22+'Análise Fluxo'!F23 -> 0 | G32: ='Análise Fluxo'!G21+'Análise Fluxo'!G22+'Análise Fluxo'!G23 -> 0 | H32: ='Análise Fluxo'!H21+'Análise Fluxo'!H22+'Análise Fluxo'!H23 -> 0 | I32: ='Análise Fluxo'!I21+'Análise Fluxo'!I22+'Análise Fluxo'!I23 -> 0 | ... BI32: ='Análise Fluxo'!BI21+'Análise Fluxo'!BI22+'Análise Fluxo'!BI23 -> -490395.44 | BJ32: =SUM(B32:BI32) -> -12009016 | BK32: Inclui a propaganda de lançamento, tratada como despesa e não como investimento.
A33: (−) Despesas administrativas | B33: ='Análise Fluxo'!B27 -> 0 | C33: ='Análise Fluxo'!C27 -> 0 | D33: ='Análise Fluxo'!D27 -> 0 | E33: ='Análise Fluxo'!E27 -> -1500 | F33: ='Análise Fluxo'!F27 -> -1500 | G33: ='Análise Fluxo'!G27 -> -1500 | H33: ='Análise Fluxo'!H27 -> -1500 | I33: ='Análise Fluxo'!I27 -> -1500 | ... BI33: ='Análise Fluxo'!BI27 -> -110000 | BJ33: =SUM(B33:BI33) -> -2425500 | BK33: =IFERROR(BJ33/BJ$16,0) -> -0.038541378
A34: (=) EBITDA | B34: =B27+SUM(B31:B33) -> 0 | C34: =C27+SUM(C31:C33) -> 0 | D34: =D27+SUM(D31:D33) -> 0 | E34: =E27+SUM(E31:E33) -> -1500 | F34: =F27+SUM(F31:F33) -> -2100 | G34: =G27+SUM(G31:G33) -> -2100 | H34: =H27+SUM(H31:H33) -> -2100 | I34: =I27+SUM(I31:I33) -> -2100 | ... BI34: =BI27+SUM(BI31:BI33) -> 1213823.4 | BJ34: =SUM(B34:BI34) -> 18055035
A35: Margem EBITDA (% da receita líquida) | B35: =IFERROR(B34/B22,0) -> 0 | C35: =IFERROR(C34/C22,0) -> 0 | D35: =IFERROR(D34/D22,0) -> 0 | E35: =IFERROR(E34/E22,0) -> 0 | F35: =IFERROR(F34/F22,0) -> 0 | G35: =IFERROR(G34/G22,0) -> 0 | H35: =IFERROR(H34/H22,0) -> 0 | I35: =IFERROR(I34/I22,0) -> 0 | ... BJ35: =IFERROR(BJ34/BJ22,0) -> 0.39740838
A37: RESULTADO
A38: (−) Depreciação e amortização | B38: =-Investimentos!B30 -> 0 | C38: =-Investimentos!C30 -> 0 | D38: =-Investimentos!D30 -> 0 | E38: =-Investimentos!E30 -> 0 | F38: =-Investimentos!F30 -> 0 | G38: =-Investimentos!G30 -> -100 | H38: =-Investimentos!H30 -> -100 | I38: =-Investimentos!I30 -> -100 | ... BI38: =-Investimentos!BI30 -> -2485.4637 | BJ38: =SUM(B38:BI38) -> -79369.111 | BK38: Investimentos amortizados linearmente em 60 meses.
A39: (=) EBIT — resultado operacional | B39: =B34+B38 -> 0 | C39: =C34+C38 -> 0 | D39: =D34+D38 -> 0 | E39: =E34+E38 -> -1500 | F39: =F34+F38 -> -2100 | G39: =G34+G38 -> -2200 | H39: =H34+H38 -> -2200 | I39: =I34+I38 -> -2200 | ... BI39: =BI34+BI38 -> 1211337.9 | BJ39: =SUM(B39:BI39) -> 17975666
A40: (+/−) Resultado financeiro | B40: =0 -> 0 | C40: =0 -> 0 | D40: =0 -> 0 | E40: =0 -> 0 | F40: =0 -> 0 | G40: =0 -> 0 | H40: =0 -> 0 | I40: =0 -> 0 | ... BI40: =0 -> 0 | BJ40: =SUM(B40:BI40) -> 0 | BK40: Rendimento do caixa não considerado (premissa conservadora).
A41: (=) RESULTADO ANTES DO IR | B41: =B39+B40 -> 0 | C41: =C39+C40 -> 0 | D41: =D39+D40 -> 0 | E41: =E39+E40 -> -1500 | F41: =F39+F40 -> -2100 | G41: =G39+G40 -> -2200 | H41: =H39+H40 -> -2200 | I41: =I39+I40 -> -2200 | ... BI41: =BI39+BI40 -> 1211337.9 | BJ41: =SUM(B41:BI41) -> 17975666
A42: (−) IRPJ e CSLL | B42: =0 -> 0 | C42: =0 -> 0 | D42: =0 -> 0 | E42: =0 -> 0 | F42: =0 -> 0 | G42: =0 -> 0 | H42: =0 -> 0 | I42: =0 -> 0 | ... BI42: =0 -> 0 | BJ42: =SUM(B42:BI42) -> 0 | BK42: Já incluídos na linha de impostos sobre a receita (DAS do Simples ou Lucro Presumido).
A43: (=) LUCRO LÍQUIDO DO EXERCÍCIO | B43: =B41+B42 -> 0 | C43: =C41+C42 -> 0 | D43: =D41+D42 -> 0 | E43: =E41+E42 -> -1500 | F43: =F41+F42 -> -2100 | G43: =G41+G42 -> -2200 | H43: =H41+H42 -> -2200 | I43: =I41+I42 -> -2200 | ... BI43: =BI41+BI42 -> 1211337.9 | BJ43: =SUM(B43:BI43) -> 17975666
A44: Margem líquida (% da receita líquida) | B44: =IFERROR(B43/B22,0) -> 0 | C44: =IFERROR(C43/C22,0) -> 0 | D44: =IFERROR(D43/D22,0) -> 0 | E44: =IFERROR(E43/E22,0) -> 0 | F44: =IFERROR(F43/F22,0) -> 0 | G44: =IFERROR(G43/G22,0) -> 0 | H44: =IFERROR(H43/H22,0) -> 0 | I44: =IFERROR(I43/I22,0) -> 0 | ... BJ44: =IFERROR(BJ43/BJ22,0) -> 0.39566139
A45: Lucro líquido acumulado | B45: =B43 -> 0 | C45: =B45+C43 -> 0 | D45: =C45+D43 -> 0 | E45: =D45+E43 -> -1500 | F45: =E45+F43 -> -3600 | G45: =F45+G43 -> -5800 | H45: =G45+H43 -> -8000 | I45: =H45+I43 -> -10200 | J45: =I45+J43 -> -12552.13 | ... BI45: =BH45+BI43 -> 17975666
A47: DRE ANUAL CONSOLIDADA — a mesma DRE acima, somada por ano
A48: Demonstração do Resultado | B48: 2026 | C48: 2027 | D48: 2028 | E48: 2029 | F48: 2030 | G48: 5 ANOS
A49: RECEITA BRUTA | B49: =SUMIFS($B$16:$BI$16,$B$6:$BI$6,B$48) -> 39441.8 | C49: =SUMIFS($B$16:$BI$16,$B$6:$BI$6,C$48) -> 2878342.4 | D49: =SUMIFS($B$16:$BI$16,$B$6:$BI$6,D$48) -> 8769934.8 | E49: =SUMIFS($B$16:$BI$16,$B$6:$BI$6,E$48) -> 17990723 | F49: =SUMIFS($B$16:$BI$16,$B$6:$BI$6,F$48) -> 33253920 | G49: =SUM(B49:F49) -> 62932363
A50: (−) Impostos sobre a receita | B50: =SUMIFS($B$19:$BI$19,$B$6:$BI$6,B$48) -> -6113.479 | C50: =SUMIFS($B$19:$BI$19,$B$6:$BI$6,C$48) -> -540250.85 | D50: =SUMIFS($B$19:$BI$19,$B$6:$BI$6,D$48) -> -1510402.2 | E50: =SUMIFS($B$19:$BI$19,$B$6:$BI$6,E$48) -> -2937885.1 | F50: =SUMIFS($B$19:$BI$19,$B$6:$BI$6,F$48) -> -5430365.2 | G50: =SUM(B50:F50) -> -10425017
A51: (−) Comissão das lojas de aplicativos | B51: =SUMIFS($B$20:$BI$20,$B$6:$BI$6,B$48) -> -5028.8295 | C51: =SUMIFS($B$20:$BI$20,$B$6:$BI$6,C$48) -> -332770.42 | D51: =SUMIFS($B$20:$BI$20,$B$6:$BI$6,D$48) -> -913689.41 | E51: =SUMIFS($B$20:$BI$20,$B$6:$BI$6,E$48) -> -1743109.7 | F51: =SUMIFS($B$20:$BI$20,$B$6:$BI$6,F$48) -> -3192823.5 | G51: =SUM(B51:F51) -> -6187421.9
A52: (−) Taxas de meios de pagamento | B52: =SUMIFS($B$21:$BI$21,$B$6:$BI$6,B$48) -> -266.23215 | C52: =SUMIFS($B$21:$BI$21,$B$6:$BI$6,C$48) -> -29694.285 | D52: =SUMIFS($B$21:$BI$21,$B$6:$BI$6,D$48) -> -108390.24 | E52: =SUMIFS($B$21:$BI$21,$B$6:$BI$6,E$48) -> -248849.65 | F52: =SUMIFS($B$21:$BI$21,$B$6:$BI$6,F$48) -> -500779.37 | G52: =SUM(B52:F52) -> -887979.78
A53: (=) RECEITA LÍQUIDA | B53: =SUMIFS($B$22:$BI$22,$B$6:$BI$6,B$48) -> 28033.259 | C53: =SUMIFS($B$22:$BI$22,$B$6:$BI$6,C$48) -> 1975626.9 | D53: =SUMIFS($B$22:$BI$22,$B$6:$BI$6,D$48) -> 6237453 | E53: =SUMIFS($B$22:$BI$22,$B$6:$BI$6,E$48) -> 13060879 | F53: =SUMIFS($B$22:$BI$22,$B$6:$BI$6,F$48) -> 24129952 | G53: =SUM(B53:F53) -> 45431944
A54: (−) Infraestrutura e nuvem | B54: =SUMIFS($B$25:$BI$25,$B$6:$BI$6,B$48) -> -9791.8368 | C54: =SUMIFS($B$25:$BI$25,$B$6:$BI$6,C$48) -> -211189.1 | D54: =SUMIFS($B$25:$BI$25,$B$6:$BI$6,D$48) -> -524043.29 | E54: =SUMIFS($B$25:$BI$25,$B$6:$BI$6,E$48) -> -887766.66 | F54: =SUMIFS($B$25:$BI$25,$B$6:$BI$6,F$48) -> -1422666 | G54: =SUM(B54:F54) -> -3055456.9
A55: (−) Suporte ao cliente | B55: =SUMIFS($B$26:$BI$26,$B$6:$BI$6,B$48) -> -693.7 | C55: =SUMIFS($B$26:$BI$26,$B$6:$BI$6,C$48) -> -37129.4 | D55: =SUMIFS($B$26:$BI$26,$B$6:$BI$6,D$48) -> -75633 | E55: =SUMIFS($B$26:$BI$26,$B$6:$BI$6,E$48) -> -127333.92 | F55: =SUMIFS($B$26:$BI$26,$B$6:$BI$6,F$48) -> -194946 | G55: =SUM(B55:F55) -> -435736.02
A56: (=) LUCRO BRUTO | B56: =SUMIFS($B$27:$BI$27,$B$6:$BI$6,B$48) -> 17547.723 | C56: =SUMIFS($B$27:$BI$27,$B$6:$BI$6,C$48) -> 1727308.4 | D56: =SUMIFS($B$27:$BI$27,$B$6:$BI$6,D$48) -> 5637776.7 | E56: =SUMIFS($B$27:$BI$27,$B$6:$BI$6,E$48) -> 12045778 | F56: =SUMIFS($B$27:$BI$27,$B$6:$BI$6,F$48) -> 22512340 | G56: =SUM(B56:F56) -> 41940752
A57: Margem bruta | B57: =IFERROR(B56/B53,0) -> 0.62596084 | C57: =IFERROR(C56/C53,0) -> 0.87430901 | D57: =IFERROR(D56/D53,0) -> 0.90385879 | E57: =IFERROR(E56/E53,0) -> 0.92227931 | F57: =IFERROR(F56/F53,0) -> 0.93296248 | G57: =IFERROR(G56/G53,0) -> 0.92315555
A58: (−) Pessoal | B58: =SUMIFS($B$31:$BI$31,$B$6:$BI$6,B$48) -> 0 | C58: =SUMIFS($B$31:$BI$31,$B$6:$BI$6,C$48) -> -510000 | D58: =SUMIFS($B$31:$BI$31,$B$6:$BI$6,D$48) -> -1410000 | E58: =SUMIFS($B$31:$BI$31,$B$6:$BI$6,E$48) -> -3039600 | F58: =SUMIFS($B$31:$BI$31,$B$6:$BI$6,F$48) -> -4491600 | G58: =SUM(B58:F58) -> -9451200
A59: (−) Marketing e aquisição | B59: =SUMIFS($B$32:$BI$32,$B$6:$BI$6,B$48) -> -129025 | C59: =SUMIFS($B$32:$BI$32,$B$6:$BI$6,C$48) -> -816939 | D59: =SUMIFS($B$32:$BI$32,$B$6:$BI$6,D$48) -> -1770246.8 | E59: =SUMIFS($B$32:$BI$32,$B$6:$BI$6,E$48) -> -3408060 | F59: =SUMIFS($B$32:$BI$32,$B$6:$BI$6,F$48) -> -5884745.3 | G59: =SUM(B59:F59) -> -12009016
A60: (−) Despesas administrativas | B60: =SUMIFS($B$33:$BI$33,$B$6:$BI$6,B$48) -> -13500 | C60: =SUMIFS($B$33:$BI$33,$B$6:$BI$6,C$48) -> -72000 | D60: =SUMIFS($B$33:$BI$33,$B$6:$BI$6,D$48) -> -300000 | E60: =SUMIFS($B$33:$BI$33,$B$6:$BI$6,E$48) -> -720000 | F60: =SUMIFS($B$33:$BI$33,$B$6:$BI$6,F$48) -> -1320000 | G60: =SUM(B60:F60) -> -2425500
A61: (=) EBITDA | B61: =SUMIFS($B$34:$BI$34,$B$6:$BI$6,B$48) -> -124977.28 | C61: =SUMIFS($B$34:$BI$34,$B$6:$BI$6,C$48) -> 328369.4 | D61: =SUMIFS($B$34:$BI$34,$B$6:$BI$6,D$48) -> 2157529.8 | E61: =SUMIFS($B$34:$BI$34,$B$6:$BI$6,E$48) -> 4878118.4 | F61: =SUMIFS($B$34:$BI$34,$B$6:$BI$6,F$48) -> 10815995 | G61: =SUM(B61:F61) -> 18055035
